Workbook

Sheet Leads verificados
A1: ﻿Nombre | B1: Categoría | C1: Direccion | D1: Localidad | E1: Provincia | F1: Website | G1: Teléfono | H1: email | I1: mail verificado
A2: FONTANERÍA ERIKA | B2: Fontanero | C2: Plaza de los Oficios, 1, 04230 Huércal de Almería, Almería | D2: Huércal de Almería | E2: Almería | F2: fontaneriaerika.com | G2: 643 43 06 37 | H2: jlorenzofernandez32@gmail.com | I2: TRUE
A3: ROTRISA S.L.U | B3: Tienda de artículos de fontanería | C3: Ctra. Sierra Alhamilla, 306, 04007 Almería | D3: Almería | E3: Almería | F3: rotrisa.com | G3: 950 22 03 11 | H3: cial@rotrisa.com | I3: TRUE
A4: Rafael López Obstrucciones Y Recalos | B4: Fontanero | C4: Calle Sierra de Castillejo, 11, BAJO, 04240 Viator, Almería | D4: Viator | E4: Almería | F4: rafaellopezfontaneriayreformas.com | G4: 950 14 25 60 | H4: rafaellopez@rlopezm.com | I4: TRUE
A5: SC Hogar Multiservicio | B5: Fontanero | D5: Abla | F5: schogar.com | G5: 638 82 46 15 | H5: servicios@schogar.com | I5: TRUE
A6: FONTACLIMA | B6: Fontanero | C6: Av. Segunda Aguada, 21, 11012 Cádiz | D6: Cádiz | E6: Cádiz | F6: fontaclimacadiz.es | G6: 856 07 36 25 | H6: fontaclima@hotmail.es | I6: TRUE
A7: Fontanería Altamirano | B7: Fontanero | C7: Calle Francisco García de Sola, 10, 11008 Cádiz | D7: Cádiz | E7: Cádiz | F7: fontaneriaaltamirano.es | G7: 956 22 15 87 | H7: altamiranosl@live.com | I7: TRUE
A8: DESATASCOS PA’YÁ | B8: Fontanero | C8: Calle Virgen de las Angustias, 5, 11010 Cádiz | D8: Cádiz | E8: Cádiz | F8: desatascos-paya.ueniweb.com | G8: 655 09 94 85 | H8: jose.m.sanchez.paya@gmail.com | I8: TRUE
A9: Suinprosur SL | B9: Fontanero | C9: Poligono Industrial Salinas de Poniente, c/ Alfred Nobel 22, Nave 2, Módulo B, Buzón 8, 11500 Puerto de Santa María (El), Cádiz | D9: El Puerto de Sta María | E9: Cádiz | F9: suinprosur.es | G9: 956 85 75 96 | H9: suinprosur@suinprosur.es | I9: TRUE
A10: Desatascos Chiclana urgentes 24h | B10: Fontanero | C10: Calle Aurora, 3, 11130 Chiclana de la Frontera, Cádiz | D10: Chiclana de la Frontera | E10: Cádiz | F10: desatascoscurro.es | G10: 650 54 14 92 | H10: desatascosomega@gmail.com | I10: TRUE
A11: Fugascor localizacion de fugas de agua en Córdoba, detección de fugas averías y localizador en Córdoba | B11: Fontanero | C11: Calle Escritora Ana María Matutes, 6, local, 14014 Córdoba | D11: Córdoba | E11: Córdoba | F11: fugascor.com | G11: 661 92 22 32 | H11: fugascor@gmail.com | I11: TRUE
A12: Esmebra | B12: Tienda de artículos de fontanería | C12: Av. de Libia, 71, 14014 Córdoba | D12: Córdoba | E12: Córdoba | F12: esmebra.com | G12: 957 26 10 08 | H12: esmebra@esmebra.com | I12: TRUE
A13: Fontanería Y Gas | B13: Fontanero | D13: Adamuz | F13: fontaneriaygas.com | G13: 667 56 20 77 | H13: fontaneriaygasandalucia@gmail.com | I13: TRUE
A14: SANEAMIENTOS LUQUE, S.L. | B14: Tienda de artículos de fontanería | C14: Calle Infante Molina, 3, 14700 Palma del Río, Córdoba | D14: Palma del Río | E14: Córdoba | F14: saneamientosluque.es | G14: 957 64 33 98 | H14: sanealuque@hotmail.com | I14: TRUE
A15: Canalcor - Canalones En Córdoba | B15: Tienda de artículos de fontanería | C15: Calle la Higuera, 1, 1º 1º, 14720 Almodóvar del Río, Córdoba | D15: Almodóvar del Río | E15: Córdoba | F15: canalcor.com | G15: 610 03 23 91 | H15: canalcor@hotmail.com | I15: TRUE
A16: Julio Saneamientos - Revestimientos | B16: Tienda de artículos de fontanería | C16: Calle Fontanal, 14800 Priego de Córdoba, Córdoba | D16: Priego de Córdoba | E16: Córdoba | F16: revestimientosjulio.es | G16: 957 54 09 43 | H16: revestimiento@revestimientosjulio.es | I16: TRUE
A17: Fontanero en Cordoba | B17: Fontanero | C17: Calle Mateo Inurria, 14001 Córdoba | D17: Córdoba | E17: Córdoba | F17: fontanerocordoba.es | G17: 608 52 40 73 | H17: fontaneroscordoba@gmail.com | I17: TRUE
A18: fontanerogranada.net | B18: Fontanero | D18: Agrón | F18: fontanerogranada.net | G18: 666 58 41 90 | H18: jramonruizcastro@gmail.com | I18: TRUE
A19: Antonio Benítez Torres - Fontanería | B19: Fontanero | C19: Calle Imperio, 32, BAJO, 18007 Granada | D19: Granada | E19: Granada | F19: reformasbenitez.com | G19: 958 12 79 51 | H19: antoniobenitezt@telefonica.net | I19: TRUE
A20: Fontanería Reyes | B20: Fontanero | C20: Calle Laurel, 7, 18195 Cúllar Vega, Granada | D20: Cúllar Vega | E20: Granada | F20: fontaneriareyes.com | G20: 661 84 06 66 | H20: sergioreyesye@gmail.com | I20: TRUE
A21: Desatranques TUBORED Granada | B21: Fontanero | C21: Calle Viñas Viejas, 16, bajo a, 18194 Churriana de la Vega, Granada | D21: Churriana de la Vega | E21: Granada | F21: desatascosgranada.biz | G21: 651 51 03 52 | H21: desatranquessierranevada@gmail.com | I21: TRUE
A22: Suministros Antonio Ruiz | B22: Tienda de artículos de fontanería | C22: N-432, KM. 22, 18230 Atarfe, Granada | D22: Atarfe | E22: Granada | F22: todofontaneria.com | G22: 958 43 90 90 | H22: carlos@todofontaneria.com | I22: TRUE
A23: DESATASCOS GRANADA (FONTADUR) | B23: Fontanero | D23: Agrón | F23: desatascos-granada.es | G23: 677 41 11 40 | H23: instalacionesfontadur@gmail.com | I23: TRUE
A24: Reparaciones y Servicios Dhogar | B24: Fontanero | C24: Calle Casillas de Prats, 16, 18002 Granada | D24: Granada | E24: Granada | F24: reparacionesdhogar.com | G24: 634 61 47 76 | H24: reparaciones@reparacionesdhogar.com | I24: TRUE
A25: DESATASCOS TARTESOS HUELVA | B25: Fontanero | C25: Calle Gonzalo de Berceo, 24, 21005 Huelva | D25: Huelva | E25: Huelva | F25: desatascosenhuelvatartesos.com | G25: 615 54 68 51 | H25: multiserviciostartesos@hotmail.com | I25: TRUE
A26: Fontaneria y Gas Huelva | B26: Fontanero | D26: Alájar | F26: fontaneriaygashuelva.es | G26: 603 45 28 79 | H26: valeocarrasco@gmail.com | I26: TRUE
A27: Fontaneria Prera | B27: Fontanero | C27: Calle Alondra, N 8, 21620 Trigueros, Huelva | D27: Trigueros | E27: Huelva | F27: fontaneria-prera.ueniweb.com | G27: 628 85 02 44 | H27: el090584@hotmail.com | I27: TRUE
A28: Instalaciones Andevalo, S.L.U. | B28: Fontanero | C28: Calle Cuartel, 21560 Paymogo, Huelva | D28: Paymogo | E28: Huelva | F28: instalacionesandevalo.es | G28: 959 57 05 64 | H28: comercio@instalacionesandevalo.es | I28: TRUE
A29: MasFugas localizacion de fugas de agua en Huelva, detección de fugas averías y localizador en Huelva | B29: Fontanero | C29: Calle Menéndez Pelayo, 66, 21730 Almonte, Huelva | D29: Almonte | E29: Huelva | F29: masfugas.es | G29: 635 96 17 57 | H29: masfugas@gmail.com | I29: TRUE
A30: Mulbay Multiservicios | B30: Fontanero | C30: Calle Carlos Cano, 17, 23710 Bailén, Jaén | D30: Bailén | E30: Jaén | F30: mulbay.es | G30: 953 67 01 05 | H30: mulbaymultiservicios@gmail.com | I30: TRUE
A31: Fontanero Autónomo Málaga 649 09 91 90 | B31: Fontanero | C31: Calle, Plaza Arriola, Nº 3, 29005 Málaga | D31: Málaga | E31: Málaga | F31: malagafontanero.es | G31: 649 09 91 90 | H31: malagafont@gmail.com | I31: TRUE
A32: Fontanero en Torremolinos | B32: Fontanero | C32: Av. del Lido, 30, 29620 Torremolinos, Málaga | D32: Torremolinos | E32: Málaga | F32: fontanero-torremolinos.es | G32: 635 15 43 30 | H32: jms@malaga-fontanero.com | I32: TRUE
A33: Sermafugas | B33: Fontanero | C33: Calle Río Sil, n59 Polígono Industrial Trévenez, 29196 Málaga | D33: Málaga | E33: Málaga | F33: sermafugas.com | G33: 690 28 29 96 | H33: sermafugas@gmail.com | I33: TRUE
A34: SUSANFO S.L. Arroyo de la Miel | B34: Tienda de artículos de fontanería | C34: Calle Moscatel, 29, 29631 Benalmádena, Málaga | D34: Benalmádena | E34: Málaga | F34: susanfo.es | G34: 952 44 44 28 | H34: susanfonave@hotmail.com | I34: TRUE
A35: Multiservicios Ceres | B35: Fontanero | C35: Calle Vasija, numero 11, 29591 Maqueda, Málaga | D35: Maqueda | E35: Málaga | F35: multiservicios-ceres.com | G35: 695 87 70 98 | H35: multiserviciosceresmlg@gmail.com | I35: TRUE
A36: Bomdesa | B36: Tienda de artículos de fontanería | C36: La Boheme 14 Pg Alameda, 29006 Málaga | D36: Málaga | E36: Málaga | F36: bomdesa.com | G36: 952 35 20 12 | H36: bomdesa@bomdesa.com | I36: TRUE
A37: Fontanero Málaga Urgente | B37: Fontanero | C37: Calle Acebuche, 34, b3, 29730 Rincón de la Victoria, Málaga | D37: Rincón de la Victoria | E37: Málaga | F37: fontaneromalagaurgente.es | G37: 656 73 74 12 | H37: mundoweb.d@gmail.com | I37: TRUE
A38: Montes Torres Suministros ~ Achedosol Estepona | B38: Tienda de artículos de fontanería | C38: Calle Franklin, 15, 19, 29680 Estepona, Málaga | D38: Estepona | E38: Málaga | F38: montestorres.es | G38: 952 80 46 96 | H38: proyectos@achedosol.es | I38: TRUE
... A43: Repa Instalaciones y Mantenimiento S.L. | B43: Fontanero | C43: Calle María Ortiz, 11 A;BAJO;LOCAL-ACC, 41010 Sevilla | D43: Sevilla | E43: Sevilla | F43: repa.es | G43: 954 33 30 42 | H43: repa@repa.es | I43: TRUE
A44: ROYNOR. Fontanrería - Instalaciones | B44: Fontanero | D44: Aguadulce | F44: roynor.com | G44: 627 43 87 75 | H44: fontaneria@roynor.com | I44: TRUE
A45: Cohiser obras y servicios | B45: Fontanero | C45: Avda. Republica Argentina nº40, 41011 Sevilla | D45: Sevilla | E45: Sevilla | F45: cohiser.es | G45: 954 27 57 96 | H45: cohiser@cohiser.es | I45: TRUE
A46: Talleres Desa | B46: Fontanero | C46: Calle Sta. Maria, 13, 41960 Gines, Sevilla | D46: Gines | E46: Sevilla | F46: talleresdesasl.es | G46: 954 71 92 80 | H46: desa@talleresdesasl.es | I46: TRUE
A47: ok fugas de agua | B47: Fontanero | C47: Calle Jaén, 22, 41120 Gelves, Sevilla | D47: Gelves | E47: Sevilla | F47: okfugasdeagua.com | G47: 685 83 39 44 | H47: okfugasdeagua@gmail.com | I47: TRUE
A48: FONTATUBO | B48: Fontanero | C48: C/JUAN ANTONIO MELO MONTIEL,2K, 41960 Gines, Sevilla | D48: Aguadulce | E48: Sevilla | F48: fontatubo.com | G48: 955 70 82 08 | H48: fontatubo@fontatubo.com | I48: TRUE
A49: Solymel | B49: Fontanero | C49: Calle Ganadería PARCELA 27-B, NAVE 2, 22006 Huesca | D49: Huesca | E49: Huesca | F49: solymel.com | G49: 974 24 52 05 | H49: solymel@solymel.com | I49: TRUE
A50: Suministros de Calefacción Aragón S.L. | B50: Tienda de artículos de fontanería | C50: Polígono Sepes, Ronda de la Industria, 103, Parcela 4, nave 1, 22006 Huesca | D50: Huesca | E50: Huesca | F50: sumicar.es | G50: 974 23 00 68 | H50: huesca@sumicarpropibsa.com | I50: TRUE
A51: Fontanería Chema | B51: Fontanero | C51: Calle Luis Buñuel, 8, 22200 Sariñena, Huesca | D51: Sariñena | E51: Huesca | F51: fontaneriachema.com | G51: 974 57 13 80 | H51: chema@fontaneriachema.com | I51: TRUE
A52: Montaser Aragón Sociedad Limitada | B52: Fontanero | C52: Calle Berenice, 20, 50012 Zaragoza | D52: Zaragoza | E52: Zaragoza | F52: montaseraragon.negocio.site | G52: 615 89 38 66 | H52: montaseraragon@gmail.com | I52: TRUE
A53: Fontanería Manuel Rodríguez | B53: Fontanero | C53: Calle Encomienda, 4, 22300 Barbastro, Huesca | D53: Barbastro | E53: Huesca | F53: fontaneriamanuelrodriguez.es | G53: 974 31 14 45 | H53: manuel@fontaneriamanuelrodriguez.es | I53: TRUE
A54: INSTALACIONES LARRAMONA | B54: Fontanero | C54: Av. Sudiera, 22330 Aínsa, Huesca | D54: Aínsa | E54: Huesca | F54: ilarramona.blogspot.com.es | G54: 607 95 06 98 | H54: jdelarramona@gmail.com | I54: TRUE
A55: Jose Abril e Hijos, S.L. | B55: Tienda de artículos de fontanería | C55: Poligono La Paz C/A Parc.2, 44195 Teruel | D55: Teruel | E55: Teruel | F55: abrilehijos.com | G55: 978 62 11 90 | H55: abrilehijos@abrilehijos.com | I55: TRUE
A56: Urbabany Fontaneros | B56: Fontanero | D56: Ababuj | F56: fontanerocastellon.es | G56: 656 98 48 45 | H56: urbabany@gmail.com | I56: TRUE
A57: Fontanero en Castellon Rodalar S.L | B57: Fontanero | C57: Calle Marie Curie, 14, 12200 Onda, Castellón | D57: Onda | E57: Castellón | F57: rodalar.es | G57: 964 60 04 64 | H57: rodalar@rodalar.com | I57: TRUE
A58: Rales Fontanería | B58: Fontanero | C58: Calle Tomaso Albinoni, 2, 50012 Zaragoza | D58: Zaragoza | E58: Zaragoza | F58: ralesfontaneria.com | G58: 620 08 81 60 | H58: ralesfontaneria@gmail.com | I58: TRUE
A59: FONTANERIA ITURBIDE | B59: Fontanero | C59: Calle Comuneros de Castilla, 1, 50002 Zaragoza | D59: Zaragoza | E59: Zaragoza | F59: fontaneriaiturbide.es | G59: 976 29 40 52 | H59: fontaneria@iturbidesl.com | I59: TRUE
A60: Aquacenter Ebro | B60: Tienda de artículos de fontanería | C60: Calle Mariano Baselga, 16, 50015 Zaragoza | D60: Zaragoza | E60: Zaragoza | F60: aquacenterebro.com | G60: 976 73 73 05 | H60: pedidos@aquacenterebro.com | I60: TRUE
A61: FONTANEROS ZARAGOZA 24H SL | B61: Fontanero | C61: Calle del Río Matarraña, 6, 50014 Zaragoza | D61: Zaragoza | E61: Zaragoza | F61: fontaneroszaragoza24h.com | G61: 976 90 64 06 | H61: contable2016@gmail.com | I61: TRUE
A62: Fontanero zaragoza | B62: Fontanero | C62: Calle Félix Latassa, 17, 50006 Zaragoza | D62: Zaragoza | E62: Zaragoza | F62: fontanero-zaragoza.com | G62: 976 56 98 31 | H62: reformaslatassa@hotmail.com | I62: TRUE
A63: Fugas de Agua Zaragoza (PRESUPUESTO GRATIS) | B63: Fontanero | D63: Abanto | F63: fugasdeaguazaragoza.es | G63: 657 99 02 59 | H63: ebnburgo1@hotmail.com | I63: TRUE
A64: Bartolí Calefacción y Fontanería S.L. | B64: Fontanero | C64: Calle Sevilla, 8, 50006 Zaragoza | D64: Zaragoza | E64: Zaragoza | F64: bartolifontaneria.es | G64: 629 62 54 99 | H64: bartolicalfon@gmail.com | I64: TRUE
A65: Cerámicas Bagil | B65: Tienda de artículos de fontanería | C65: Camino de las Torres, 50, 50008 Zaragoza | D65: Zaragoza | E65: Zaragoza | F65: bagil.com | G65: 976 29 28 46 | H65: bagil@bagil.com | I65: TRUE
A66: Compañía BF de Comercio Zaragoza | B66: Tienda de artículos de fontanería | C66: Agrupación Nido, Calle Jaime Ferrán, 11, NAVE 11, 50014 Zaragoza | D66: Zaragoza | E66: Zaragoza | F66: bfdecomercio.es | G66: 976 47 08 48 | H66: bfclientes@bfdecomercio.es | I66: TRUE
A67: Abance Instalaciones | B67: Fontanero | C67: Calle Pablo Iglesias, 28, Local 1, 50018 Zaragoza | D67: Zaragoza | E67: Zaragoza | F67: abanceinstalaciones.com | G67: 606 19 31 36 | H67: abance@abanceinstalaciones.com | I67: TRUE
A68: Fontanería Casa Fácil | B68: Fontanero | C68: Avda. Madrid, 241, 50017 Zaragoza | D68: Zaragoza | E68: Zaragoza | F68: casafacilfontaneria.es | G68: 876 16 01 93 | H68: f.casafacil@gmail.com | I68: TRUE
A69: Hermanos Heredia Instalaciones Urbanas | B69: Fontanero | C69: Calle Tulipán, 28, 50012 Zaragoza | D69: Zaragoza | E69: Zaragoza | F69: hermanosheredia.com | G69: 670 29 42 29 | H69: hermanosheredia@gmail.com | I69: TRUE
A70: Desatascos en Zaragoza Pro: Fregaderos, Tuberías, WC | Económicos | B70: Fontanero | C70: Calle Ramiro I de Aragón, 18, P-2 L-E, 50017 Zaragoza | D70: Zaragoza | E70: Zaragoza | F70: desatascoszaragoza.pro | G70: 644 57 69 19 | H70: 24hprofesionales@gmail.com | I70: TRUE
A71: Rehabilitaweb Zaragoza - Oficinas | B71: Tienda de artículos de fontanería | C71: Paseo de la Independencia, 8, planta 2, 50004 Zaragoza | D71: Zaragoza | E71: Zaragoza | F71: rehabilitaweb.es | G71: 876 66 01 23 | H71: webinfo@rehabilitaweb.com | I71: TRUE
A72: Comercial Quemoil | B72: Tienda de artículos de fontanería | C72: Calle de Don Manuel Lorenzo Pardo, 28, 50008 Zaragoza | D72: Zaragoza | E72: Zaragoza | F72: quemoil.es | G72: 976 49 36 94 | H72: protecciondedatos@quemoil.es | I72: TRUE
A73: Cocinas Y Baños Lamar | B73: Tienda de artículos de fontanería | C73: Calle Padre Manjón, 29, 50010 Zaragoza | D73: Zaragoza | E73: Zaragoza | F73: cocinaslamar.com | G73: 976 30 43 16 | H73: cocinaslamar@gmail.com | I73: TRUE
A74: REPARA LIZARA | B74: Fontanero | C74: Calle Domingo Ram, 54, 50017 Zaragoza | D74: Zaragoza | E74: Zaragoza | F74: reparalizara.com | G74: 627 91 44 98 | H74: reparalizara@gmail.com | I74: TRUE
A75: Ajuar del Baño | B75: Tienda de artículos de fontanería | C75: Calle Sta. Teresa de Jesús, 7, 50006 Zaragoza | D75: Zaragoza | E75: Zaragoza | F75: ajuardelbano.es | G75: 976 35 50 18 | H75: caragonesa@hotmail.com | I75: TRUE
... A103: Fontasol | B103: Fontanero | C103: Calle Tijarafe, nº 19, 38108 San Cristóbal de La Laguna, Santa Cruz de Tenerife | D103: San Cristóbal de La Laguna | E103: Santa Cruz de Tenerife | F103: fontasol.com | G103: 922 31 13 41 | H103: vanessa@fontasol.com | I103: TRUE
A104: Tinerfe7Fontaneros | B104: Fontanero | C104: Calle el Calvario, 74, 38107 Los Baldios, Santa Cruz de Tenerife | D104: Los Baldios | E104: Santa Cruz de Tenerife | F104: tinerfe7fontaneros.com | H104: tomaspereram@gmail.com | I104: TRUE
A105: Servicio 24 horas - Empresa de desatascos urgentes 24 horas en Tenerife | B105: Fontanero | D105: Adeje | F105: desatascosentenerife.com | G105: 633 91 50 37 | H105: nibaldosingler@hotmail.com | I105: TRUE
A106: ACG Abastecimientos | B106: Tienda de artículos de fontanería | C106: Calle Fuencaliente, 2-4, 38108 San Cristóbal de La Laguna, Santa Cruz de Tenerife | D106: San Cristóbal de La Laguna | E106: Santa Cruz de Tenerife | F106: acgabastecimientos.es | G106: 922 31 08 40 | H106: acg@acgabastecimientos.com | I106: TRUE
A107: Fontanero 24H Tenerife | B107: Fontanero | D107: Adeje | F107: fontanero24h-tenerife.es | G107: 650 68 43 99 | H107: fontabel24h@gmail.com | I107: TRUE
A108: Fontanería Alexis | B108: Fontanero | C108: Calle la Cruz, 68, 38620 San Miguel, Santa Cruz de Tenerife | D108: San Miguel | E108: Santa Cruz de Tenerife | F108: insttf.com | G108: 670 82 24 60 | H108: gonmaralexis@gmail.com | I108: TRUE
A109: A-Z Hidráulica | B109: Fontanero | C109: Av. Reina Sofía, 4, 38687 Playa San Juan, Santa Cruz de Tenerife | D109: Playa San Juan | E109: Santa Cruz de Tenerife | F109: azhidraulica.com | G109: 672 46 11 14 | H109: azhidraulica@hotmail.com | I109: TRUE
A110: Desatascos Cantabria F.C.G. | B110: Fontanero | C110: Grupo Santa Teresa, 13 Oficina Acristalada, 39610 Guarnizo, Cantabria | D110: Guarnizo | E110: Cantabria | F110: fcgcantabria.com | G110: 661 65 00 85 | H110: jesus@fcgcantabria.com | I110: TRUE
A111: Suministros Luis Pinto | B111: Tienda de artículos de fontanería | C111: Av. de los Castros, 95, 39005 Santander, Cantabria | D111: Santander | E111: Cantabria | F111: suministrosluispinto.com | G111: 942 23 80 90 | H111: loscastros@suministrosluispinto.com | I111: TRUE
A112: Carmelo Rojas Fontaneria y Calefaccion | B112: Fontanero | C112: Poligono Trascueto CEM, 217, 39600 Revilla de Camargo, Cantabria | D112: Revilla de Camargo | E112: Cantabria | F112: carmelorojas.com | G112: 679 01 42 12 | H112: carmelofyc@gmail.com | I112: TRUE
A113: Fontaneria Fontcal | B113: Fontanero | C113: P.º de la Estación, número 26, bajo, 39710 Solares, Cantabria | D113: Solares | E113: Cantabria | F113: fontaneriafontcal.com | G113: 942 52 30 28 | H113: tecnico@fontaneriafontcal.com | I113: TRUE
A114: Aguas Expert | B114: Fontanero | C114: Calle Gral. Dávila, 304, 39007 Santander, Cantabria | D114: Santander | E114: Cantabria | F114: aguasexpert.es | G114: 942 10 87 42 | H114: aguasexpert@hotmail.com | I114: TRUE
A115: Briccal, S.L. | B115: Tienda de artículos de fontanería | C115: Poligono Industrial La Cerrada s/n, 39600 Camargo | D115: Camargo | E115: Camargo | F115: briccal.com | G115: 942 26 20 21 | H115: briccal@briccal.com | I115: TRUE
A116: TUCALDERAYA | B116: Fontanero | D116: Alfoz de Lloredo | F116: tucalderaya.com | G116: 600 27 17 31 | H116: alexruizgomez1975@gmail.com | I116: TRUE
A117: Fontanería Azcona | B117: Fontanero | C117: El Carmen, 23A, 39600 Revilla de Camargo, Cantabria | D117: Revilla de Camargo | E117: Cantabria | F117: azconafontaneria.es | G117: 626 51 51 13 | H117: AZCONAFONTANERIA@GMAIL.COM | I117: TRUE
A118: Calefacción y Fontanería Gómez Bravo S.L. | B118: Fontanero | C118: Av. Ronda, 34, 34800 Aguilar de Campoo, Palencia | D118: Aguilar de Campoo | E118: Palencia | F118: gomezbravoaguilar.es | G118: 979 12 32 18 | H118: cyfgomezbravo@gmail.com | I118: TRUE
A119: DENA FONTANERIA Y DESATASCOS, S.L. | B119: Fontanero | C119: Luchana Mining Kalea, 4, 2b, 48903 Barakaldo, Bizkaia | D119: Baracaldo | E119: Bizkaia | F119: denafontaneriaydesatascos.es | G119: 626 71 95 41 | H119: gpodena@gmail.com | I119: TRUE
A120: Fontaneria Ollaretxe | B120: Fontanero | C120: Eleizalde Kalea, 6, 48600 Sopela, Bizkaia | D120: Sopelana | E120: Bizkaia | F120: fontaneriaollaretxe.com | G120: 946 76 53 55 | H120: ollaretxesopelana@hotmail.com | I120: TRUE
A121: Fontanería Anadón | B121: Fontanero | C121: Labayru Kalea, 37, 48012 Bilbo, Bizkaia | D121: Bilbao | E121: Bizkaia | F121: fontaneriaanadonbilbao.es | G121: 944 22 38 98 | H121: fontaneriaanadon@gmail.com | I121: TRUE
A122: Fontanería y Calefacción Cemar | B122: Fontanero | C122: Calle Ignacio Monturiol, 12, 02005 Albacete | D122: Albacete | E122: Albacete | F122: fontaneriacemar.es | G122: 967 52 29 66 | H122: cemar@fontaneriacemar.es | I122: TRUE
A123: Fontaneria Escudero | B123: Fontanero | C123: Calle Joaquín Quijada, 27, LOCAL, 02004 Albacete | D123: Albacete | E123: Albacete | F123: fontaneriaescudero.es | G123: 687 72 82 22 | H123: alonso_jea@hotmail.com | I123: TRUE
A124: Comercial del Instalador | B124: Fontanero | C124: Calle Autovia, 23, 02007 Albacete | D124: Albacete | E124: Albacete | F124: comercialdelinstalador.com | G124: 967 52 43 16 | H124: cv@comercialdelinstalador.com | I124: TRUE
A125: Desatascos Alarcon | B125: Fontanero | C125: Paseo Circunvalación, 71, 3º D, 02004 Albacete | D125: Albacete | E125: Albacete | F125: alarconlimpiezas.es | G125: 676 13 18 54 | H125: limp.alarcon@gmail.com | I125: TRUE
A126: Hidroman | B126: Tienda de artículos de fontanería | C126: Calle Lérida, 48, 02006 Albacete | D126: Albacete | E126: Albacete | F126: hidromanalba.es | G126: 627 55 20 18 | H126: hidroman@hidromanalba.es | I126: TRUE
A127: Germán Baños | B127: Tienda de artículos de fontanería | C127: Av. 4ª, 25, 02007 Albacete | D127: Albacete | E127: Albacete | F127: germanbanos.es | G127: 967 21 05 15 | H127: germanbanos@hotmail.com | I127: TRUE
A128: Fontaneria Albacete - Antonio Ruescas | B128: Fontanero | C128: C/ Honda, 4, 02049 Aguas Nuevas, Albacete | D128: Abengibre | E128: Albacete | F128: fontaneriaalbacete.es | G128: 670 26 96 60 | H128: tecnico@fontaneriaalbacete.es | I128: TRUE
... A135: Desatasco crumo | B135: Fontanero | C135: 17 2d, Calle Mercedes Escribano, 16003 Cuenca | D135: Cuenca | E135: Cuenca | F135: desatascoscrumo.es | G135: 622 63 83 09 | H135: desatascoscrumo@hotmail.com | I135: TRUE
A136: FONTANERÍA Y SERVICIOS MARIO | B136: Fontanero | D136: Abia de la Obispalía | F136: fontaneromadridguadalajara.es | G136: 642 91 16 91 | H136: mariusadryan.01@gmail.com | I136: TRUE
A137: Francisco Garrido, Fontanería Calefacción y Aire acondicionado | B137: Tienda de artículos de fontanería | C137: Calle Administración, 19, 16260 Minglanilla, Cuenca | D137: Minglanilla | E137: Cuenca | F137: franciscogarrido.es | G137: 605 12 31 85 | H137: correo@franciscogarrido.es | I137: TRUE
...

Sheet centraldecomunicacion.es
A1: ﻿Nombre | B1: Categoría | C1: Direccion | D1: Localidad | E1: Provincia | F1: Website | G1: Teléfono | H1: email | I1: mail verificado
A2: Telegas fontaneria y gas | B2: Fontanero | C2: Av. del Mediterráneo, 95, 04007 Almería | D2: Almería | E2: Almería | G2: 950 15 12 25 | H2: - | I2: =COUNTIF(Estadísticas!I:I,'centraldecomunicacion.es'!H2)>0 -> FALSE
A3: Aquagas Almería S.L. | B3: Fontanero | C3: Calle Juan Lirola, 34, 04004 Almería | D3: Almería | E3: Almería | F3: aquagasalmeria.es | G3: 950 14 15 94 | H3: info@aquagasalmeria.es | I3: =COUNTIF(Estadísticas!I:I,'centraldecomunicacion.es'!H3)>0 -> FALSE
A4: Fontanero en Almería, Fontanería Ignacio González. | B4: Fontanero | C4: Calle Pablo Ruiz Picasso, 20, 04005 Almería | D4: Almería | E4: Almería | F4: fontaneriaignaciogonzalez.es | G4: 950 26 42 35 | H4: info@fontaneriaignaciogonzalez.es | I4: =COUNTIF(Estadísticas!I:I,'centraldecomunicacion.es'!H4)>0 -> FALSE
A5: Saneamientos José Gómez S.L. | B5: Tienda de artículos de fontanería | C5: Av. Mare Nostrum, 41, 04009 Almería | D5: Almería | E5: Almería | F5: saneamientosjgomez.com | G5: 950 22 23 99 | H5: - | I5: =COUNTIF(Estadísticas!I:I,'centraldecomunicacion.es'!H5)>0 -> FALSE
A6: FONTANERÍA Y REFORMAS MIGUEL GARCÍA SERVIRAPID | B6: Fontanero | D6: Abla | G6: 670 50 94 30 | H6: - | I6: =COUNTIF(Estadísticas!I:I,'centraldecomunicacion.es'!H6)>0 -> FALSE
A7: Fontanería Eva Fontaneros | B7: Fontanero | C7: Calle Acacia, 8, 04240 Almería | D7: Almería | E7: Almería | F7: fontaneriaevaaguaygas.com | G7: 630 87 41 78 | H7: a36b86319e6542838a534122c8870e3f@sentry.qdqmedia.com | I7: =COUNTIF(Estadísticas!I:I,'centraldecomunicacion.es'!H7)>0 -> FALSE
A8: Fontanería Portocarrero | B8: Fontanero | C8: Calle Rosa Felices, Nº 134, 1º A, 04006 Almería | D8: Almería | E8: Almería | G8: 653 33 35 15 | H8: - | I8: =COUNTIF(Estadísticas!I:I,'centraldecomunicacion.es'!H8)>0 -> FALSE
A9: Saneamientos Jose Gomez SL | B9: Tienda de artículos de fontanería | C9: Calle Instinción, 2, 04006 Almería | D9: Almería | E9: Almería | F9: saneamientosjgomez.com | G9: 950 22 69 86 | H9: - | I9: =COUNTIF(Estadísticas!I:I,'centraldecomunicacion.es'!H9)>0 -> FALSE
A10: Saneamientos Alba | B10: Tienda de artículos de fontanería | C10: Calle Bidasoa, 6, 04006 Almería | D10: Almería | E10: Almería | F10: saneamientosalba.com | G10: 950 23 46 08 | H10: - | I10: =COUNTIF(Estadísticas!I:I,'centraldecomunicacion.es'!H10)>0 -> FALSE
A11: Fontanería Angel Nieto | B11: Fontanero | C11: Calle Calvario, 71, 04008 Almería | D11: Almería | E11: Almería | G11: 607 79 44 37 | H11: - | I11: =COUNTIF(Estadísticas!I:I,'centraldecomunicacion.es'!H11)>0 -> FALSE
A12: FONTANERÍA ERIKA | B12: Fontanero | C12: Plaza de los Oficios, 1, 04230 Huércal de Almería, Almería | D12: Huércal de Almería | E12: Almería | F12: fontaneriaerika.com | G12: 643 43 06 37 | H12: jlorenzofernandez32@gmail.com | I12: =COUNTIF(Estadísticas!I:I,'centraldecomunicacion.es'!H12)>0 -> TRUE
A13: ROTRISA S.L.U | B13: Tienda de artículos de fontanería | C13: Ctra. Sierra Alhamilla, 306, 04007 Almería | D13: Almería | E13: Almería | F13: rotrisa.com | G13: 950 22 03 11 | H13: cial@rotrisa.com | I13: =COUNTIF(Estadísticas!I:I,'centraldecomunicacion.es'!H13)>0 -> TRUE
A14: I.T. Fontelec | B14: Fontanero | C14: Calle Largo Caballero, 61, 04008 Almería | D14: Almería | E14: Almería | G14: 659 05 68 27 | H14: - | I14: =COUNTIF(Estadísticas!I:I,'centraldecomunicacion.es'!H14)>0 -> FALSE
A15: fontaneria salvador baena | B15: Fontanero | C15: Calle el Almendro, nº35, 04009 Almería | D15: Almería | E15: Almería | G15: 630 39 32 16 | H15: - | I15: =COUNTIF(Estadísticas!I:I,'centraldecomunicacion.es'!H15)>0 -> FALSE
A16: Fontanería Y Gas Luis Berenguel | B16: Fontanero | C16: Calle Jaúl, 1, 04007 Almería | D16: Almería | E16: Almería | G16: 617 44 71 22 | H16: - | I16: =COUNTIF(Estadísticas!I:I,'centraldecomunicacion.es'!H16)>0 -> FALSE
A17: Fontanería Uroz | B17: Fontanero | C17: Calle Poeta Luis Cernuda, 0, 04006 Almería | D17: Almería | E17: Almería | G17: 618 27 88 08 | H17: - | I17: =COUNTIF(Estadísticas!I:I,'centraldecomunicacion.es'!H17)>0 -> FALSE
A18: Fontaneria F.Delgado | B18: Fontanero | C18: Calle Real del Barrio Alto, 45, 04008 Almería | D18: Almería | E18: Almería | F18: fontaneriafdelgado.es | G18: 619 82 40 84 | H18: - | I18: =COUNTIF(Estadísticas!I:I,'centraldecomunicacion.es'!H18)>0 -> FALSE
A19: Fontaneros en Almería | Servicio Urgente y Económico en Zapillo | B19: Fontanero | D19: Abla | F19: fontaneroszapillo.com | G19: 658 68 89 62 | H19: tinfo@fontaneroszapillo.com | I19: =COUNTIF(Estadísticas!I:I,'centraldecomunicacion.es'!H19)>0 -> FALSE
A20: Multiservicios Fernández | B20: Fontanero | C20: Calle Gral. Luque, 36, 04002 Almería | D20: Almería | E20: Almería | F20: serviciosfernandez.es | G20: 604 18 15 94 | H20: info@serviciosfernandez.es | I20: =COUNTIF(Estadísticas!I:I,'centraldecomunicacion.es'!H20)>0 -> FALSE
A21: Comercial Maestria S.L. | B21: Tienda de artículos de fontanería | C21: Calle Maestría, 38, 04008 Almería | D21: Almería | E21: Almería | F21: fb.me | G21: 950 23 48 94 | H21: - | I21: =COUNTIF(Estadísticas!I:I,'centraldecomunicacion.es'!H21)>0 -> FALSE
A22: Fontaneria Puertas | B22: Fontanero | C22: Calle Cristóbal López Lupiañez, 04006 Almería | D22: Almería | E22: Almería | G22: 620 73 38 99 | H22: - | I22: =COUNTIF(Estadísticas!I:I,'centraldecomunicacion.es'!H22)>0 -> FALSE
A23: Fontanería Guillermo Cabeo | B23: Fontanero | D23: Abla | F23: facebook.com | G23: 607 60 71 36 | H23: - | I23: =COUNTIF(Estadísticas!I:I,'centraldecomunicacion.es'!H23)>0 -> FALSE
A24: INSTALACIONES &amp; REPARACIONES JOSÉ RODRIGUEZ | B24: Fontanero | C24: Calle Marchales, 90, bajo, 04008 Almería | D24: Almería | E24: Almería | G24: 607 18 76 62 | H24: - | I24: =COUNTIF(Estadísticas!I:I,'centraldecomunicacion.es'!H24)>0 -> FALSE
A25: Localización fugas de agua Almería | B25: Fontanero | C25: Calle la Plata, 33, 04008 Almería | D25: Almería | E25: Almería | G25: 950 14 15 94 | H25: - | I25: =COUNTIF(Estadísticas!I:I,'centraldecomunicacion.es'!H25)>0 -> FALSE
A26: Milán Fontaneros | B26: Fontanero | C26: C. Campogris, 33A, 04008 Almería | D26: Almería | E26: Almería | H26: - | I26: =COUNTIF(Estadísticas!I:I,'centraldecomunicacion.es'!H26)>0 -> FALSE
A27: fontaneria saez | B27: Fontanero | C27: Calle Cámaras, 22, 04003 Almería | D27: Almería | E27: Almería | F27: fontaneriasaezalmeria.com | G27: 950 26 71 58 | H27: - | I27: =COUNTIF(Estadísticas!I:I,'centraldecomunicacion.es'!H27)>0 -> FALSE
A28: VALSAN Delegación ALMERÍA | B28: Tienda de artículos de fontanería | C28: Calle Carbon, 121, 04009 Almería | D28: Almería | E28: Almería | F28: valsan.es | G28: 950 17 35 91 | H28: ventas@valsan.es | I28: =COUNTIF(Estadísticas!I:I,'centraldecomunicacion.es'!H28)>0 -> FALSE
A29: Intec Climatizacion-Electricidad-Fontaneria | B29: Fontanero | C29: Calle Estaño, 04009 Almería | D29: Almería | E29: Almería | H29: - | I29: =COUNTIF(Estadísticas!I:I,'centraldecomunicacion.es'!H29)>0 -> FALSE
A30: Fontanería M&amp;R | B30: Fontanero | C30: Av. de Cabo de Gata, 88, 04007 Almería | D30: Almería | E30: Almería | F30: fontaneria-mr.negocio.site | H30: - | I30: =COUNTIF(Estadísticas!I:I,'centraldecomunicacion.es'!H30)>0 -> FALSE
A31: Albanileria Y Fontanería | B31: Fontanero | C31: Calle Plus Ultra, 9, 04005 Almería | D31: Almería | E31: Almería | H31: - | I31: =COUNTIF(Estadísticas!I:I,'centraldecomunicacion.es'!H31)>0 -> FALSE
A32: Localización y Detección de Fugas Almeria | B32: Fontanero | C32: Calle Maldonado Entrena bloque 2-4, 5ª puerta, 04003 Almería | D32: Almería | E32: Almería | F32: grupovico.com | G32: 627 42 10 32 | H32: info@grupovico.com | I32: =COUNTIF(Estadísticas!I:I,'centraldecomunicacion.es'!H32)>0 -> FALSE
A33: Fontaneria Fortuna | B33: Fontanero | C33: Calle Pedro Jover, 8, 04002 Almería | D33: Almería | E33: Almería | H33: - | I33: =COUNTIF(Estadísticas!I:I,'centraldecomunicacion.es'!H33)>0 -> FALSE
A34: Gas Fellas Plumber Almeria | B34: Fontanero | C34: Calle Navarro Rodrigo, 8, 4D, 04001 Almería | D34: Almería | E34: Almería | F34: gasfellas.com | G34: 911 23 25 18 | H34: - | I34: =COUNTIF(Estadísticas!I:I,'centraldecomunicacion.es'!H34)>0 -> FALSE
A35: Reparaciones Urgencias Almería | B35: Fontanero | C35: Plaza Carabineros, 14, 04007 Almería | D35: Almería | E35: Almería | F35: reparacionesurgencias.online | G35: 950 95 56 64 | H35: Contacto@servicioshogaralmeria.es | I35: =COUNTIF(Estadísticas!I:I,'centraldecomunicacion.es'!H35)>0 -> FALSE
A36: YAVAMOS | B36: Fontanero | C36: Calle Búfalo, 42, 04720 Aguadulce, Almería | D36: Aguadulce | E36: Almería | F36: yavamos.es | G36: 950 65 34 06 | H36: core-js-bundle@3.2.1 | I36: =COUNTIF(Estadísticas!I:I,'centraldecomunicacion.es'!H36)>0 -> FALSE
A37: Materiales y Sistemas de Calefacción S.L. | B37: Fontanero | C37: Polígono Industrial Mezquita, 398, 04007 Almería | D37: Almería | E37: Almería | G37: 950 22 74 50 | H37: - | I37: =COUNTIF(Estadísticas!I:I,'centraldecomunicacion.es'!H37)>0 -> FALSE
A38: Oil Barol | B38: Fontanero | C38: Calle Vélez Rubio, 04001 Almería | D38: Almería | E38: Almería | H38: - | I38: =COUNTIF(Estadísticas!I:I,'centraldecomunicacion.es'!H38)>0 -> FALSE
A39: Almería AguaConfort S.L. (Tienda en Almería Capital) | B39: Tienda de artículos de fontanería | C39: Carretera Níjar - la Cañada, nº398, 04007 Almería | D39: Almería | E39: Almería | F39: grupoaguaconfort.com | G39: 950 22 79 00 | H39: core-js-bundle@3.2.1 | I39: =COUNTIF(Estadísticas!I:I,'centraldecomunicacion.es'!H39)>0 -> FALSE
A40: Fontanería Cabrera | B40: Fontanero | C40: Calle Gardenia, 6, 04720 Aguadulce, Almería | D40: Aguadulce | E40: Almería | F40: fontaneroalmeria.business.site | G40: 950 34 26 61 | H40: - | I40: =COUNTIF(Estadísticas!I:I,'centraldecomunicacion.es'!H40)>0 -> FALSE
A41: Rafael López Obstrucciones Y Recalos | B41: Fontanero | C41: Calle Sierra de Castillejo, 11, BAJO, 04240 Viator, Almería | D41: Viator | E41: Almería | F41: rafaellopezfontaneriayreformas.com | G41: 950 14 25 60 | H41: rafaellopez@rlopezm.com | I41: =COUNTIF(Estadísticas!I:I,'centraldecomunicacion.es'!H41)>0 -> TRUE
A42: Fontaneria Enrial | B42: Fontanero | C42: Calle Sierra de Ronda, 33, 04240 Viator, Almería | D42: Viator | E42: Almería | H42: - | I42: =COUNTIF(Estadísticas!I:I,'centraldecomunicacion.es'!H42)>0 -> FALSE
A43: Quensis Oil | B43: Fontanero | C43: Calle Vélez Rubio, 04001 Almería | D43: Almería | E43: Almería | H43: - | I43: =COUNTIF(Estadísticas!I:I,'centraldecomunicacion.es'!H43)>0 -> FALSE
A44: (Servicios Elias) Fontaneria, electricidad , aire acondicionado | B44: Fontanero | C44: s/n,, Calle Olula de Castro, 04008 Almería | D44: Almería | E44: Almería | G44: 609 02 19 15 | H44: - | I44: =COUNTIF(Estadísticas!I:I,'centraldecomunicacion.es'!H44)>0 -> FALSE
A45: SC Hogar Multiservicio | B45: Fontanero | D45: Abla | F45: schogar.com | G45: 638 82 46 15 | H45: servicios@schogar.com | I45: =COUNTIF(Estadísticas!I:I,'centraldecomunicacion.es'!H45)>0 -> TRUE
A46: Alisur | B46: Fontanero | D46: Abla | G46: 679 66 18 21 | H46: - | I46: =COUNTIF(Estadísticas!I:I,'centraldecomunicacion.es'!H46)>0 -> FALSE
A47: Fontanería JAF | B47: Fontanero | C47: Calle Virgen de las Angustias, 12, 04240 Viator, Almería | D47: Viator | E47: Almería | F47: fontaneriajaf.com | G47: 643 87 12 05 | H47: - | I47: =COUNTIF(Estadísticas!I:I,'centraldecomunicacion.es'!H47)>0 -> FALSE
A48: Blancosur | B48: Fontanero | C48: Camino Haza Tableada-Juaida, 43, 04120 Almería | D48: Almería | E48: Almería | G48: 670 99 81 86 | H48: - | I48: =COUNTIF(Estadísticas!I:I,'centraldecomunicacion.es'!H48)>0 -> FALSE
A49: Hermanos Valdivia | B49: Tienda de artículos de fontanería | C49: Calle Alicún, 04007 Almería | D49: Almería | E49: Almería | H49: - | I49: =COUNTIF(Estadísticas!I:I,'centraldecomunicacion.es'!H49)>0 -> FALSE
A50: Multiservicios MullOrtiz | B50: Fontanero | C50: Paraje Guillén, 17, 04120 Almería | D50: Almería | E50: Almería | G50: 722 20 86 43 | H50: - | I50: =COUNTIF(Estadísticas!I:I,'centraldecomunicacion.es'!H50)>0 -> FALSE
A51: Anpi Fontaneros | B51: Fontanero | C51: Calle Sierra de Orce, 17 BAJO, POLIG.INDUSTRIAL, 04240 Viator, Almería | D51: Viator | E51: Almería | F51: anpiconstrucciones.com | G51: 616 62 15 86 | H51: - | I51: =COUNTIF(Estadísticas!I:I,'centraldecomunicacion.es'!H51)>0 -> FALSE
A52: FUGAS DE AGUA | B52: Fontanero | C52: Av. Juan Carlos I, n°65, 4e, 04740 Roquetas de Mar, Almería | D52: Roquetas de Mar | E52: Almería | G52: 604 34 97 50 | H52: - | I52: =COUNTIF(Estadísticas!I:I,'centraldecomunicacion.es'!H52)>0 -> FALSE
A53: Fontaneros en Almería | B53: Fontanero | C53: Calle Ulises, 26, 04740 Roquetas de Mar, Almería | D53: Roquetas de Mar | E53: Almería | G53: 670 63 80 85 | H53: - | I53: =COUNTIF(Estadísticas!I:I,'centraldecomunicacion.es'!H53)>0 -> FALSE
A54: Fontanería Hermanos Fernández S.L. | B54: Fontanero | C54: Bulevar Cdad. de Vicar, 625, 04738 Vícar, Almería | D54: Vícar | E54: Almería | G54: 950 34 35 20 | H54: - | I54: =COUNTIF(Estadísticas!I:I,'centraldecomunicacion.es'!H54)>0 -> FALSE
A55: FONTANERIA INDALICA SL | B55: Fontanero | C55: Calle Encofradores, 10, 04740 Roquetas de Mar, Almería | D55: Roquetas de Mar | E55: Almería | G55: 659 21 41 62 | H55: - | I55: =COUNTIF(Estadísticas!I:I,'centraldecomunicacion.es'!H55)>0 -> FALSE
A56: Fontaneria Moya | B56: Fontanero | C56: Calle Segovia, 19, 04700 El Ejido, Almería | D56: El Ejido | E56: Almería | G56: 670 67 22 70 | H56: - | I56: =COUNTIF(Estadísticas!I:I,'centraldecomunicacion.es'!H56)>0 -> FALSE
A57: Fontanería García &amp; González S.L | B57: Fontanero | C57: Calle Jesus de Perceval, 4, 04700 El Ejido, Almería | D57: El Ejido | E57: Almería | G57: 950 48 58 94 | H57: - | I57: =COUNTIF(Estadísticas!I:I,'centraldecomunicacion.es'!H57)>0 -> FALSE
A58: Fontanero Almería | B58: Fontanero | D58: Abla | F58: fontanero-almeria.com | G58: 655 76 32 18 | H58: info@aquagasalmeria.es | I58: =COUNTIF(Estadísticas!I:I,'centraldecomunicacion.es'!H58)>0 -> FALSE
A59: Fontaneria Cobos | B59: Fontanero | C59: Calle Julio Cortázar, 6, 04720 El Parador de las Hortichuelas, Almería | D59: El Parador de las Hortichuelas | E59: Almería | H59: - | I59: =COUNTIF(Estadísticas!I:I,'centraldecomunicacion.es'!H59)>0 -> FALSE
A60: Servicio de reparaciones y reformas | B60: Fontanero | C60: Paseo de las Acacias, 2, 04720 Aguadulce, Almería | D60: Aguadulce | E60: Almería | G60: 636 84 13 54 | H60: - | I60: =COUNTIF(Estadísticas!I:I,'centraldecomunicacion.es'!H60)>0 -> FALSE
A61: Fontanería Rocío Almería | B61: Fontanero | D61: Abla | F61: fontanero-almeria.com | G61: 654 08 26 70 | H61: info@aquagasalmeria.es | I61: =COUNTIF(Estadísticas!I:I,'centraldecomunicacion.es'!H61)>0 -> FALSE
A62: Multiservicios, fontaneros y cerrajeros | B62: Fontanero | C62: appartamento 14, Calle Campillo del Moro, 1, 04720 Roquetas de Mar, Almería | D62: Roquetas de Mar | E62: Almería | G62: 605 23 44 07 | H62: - | I62: =COUNTIF(Estadísticas!I:I,'centraldecomunicacion.es'!H62)>0 -> FALSE
A63: Fontaneria Cabrera,S.L. | B63: Fontanero | C63: Calle Cangas de Onís, 30, 04740 Roquetas de Mar, Almería | D63: Roquetas de Mar | E63: Almería | H63: - | I63: =COUNTIF(Estadísticas!I:I,'centraldecomunicacion.es'!H63)>0 -> FALSE
A64: Antonio Ferrer Molina | B64: Fontanero | C64: Calle Bº los Navarros, 8, 04745 La Mojonera, Almería | D64: La Mojonera | E64: Almería | G64: 950 33 14 98 | H64: - | I64: =COUNTIF(Estadísticas!I:I,'centraldecomunicacion.es'!H64)>0 -> FALSE
A65: PEYPE FONTANERIA | B65: Fontanero | C65: Calle la Rambla, 6, 04630 Garrucha, Almería | D65: Garrucha | E65: Almería | G65: 950 46 01 38 | H65: - | I65: =COUNTIF(Estadísticas!I:I,'centraldecomunicacion.es'!H65)>0 -> FALSE
A66: Ramón José Rodriguez Cazorla | B66: Fontanero | C66: Calle Rambla del Rey, 1, 04260 Rioja, Almería | D66: Rioja | E66: Almería | G66: 950 00 78 01 | H66: - | I66: =COUNTIF(Estadísticas!I:I,'centraldecomunicacion.es'!H66)>0 -> FALSE
A67: AguaConfort Hydroec S.L. (Tienda en El Ejido) | B67: Tienda de artículos de fontanería | C67: Paraje Tance Nuevo nº117, 04710 Santa María del Águila (El Ejido), Almería | D67: Santa María del Águila | E67: Almería | F67: grupoaguaconfort.com | G67: 950 58 32 40 | H67: core-js-bundle@3.2.1 | I67: =COUNTIF(Estadísticas!I:I,'centraldecomunicacion.es'!H67)>0 -> FALSE
A68: Porras Granada | B68: Tienda de artículos de fontanería | C68: Calle Sierra de Almijara, 1, 04240 Viator, Almería | D68: Viator | E68: Almería | H68: - | I68: =COUNTIF(Estadísticas!I:I,'centraldecomunicacion.es'!H68)>0 -> FALSE
A69: Francisco García González | B69: Fontanero | C69: Calle Andarax, 16, 04745 La Mojonera, Almería | D69: La Mojonera | E69: Almería | H69: - | I69: =COUNTIF(Estadísticas!I:I,'centraldecomunicacion.es'!H69)>0 -> FALSE
A70: Fontanería Quesada | B70: Fontanero | C70: Calle Moratín, 1, 04630 Garrucha, Almería | D70: Garrucha | E70: Almería | F70: fontaneriaquesada.com | G70: 670 66 75 65 | H70: - | I70: =COUNTIF(Estadísticas!I:I,'centraldecomunicacion.es'!H70)>0 -> FALSE
A71: José Salvador Romero | B71: Fontanero | C71: Av. América, 47, 04700 Ejido (El), Almería | D71: El Ejido | E71: Almería | G71: 950 48 60 04 | H71: - | I71: =COUNTIF(Estadísticas!I:I,'centraldecomunicacion.es'!H71)>0 -> FALSE
A72: Fontarboleas | B72: Tienda de artículos de fontanería | C72: Pol.Ind. Los Llanos de Arboleas, s/n. C/ Los Muebles, 04660 Arboleas, Almería | D72: Arboleas | E72: Almería | F72: fontarboleas.es | G72: 950 43 14 15 | H72: web@fontarboleas.es | I72: =COUNTIF(Estadísticas!I:I,'centraldecomunicacion.es'!H72)>0 -> FALSE
A73: FONTANERO ROCIO ALMERIA | B73: Fontanero | D73: Abla | F73: negocio.site | G73: 654 08 26 70 | H73: - | I73: =COUNTIF(Estadísticas!I:I,'centraldecomunicacion.es'!H73)>0 -> FALSE
A74: Fontaneria Martin | B74: Fontanero | C74: Calle Paseo de los Tristes, 38, 04770 Adra, Almería | D74: Adra | E74: Almería | G74: 615 02 26 94 | H74: - | I74: =COUNTIF(Estadísticas!I:I,'centraldecomunicacion.es'!H74)>0 -> FALSE
A75: Suministros Fontbraut SL | B75: Tienda de artículos de fontanería | C75: Polígono industrial la Boquera, 04270 Sorbas, Almería | D75: Sorbas | E75: Almería | G75: 950 06 62 10 | H75: - | I75: =COUNTIF(Estadísticas!I:I,'centraldecomunicacion.es'!H75)>0 -> FALSE
A76: Instalaciones Juframar | B76: Fontanero | C76: Calle Mar de Filipinas, 23, 04770 Adra, Almería | D76: Adra | E76: Almería | G76: 950 56 07 03 | H76: - | I76: =COUNTIF(Estadísticas!I:I,'centraldecomunicacion.es'!H76)>0 -> FALSE
A77: Fontaneria | B77: Fontanero | C77: Calle Fabrica de Conservas, 04770 Adra, Almería | D77: Adra | E77: Almería | H77: - | I77: =COUNTIF(Estadísticas!I:I,'centraldecomunicacion.es'!H77)>0 -> FALSE
A78: Almería AguaConfort S.L. (Tienda en Antas) | B78: Tienda de artículos de fontanería | C78: C/Vente Vacio, nº14 - P.I, Antas, 04628 El Real, Almería | D78: El Real | E78: Almería | F78: grupoaguaconfort.com | G78: 950 39 32 30 | H78: core-js-bundle@3.2.1 | I78: =COUNTIF(Estadísticas!I:I,'centraldecomunicacion.es'!H78)>0 -> FALSE
A79: FONTANERÍA GICER | B79: Fontanero | C79: Las Marianas, 04621 Vera, Almería | D79: Vera | E79: Almería | G79: 677 77 48 95 | H79: - | I79: =COUNTIF(Estadísticas!I:I,'centraldecomunicacion.es'!H79)>0 -> FALSE
A80: Fontanería Viurba | B80: Fontanero | C80: Calle Tarrasa, 0, 04770 Adra, Almería | D80: Adra | E80: Almería | G80: 950 40 11 11 | H80: - | I80: =COUNTIF(Estadísticas!I:I,'centraldecomunicacion.es'!H80)>0 -> FALSE
A81: Sanitarios Emilio Hernandez | B81: Tienda de artículos de fontanería | C81: Carr. de la Mojonera, 3, 35, 04740 Roquetas de Mar, Almería | D81: Roquetas de Mar | E81: Almería | H81: - | I81: =COUNTIF(Estadísticas!I:I,'centraldecomunicacion.es'!H81)>0 -> FALSE
A82: Fontanería Gicer | B82: Fontanero | C82: 04638 Mojácar, Almería | D82: Mojácar | E82: Almería | G82: 677 77 48 95 | H82: - | I82: =COUNTIF(Estadísticas!I:I,'centraldecomunicacion.es'!H82)>0 -> FALSE
A83: Maurice Robert Doucet Burke | B83: Fontanero | C83: Calle Rosal, 6, 04760 Berja, Almería | D83: Berja | E83: Almería | H83: - | I83: =COUNTIF(Estadísticas!I:I,'centraldecomunicacion.es'!H83)>0 -> FALSE
A84: EDUARDO M. Jiménez Bonilla | B84: Fontanero | C84: Calle Isaac Peral, 24, 04700 El Ejido, Almería | D84: El Ejido | E84: Almería | F84: negocio.site | G84: 625 46 97 41 | H84: - | I84: =COUNTIF(Estadísticas!I:I,'centraldecomunicacion.es'!H84)>0 -> FALSE
A85: Fontanería e Instalaciones Luis | B85: Fontanero | C85: 04750 Dalías, Almería | D85: Dalías | E85: Almería | F85: negocio.site | G85: 607 85 62 31 | H85: - | I85: =COUNTIF(Estadísticas!I:I,'centraldecomunicacion.es'!H85)>0 -> FALSE
A86: Fontanería Y Calefacción Francisco Ávila | B86: Fontanero | C86: Calle Constitución, 9, 04628 Antas, Almería | D86: Antas | E86: Almería | G86: 653 85 63 37 | H86: - | I86: =COUNTIF(Estadísticas!I:I,'centraldecomunicacion.es'!H86)>0 -> FALSE
A87: Soemi S.L | B87: Fontanero | C87: Calle Alfonso XIII, 60, 04630 Garrucha, Almería | D87: Garrucha | E87: Almería | G87: 670 63 59 07 | H87: - | I87: =COUNTIF(Estadísticas!I:I,'centraldecomunicacion.es'!H87)>0 -> FALSE
A88: Fuel Sur S.a. | B88: Fontanero | C88: Carr. de la Mojonera, 107, 04716 El Ejido, Almería | D88: El Ejido | E88: Almería | H88: - | I88: =COUNTIF(Estadísticas!I:I,'centraldecomunicacion.es'!H88)>0 -> FALSE
A89: Fontanería y Calefacción Francisco Ávila S.L. | B89: Fontanero | C89: Calle Blas Infante, 27, 04628 Antas, Almería | D89: Antas | E89: Almería | G89: 950 45 35 53 | H89: - | I89: =COUNTIF(Estadísticas!I:I,'centraldecomunicacion.es'!H89)>0 -> FALSE
A90: Fontaneria y desatascos zurano | B90: Fontanero | D90: Abla | F90: fontaneriaydesatascoszurano.es | G90: 647 64 71 31 | H90: a36b86319e6542838a534122c8870e3f@sentry.qdqmedia.com | I90: =COUNTIF(Estadísticas!I:I,'centraldecomunicacion.es'!H90)>0 -> FALSE
A91: Hecam Instaladores | B91: Tienda de artículos de fontanería | C91: Calle Puertas de Lorca, 14, 04820 Vélez-Rubio, Almería | D91: Vélez-Rubio | E91: Almería | G91: 950 41 23 28 | H91: - | I91: =COUNTIF(Estadísticas!I:I,'centraldecomunicacion.es'!H91)>0 -> FALSE
A92: Fontaneros Cádiz 24 horas | B92: Fontanero | C92: Av. del Perú, 14, 11010 Cádiz | D92: Cádiz | E92: Cádiz | F92: fontanerocadiz.info | G92: 620 17 51 31 | H92: - | I92: =COUNTIF(Estadísticas!I:I,'centraldecomunicacion.es'!H92)>0 -> FALSE
A93: FONTACLIMA | B93: Fontanero | C93: Av. Segunda Aguada, 21, 11012 Cádiz | D93: Cádiz | E93: Cádiz | F93: fontaclimacadiz.es | G93: 856 07 36 25 | H93: fontaclima@hotmail.es | I93: =COUNTIF(Estadísticas!I:I,'centraldecomunicacion.es'!H93)>0 -> TRUE
A94: Fontaclima | B94: Fontanero | C94: Brunete, 4, 11008 Cádiz | D94: Cádiz | E94: Cádiz | F94: fontaclimacadiz.es | G94: 956 01 86 00 | H94: - | I94: =COUNTIF(Estadísticas!I:I,'centraldecomunicacion.es'!H94)>0 -> FALSE
A95: Fontanería Fuentes | B95: Fontanero | C95: Calle Valverde, 16, 11004 Cádiz | D95: Cádiz | E95: Cádiz | G95: 956 21 40 55 | H95: - | I95: =COUNTIF(Estadísticas!I:I,'centraldecomunicacion.es'!H95)>0 -> FALSE
A96: Fontaneria y Gas Cabello s,l. | B96: Fontanero | C96: Calle Goya, 13, 11010 Cádiz | D96: Cádiz | E96: Cádiz | F96: fontaneriacabello.es | G96: 856 04 50 21 | H96: tienda@fontanericabello.es | I96: =COUNTIF(Estadísticas!I:I,'centraldecomunicacion.es'!H96)>0 -> FALSE
A97: Fontanería Altamirano | B97: Fontanero | C97: Calle Francisco García de Sola, 10, 11008 Cádiz | D97: Cádiz | E97: Cádiz | F97: fontaneriaaltamirano.es | G97: 956 22 15 87 | H97: altamiranosl@live.com | I97: =COUNTIF(Estadísticas!I:I,'centraldecomunicacion.es'!H97)>0 -> TRUE
A98: Fontanería Andalucía | B98: Tienda de artículos de fontanería | C98: Calle Torre, 43, 11001 Cádiz | D98: Cádiz | E98: Cádiz | G98: 615 07 07 10 | H98: - | I98: =COUNTIF(Estadísticas!I:I,'centraldecomunicacion.es'!H98)>0 -> FALSE
A99: Saneamientos Y Fontanería Flores S L | B99: Fontanero | C99: Calle Manzanares, 4, 11005 Cádiz | D99: Cádiz | E99: Cádiz | G99: 956 25 78 54 | H99: - | I99: =COUNTIF(Estadísticas!I:I,'centraldecomunicacion.es'!H99)>0 -> FALSE
A100: Fontanería Talavera | B100: Fontanero | C100: Calle de la Rosa, 15, 11002 Cádiz | D100: Cádiz | E100: Cádiz | G100: 956 22 95 46 | H100: - | I100: =COUNTIF(Estadísticas!I:I,'centraldecomunicacion.es'!H100)>0 -> FALSE
...

Sheet Estadísticas
A1: Número de empresas | B1: Número de correos electrónicos | C1: Número de webs | D1: Números de teléfono | E1: Números de teléfono fijo | F1: Números de teléfono móvil | G1: Sectores | H1: Mails únicos | I1: Mails verificados
A2: =COUNTIF('centraldecomunicacion.es'!A2:'centraldecomunicacion.es'!A19470,"*") -> 4836 | B2: =COUNTIF('centraldecomunicacion.es'!H2:'centraldecomunicacion.es'!H19470,"*@*") -> 1124 | C2: =COUNTIF('centraldecomunicacion.es'!F2:'centraldecomunicacion.es'!F19470,"*.*") -> 1957 | D2: =COUNTIF('centraldecomunicacion.es'!G2:'centraldecomunicacion.es'!G19470,"6*")+COUNTIF('centraldecomunicacion.es'!G2:'centraldecomunicacion.es'!G19470,"9*") -> 3997 | E2: =COUNTIF('centraldecomunicacion.es'!G2:'centraldecomunicacion.es'!G19470,"9*") -> 2116 | F2: =COUNTIF('centraldecomunicacion.es'!G2:'centraldecomunicacion.es'!G19470,"6*") -> 1881 | G2: {=_xlfn.UNIQUE('centraldecomunicacion.es'!B2:'centraldecomunicacion.es'!B19470)} -> Fontanero | H2: {=_xlfn.UNIQUE('centraldecomunicacion.es'!H2:'centraldecomunicacion.es'!H19470)} -> - | I2: jlorenzofernandez32@gmail.com
G3: Tienda de artículos de fontanería | H3: info@aquagasalmeria.es | I3: cial@rotrisa.com
G4: Fontanería | H4: info@fontaneriaignaciogonzalez.es | I4: rafaellopez@rlopezm.com
G5: 0 | H5: a36b86319e6542838a534122c8870e3f@sentry.qdqmedia.com | I5: servicios@schogar.com
H6: jlorenzofernandez32@gmail.com | I6: fontaclima@hotmail.es
H7: cial@rotrisa.com | I7: altamiranosl@live.com
H8: tinfo@fontaneroszapillo.com | I8: jose.m.sanchez.paya@gmail.com
H9: info@serviciosfernandez.es | I9: suinprosur@suinprosur.es
H10: ventas@valsan.es | I10: desatascosomega@gmail.com
H11: info@grupovico.com | I11: fugascor@gmail.com
H12: Contacto@servicioshogaralmeria.es | I12: esmebra@esmebra.com
H13: core-js-bundle@3.2.1 | I13: fontaneriaygasandalucia@gmail.com
H14: rafaellopez@rlopezm.com | I14: sanealuque@hotmail.com
H15: servicios@schogar.com | I15: canalcor@hotmail.com
H16: web@fontarboleas.es | I16: revestimiento@revestimientosjulio.es
H17: fontaclima@hotmail.es | I17: fontaneroscordoba@gmail.com
... H313: tecnico@fontaneriafontcal.com | I313: fmatiena@euskalnet.net
H314: contacto@fontaneriaycalefaccionguarnizo.com
H315: info@grupodelavega.es
H316: aguasexpert@hotmail.com
H317: briccal@briccal.com
H318: fontaneriamuskiz@gmail.com
H319: alexruizgomez1975@gmail.com
H320: AZCONAFONTANERIA@GMAIL.COM
H321: administracion@dayvo.com
H322: info@fontaneriabizkaia.com
H323: cyfgomezbravo@gmail.com
H324: gpodena@gmail.com
H325: info@masqueduchas.com
... H881: fmatiena@euskalnet.net
H882: 0

Sheet Copyright
A1: Esta base de datos de empresas se encuentra protegida bajo derechos de autor. Está prohibida su copia y reproducción con o sin ánimo de lucro bajo autorización expresa del autor según artículo 270, 270.2, 270.3, 270.4, 270.5, 270.6, 270.7 Como medida de seguridad hay registros clave a modo de firma digital registrados ante notario y ante la consejería de cultura y patrimonio histórico con número GR-00416-2020
