Workbook

Sheet Centraldecomunicacion.es
A1: ﻿Nombre | B1: Categoría | C1: Direccion | D1: Localidad | E1: Provincia | F1: Website | G1: Teléfono | H1: email | I1: mail verificado
A2: Herbolario Ángel | B2: Herbolario | C2: C. José Artés de Arcos, 15, 04004 Almería | D2: Almería | E2: Almería | F2: herbolarioangel.net | G2: 950 26 24 39 | H2: - | I2: =COUNTIF(Estadísticas!I:I,'Centraldecomunicacion.es'!H2)>0 -> FALSE
A3: Herbolario El Agape | B3: Herbolario | C3: C. Granada, 185, 04008 Almería | D3: Almería | E3: Almería | F3: herbolarioelagape.es | G3: 658 93 56 36 | H3: info@herbolarioelagape.es | I3: =COUNTIF(Estadísticas!I:I,'Centraldecomunicacion.es'!H3)>0 -> FALSE
A4: HERBOLARIO DE LORIEN | B4: Herbolario | C4: Av. de Cabo de Gata, 139, 04007 Almería | D4: Almería | E4: Almería | G4: 950 08 83 69 | H4: - | I4: =COUNTIF(Estadísticas!I:I,'Centraldecomunicacion.es'!H4)>0 -> FALSE
A5: Herbolario HIERBA LUISA | B5: Herbolario | C5: C. Juan Leal, 2, 04001 Almería | D5: Almería | E5: Almería | G5: 950 23 98 57 | H5: - | I5: =COUNTIF(Estadísticas!I:I,'Centraldecomunicacion.es'!H5)>0 -> FALSE
A6: Herbolario Alonso | B6: Herbolario | C6: C. el Alcázar, 28, 04006 Almería | D6: Almería | E6: Almería | G6: 657 27 73 16 | H6: - | I6: =COUNTIF(Estadísticas!I:I,'Centraldecomunicacion.es'!H6)>0 -> FALSE
A7: Bio Amapola Amapola | B7: Herbolario | C7: C. Amapola, 11, 04004 Almería | D7: Almería | E7: Almería | G7: 950 25 33 65 | H7: - | I7: =COUNTIF(Estadísticas!I:I,'Centraldecomunicacion.es'!H7)>0 -> FALSE
A8: Herbolario Mirto | B8: Herbolario | C8: C. Perdiz, 15, 04009 Almería | D8: Almería | E8: Almería | G8: 950 03 57 11 | H8: - | I8: =COUNTIF(Estadísticas!I:I,'Centraldecomunicacion.es'!H8)>0 -> FALSE
A9: Herbolario y Estética Natural Azalea Lives | B9: Herbolario | C9: Calle Dr. Giménez Canga Argüelles, 5, 04005 Almería | D9: Almería | E9: Almería | F9: azalealives.com | G9: 611 44 35 64 | H9: Info@azalealives.com | I9: =COUNTIF(Estadísticas!I:I,'Centraldecomunicacion.es'!H9)>0 -> FALSE
A10: Herbolario Almería Natural | B10: Herbolario | C10: Carrera del Mami, 7, 04009 Almería | D10: Almería | E10: Almería | G10: 622 23 96 31 | H10: - | I10: =COUNTIF(Estadísticas!I:I,'Centraldecomunicacion.es'!H10)>0 -> FALSE
A11: Campos de Aloe | B11: Herbolario | C11: Av. de la Estación, 25, 04005 Almería | D11: Almería | E11: Almería | G11: 950 22 63 17 | H11: - | I11: =COUNTIF(Estadísticas!I:I,'Centraldecomunicacion.es'!H11)>0 -> FALSE
A12: Rafael Díaz García | B12: Herbolario | C12: C. Altamira, 9, 04005 Almería | D12: Almería | E12: Almería | G12: 950 26 99 69 | H12: - | I12: =COUNTIF(Estadísticas!I:I,'Centraldecomunicacion.es'!H12)>0 -> FALSE
A13: Herboristeria Casa Elo | B13: Herbolario | C13: Calle Dr. Gregorio Marañón, 10, 04005 Almería | D13: Almería | E13: Almería | G13: 950 25 80 21 | H13: - | I13: =COUNTIF(Estadísticas!I:I,'Centraldecomunicacion.es'!H13)>0 -> FALSE
A14: Herbolario Farmaline | B14: Herbolario | C14: Av. de Cabo de Gata, 115, 04007 Almería | D14: Almería | E14: Almería | F14: business.site | G14: 686 00 72 85 | H14: - | I14: =COUNTIF(Estadísticas!I:I,'Centraldecomunicacion.es'!H14)>0 -> FALSE
A15: HERBOLANIC NATURAL | B15: Herbolario | C15: Av. de Pablo Iglesias, 55, LOCAL, 04003 Almería | D15: Almería | E15: Almería | F15: herbolanic.com | G15: 634 49 37 44 | H15: - | I15: =COUNTIF(Estadísticas!I:I,'Centraldecomunicacion.es'!H15)>0 -> FALSE
A16: onnea concept | B16: Herbolario | C16: C. Benizalón, 3, 04007 Almería | D16: Almería | E16: Almería | G16: 692 91 79 60 | H16: - | I16: =COUNTIF(Estadísticas!I:I,'Centraldecomunicacion.es'!H16)>0 -> FALSE
A17: HERBOLARIO LA MILAGROSA | B17: Herbolario | C17: Ctra.Almeria, Urb.El Cercado, 132, 04230 Huércal de Almería, Almería | D17: Huércal de Almería | E17: Almería | F17: herbolariolamilagrosa.com | G17: 667 63 02 58 | H17: - | I17: =COUNTIF(Estadísticas!I:I,'Centraldecomunicacion.es'!H17)>0 -> FALSE
A18: Virtual Data SLU | B18: Herbolario | C18: Av. de Cabo de Gata, 139, 04007 Almería | D18: Almería | E18: Almería | G18: 950 08 83 69 | H18: - | I18: =COUNTIF(Estadísticas!I:I,'Centraldecomunicacion.es'!H18)>0 -> FALSE
A19: Herbolario | B19: Herbolario | C19: Pl. Antonio de Torres, 7, 04120 La Cañada, Almería | D19: La Cañada | E19: Almería | G19: 950 29 20 61 | H19: - | I19: =COUNTIF(Estadísticas!I:I,'Centraldecomunicacion.es'!H19)>0 -> FALSE
A20: Mar Natura Herbolario | B20: Herbolario | C20: C. Solidaridad, 1, 04130 El Alquián, Almería | D20: El Alquián | E20: Almería | G20: 609 11 76 70 | H20: - | I20: =COUNTIF(Estadísticas!I:I,'Centraldecomunicacion.es'!H20)>0 -> FALSE
A21: HERBOLARIO LA VENTANA NATURAL | B21: Herbolario | C21: Cam. de los Parrales, 338, 04720 Aguadulce, Almería | D21: Aguadulce | E21: Almería | F21: laventananatural.com | G21: 665 53 05 11 | H21: contacto@laventananatural.com | I21: =COUNTIF(Estadísticas!I:I,'Centraldecomunicacion.es'!H21)>0 -> FALSE
A22: Herbolario Mentadulce | B22: Herbolario | C22: Carr de Alicún, 26, 04740 Roquetas de Mar, Almería | D22: Roquetas de Mar | E22: Almería | G22: 950 32 11 57 | H22: - | I22: =COUNTIF(Estadísticas!I:I,'Centraldecomunicacion.es'!H22)>0 -> FALSE
A23: Herbolario Silvestre | B23: Herbolario | C23: C. Manuel Machado, 45, 04740 Roquetas de Mar, Almería | D23: Roquetas de Mar | E23: Almería | G23: 950 32 10 46 | H23: - | I23: =COUNTIF(Estadísticas!I:I,'Centraldecomunicacion.es'!H23)>0 -> FALSE
A24: Parafarmacia Herbolario | B24: Herbolario | C24: C. Carlos Arniches, 04720 El Parador de las Hortichuelas, Almería | D24: El Parador de las Hortichuelas | E24: Almería | G24: 950 34 15 42 | H24: - | I24: =COUNTIF(Estadísticas!I:I,'Centraldecomunicacion.es'!H24)>0 -> FALSE
A25: Herbolario El Jardin De La Salud | B25: Herbolario | C25: Av. Reino de España, 35, 04740 Roquetas de Mar, Almería | D25: Roquetas de Mar | E25: Almería | G25: 950 53 31 26 | H25: - | I25: =COUNTIF(Estadísticas!I:I,'Centraldecomunicacion.es'!H25)>0 -> FALSE
A26: Herboristería, tienda esotérica y artículos de regalo El secreto | B26: Herbolario | C26: Av. de Carlos III, 447, 04720 Aguadulce, Almería | D26: Aguadulce | E26: Almería | G26: 615 98 36 74 | H26: - | I26: =COUNTIF(Estadísticas!I:I,'Centraldecomunicacion.es'!H26)>0 -> FALSE
A27: Bottega Verde | B27: Herbolario | C27: Carretera Roquetas - Alicun, 0 S/N, 04740 Roquetas de Mar, Almería | D27: Roquetas de Mar | E27: Almería | G27: 950 32 95 49 | H27: - | I27: =COUNTIF(Estadísticas!I:I,'Centraldecomunicacion.es'!H27)>0 -> FALSE
A28: Herbolario Jazmín | B28: Herbolario | C28: Av. de las Marinas, 209, 04740 Roquetas de Mar, Almería | D28: Roquetas de Mar | E28: Almería | G28: 630 53 89 82 | H28: - | I28: =COUNTIF(Estadísticas!I:I,'Centraldecomunicacion.es'!H28)>0 -> FALSE
A29: HERBAL PHARMACY | B29: Herbolario | C29: Av. de Juan Bonachera, 24, 04740 Roquetas de Mar, Almería | D29: Roquetas de Mar | E29: Almería | G29: 698 51 29 08 | H29: - | I29: =COUNTIF(Estadísticas!I:I,'Centraldecomunicacion.es'!H29)>0 -> FALSE
A30: Herbolario Almerinatur | B30: Herbolario | C30: C. Fragata, 10, 04711 Almerimar, Almería | D30: Almerimar | E30: Almería | G30: 950 49 78 12 | H30: - | I30: =COUNTIF(Estadísticas!I:I,'Centraldecomunicacion.es'!H30)>0 -> FALSE
A31: Tara Natura | B31: Herbolario | C31: Cjón. de Istria, 38, 04118 San José, Almería | D31: San José | E31: Almería | G31: 669 49 64 13 | H31: - | I31: =COUNTIF(Estadísticas!I:I,'Centraldecomunicacion.es'!H31)>0 -> FALSE
A32: Herbolario Mary | B32: Herbolario | C32: C. Murgis, 15, 04700 El Ejido, Almería | D32: El Ejido | E32: Almería | F32: herbolariomary.es | G32: 950 48 03 63 | H32: info@herbolariomary.es | I32: =COUNTIF(Estadísticas!I:I,'Centraldecomunicacion.es'!H32)>0 -> FALSE
A33: La Botica de Fuen | B33: Herbolario | C33: C. Infanta Elena, 5, 04745 La Mojonera, Almería | D33: La Mojonera | E33: Almería | G33: 950 33 03 84 | H33: - | I33: =COUNTIF(Estadísticas!I:I,'Centraldecomunicacion.es'!H33)>0 -> FALSE
A34: Saica Natur S.L. | B34: Herbolario | C34: Ctra de la Mojonera a San Agustín, 04745 Mojonera (la), Almería | D34: Abla | E34: Almería | G34: 950 60 33 38 | H34: - | I34: =COUNTIF(Estadísticas!I:I,'Centraldecomunicacion.es'!H34)>0 -> FALSE
A35: Herbolario Mary | B35: Herbolario | C35: P.º Alcalde Garcia Acien, 9, 04700 El Ejido, Almería | D35: El Ejido | E35: Almería | F35: herbolariomary.es | G35: 950 48 71 63 | H35: - | I35: =COUNTIF(Estadísticas!I:I,'Centraldecomunicacion.es'!H35)>0 -> FALSE
A36: Herbolario Elisa | B36: Herbolario | C36: C. Gustavo Adolfo Bécquer, 9, 04700 El Ejido, Almería | D36: El Ejido | E36: Almería | F36: herbolarioelisa.com | G36: 950 57 06 85 | H36: - | I36: =COUNTIF(Estadísticas!I:I,'Centraldecomunicacion.es'!H36)>0 -> FALSE
A37: Herboristeria Carmen Ramos | B37: Herbolario | C37: C. Aljibe, 2, 04110 Campohermoso, Almería | D37: Campohermoso | E37: Almería | G37: 627 83 43 41 | H37: - | I37: =COUNTIF(Estadísticas!I:I,'Centraldecomunicacion.es'!H37)>0 -> FALSE
A38: Herbolisteria | B38: Herbolario | C38: Blvr. de el Ejido, 445, 04700 El Ejido, Almería | D38: El Ejido | E38: Almería | H38: - | I38: =COUNTIF(Estadísticas!I:I,'Centraldecomunicacion.es'!H38)>0 -> FALSE
A39: Herbolario Naturdivina Carboneras | B39: Herbolario | C39: C. Plus Ultra, 37, 04140 Carboneras, Almería | D39: Carboneras | E39: Almería | G39: 693 69 08 55 | H39: - | I39: =COUNTIF(Estadísticas!I:I,'Centraldecomunicacion.es'!H39)>0 -> FALSE
A40: herbolario la Jara de Ana | B40: Herbolario | C40: parque comercial Mojácar playa local bajo, 4, 04638 Mojácar, Almería | D40: Mojácar | E40: Almería | G40: 950 47 25 59 | H40: - | I40: =COUNTIF(Estadísticas!I:I,'Centraldecomunicacion.es'!H40)>0 -> FALSE
A41: Herbolario &quot;Las Buenas Hierbas&quot; | B41: Herbolario | C41: Av. Guillermo Reyna, S/N, 04600 Huércal-Overa, Almería | D41: Huércal-Overa | E41: Almería | G41: 950 13 48 17 | H41: - | I41: =COUNTIF(Estadísticas!I:I,'Centraldecomunicacion.es'!H41)>0 -> FALSE
A42: Herbolario Azahar | B42: Herbolario | C42: Calle Carlos Cano, 1, 04620 Vera, Almería | D42: Vera | E42: Almería | G42: 699 45 77 07 | H42: - | I42: =COUNTIF(Estadísticas!I:I,'Centraldecomunicacion.es'!H42)>0 -> FALSE
A43: Ecotienda Ganesha | B43: Herbolario | C43: C. Angustias, 04620 Vera, Almería | D43: Vera | E43: Almería | G43: 630 35 28 55 | H43: - | I43: =COUNTIF(Estadísticas!I:I,'Centraldecomunicacion.es'!H43)>0 -> FALSE
A44: Trinidad Parra Castellón | B44: Herbolario | C44: Av. Guillermo Reyna, 0, 04600 Huércal-Overa, Almería | D44: Huércal-Overa | E44: Almería | G44: 950 13 48 17 | H44: - | I44: =COUNTIF(Estadísticas!I:I,'Centraldecomunicacion.es'!H44)>0 -> FALSE
A45: Herbolario / Parafarmacia Life | B45: Herbolario | C45: Calle Mayor, 5, 04630 Garrucha, Almería | D45: Garrucha | E45: Almería | F45: herbolariolife.es | G45: 950 13 37 59 | H45: - | I45: =COUNTIF(Estadísticas!I:I,'Centraldecomunicacion.es'!H45)>0 -> FALSE
A46: Pharmaherbal | B46: Herbolario | C46: C. Santiago, 1, Local 3, 04860 Olula del Río, Almería | D46: Olula del Río | E46: Almería | F46: pharmaherbal.es | G46: 609 95 25 20 | H46: info@pharmaherbal.es | I46: =COUNTIF(Estadísticas!I:I,'Centraldecomunicacion.es'!H46)>0 -> FALSE
A47: Herbolario Manos Que Sanan | B47: Herbolario | C47: C. El Arenal, 04638, Almería | D47: Vista de los Ángeles-Rumina | E47: Almería | G47: 607 11 03 43 | H47: - | I47: =COUNTIF(Estadísticas!I:I,'Centraldecomunicacion.es'!H47)>0 -> FALSE
A48: Parafarmacia Serma | B48: Herbolario | C48: P.º del Huerto, 21, 04628 Antas, Almería | D48: Antas | E48: Almería | G48: 950 61 90 97 | H48: - | I48: =COUNTIF(Estadísticas!I:I,'Centraldecomunicacion.es'!H48)>0 -> FALSE
A49: FEPSA GLOBAL SA | B49: Herbolario | C49: CALLE LOS IBEROS, 13, 04769 Berja, Almería | D49: Berja | E49: Almería | G49: 950 49 00 65 | H49: - | I49: =COUNTIF(Estadísticas!I:I,'Centraldecomunicacion.es'!H49)>0 -> FALSE
A50: Mandragora Herbolario | B50: Herbolario | C50: C. Agua del Albayzín, 27, 18010 Granada | D50: Granada | E50: Granada | G50: 627 06 28 48 | H50: - | I50: =COUNTIF(Estadísticas!I:I,'Centraldecomunicacion.es'!H50)>0 -> FALSE
A51: Herbolario Sierra Nevada | B51: Herbolario | C51: Av. de la Alpujarra, 35, 18420 Lanjarón, Granada | D51: Lanjarón | E51: Granada | G51: 958 77 22 45 | H51: - | I51: =COUNTIF(Estadísticas!I:I,'Centraldecomunicacion.es'!H51)>0 -> FALSE
A52: Herbolario Antonia | B52: Herbolario | C52: C. Almería, 31, 18360 Huétor Tájar, Granada | D52: Huétor Tájar | E52: Granada | G52: 619 36 89 57 | H52: - | I52: =COUNTIF(Estadísticas!I:I,'Centraldecomunicacion.es'!H52)>0 -> FALSE
A53: Ecobarrio Herbolario | B53: Herbolario | C53: C. Joaquina Eguaras, 84, 18013 Granada | D53: Granada | E53: Granada | G53: 958 96 36 14 | H53: - | I53: =COUNTIF(Estadísticas!I:I,'Centraldecomunicacion.es'!H53)>0 -> FALSE
A54: Herbolario | B54: Herbolario | C54: Plaza Constutucion, 11, 18670 Vélez de Benaudalla, Granada | D54: Vélez de Benaudalla | E54: Granada | G54: 958 65 80 26 | H54: - | I54: =COUNTIF(Estadísticas!I:I,'Centraldecomunicacion.es'!H54)>0 -> FALSE
A55: Herbolario Naturana | B55: Herbolario | C55: C. Parras, 6, 23160 Los Villares, Jaén | D55: Los Villares | E55: Jaén | G55: 669 62 30 05 | H55: - | I55: =COUNTIF(Estadísticas!I:I,'Centraldecomunicacion.es'!H55)>0 -> FALSE
A56: Herbolario Soria Natural GC Priego | B56: Herbolario | C56: C. San Luis, 13, 14800 Priego de Córdoba, Córdoba | D56: Priego de Córdoba | E56: Córdoba | G56: 957 70 19 90 | H56: - | I56: =COUNTIF(Estadísticas!I:I,'Centraldecomunicacion.es'!H56)>0 -> FALSE
A57: Sanodiet Herbolario-Parafarmacia. | B57: Herbolario | C57: C. Almería, nº2, local, 41200 Alcalá del Río, Sevilla | D57: Alcalá del Río | E57: Sevilla | F57: sanodiet.com | G57: 621 21 67 32 | H57: su@email.com | I57: =COUNTIF(Estadísticas!I:I,'Centraldecomunicacion.es'!H57)>0 -> FALSE
A58: Centro dietético Víquez- Herbolario Cadiz | B58: Herbolario | C58: Av. Ana de Viya, 9, 11009 Cádiz | D58: Cádiz | E58: Cádiz | F58: centrodieteticoviquez.com | G58: 856 07 57 91 | H58: info@centrodieteticoviquez.com | I58: =COUNTIF(Estadísticas!I:I,'Centraldecomunicacion.es'!H58)>0 -> FALSE
A59: La Mandrágora Herbolario | B59: Herbolario | C59: C. Feduchy, 16, 11005 Cádiz | D59: Cádiz | E59: Cádiz | G59: 956 28 25 28 | H59: - | I59: =COUNTIF(Estadísticas!I:I,'Centraldecomunicacion.es'!H59)>0 -> FALSE
A60: Herbolario Edén | B60: Herbolario | C60: C. Corneta Soto Guerrero, 6, 11004 Cádiz | D60: Cádiz | E60: Cádiz | G60: 956 21 38 49 | H60: - | I60: =COUNTIF(Estadísticas!I:I,'Centraldecomunicacion.es'!H60)>0 -> FALSE
A61: Herbolario Víquez - Cadiz | B61: Herbolario | C61: Av. Segunda Aguada, 15, 11012 Cádiz | D61: Cádiz | E61: Cádiz | F61: centrodieteticoviquez.com | G61: 856 07 57 65 | H61: info@centrodieteticoviquez.com | I61: =COUNTIF(Estadísticas!I:I,'Centraldecomunicacion.es'!H61)>0 -> FALSE
A62: Biogadir | B62: Herbolario | C62: C. Zurbarán, 2, Local 2, 11010 Cádiz | D62: Cádiz | E62: Cádiz | G62: 695 14 82 40 | H62: - | I62: =COUNTIF(Estadísticas!I:I,'Centraldecomunicacion.es'!H62)>0 -> FALSE
A63: La ventana natural | B63: Herbolario | C63: Av. San Severiano, 12, 11007 Cádiz | D63: Cádiz | E63: Cádiz | F63: laventananatural.com | G63: 956 77 72 06 | H63: contacto@laventananatural.com | I63: =COUNTIF(Estadísticas!I:I,'Centraldecomunicacion.es'!H63)>0 -> FALSE
A64: Herbolario Titi &amp; Carpi | B64: Herbolario | C64: 11005 Cádiz | D64: Cádiz | E64: Cádiz | G64: 622 69 62 24 | H64: - | I64: =COUNTIF(Estadísticas!I:I,'Centraldecomunicacion.es'!H64)>0 -> FALSE
A65: Herbolario La Valeriana | B65: Herbolario | C65: Calle de la Pl., 80, 11510 El Pinar, Cádiz | D65: Puerto Real | E65: Cádiz | H65: - | I65: =COUNTIF(Estadísticas!I:I,'Centraldecomunicacion.es'!H65)>0 -> FALSE
A66: Herbolarioa la Jara | B66: Herbolario | C66: C. Benjamín López, 14, 11100 San Fernando, Cádiz | D66: San Fernando | E66: Cádiz | G66: 956 59 54 74 | H66: - | I66: =COUNTIF(Estadísticas!I:I,'Centraldecomunicacion.es'!H66)>0 -> FALSE
A67: Herbolario Ismael | B67: Herbolario | C67: C. San Rafael, 80, LOCAL, 11100 San Fernando, Cádiz | D67: San Fernando | E67: Cádiz | G67: 956 59 13 47 | H67: - | I67: =COUNTIF(Estadísticas!I:I,'Centraldecomunicacion.es'!H67)>0 -> FALSE
A68: La Ventana Natural | B68: Herbolario | C68: C. Rosario, 28, 11100 San Fernando, Cádiz | D68: San Fernando | E68: Cádiz | F68: laventananatural.com | G68: 956 59 13 89 | H68: contacto@laventananatural.com | I68: =COUNTIF(Estadísticas!I:I,'Centraldecomunicacion.es'!H68)>0 -> FALSE
A69: Bevate | B69: Herbolario | C69: Calle de la Pl., 52, 11510 Puerto Real, Cádiz | D69: Puerto Real | E69: Cádiz | F69: herbolariobevate.com | G69: 677 68 16 55 | H69: - | I69: =COUNTIF(Estadísticas!I:I,'Centraldecomunicacion.es'!H69)>0 -> FALSE
A70: Herbolario la Argentina 2 | B70: Herbolario | C70: C. Manuel Álvaro Bonet, 1, 11500 El Puerto de Sta María, Cádiz | D70: El Puerto de Sta María | E70: Cádiz | G70: 956 85 95 91 | H70: - | I70: =COUNTIF(Estadísticas!I:I,'Centraldecomunicacion.es'!H70)>0 -> FALSE
A71: Herbolario Tetería Vida Sana | B71: Herbolario | C71: local 12 de Sta María, C. Rodrigo de Bastidas, 1, 11500 El Puerto de Sta María, Cádiz | D71: El Puerto de Sta María | E71: Cádiz | F71: herbolariovidasana.com | G71: 956 85 46 14 | H71: info@amanecerdedia.com | I71: =COUNTIF(Estadísticas!I:I,'Centraldecomunicacion.es'!H71)>0 -> FALSE
A72: Celia Cabaña Jiménez | B72: Herbolario | C72: C. Santo Domingo, 9, 11510 Puerto Real, Cádiz | D72: Puerto Real | E72: Cádiz | G72: 956 83 03 38 | H72: - | I72: =COUNTIF(Estadísticas!I:I,'Centraldecomunicacion.es'!H72)>0 -> FALSE
A73: La Despensa de Gaia | B73: Herbolario | C73: Av. de los Toreros, 9, 11500 El Puerto de Sta María, Cádiz | D73: El Puerto de Sta María | E73: Cádiz | F73: ladespensadegaia.com | G73: 600 68 19 83 | H73: contacto@ladespensadegaia.com | I73: =COUNTIF(Estadísticas!I:I,'Centraldecomunicacion.es'!H73)>0 -> FALSE
A74: Salud Natural Herbolario | B74: Herbolario | C74: Av. Valdecarretas, 1, 11520 Rota, Cádiz | D74: Rota | E74: Cádiz | F74: herbolariossaludnatural.es | G74: 956 75 01 20 | H74: - | I74: =COUNTIF(Estadísticas!I:I,'Centraldecomunicacion.es'!H74)>0 -> FALSE
A75: Herbolario La Flor de Vida | B75: Herbolario | C75: C. Segismundo Moret, 19, 11130 Chiclana de la Frontera, Cádiz | D75: Chiclana de la Frontera | E75: Cádiz | F75: herbolariolaflordevida.com | G75: 956 40 15 98 | H75: - | I75: =COUNTIF(Estadísticas!I:I,'Centraldecomunicacion.es'!H75)>0 -> FALSE
A76: Herboristeria La Milagrosa | B76: Herbolario | C76: C. Larga, 14, 11130 Chiclana de la Frontera, Cádiz | D76: Chiclana de la Frontera | E76: Cádiz | G76: 607 64 99 48 | H76: - | I76: =COUNTIF(Estadísticas!I:I,'Centraldecomunicacion.es'!H76)>0 -> FALSE
A77: Farmacia M.ª Josefa Martínez Guerra | B77: Herbolario | C77: San Bartolomé, 35, 11500 El Puerto de Sta María, Cádiz | D77: El Puerto de Sta María | E77: Cádiz | G77: 956 85 41 31 | H77: - | I77: =COUNTIF(Estadísticas!I:I,'Centraldecomunicacion.es'!H77)>0 -> FALSE
A78: Con un toque de canela | B78: Herbolario | C78: C. Carmen Picazo, 12, 11130 Chiclana de la Frontera, Cádiz | D78: Chiclana de la Frontera | E78: Cádiz | G78: 647 22 58 76 | H78: - | I78: =COUNTIF(Estadísticas!I:I,'Centraldecomunicacion.es'!H78)>0 -> FALSE
A79: HERBORISTERIA FUENTE AMARGA | B79: Herbolario | C79: Av. de Fuente Amarga, 47, 11130 Chiclana de la Frontera, Cádiz | D79: Chiclana de la Frontera | E79: Cádiz | G79: 656 37 20 09 | H79: - | I79: =COUNTIF(Estadísticas!I:I,'Centraldecomunicacion.es'!H79)>0 -> FALSE
A80: Vida mas Sana | B80: Herbolario | C80: Calle Dr. Duarte Acosta, 7, 11500 El Puerto de Sta María, Cádiz | D80: El Puerto de Sta María | E80: Cádiz | F80: vidamassana.com | G80: 956 11 20 04 | H80: info@vidamassana.com | I80: =COUNTIF(Estadísticas!I:I,'Centraldecomunicacion.es'!H80)>0 -> FALSE
A81: Ynsadiet S A | B81: Herbolario | C81: Carretera Cádiz Algeciras, 0 Km 0003 6, 11130 Chiclana de la Frontera, Cádiz | D81: Chiclana de la Frontera | E81: Cádiz | H81: - | I81: =COUNTIF(Estadísticas!I:I,'Centraldecomunicacion.es'!H81)>0 -> FALSE
A82: El Brote Verde | B82: Herbolario | C82: C. Ganado, 43, 11500 El Puerto de Sta María, Cádiz | D82: El Puerto de Sta María | E82: Cádiz | G82: 618 06 22 61 | H82: - | I82: =COUNTIF(Estadísticas!I:I,'Centraldecomunicacion.es'!H82)>0 -> FALSE
A83: La Ventana Natural Chiclana | B83: Herbolario | C83: Ctra. nacional 340, km. 3.6, Eroski local 12, 11130 Chiclana de la Frontera, Cádiz | D83: Chiclana de la Frontera | E83: Cádiz | F83: laventananatural.com | G83: 956 53 67 61 | H83: contacto@laventananatural.com | I83: =COUNTIF(Estadísticas!I:I,'Centraldecomunicacion.es'!H83)>0 -> FALSE
A84: Rocio Gonzalez Baena | B84: Herbolario | C84: C. Larga, 14, 11130 Chiclana de la Frontera, Cádiz | D84: Chiclana de la Frontera | E84: Cádiz | G84: 956 40 08 56 | H84: - | I84: =COUNTIF(Estadísticas!I:I,'Centraldecomunicacion.es'!H84)>0 -> FALSE
A85: Las plantas de la Sierra | B85: Herbolario | C85: Cjón. de los Frailes, 7, 11130 Chiclana de la Frontera, Cádiz | D85: Chiclana de la Frontera | E85: Cádiz | G85: 956 40 60 88 | H85: - | I85: =COUNTIF(Estadísticas!I:I,'Centraldecomunicacion.es'!H85)>0 -> FALSE
A86: Santiveri | B86: Herbolario | C86: C. la Pl., 19, 11130 Chiclana de la Frontera, Cádiz | D86: Chiclana de la Frontera | E86: Cádiz | F86: santiveri.es | G86: 956 40 45 52 | H86: informacion@santiveri.es | I86: =COUNTIF(Estadísticas!I:I,'Centraldecomunicacion.es'!H86)>0 -> FALSE
A87: San Telmo Integral S.L. | B87: Herbolario | C87: C. Ayala, 0, 11130 Chiclana de la Frontera, Cádiz | D87: Chiclana de la Frontera | E87: Cádiz | G87: 956 40 00 34 | H87: - | I87: =COUNTIF(Estadísticas!I:I,'Centraldecomunicacion.es'!H87)>0 -> FALSE
A88: Daniel Ramón Sampietro Alleman | B88: Herbolario | C88: Callejón Huerta Rosario, 0 S/N, 11130 Chiclana de la Frontera, Cádiz | D88: Chiclana de la Frontera | E88: Cádiz | G88: 956 40 60 88 | H88: - | I88: =COUNTIF(Estadísticas!I:I,'Centraldecomunicacion.es'!H88)>0 -> FALSE
A89: Cien Por Cien Natural S.L. | B89: Herbolario | C89: Lugar Urbanización Coto de la Campa, 0, 11139, Cádiz | D89: Chiclana de la Frontera | E89: Cádiz | G89: 956 49 48 23 | H89: - | I89: =COUNTIF(Estadísticas!I:I,'Centraldecomunicacion.es'!H89)>0 -> FALSE
A90: Herbolario Verde Esperanza | B90: Herbolario | C90: Av. de la Música, 17, 11140 Conil de la Frontera, Cádiz | D90: Conil de la Frontera | E90: Cádiz | F90: herbolarioverdeesperanza.es | G90: 621 23 21 12 | H90: - | I90: =COUNTIF(Estadísticas!I:I,'Centraldecomunicacion.es'!H90)>0 -> FALSE
A91: Herboristería Jucar | B91: Herbolario | C91: Avd. Cruz Roja s/n. CC Merca 80 San Benito Local 20-21, 11407 Jerez de la Frontera, Cádiz | D91: Jerez de la Frontera | E91: Cádiz | G91: 956 31 24 58 | H91: - | I91: =COUNTIF(Estadísticas!I:I,'Centraldecomunicacion.es'!H91)>0 -> FALSE
A92: HERBORISTERIA LOS NARANJOS | B92: Herbolario | C92: Pl. los Naranjos, 4, 11404 Jerez de la Frontera, Cádiz | D92: Jerez de la Frontera | E92: Cádiz | G92: 615 85 00 45 | H92: - | I92: =COUNTIF(Estadísticas!I:I,'Centraldecomunicacion.es'!H92)>0 -> FALSE
A93: Salud Natural Herbolario | B93: Herbolario | C93: C. Nao San Antonio, 3, 11540 Sanlúcar de Barrameda, Cádiz | D93: Sanlúcar de Barrameda | E93: Cádiz | F93: herbolariossaludnatural.es | G93: 856 10 23 96 | H93: info@saludnaturalparati.com | I93: =COUNTIF(Estadísticas!I:I,'Centraldecomunicacion.es'!H93)>0 -> FALSE
A94: Herboristería La La | B94: Herbolario | C94: C. Bizcocheros, 10, 11402 Jerez de la Frontera, Cádiz | D94: Jerez de la Frontera | E94: Cádiz | G94: 670 56 97 08 | H94: - | I94: =COUNTIF(Estadísticas!I:I,'Centraldecomunicacion.es'!H94)>0 -> FALSE
A95: Edoras Ilimitado | B95: Herbolario | C95: Ctra.Almeria, Urb.El Cercado, 132, 04230 Huércal de Almería, Almería | D95: Huércal de Almería | E95: Almería | F95: herbolariolamilagrosa.com | G95: 667 63 02 58 | H95: - | I95: =COUNTIF(Estadísticas!I:I,'Centraldecomunicacion.es'!H95)>0 -> FALSE
A96: Centro Natural Abora | B96: Herbolario | C96: Local 1, C. Grecia, 5, 11408 Jerez de la Frontera, Cádiz | D96: Jerez de la Frontera | E96: Cádiz | G96: 956 03 63 00 | H96: - | I96: =COUNTIF(Estadísticas!I:I,'Centraldecomunicacion.es'!H96)>0 -> FALSE
A97: Natura Janda - Herbolario Conil | B97: Herbolario | C97: C. Vendimiadores, 7, 11140 Conil de la Frontera, Cádiz | D97: Conil de la Frontera | E97: Cádiz | G97: 956 44 33 73 | H97: - | I97: =COUNTIF(Estadísticas!I:I,'Centraldecomunicacion.es'!H97)>0 -> FALSE
A98: EcoVerdeEsperanza | B98: Herbolario | C98: Av. de la Música, 17, 11140 Conil de la Frontera, Cádiz | D98: Conil de la Frontera | E98: Cádiz | G98: 652 64 87 14 | H98: - | I98: =COUNTIF(Estadísticas!I:I,'Centraldecomunicacion.es'!H98)>0 -> FALSE
A99: Herboristería Jucar | B99: Herbolario | C99: Avd. Europa s/n. CC Jerez Norte, Local 34, 11405 Jerez de la Frontera, Cádiz | D99: Jerez de la Frontera | E99: Cádiz | G99: 956 30 78 73 | H99: - | I99: =COUNTIF(Estadísticas!I:I,'Centraldecomunicacion.es'!H99)>0 -> FALSE
A100: Herbolario Mundo Holístico | B100: Herbolario | C100: C. Chiclana, 62, 11140 Conil de la Frontera, Cádiz | D100: Conil de la Frontera | E100: Cádiz | G100: 669 31 11 92 | H100: - | I100: =COUNTIF(Estadísticas!I:I,'Centraldecomunicacion.es'!H100)>0 -> FALSE
...

Sheet Estadísticas
A1: Número de empresas | B1: Número de correos electrónicos | C1: Número de webs | D1: Números de teléfono | E1: Números de teléfono fijo | F1: Números de teléfono móvil | G1: Sectores | H1: Mails únicos | I1: Mails verificados
A2: =COUNTIF('Centraldecomunicacion.es'!A2:'Centraldecomunicacion.es'!A19470,"*") -> 2271 | B2: =COUNTIF('Centraldecomunicacion.es'!H2:'Centraldecomunicacion.es'!H19470,"*@*") -> 580 | C2: =COUNTIF('Centraldecomunicacion.es'!F2:'Centraldecomunicacion.es'!F19470,"*.*") -> 856 | D2: =COUNTIF('Centraldecomunicacion.es'!G2:'Centraldecomunicacion.es'!G19470,"6*")+COUNTIF('Centraldecomunicacion.es'!G2:'Centraldecomunicacion.es'!G19470,"9*") -> 2057 | E2: =COUNTIF('Centraldecomunicacion.es'!G2:'Centraldecomunicacion.es'!G19470,"9*") -> 1608 | F2: =COUNTIF('Centraldecomunicacion.es'!G2:'Centraldecomunicacion.es'!G19470,"6*") -> 449 | G2: {=_xlfn.UNIQUE('Centraldecomunicacion.es'!B2:'Centraldecomunicacion.es'!B19470)} -> Herbolario | H2: {=_xlfn.UNIQUE('Centraldecomunicacion.es'!H2:'Centraldecomunicacion.es'!H19470)} -> - | I2: santiverialgeciras@gmail.com
G3: 0 | H3: info@herbolarioelagape.es | I3: mundoherbolariocordoba@gmail.com
H4: Info@azalealives.com | I4: service.consommateur@daregal.fr
H5: contacto@laventananatural.com | I5: herbolariomontoro@casmasalud.es
H6: info@herbolariomary.es | I6: pedidos@aceitesansorena.com
H7: info@pharmaherbal.es | I7: granadiet@granadiet.com
H8: su@email.com | I8: herbolarioespacionatura@gmail.com
H9: info@centrodieteticoviquez.com | I9: herbolariolaspezia@gmail.com
H10: info@amanecerdedia.com | I10: franciscojose.moreno@gmail.com
H11: contacto@ladespensadegaia.com | I11: natural@herbolariomadrenaturaleza.com
H12: info@vidamassana.com | I12: centrointernacionaldedietetica@gmail.com
H13: informacion@santiveri.es | I13: mercado@zurcanatural.com
H14: info@saludnaturalparati.com | I14: marisolesencia@gmail.com
H15: support@webnode.es | I15: mapielena@hotmail.com
... H102: ceresherbal@hotmail.com | I102: bizilegorreta@gmail.com
H103: info@herbolariosdoemi.com
H104: info@anemonaherbolario.com
H105: boticadecarmenoviedo@gmail.com
H106: herbosura@gmail.com
H107: herboristeriarobledo@hotmail.com
H108: info@dieteticoastur.com
H109: info@hierbabuenadiet.com
H110: info@herbolarioelxabu.com
H111: sanabel@sanabel.com.es
H112: eltilar@herbolarioeltilar.com
H113: press@google.com
H114: info@plantasanagijon.com
... H392: info@amalurbelardenda.com
H393: 0

Sheet Copyright
A1: Esta base de datos de empresas se encuentra protegida bajo derechos de autor. Está prohibida su copia y reproducción con o sin ánimo de lucro bajo autorización expresa del autor según artículo 270, 270.2, 270.3, 270.4, 270.5, 270.6, 270.7 Como medida de seguridad hay registros clave a modo de firma digital registrados ante notario y ante la consejería de cultura y patrimonio histórico con número GR-00416-2020

Sheet Leads verificados
A1: ﻿Nombre | B1: Categoría | C1: Direccion | D1: Localidad | E1: Provincia | F1: Website | G1: Teléfono | H1: email | I1: mail verificado
A2: SANTIVERI | B2: Herbolario | C2: C. Alfonso XI, 15, BAJO, 11201 Algeciras, Cádiz | D2: Algeciras | E2: Cádiz | F2: santiverialgeciras.com | G2: 956 66 39 67 | H2: santiverialgeciras@gmail.com | I2: TRUE
A3: Mundo Herbolario | B3: Herbolario | C3: Calle Isla Formentera &amp;, Gta. Amadora, 14011 Córdoba | D3: Córdoba | E3: Córdoba | F3: mundoherbolariocordoba.es | G3: 957 04 35 37 | H3: mundoherbolariocordoba@gmail.com | I3: TRUE
A4: Darégal | B4: Herbolario | C4: Carretera Aldea Quintana Puente Genil, 0 Km 42 5 ( A-379 ), 14546 Santaella, Córdoba | D4: Santaella | E4: Córdoba | F4: daregal.fr | G4: 957 31 33 55 | H4: service.consommateur@daregal.fr | I4: TRUE
A5: Herbolario CasmaSalud | B5: Herbolario | C5: C. Cervantes, 17, Local Izqda, 14600 Montoro, Córdoba | D5: Montoro | E5: Córdoba | F5: casmasalud.es | G5: 957 16 24 15 | H5: herbolariomontoro@casmasalud.es | I5: TRUE
A6: ACEITES ANSORENA &amp; ASOC. S.L. | B6: Herbolario | C6: C. del Aceite, 7, 14850 Baena, Córdoba | D6: Baena | E6: Córdoba | F6: aceitesansorena.com | G6: 957 67 05 84 | H6: pedidos@aceitesansorena.com | I6: TRUE
A7: Herbolarios Granadiet Martínez Campos | B7: Herbolario | C7: C. Martínez Campos, nº11, 18002 Granada | D7: Granada | E7: Granada | F7: granadiet.com | G7: 958 08 22 72 | H7: granadiet@granadiet.com | I7: TRUE
A8: Espacio Natura Herbolario | B8: Herbolario | C8: Calle Dr. Barraquer, 1, 3, 18220 Albolote, Granada | D8: Albolote | E8: Granada | F8: espacionaturaherbolario.com | G8: 958 04 23 38 | H8: herbolarioespacionatura@gmail.com | I8: TRUE
A9: El Herbolario la Spezia | B9: Herbolario | C9: C. de la Cárcel, 4, 18230 Atarfe, Granada | D9: Atarfe | E9: Granada | F9: elherbolarionatural.es | G9: 670 06 54 86 | H9: herbolariolaspezia@gmail.com | I9: TRUE
A10: Herbolario &quot;Equinácea&quot; | B10: Herbolario | C10: C. Berdigón, 18, 21003 Huelva | D10: Huelva | E10: Huelva | F10: herbolarioequinacea.com | G10: 959 24 68 84 | H10: franciscojose.moreno@gmail.com | I10: TRUE
A11: HERBOLARIO MADRE NATURALEZA- ISLA CHICA HUELVA | B11: Herbolario | C11: Isla Chica enfrente del Bar San Ramón, C. Manuel Sánchez, 13, 21006 Huelva | D11: Huelva | E11: Huelva | F11: herbolariomadrenaturaleza.com | G11: 641 79 43 85 | H11: natural@herbolariomadrenaturaleza.com | I11: TRUE
A12: Centro Internacional de Dietética | B12: Herbolario | C12: C. Niebla, 1, BAJO, 21007 Huelva | D12: Huelva | E12: Huelva | F12: centrointernacionaldedietetica.com | G12: 959 22 20 48 | H12: centrointernacionaldedietetica@gmail.com | I12: TRUE
A13: ZURCA Mercado Natural. ✅ Tienda de Productos Ecológicos. Herbolario. | B13: Herbolario | C13: Av. del Mediterráneo, 119, A, 29730 Rincón de la Victoria, Málaga | D13: Rincón de la Victoria | E13: Málaga | F13: zurcanatural.com | G13: 657 32 31 34 | H13: mercado@zurcanatural.com | I13: TRUE
... A28: HERBOLARIO GAROE | B28: Herbolario | C28: Multicentro Club, Av. Juan Carlos I, 6, 38650 Los Cristianos, Santa Cruz de Tenerife | D28: Los Cristianos | E28: Santa Cruz de Tenerife | F28: herbolariogaroe.com | G28: 922 75 20 71 | H28: herbolariogaroe@hotmail.es | I28: TRUE
A29: El Camino The Way Herbolario Online | B29: Herbolario | D29: Adeje | F29: elcaminotheway.shop | H29: THEWAY.2020PARAFARMACIAHERBOLARIO@HOTMAIL.COM | I29: TRUE
A30: Herbolario Nueva Luna | B30: Herbolario | C30: Av. San Francisco, 6, 38650 Los Cristianos, Santa Cruz de Tenerife | D30: Los Cristianos | E30: Santa Cruz de Tenerife | F30: herbolariosenloscristianos.com | G30: 922 78 99 90 | H30: pibotto@hotmail.com | I30: TRUE
A31: HERBALIFE. Dist.Independiente en Tenerife | B31: Herbolario | C31: Calle del Dr. Ingram, 8, 38400 Puerto de la Cruz, Santa Cruz de Tenerife | D31: Puerto de la Cruz | E31: Santa Cruz de Tenerife | F31: mantentufigura.com | G31: 637 27 46 23 | H31: cbherbal@hotmail.com | I31: TRUE
A32: Herbolario Salud y Belleza | B32: Herbolario | C32: TF-28, 115, 38626 Valle de San Lorenzo, Santa Cruz de Tenerife | D32: Valle de San Lorenzo | E32: Santa Cruz de Tenerife | F32: saludybellezatenerife.es | G32: 922 72 23 78 | H32: esperanzabergaz@hotmail.com | I32: TRUE
A33: Salud en Casa! | B33: Herbolario | C33: San Isidro 6, 38611 San Isidro, Santa Cruz de Tenerife | D33: San Isidro | E33: Santa Cruz de Tenerife | F33: saludencasa.ueniweb.com | G33: 633 77 01 43 | H33: antonia_crespo_martin@hotmail.com | I33: TRUE
A34: Herbolario Jeler | B34: Herbolario | C34: C. la Industria, 5, 39610 Astillero, Cantabria | D34: Astillero | E34: Cantabria | F34: herbolariojeler.com | G34: 942 54 27 24 | H34: maite.terapiasnaturales@hotmail.com | I34: TRUE
A35: Azu Factoría Natural | B35: Herbolario | C35: Bo. las Escuelas, 17, B, 39608 Igollo de Camargo, Cantabria | D35: Igollo de Camargo | E35: Cantabria | F35: azufactorianatural.com | G35: 608 27 63 56 | H35: Factorianatural@gmail.com | I35: TRUE
A36: Herbolario Mayor | B36: Herbolario | C36: C. Mayor, 40, 02002 Albacete | D36: Albacete | E36: Albacete | F36: ecoherbolariomayor.com | G36: 967 18 92 86 | H36: tienda@ecoherbolariomayor.com | I36: TRUE
A37: HERBOLARIO SOL Y TIERRA | B37: Herbolario | C37: C. de Alarcos, 13, 13001 Ciudad Real, Cdad. Real | D37: Ciudad Real | E37: Cdad. Real | F37: herbolariosolytierra.es | G37: 926 21 13 98 | H37: tiendaonline@herbolariosolytierra.es | I37: TRUE
A38: Herbolario Puertovera | B38: Herbolario | C38: C. Alejandro Prieto, 10, 13500 Puertollano, Cdad. Real | D38: Puertollano | E38: Cdad. Real | F38: puertovera.com | G38: 926 43 10 09 | H38: pedidos@puertovera.com | I38: TRUE
A39: Herboristería Ginkgo Biloba | B39: Herbolario | C39: C. Don Juan de Austria, 5, BAJO, 13630 Socuéllamos, Cdad. Real | D39: Socuéllamos | E39: Cdad. Real | F39: herboristeriaginkgobiloba.com | G39: 926 53 18 23 | H39: loren-carrasco@herboristeriaginkgobiloba.com | I39: TRUE
A40: Herbolario Hierbabuena | B40: Herbolario | C40: Pl. Cdad. de Nara N2, Módulo 2, Local 34, 45005 Toledo | D40: Toledo | E40: Toledo | F40: herbolariotoledo.com | G40: 644 27 17 58 | H40: herbolariotoledo@gmail.com | I40: TRUE
A41: STEVIA HERBOLARIO Y CENTRO TERAPIAS | B41: Herbolario | C41: herbolario, C. Beato Juan de Ávila, 5, 45510 Fuensalida, Toledo | D41: Fuensalida | E41: Toledo | F41: xalumedix.com | G41: 925 71 14 41 | H41: xalumedix@xalumedix.com | I41: TRUE
... A71: Más Cuidarse | B71: Herbolario | C71: Av. de la Ribera Alta, 12, Bajo Izquierda, 46260 Alberic, Valencia, Valencia | D71: Alberique | E71: Valencia | F71: mascuidarse.es | G71: 644 43 69 93 | H71: mascuidarse@gmail.com | I71: TRUE
A72: Pharmalife | B72: Herbolario | C72: Calle, Pl. Constitución, 06480 Montijo, Badajoz | D72: Montijo | E72: Badajoz | F72: pharmalife.ueniweb.com | H72: lperezm6644@hotmail.com | I72: TRUE
A73: Ecoespazo VITRIOL | B73: Herbolario | C73: Rúa Diego Pazos, 18, 27600 Sarria, Lugo | D73: Sarria | E73: Lugo | F73: ecoespazovitriol.com | G73: 982 88 66 16 | H73: ecoespazovitriol@gmail.com | I73: TRUE
A74: Milhflor | B74: Herbolario | C74: Cardenal de Quevedo, 4, 32004 Ourense, Province of Ourense | D74: Ourense | E74: Province of Ourense | F74: milhflor.com | G74: 988 24 92 45 | H74: tienda@milhflor.com | I74: TRUE
A75: El Bazar Natural ® | B75: Herbolario | C75: Ourense, 32830 Ourense | D75: Ourense | E75: Ourense | F75: elbazarnatural.com | G75: 988 54 42 00 | H75: correo@elbazarnatural.com | I75: TRUE
A76: Centro Dietético Hortelán Moaña | B76: Herbolario | C76: Av. de Concepción Arenal, 220, 36959 Moaña, Pontevedra | D76: Moaña | E76: Pontevedra | F76: hortelan.com | G76: 986 31 54 64 | H76: herbolario@hortelan.com | I76: TRUE
A77: Eco Cash | B77: Herbolario | C77: Rúa Cunchido de Arriba, nº1, 36940 Darbo, Pontevedra | D77: Darbo | E77: Pontevedra | F77: ecocash.es | G77: 986 30 23 43 | H77: david@ecocash.es | I77: TRUE
A78: ELIXIR BIOTIENDA | B78: Herbolario | C78: Rúa México, 62, 36204 Vigo, Pontevedra | D78: Vigo | E78: Pontevedra | F78: elixirbiotienda.es | G78: 630 03 04 56 | H78: elixirbiotienda@gmail.com | I78: TRUE
A79: Exialoe - Productos Naturales con Aloe Vera | B79: Herbolario | C79: Calle Monte del Sino, 29, 36206 Vigo, Pontevedra | D79: Vigo | E79: Pontevedra | F79: exialoe.es | G79: 607 39 92 84 | H79: aloe@euroexito.com | I79: TRUE
A80: Hierbabuena Herbolario | B80: Herbolario | C80: C. Capitán Gaona, 3, 26001 Logroño, La Rioja | D80: Logroño | E80: La Rioja | F80: hierbabuenaherbolario.com | G80: 941 24 27 93 | H80: susanahierbabuena@gmail.com | I80: TRUE
A81: Catanatura | B81: Herbolario | C81: Av. Gran Vía Juan Carlos I, 41, Local, 26004 Logroño, La Rioja | D81: Logroño | E81: La Rioja | F81: catanatura.es | G81: 941 57 86 13 | H81: catanatura@catanatura.com | I81: TRUE
A82: Jacaranda Herbolario | B82: Herbolario | C82: Calle Chile, 5, 26002 Logroño, La Rioja | D82: Logroño | E82: La Rioja | F82: jacarandaherbolario.es | G82: 941 03 58 84 | H82: jacaranda821@hotmail.com | I82: TRUE
A83: Consulta De Masaje Y Osteopatía José Ángel Rodríguez | B83: Herbolario | C83: C. Siete Infantes de Lara, 16, 26007 Logroño, La Rioja | D83: Logroño | E83: La Rioja | F83: osteopatiajoseangelrodriguez.com | G83: 659 61 48 70 | H83: jangelralfaro@gmail.com | I83: TRUE
A84: Herbolario La Flota | B84: Herbolario | C84: Av. Victoria, 8, local 2, 30007 Murcia | D84: Murcia | E84: Murcia | F84: herbolariolaflota.es | G84: 623 18 56 76 | H84: herbolario.laflota@gmail.com | I84: TRUE
... A98: Centro Dietetico Erika | B98: Herbolario | C98: Calle barren, 33, 48200 Durango, Biscay | D98: Durango | E98: Biscay | F98: centrodieteticoerika.com | G98: 946 81 70 45 | H98: erikadiet@hotmail.com | I98: TRUE
A99: Herbolario Online Okira | B99: Herbolario | D99: Abadiño | F99: okira.es | H99: lopd@okira.es | I99: TRUE
A100: Ekolur Herboristeria | B100: Herbolario | C100: Buenaventura Zapirain Kalea, N4, Bajo, 48280 Lekeitio, Biscay | D100: Lequeitio | E100: Biscay | F100: eko-lur6.webnode.es | G100: 688 73 96 99 | H100: eko-lurra@hotmail.com | I100: TRUE
A101: BIO Herboristería ZENIT | B101: Herbolario | C101: Easo Plaza, 3, 20006 Donostia, Gipuzkoa | D101: San Sebastián | E101: Gipuzkoa | F101: herboristeriazenit.com | G101: 943 47 01 56 | H101: zenit@herboristeriazenit.com | I101: TRUE
A102: BIZI NATURALEN ONURAK | B102: Herbolario | C102: Kale Nagusia, 19, 20250 Legorreta, Gipuzkoa | D102: Legorreta | E102: Gipuzkoa | F102: bizi-natural.com | G102: 943 53 90 64 | H102: bizilegorreta@gmail.com | I102: TRUE
