Workbook

Sheet centraldecomunicacion.es
A1: ﻿Nombre | B1: Categoría | C1: Dirección | D1: Ciudad | E1: Provincia | F1: website | G1: Teléfono | H1: email | I1: mail verificado
A2: Lavandería autoservicio Almeria La Colada | B2: Lavandería de autoservicio | C2: Calle Dr. Aráez Pacheco, 16, 04004 Almería, España | D2: Almería, España | E2: España | F2: lacoladaalmeria.com | G2: +34 640 07 96 54 | H2: info@lacoladaalmeria.com | I2: =COUNTIF(Estadísticas!I:I,'centraldecomunicacion.es'!H2)>0 -> FALSE
A3: Lavandería Autoservicio Lavanda Nueva Andalucía | B3: Lavandería de autoservicio | C3: Calle Blasco Ibáñez, 34, 04006 Almería, España | D3: Almería, España | E3: España | F3: facebook.com | G3: +34 603 29 51 69 | H3: - | I3: =COUNTIF(Estadísticas!I:I,'centraldecomunicacion.es'!H3)>0 -> FALSE
A4: Lavandería autoservicio Speed Queen Almeria 2 | B4: Lavandería de autoservicio | C4: Av. de Pablo Iglesias, 27, 04003 Almería, España | D4: Almería, España | E4: España | F4: speedqueenalmeria.blogspot.com.es | I4: =COUNTIF(Estadísticas!I:I,'centraldecomunicacion.es'!H4)>0 -> FALSE
A5: Lavandería Speed Queen | B5: Lavandería de autoservicio | C5: Calle Poeta Paco Aquino, 16, 04005 Almería, España | D5: Almería, España | E5: España | F5: negocio.site | G5: +34 626 24 16 52 | H5: - | I5: =COUNTIF(Estadísticas!I:I,'centraldecomunicacion.es'!H5)>0 -> FALSE
A6: Lavandería Autoservicio Lavanda Los Ángeles | B6: Lavandería de autoservicio | C6: Calle Granada, 210, 04008 Almería, España | D6: Almería, España | E6: España | G6: +34 603 29 51 69 | H6: - | I6: =COUNTIF(Estadísticas!I:I,'centraldecomunicacion.es'!H6)>0 -> FALSE
A7: Lavandería Plaza Almería, S.L | B7: Servicio de lavandería | C7: C/Esperanza, 27 y 29 Poligono San Rafael, 04230 Huércal de Almería, Almería, España | D7: Huércal de Almería, España | E7: España | F7: lavanderiaplaza.com | G7: +34 950 14 28 88 | H7: - | I7: =COUNTIF(Estadísticas!I:I,'centraldecomunicacion.es'!H7)>0 -> FALSE
A8: Lacolada | B8: Lavandería de autoservicio | C8: Calle José Artés de Arcos, 21, 04004 Almería, España | D8: Almería, España | E8: España | H8: - | I8: =COUNTIF(Estadísticas!I:I,'centraldecomunicacion.es'!H8)>0 -> FALSE
A9: Leylaundry Lavanderia Autoservicio | B9: Lavandería de autoservicio | C9: Calle María Zambrano, 04006 Almería, España | D9: Almería, España | E9: España | H9: - | I9: =COUNTIF(Estadísticas!I:I,'centraldecomunicacion.es'!H9)>0 -> FALSE
A10: Lavomatic Almería | B10: Lavandería | C10: Av. de Cabo de Gata, 171, 04007 Almería, España | D10: Almería, España | E10: España | F10: lavomaticalmeria.es | G10: +34 630 93 20 83 | H10: - | I10: =COUNTIF(Estadísticas!I:I,'centraldecomunicacion.es'!H10)>0 -> FALSE
A11: TINTORERÍA LAVANDERÍA NIETO | B11: Lavandería | C11: Av. de Cabo de Gata, 119, 04007 Almería, España | D11: Almería, España | E11: España | F11: business.site | G11: +34 950 26 53 61 | H11: - | I11: =COUNTIF(Estadísticas!I:I,'centraldecomunicacion.es'!H11)>0 -> FALSE
A12: Lavandería Almería - Nature Lavandería | B12: Lavandería de autoservicio | C12: Calle Calz. de Castro, 36, 04006 Almería, España | D12: Almería, España | E12: España | F12: naturelavanderia.es | G12: +34 663 86 68 22 | H12: malaga@naturelavanderia.es | I12: =COUNTIF(Estadísticas!I:I,'centraldecomunicacion.es'!H12)>0 -> TRUE
A13: Lavandería y Tintorería Venezuela, S.L. | B13: Lavandería | C13: Calle San Juan Bosco, 20, 04005 Almería, España | D13: Almería, España | E13: España | G13: +34 950 26 18 70 | H13: - | I13: =COUNTIF(Estadísticas!I:I,'centraldecomunicacion.es'!H13)>0 -> FALSE
A14: Lavandería autoservicio La Abuelita | B14: Lavandería de autoservicio | C14: Calle Gustavo Villapalos, 13, 04006 Almería, España | D14: Almería, España | E14: España | F14: facebook.com | G14: +34 646 54 05 97 | H14: - | I14: =COUNTIF(Estadísticas!I:I,'centraldecomunicacion.es'!H14)>0 -> FALSE
A15: Tintorerias Adesso | B15: Tintorería | C15: Calle Lucano, 3, 04001 Almería, España | D15: Almería, España | E15: España | F15: adessotintorerias.com | G15: +34 950 95 16 37 | H15: - | I15: =COUNTIF(Estadísticas!I:I,'centraldecomunicacion.es'!H15)>0 -> FALSE
A16: New Sec Cleanner | B16: Tintorería | C16: Av. del Mediterráneo, 04007 Almería, España | D16: Almería, España | E16: España | H16: - | I16: =COUNTIF(Estadísticas!I:I,'centraldecomunicacion.es'!H16)>0 -> FALSE
A17: Lavomatic Lavandería Autoservicio | B17: Lavandería de autoservicio | C17: 04009 Almería, España | D17: Almería, España | E17: España | F17: lavomatic.es | H17: info@lavomatic.es | I17: =COUNTIF(Estadísticas!I:I,'centraldecomunicacion.es'!H17)>0 -> FALSE
A18: La Américas | B18: Tintorería | C18: Av. de Santa Isabel, 40, 04009 Almería, España | D18: Almería, España | E18: España | G18: +34 950 23 95 94 | H18: - | I18: =COUNTIF(Estadísticas!I:I,'centraldecomunicacion.es'!H18)>0 -> FALSE
A19: Tintorería Lavaclean | B19: Tintorería | C19: Calle José Artés de Arcos, 21, BAJO, 04004 Almería, España | D19: Almería, España | E19: España | F19: tintorerialavaclean.com | G19: +34 950 25 31 42 | H19: tintorerialavaclean@hotmail.com | I19: =COUNTIF(Estadísticas!I:I,'centraldecomunicacion.es'!H19)>0 -> TRUE
A20: Tintorerías Adesso S L | B20: Tintorería | C20: Av. Federico García Lorca, 40, 04004 Almería, España | D20: Almería, España | E20: España | F20: adessotintorerias.com | G20: +34 950 26 07 24 | H20: - | I20: =COUNTIF(Estadísticas!I:I,'centraldecomunicacion.es'!H20)>0 -> FALSE
A21: New Sec Cleaner | B21: Tintorería | C21: Av. del Mediterráneo, 244, 04006 Almería, España | D21: Almería, España | E21: España | G21: +34 950 22 23 29 | H21: - | I21: =COUNTIF(Estadísticas!I:I,'centraldecomunicacion.es'!H21)>0 -> FALSE
A22: Tintorerias Adesso S L | B22: Tintorería | C22: Av. del Mediterráneo, 428, 04009 Almería, España | D22: Almería, España | E22: España | F22: adessotintorerias.com | G22: +34 950 62 45 06 | H22: - | I22: =COUNTIF(Estadísticas!I:I,'centraldecomunicacion.es'!H22)>0 -> FALSE
A23: La colada de Natalia | B23: Lavandería de autoservicio | C23: Calle Alcazaba de Almeria, 32, 04230 Huércal de Almería, Almería, España | D23: Huércal de Almería, España | E23: España | G23: +34 692 56 64 25 | H23: - | I23: =COUNTIF(Estadísticas!I:I,'centraldecomunicacion.es'!H23)>0 -> FALSE
A24: Pressto | B24: Tintorería | C24: 04001 Almería, España | D24: Almería, España | E24: España | H24: - | I24: =COUNTIF(Estadísticas!I:I,'centraldecomunicacion.es'!H24)>0 -> FALSE
A25: Lavandería Mir Sl | B25: Lavandería | C25: Nº, Calle Rio Guadiana, 72, 04240 Viator, Almería, España | D25: Viator, España | E25: España | F25: lavanderiamir.com | G25: +34 950 30 43 89 | H25: lavanderiamir@lavanderiamir.com | I25: =COUNTIF(Estadísticas!I:I,'centraldecomunicacion.es'!H25)>0 -> TRUE
A26: Limpia Sec | B26: Tintorería | C26: Ctra. Campamento, 8, B, 04230 Huércal de Almería, Almería, España | D26: Huércal de Almería, España | E26: España | G26: +34 950 30 00 43 | H26: - | I26: =COUNTIF(Estadísticas!I:I,'centraldecomunicacion.es'!H26)>0 -> FALSE
A27: Limpiezas Nieto - NIETOLIMP | B27: Servicio de limpieza | C27: Av. de Santa Isabel, 88, 04009 Almería, España | D27: Almería, España | E27: España | F27: limpiezasnieto.es | G27: +34 647 41 35 79 | H27: copyright@cpanel.net | I27: =COUNTIF(Estadísticas!I:I,'centraldecomunicacion.es'!H27)>0 -> FALSE
A28: Tintoreria Ama | B28: Tintorería | C28: 04005 Almería, España | D28: Almería, España | E28: España | H28: - | I28: =COUNTIF(Estadísticas!I:I,'centraldecomunicacion.es'!H28)>0 -> FALSE
A29: Lavanderias Roquetas Kwlaqua | B29: Lavandería de autoservicio | C29: Paseo los Baños, 45, 04740 Roquetas de Mar, Almería, España | D29: Roquetas de Mar, España | E29: España | G29: +34 610 21 64 81 | H29: - | I29: =COUNTIF(Estadísticas!I:I,'centraldecomunicacion.es'!H29)>0 -> FALSE
A30: Lavanderia Autoservicio LAVAMAR | B30: Lavandería | C30: Av. Unión Europea, 64, 04740 Roquetas de Mar, Almería, España | D30: Roquetas de Mar, España | E30: España | G30: +34 629 56 42 03 | H30: - | I30: =COUNTIF(Estadísticas!I:I,'centraldecomunicacion.es'!H30)>0 -> FALSE
A31: Clothing Wash - Lavanderia | B31: Lavandería de autoservicio | C31: Bulevar Cdad. de Vicar, 614, 04738 La Gangosa, Almería, España | D31: La Gangosa, España | E31: España | G31: +34 617 48 36 81 | H31: - | I31: =COUNTIF(Estadísticas!I:I,'centraldecomunicacion.es'!H31)>0 -> FALSE
A32: Lavandería autoservicio Sweetwater | B32: Lavandería de autoservicio | C32: Av. de Carlos III, Nº 583, 04720 Aguadulce, Almería, España | D32: Aguadulce, España | E32: España | G32: +34 619 71 23 19 | H32: - | I32: =COUNTIF(Estadísticas!I:I,'centraldecomunicacion.es'!H32)>0 -> FALSE
A33: Lavanderia Rosi | B33: Lavandería | C33: Calle Julián Arcas Lacal, 5, 04740 Roquetas de Mar, Almería, España | D33: Roquetas de Mar, España | E33: España | F33: rosilimpiezaroquet.wix.com | G33: +34 950 32 07 05 | H33: - | I33: =COUNTIF(Estadísticas!I:I,'centraldecomunicacion.es'!H33)>0 -> FALSE
A34: Lacolada Roquetas Lavanderia autoservicio | B34: Lavandería de autoservicio | C34: Calle Pintor Rosales, 64, 04740 Roquetas de Mar, Almería, España | D34: Roquetas de Mar, España | E34: España | F34: facebook.com | G34: +34 950 00 23 64 | H34: - | I34: =COUNTIF(Estadísticas!I:I,'centraldecomunicacion.es'!H34)>0 -> FALSE
A35: La colada de María lavandería autoservicio | B35: Lavandería de autoservicio | C35: Calle Muluya, 17, 04740 Roquetas de Mar, Almería, España | D35: Roquetas de Mar, España | E35: España | G35: +34 642 50 66 39 | H35: - | I35: =COUNTIF(Estadísticas!I:I,'centraldecomunicacion.es'!H35)>0 -> FALSE
A36: Tendedero | B36: Lavandería de autoservicio | C36: Calle de Don Juan de Aústria, 162, 04720 Roquetas de Mar, Almería, España | D36: Roquetas de Mar, España | E36: España | F36: tendedero.negocio.site | G36: +34 658 11 89 74 | H36: - | I36: =COUNTIF(Estadísticas!I:I,'centraldecomunicacion.es'!H36)>0 -> FALSE
A37: Lavandería Speed Queen | B37: Lavandería de autoservicio | C37: Bulevar Cdad. de Vicar, 1411, 04738 Puebla de Vícar, Almería, España | D37: Puebla de Vícar, España | E37: España | F37: speedqueeninvestor.com | G37: +34 950 56 55 11 | H37: - | I37: =COUNTIF(Estadísticas!I:I,'centraldecomunicacion.es'!H37)>0 -> FALSE
A38: Lavaexpress | B38: Lavandería de autoservicio | C38: Av. las Gaviotas, 19, 04740 Roquetas de Mar, Almería, España | D38: Roquetas de Mar, España | E38: España | G38: +34 637 40 12 20 | H38: - | I38: =COUNTIF(Estadísticas!I:I,'centraldecomunicacion.es'!H38)>0 -> FALSE
A39: Lavandería autoservicio Indalo Rosa | B39: Lavandería de autoservicio | C39: Av. Europa, 161, 04745 La Mojonera, Almería, España | D39: La Mojonera, España | E39: España | G39: +34 655 17 12 09 | H39: - | I39: =COUNTIF(Estadísticas!I:I,'centraldecomunicacion.es'!H39)>0 -> FALSE
A40: LAVANDERIA CARTHAGO | B40: Lavandería | C40: Ctra. de Alicun, 356, 04721 El Parador de las Hortichuelas, Almería, España | D40: El Parador de las Hortichuelas, España | E40: España | F40: lavanderiacarthago.es | G40: +34 950 34 30 45 | H40: lavanderiacarthago@yahoo.es | I40: =COUNTIF(Estadísticas!I:I,'centraldecomunicacion.es'!H40)>0 -> FALSE
A41: Lavandería Lavamar | B41: Servicio de lavandería | C41: Calle Dioniso, s/n, 04740 Roquetas de Mar, Almería, España | D41: Roquetas de Mar, España | E41: España | F41: lavanderialavamar.com | G41: +34 950 32 71 67 | H41: lavamarlavanderia@gmail.com | I41: =COUNTIF(Estadísticas!I:I,'centraldecomunicacion.es'!H41)>0 -> TRUE
A42: LAVOMATIC LAVANDERIA AUTOSERVICIO | B42: Lavandería de autoservicio | C42: 04720 El Parador de las Hortichuelas, Almería, España | D42: El Parador de las Hortichuelas, España | E42: España | F42: lavomaticalmeria.es | H42: - | I42: =COUNTIF(Estadísticas!I:I,'centraldecomunicacion.es'!H42)>0 -> FALSE
A43: Ferrteria | B43: Lavandería | C43: Av. Pablo Picasso, 75, 04740 Roquetas de Mar, Almería, España | D43: Roquetas de Mar, España | E43: España | H43: - | I43: =COUNTIF(Estadísticas!I:I,'centraldecomunicacion.es'!H43)>0 -> FALSE
A44: Lavanderia clothing wash | B44: Lavandería | C44: Av. las Negras, 04100 Campohermoso, Almería, España | D44: Campohermoso, España | E44: España | G44: +34 632 66 15 52 | H44: - | I44: =COUNTIF(Estadísticas!I:I,'centraldecomunicacion.es'!H44)>0 -> FALSE
A45: Lavanderia Autoservico LAVAMAR | B45: Lavandería | C45: Calle Venezuela, 20, 26, 04700 El Ejido, Almería, España | D45: El Ejido, España | E45: España | G45: +34 629 56 42 03 | H45: - | I45: =COUNTIF(Estadísticas!I:I,'centraldecomunicacion.es'!H45)>0 -> FALSE
A46: Lacolada | B46: Lavandería de autoservicio | C46: Carr. de la Mojonera, 109, 04716 Las Norias de Daza, Almería, España | D46: Las Norias de Daza, España | E46: España | H46: - | I46: =COUNTIF(Estadísticas!I:I,'centraldecomunicacion.es'!H46)>0 -> FALSE
A47: The Cars Clear | B47: Lavandería | C47: 04240, Almería, España | D47: Huércal de Almería, España | E47: España | H47: - | I47: =COUNTIF(Estadísticas!I:I,'centraldecomunicacion.es'!H47)>0 -> FALSE
A48: Lavanderia La ropa limpia | B48: Lavandería | C48: Paseo las Lomas, 56, 04700 El Ejido, Almería, España | D48: El Ejido, España | E48: España | H48: - | I48: =COUNTIF(Estadísticas!I:I,'centraldecomunicacion.es'!H48)>0 -> FALSE
A49: Lavandería Industrial Flisa De Almería S A | B49: Lavandería | C49: Calle Sierra de los Filabres, 6, 04738 Gangosa ( La ), Almería, España | D49: La Gangosa, España | E49: España | H49: - | I49: =COUNTIF(Estadísticas!I:I,'centraldecomunicacion.es'!H49)>0 -> FALSE
A50: Lavandería Industrial Pto. Ordaz, S.L. | B50: Servicio de lavandería | C50: Av Almeria, 04400 Alhama de Almería, Almería, España | D50: Alhama de Almería, España | E50: España | G50: +34 950 64 10 19 | H50: - | I50: =COUNTIF(Estadísticas!I:I,'centraldecomunicacion.es'!H50)>0 -> FALSE
A51: Lavadero Almerimar | B51: Lavandería de autoservicio | C51: Calle Varadero, 2, 04711 Almerimar, Almería, España | D51: Almerimar, España | E51: España | G51: +34 642 82 34 14 | H51: - | I51: =COUNTIF(Estadísticas!I:I,'centraldecomunicacion.es'!H51)>0 -> FALSE
A52: Tintorería Adesso | B52: Lavandería | C52: Diseminado Ctra Almerimar, 35, 04700, Almería, España | D52: El Ejido, España | E52: España | H52: - | I52: =COUNTIF(Estadísticas!I:I,'centraldecomunicacion.es'!H52)>0 -> FALSE
A53: Lavandería Industrial 2010 | B53: Lavandería | C53: Calle Plateros, 26, 04738 Las Cabañuelas, Almería, España | D53: Las Cabañuelas, España | E53: España | H53: - | I53: =COUNTIF(Estadísticas!I:I,'centraldecomunicacion.es'!H53)>0 -> FALSE
A54: Ascione &amp; Antolin | B54: Servicio de limpieza | C54: Calle Michigan, 12, 04720 Aguadulce, Almería, España | D54: Aguadulce, España | E54: España | H54: - | I54: =COUNTIF(Estadísticas!I:I,'centraldecomunicacion.es'!H54)>0 -> FALSE
A55: La Boutique Del Congelado | B55: Lavandería | C55: 04004 Almería, España | D55: Almería, España | E55: España | G55: +34 627 42 94 87 | H55: - | I55: =COUNTIF(Estadísticas!I:I,'centraldecomunicacion.es'!H55)>0 -> FALSE
A56: Rosa María García Gómez | B56: Tintorería | C56: Calle Julián Arcas Lacal, 5, 04740 Roquetas de Mar, Almería, España | D56: Roquetas de Mar, España | E56: España | G56: +34 950 32 07 05 | H56: - | I56: =COUNTIF(Estadísticas!I:I,'centraldecomunicacion.es'!H56)>0 -> FALSE
A57: Illamar. Empresa de Servicios de Limpieza | B57: Servicios de limpieza | C57: Calle Universidad de Texas, 9, 04005 Almería, España | D57: Almería, España | E57: España | F57: illamar.es | G57: +34 950 85 46 85 | H57: - | I57: =COUNTIF(Estadísticas!I:I,'centraldecomunicacion.es'!H57)>0 -> FALSE
A58: Eulen | B58: Servicio de limpieza | C58: Calle Estaño, 0, 04001 Almería, España | D58: Almería, España | E58: España | F58: eulen.com | G58: +34 950 62 44 03 | H58: dcomercial@eulen.com | I58: =COUNTIF(Estadísticas!I:I,'centraldecomunicacion.es'!H58)>0 -> TRUE
A59: LAVANDERIA Y TINTORERIA CARBONERAS | B59: Lavandería | C59: Av. Faro Mesa Roldán, 92, 04140 Carboneras, Almería, España | D59: Carboneras, España | E59: España | F59: lavanderiaytintoreriacarboneras.com | G59: +34 622 72 02 81 | H59: - | I59: =COUNTIF(Estadísticas!I:I,'centraldecomunicacion.es'!H59)>0 -> FALSE
A60: Limpiezas Indalicas | B60: Servicio de limpieza | C60: Calle Estaño, 109, 04009 Almería, España | D60: Almería, España | E60: España | F60: limpiezasindalicas.com | G60: +34 950 22 59 66 | H60: administracion@limpiezasindalicas.com | I60: =COUNTIF(Estadísticas!I:I,'centraldecomunicacion.es'!H60)>0 -> FALSE
A61: LAVOMATIC | B61: Lavandería de autoservicio | C61: 04770, Almería, España | D61: La Curva, España | E61: España | G61: +34 647 72 49 30 | H61: - | I61: =COUNTIF(Estadísticas!I:I,'centraldecomunicacion.es'!H61)>0 -> FALSE
A62: La Colada El Ejido lavandería autoservicio | B62: Lavandería de autoservicio | C62: Calle Cervantes 73, Plaza Las Flores, 04700 El Ejido, Almería, España | D62: El Ejido, España | E62: España | H62: - | I62: =COUNTIF(Estadísticas!I:I,'centraldecomunicacion.es'!H62)>0 -> FALSE
A63: CLAT CARE lavanderia tintoreria autoservicio | B63: Lavandería de autoservicio | C63: Calle Galera, 6, 04711 Almerimar, Almería, España | D63: Almerimar, España | E63: España | F63: negocio.site | G63: +34 607 19 16 80 | H63: - | I63: =COUNTIF(Estadísticas!I:I,'centraldecomunicacion.es'!H63)>0 -> FALSE
A64: La colada de Rosamari | B64: Servicio de lavandería | C64: Av. la Luz, 50, 04700 El Ejido, Almería, España | D64: El Ejido, España | E64: España | F64: negocio.site | G64: +34 625 22 10 09 | H64: - | I64: =COUNTIF(Estadísticas!I:I,'centraldecomunicacion.es'!H64)>0 -> FALSE
A65: Mara Sec Lavanderia | B65: Lavandería | C65: Calle del Cine, 22, 04700 El Ejido, Almería, España | D65: El Ejido, España | E65: España | G65: +34 950 03 31 98 | H65: - | I65: =COUNTIF(Estadísticas!I:I,'centraldecomunicacion.es'!H65)>0 -> FALSE
A66: Lava-Centro | B66: Lavandería | C66: C/ Dársena de la Batea, 40, 04711 Almerimar, Almería, España | D66: Almerimar, España | E66: España | H66: - | I66: =COUNTIF(Estadísticas!I:I,'centraldecomunicacion.es'!H66)>0 -> FALSE
A67: Lavanderia Industrial Dama | C67: Calle Hierro, 10, 04009 Almería, España | D67: Almería, España | E67: España | H67: - | I67: =COUNTIF(Estadísticas!I:I,'centraldecomunicacion.es'!H67)>0 -> FALSE
A68: La Colada, Lavandería | B68: Lavandería de autoservicio | C68: Av. Lepanto, 10, 04800 Albox, Almería, España | D68: Albox, España | E68: España | F68: facebook.com | G68: +34 637 82 74 25 | H68: - | I68: =COUNTIF(Estadísticas!I:I,'centraldecomunicacion.es'!H68)>0 -> FALSE
A69: Bish&apos;s | B69: Lavandería de autoservicio | C69: Paseo del Mediterráneo, 48, 04638 Vista de los Ángeles-Rumina, Almería, España | D69: Vista de los Ángeles-Rumina, España | E69: España | G69: +34 639 16 17 25 | H69: - | I69: =COUNTIF(Estadísticas!I:I,'centraldecomunicacion.es'!H69)>0 -> FALSE
A70: Lavanderia Saga | B70: Servicio de limpieza | C70: Calle Lucerna, 04638 Mojácar, Almería, España | D70: Mojácar, España | E70: España | H70: - | I70: =COUNTIF(Estadísticas!I:I,'centraldecomunicacion.es'!H70)>0 -> FALSE
A71: Tintoreria ARABI | B71: Tintorería | C71: Calle Fenicios, 1, 04770 Adra, Almería, España | D71: Adra, España | E71: España | H71: - | I71: =COUNTIF(Estadísticas!I:I,'centraldecomunicacion.es'!H71)>0 -> FALSE
A72: Tintorerias Almerienses | B72: Tintorería | C72: Calle Fragata, 0, 04711 Almerimar, Almería, España | D72: Almerimar, España | E72: España | H72: - | I72: =COUNTIF(Estadísticas!I:I,'centraldecomunicacion.es'!H72)>0 -> FALSE
A73: Lavanderia Higiensec Tintoreria | B73: Lavandería | C73: Av. Almería, 12, 04140 Carboneras, Almería, España | D73: Carboneras, España | E73: España | H73: - | I73: =COUNTIF(Estadísticas!I:I,'centraldecomunicacion.es'!H73)>0 -> FALSE
A74: BURBUJAS HUERCAL OVERA | B74: Lavandería de autoservicio | C74: Plaza Reina Sofía, 04600 Huércal-Overa, Almería, España | D74: Huércal-Overa, España | E74: España | G74: +34 684 29 27 30 | H74: - | I74: =COUNTIF(Estadísticas!I:I,'centraldecomunicacion.es'!H74)>0 -> FALSE
A75: Tintorerias Ainos | B75: Tintorería | C75: Camino de Vera, 14, 04110 Campohermoso, Almería, España | D75: Campohermoso, España | E75: España | G75: +34 950 38 60 07 | H75: - | I75: =COUNTIF(Estadísticas!I:I,'centraldecomunicacion.es'!H75)>0 -> FALSE
A76: Beatriz Zamora Cervantes | B76: Lavandería | C76: Av. Almería, 8, 04140 Carboneras, Almería, España | D76: Carboneras, España | E76: España | G76: +34 950 45 44 27 | H76: - | I76: =COUNTIF(Estadísticas!I:I,'centraldecomunicacion.es'!H76)>0 -> FALSE
A77: Lavapul | B77: Lavandería | C77: Av. Estación, 29, 04649 Pulpí, Almería, España | D77: Pulpí, España | E77: España | F77: lavanderiasenlimpio.com | G77: +34 657 50 28 19 | H77: lavapul@gmail.com | I77: =COUNTIF(Estadísticas!I:I,'centraldecomunicacion.es'!H77)>0 -> TRUE
A78: Lavandería Autoservicio Open Wash Mojacar | B78: Lavandería de autoservicio | C78: Parque Comercial, Calle Duende, 1, local 28, 04638 Mojácar, Almería, España | D78: Mojácar, España | E78: España | F78: openwash.es | G78: +34 664 44 35 14 | H78: info@openwash.es | I78: =COUNTIF(Estadísticas!I:I,'centraldecomunicacion.es'!H78)>0 -> FALSE
A79: AQA Laundry | B79: Servicio de lavandería | C79: Calle Magallanes, 5, 04621 Playas de Vera, Almería, España | D79: Playas de Vera, España | E79: España | F79: facebook.com | G79: +34 690 39 64 83 | H79: - | I79: =COUNTIF(Estadísticas!I:I,'centraldecomunicacion.es'!H79)>0 -> FALSE
A80: Lavandería Burbujas Indalo | B80: Lavandería | C80: Pje. Saturno, 11, 04620 Vera, Almería, España | D80: Vera, España | E80: España | G80: +34 638 37 68 58 | H80: - | I80: =COUNTIF(Estadísticas!I:I,'centraldecomunicacion.es'!H80)>0 -> FALSE
A81: MARALJO 215 SL | B81: Tintorería | C81: CALLE CONSORCIO, 6, BJ, 04760 Castala, Almería, España | D81: Castala, España | E81: España | G81: +34 950 40 12 38 | H81: - | I81: =COUNTIF(Estadísticas!I:I,'centraldecomunicacion.es'!H81)>0 -> FALSE
A82: Ivi&apos;s Lavanderia | B82: Lavandería | C82: Ronda de las Buganvillas, 04621 Vera, Almería, España | D82: Vera, España | E82: España | H82: - | I82: =COUNTIF(Estadísticas!I:I,'centraldecomunicacion.es'!H82)>0 -> FALSE
A83: Laundry Room | B83: Lavandería | C83: Carretera Vera, Carr. de Garrucha, Nr.4, bajo 1b, 04621 Garrucha, Almería, España | D83: Garrucha, España | E83: España | G83: +34 666 00 78 24 | H83: - | I83: =COUNTIF(Estadísticas!I:I,'centraldecomunicacion.es'!H83)>0 -> FALSE
A84: Ana María López Martín | B84: Tintorería | C84: Calle Manuel Fernández Arriola, 39, 04700 El Ejido, Almería, España | D84: El Ejido, España | E84: España | G84: +34 950 48 51 01 | H84: - | I84: =COUNTIF(Estadísticas!I:I,'centraldecomunicacion.es'!H84)>0 -> FALSE
A85: Químicos Castaño, S. L. | B85: Servicios de limpieza | C85: Calle Sierra de Maria, 15, 04240 Viator, Almería, España | D85: Viator, España | E85: España | F85: quimicoscastano.blogspot.com.es | G85: +34 950 30 45 49 | H85: - | I85: =COUNTIF(Estadísticas!I:I,'centraldecomunicacion.es'!H85)>0 -> FALSE
A86: City Sec Tintorería | B86: Tintorería | C86: Av. de Baria, 26, 04620 Vera, Almería, España | D86: Vera, España | E86: España | G86: +34 610 47 39 88 | H86: - | I86: =COUNTIF(Estadísticas!I:I,'centraldecomunicacion.es'!H86)>0 -> FALSE
A87: Coladísima lavandería autoservicio | B87: Lavandería de autoservicio | C87: Av. Guadalquivir, n°25, 11007 Cádiz, España | D87: Cádiz, España | E87: España | F87: coladisimalavanderia.com | G87: +34 692 32 18 79 | H87: - | I87: =COUNTIF(Estadísticas!I:I,'centraldecomunicacion.es'!H87)>0 -> FALSE
A88: Coin&amp;Clean | B88: Lavandería de autoservicio | C88: Calle Ancha, 14, 11001 Cádiz, España | D88: Cádiz, España | E88: España | G88: +34 679 92 05 65 | H88: - | I88: =COUNTIF(Estadísticas!I:I,'centraldecomunicacion.es'!H88)>0 -> FALSE
A89: Wasandrai Lavanderia Autoservicio | B89: Lavandería de autoservicio | C89: Calle Medina Sidonia, 13, 11012 Cádiz, España | D89: Cádiz, España | E89: España | F89: wasandrai.com | G89: +34 649 32 39 94 | H89: info@wasandrai.com | I89: =COUNTIF(Estadísticas!I:I,'centraldecomunicacion.es'!H89)>0 -> FALSE
A90: Wasandrai | B90: Lavandería de autoservicio | C90: Calle San Rafael, 49, 11002 Cádiz, España | D90: Cádiz, España | E90: España | F90: wasandrai.com | H90: info@wasandrai.com | I90: =COUNTIF(Estadísticas!I:I,'centraldecomunicacion.es'!H90)>0 -> FALSE
A91: iWash Lavanderías Autoservicio, S.L | B91: Lavandería de autoservicio | C91: Calle Francisco García de Sola, nº 8, Local 4, 11008 Cádiz, España | D91: Cádiz, España | E91: España | F91: lavanderiaautoserviciocadiz.es | G91: +34 626 71 68 50 | H91: - | I91: =COUNTIF(Estadísticas!I:I,'centraldecomunicacion.es'!H91)>0 -> FALSE
A92: iWash Lavanderías Autoservicio, S.L | B92: Lavandería de autoservicio | C92: Calle Pintor Zuloaga, 22, 11010 Cádiz, España | D92: Cádiz, España | E92: España | F92: lavanderiaautoserviciocadiz.es | G92: +34 626 71 68 50 | H92: - | I92: =COUNTIF(Estadísticas!I:I,'centraldecomunicacion.es'!H92)>0 -> FALSE
A93: Lavanderia Industrial Maria del carmen S.L | B93: Lavandería | C93: Plaza Capuchinos, 11005 Cádiz, España | D93: Cádiz, España | E93: España | G93: +34 956 22 45 67 | H93: - | I93: =COUNTIF(Estadísticas!I:I,'centraldecomunicacion.es'!H93)>0 -> FALSE
A94: ILUNION | B94: Lavandería | C94: Polígono Industrial Zona Franca, Calle San Roque, s/n, 11006 Cádiz, España | D94: Cádiz, España | E94: España | F94: lavanderia.ilunion.com | G94: +34 956 28 41 46 | H94: u003Einfo.lavanderia@ilunion.com | I94: =COUNTIF(Estadísticas!I:I,'centraldecomunicacion.es'!H94)>0 -> TRUE
A95: Star Wash Laundry Cádiz | B95: Lavandería de autoservicio | C95: Calle San Pedro, 11004 Cádiz, España | D95: Cádiz, España | E95: España | F95: facebook.com | G95: +34 608 43 53 53 | H95: - | I95: =COUNTIF(Estadísticas!I:I,'centraldecomunicacion.es'!H95)>0 -> FALSE
A96: Ilunion Lavanderias Industriales S.A. | B96: Lavandería | C96: Calle Algeciras, 2, 11011 Cádiz, España | D96: Cádiz, España | E96: España | G96: +34 956 28 41 46 | H96: - | I96: =COUNTIF(Estadísticas!I:I,'centraldecomunicacion.es'!H96)>0 -> FALSE
A97: Pressto | B97: Tintorería | C97: Av. las Cortes de Cádiz, 1, 11012 Cádiz, España | D97: Cádiz, España | E97: España | F97: pressto.es | G97: +34 956 26 60 64 | H97: - | I97: =COUNTIF(Estadísticas!I:I,'centraldecomunicacion.es'!H97)>0 -> FALSE
A98: Wasandrai Lavandería Autoservicio | B98: Lavandería de autoservicio | C98: Av. Marconi, 26, 11009 Cádiz, España | D98: Cádiz, España | E98: España | F98: wasandrai.com | H98: info@wasandrai.com | I98: =COUNTIF(Estadísticas!I:I,'centraldecomunicacion.es'!H98)>0 -> FALSE
A99: TINTORERIA BAHIA BLANCA | B99: Tintorería | C99: Calle Tamarindos, 20, 11007 Cádiz, España | D99: Cádiz, España | E99: España | G99: +34 956 27 36 13 | H99: - | I99: =COUNTIF(Estadísticas!I:I,'centraldecomunicacion.es'!H99)>0 -> FALSE
A100: Tintoreria Ma Del Carmen | B100: Tintorería | C100: Calle Sagasta, 21, 11001 Cádiz, España | D100: Cádiz, España | E100: España | H100: - | I100: =COUNTIF(Estadísticas!I:I,'centraldecomunicacion.es'!H100)>0 -> FALSE
...

Sheet Estadísticas
A1: Número de empresas | B1: Número de correos electrónicos | C1: Número de webs | D1: Números de teléfono | E1: Números de teléfono fijo | F1: Números de teléfono móvil | G1: Sectores | H1: Mails únicos | I1: Mails verificados
A2: =COUNTIF('centraldecomunicacion.es'!A2:'centraldecomunicacion.es'!A19470,"*") -> 5713 | B2: =COUNTIF('centraldecomunicacion.es'!H2:'centraldecomunicacion.es'!H19470,"*@*") -> 1526 | C2: =COUNTIF('centraldecomunicacion.es'!F2:'centraldecomunicacion.es'!F19470,"*.*") -> 2940 | D2: =COUNTIF('centraldecomunicacion.es'!G2:'centraldecomunicacion.es'!G19470,"+34 6*")+COUNTIF('centraldecomunicacion.es'!G2:'centraldecomunicacion.es'!G19470,"+34 9*") -> 4606 | E2: =COUNTIF('centraldecomunicacion.es'!G2:'centraldecomunicacion.es'!G19470,"+34 9*") -> 2548 | F2: =COUNTIF('centraldecomunicacion.es'!G2:'centraldecomunicacion.es'!G19470,"+34 6*") -> 2058 | G2: {=_xlfn.UNIQUE('centraldecomunicacion.es'!B2:'centraldecomunicacion.es'!B19470)} -> Lavandería de autoservicio | H2: {=_xlfn.UNIQUE('centraldecomunicacion.es'!H2:'centraldecomunicacion.es'!H19470)} -> info@lacoladaalmeria.com | I2: malaga@naturelavanderia.es
G3: Servicio de lavandería | H3: - | I3: tintorerialavaclean@hotmail.com
G4: Lavandería | H4: 0 | I4: lavanderiamir@lavanderiamir.com
G5: Tintorería | H5: malaga@naturelavanderia.es | I5: lavamarlavanderia@gmail.com
G6: Servicio de limpieza | H6: info@lavomatic.es | I6: dcomercial@eulen.com
G7: Servicios de limpieza | H7: tintorerialavaclean@hotmail.com | I7: lavapul@gmail.com
H8: lavanderiamir@lavanderiamir.com | I8: u003einfo.lavanderia@ilunion.com
G9: Comercio | H9: copyright@cpanel.net | I9: lavanderiamedina@hotmail.es
G10: Tienda de ropa | H10: lavanderiacarthago@yahoo.es | I10: salamanca@grupofissa.com
G11: Proveedor de productos de limpieza | H11: lavamarlavanderia@gmail.com | I11: atencion@washup.es
G12: Servicio de limpieza de alfombras | H12: dcomercial@eulen.com | I12: parsi@lavanderiaindustrialparsi.es
G13: Tienda de arreglos de ropa | H13: administracion@limpiezasindalicas.com | I13: cendra@cendra-higiene.es
G14: Tienda de lavadoras y secadoras | H14: lavapul@gmail.com | I14: nes@5asec.com
G15: Servicio de limpieza de tapicería | H15: info@openwash.es | I15: ayuda@washrocks.com
G16: Organización de servicios sociales | H16: info@wasandrai.com | I16: info-china@alliancels.com
G17: Servicio de lavado a presión | H17: u003Einfo.lavanderia@ilunion.com | I17: lavanderiasclickandclean@gmail.com
G18: Tienda de lencería | H18: administracion@limpiezashurtado.com | I18: avanzamm27@gmail.com
G19: Oficinas de empresa | H19: info@nglavanderias.com | I19: tintoreriasdelfin@hotmail.com
G20: Tienda de artículos para el hogar | H20: lavanderiamedina@hotmail.es | I20: josefinazurera@hotmail.com
... G25: Tienda de productos para mascotas | H25: info@hostalcampana.es | I25: speedqueengranada@gmail.com
G26: 0 | H26: info@lacoladaweb.com | I26: tintoreriasandaluzas@gmail.com
H27: hello@ecospin.es | I27: blancolorzubia@hotmail.es
H28: hello@designbuildweb.co | I28: santafe@bloomest.es
H29: info@yonolavo.com | I29: ssanchez38@gmail.com
H30: info@coladaexpres.com | I30: surtinte@gmail.com
H31: hola@lawash.es | I31: castor@limpiezascastor.es
H32: info@dimasa.org | I32: lavanderiabloomesthuelva@bloomest.es
H33: atencion@washup.es | I33: cleanature@live.com
H34: parsi@lavanderiaindustrialparsi.es | I34: cuellar@bloomest.es
H35: info@inolav.es | I35: alicanterenfe@bloomest.es
H36: cendra@cendra-higiene.es | I36: sax@bloomest.es
H37: info@novanature.es | I37: alicantemercado@bloomest.es
H38: nes@5asec.com | I38: santomera@bloomest.es
... H274: info@perfectclean.es | I274: klin.ondarroa@gmail.com
H275: contacto@icserveis.org
H276: launderettetime@gmail.com
H277: info@lavanderiamogan.com
H278: sovereignpropertymanagement@gmail.com
H279: info@mccleancanarias.com
H280: lavanderia.y.industrial@gmail.com
H281: direccion@lavanderiaatlantico.net
H282: tintoreriasataute@tintoreriasataute.com
H283: info@urbanclean.es
H284: recepcion@tintoreriaavenida.com
H285: support-deu@dish.co
H286: info@eurosanexfuerteventura.com
... H797: info@campingigara.com

Sheet Copyright
A1: Esta base de datos de empresas se encuentra protegida bajo derechos de autor. Está prohibida su copia y reproducción con o sin ánimo de lucro bajo autorización expresa del autor según artículo 270, 270.2, 270.3, 270.4, 270.5, 270.6, 270.7 Como medida de seguridad hay registros clave a modo de firma digital registrados ante notario y ante la consejería de cultura y patrimonio histórico con número GR-00416-2020

Sheet Leads verificados
A1: ﻿Nombre | B1: Categoría | C1: Dirección | D1: Ciudad | E1: Provincia | F1: website | G1: Teléfono | H1: email | I1: mail verificado
A2: Lavandería Almería - Nature Lavandería | B2: Lavandería de autoservicio | C2: Calle Calz. de Castro, 36, 04006 Almería, España | D2: Almería, España | E2: España | F2: naturelavanderia.es | G2: +34 663 86 68 22 | H2: malaga@naturelavanderia.es | I2: TRUE
A3: Tintorería Lavaclean | B3: Tintorería | C3: Calle José Artés de Arcos, 21, BAJO, 04004 Almería, España | D3: Almería, España | E3: España | F3: tintorerialavaclean.com | G3: +34 950 25 31 42 | H3: tintorerialavaclean@hotmail.com | I3: TRUE
A4: Lavandería Mir Sl | B4: Lavandería | C4: Nº, Calle Rio Guadiana, 72, 04240 Viator, Almería, España | D4: Viator, España | E4: España | F4: lavanderiamir.com | G4: +34 950 30 43 89 | H4: lavanderiamir@lavanderiamir.com | I4: TRUE
A5: Lavandería Lavamar | B5: Servicio de lavandería | C5: Calle Dioniso, s/n, 04740 Roquetas de Mar, Almería, España | D5: Roquetas de Mar, España | E5: España | F5: lavanderialavamar.com | G5: +34 950 32 71 67 | H5: lavamarlavanderia@gmail.com | I5: TRUE
A6: Eulen | B6: Servicio de limpieza | C6: Calle Estaño, 0, 04001 Almería, España | D6: Almería, España | E6: España | F6: eulen.com | G6: +34 950 62 44 03 | H6: dcomercial@eulen.com | I6: TRUE
A7: Lavapul | B7: Lavandería | C7: Av. Estación, 29, 04649 Pulpí, Almería, España | D7: Pulpí, España | E7: España | F7: lavanderiasenlimpio.com | G7: +34 657 50 28 19 | H7: lavapul@gmail.com | I7: TRUE
A8: ILUNION | B8: Lavandería | C8: Polígono Industrial Zona Franca, Calle San Roque, s/n, 11006 Cádiz, España | D8: Cádiz, España | E8: España | F8: lavanderia.ilunion.com | G8: +34 956 28 41 46 | H8: u003Einfo.lavanderia@ilunion.com | I8: TRUE
A9: Lavanderia Medina | B9: Lavandería | C9: Arroyo de Galbarro,, Cádiz, España | D9: Medina-Sidonia, España | E9: España | F9: lavanderiamedina.es | G9: +34 956 42 33 97 | H9: lavanderiamedina@hotmail.es | I9: TRUE
A10: Fissa Cádiz | B10: Servicios de limpieza | C10: Calle Viento del Sur, 6, 11100 San Fernando, Cádiz, España | D10: San Fernando, España | E10: España | F10: grupofissa.com | G10: +34 956 59 70 20 | H10: salamanca@grupofissa.com | I10: TRUE
A11: Wash-up - Huelin - Lavandería Autoservicio | B11: Lavandería de autoservicio | C11: Calle Infantes, 37, 29002 Málaga, España | D11: Málaga, España | E11: España | F11: washup.es | G11: +34 689 91 77 78 | H11: atencion@washup.es | I11: TRUE
A12: Parsi Lavandería Industrial | B12: Lavandería | C12: Calle Parsi 6, nº 44, 41016 Sevilla, España | D12: Sevilla, España | E12: España | F12: lavanderiaindustrialparsi.es | G12: +34 669 76 34 38 | H12: parsi@lavanderiaindustrialparsi.es | I12: TRUE
A13: Cendra | B13: Servicio de lavandería | C13: Calle Almonte, 10, 29004 Málaga, España | D13: Málaga, España | E13: España | F13: cendra-higiene.es | G13: +34 951 13 93 63 | H13: cendra@cendra-higiene.es | I13: TRUE
A14: Tintorería 5àsec | B14: Tintorería | C14: Calle Río, 3, 29002 Málaga, España | D14: Málaga, España | E14: España | F14: 5asec.es | G14: +34 952 34 34 86 | H14: nes@5asec.com | I14: TRUE
A15: Washrocks - APP de Tintorería a domicilio | B15: Tintorería | D15: Alcalá de los Gazules | F15: washrocks.com | G15: +34 654 27 51 62 | H15: ayuda@washrocks.com | I15: TRUE
A16: Alliance Laundry Systems Spain S L | B16: Lavandería de autoservicio | C16: Carrer del Solsonès, 2, 08820 El Prat de Llobregat, Barcelona, España | D16: El Prat de Llobregat, España | E16: España | F16: alliancelaundry.es | G16: +34 934 79 54 10 | H16: info-China@alliancels.com | I16: TRUE
A17: Click And Clean - Lavandería Autoservicio - Córdoba | B17: Lavandería | C17: Calle Ronda de la Manca, 4, 14010 Córdoba, España | D17: Córdoba, España | E17: España | F17: lavanderiasclickandclean.es | G17: +34 623 41 51 94 | H17: lavanderiasclickandclean@gmail.com | I17: TRUE
A18: Lavanderia Avanza | B18: Tintorería | C18: Pol. Ind. Pedroches, Calle los Metalúrgicos, 66, 14014 Córdoba, España | D18: Córdoba, España | E18: España | F18: lavanderiaavanza.com | G18: +34 606 23 87 87 | H18: avanzamm27@gmail.com | I18: TRUE
A19: Tintorerías Damasco y Coral | B19: Tintorería | C19: Calle el Almendro, 3, 14006 Córdoba, España | D19: Córdoba, España | E19: España | F19: tintoreriacoralcordoba.es | G19: +34 957 27 20 09 | H19: tintoreriasdelfin@hotmail.com | I19: TRUE
A20: Tintorería en Córdoba | Higiensec | B20: Tintorería | C20: Calle Felipe II, 15, 14005 Córdoba, España | D20: Córdoba, España | E20: España | F20: tintoreria-cordoba.es | G20: +34 957 41 17 44 | H20: josefinazurera@hotmail.com | I20: TRUE
A21: Hilo y Plancha | B21: Lavandería | C21: Calle Ángel de Saavedra, 2, 14003 Córdoba, España | D21: Córdoba, España | E21: España | F21: hiloyplancha.es | G21: +34 957 48 52 51 | H21: t.villena@hiloyplancha.es | I21: TRUE
A22: Empresas Limpieza | Brillo Expres | B22: Servicios de limpieza | C22: Calle Betis, 31 - Local 1, 14011 Córdoba, España | D22: Córdoba, España | E22: España | F22: brilloexpres.com | G22: +34 957 76 77 24 | H22: brilloexpres@brilloexpres.com | I22: TRUE
A23: Lavandería Industrial Rubio S.R.L | B23: Lavandería | C23: Polígono Industrial Quintos, 3 Parcela, 14193 Fontanar de Quintos, España | D23: Fontanar de Quintos, España | E23: España | F23: cplavanderiarubio.jimdo.com | G23: +34 957 32 45 81 | H23: lavanderiaindustrialrubio@gmail.com | I23: TRUE
A24: Centro de Limpieza Hermanos Espinar López S.L. | B24: Lavandería | C24: Calle el Batán, 14816 Zagrilla Baja, Córdoba, España | D24: Zagrilla Baja, España | E24: España | F24: limpiezaespinarlopez.com | G24: +34 651 84 43 22 | H24: limpiezaespinarlopez@hotmail.com | I24: TRUE
A25: Lavandería Autoservicio Granada Speed Queen-4ECO (Limpieza a Granel) | B25: Lavandería de autoservicio | C25: Calle Acera de Canasteros, 2, 18001 Granada, España | D25: Granada, España | E25: España | F25: lavanderiasgranada.com | G25: +34 667 45 62 10 | H25: speedqueengranada@gmail.com | I25: TRUE
A26: Tintorerias Andaluzas | B26: Tintorería | C26: Calle Real, 9, 18200 Maracena, Granada, España | D26: Maracena, España | E26: España | F26: tintoreriasandaluzas.com | G26: +34 633 41 97 01 | H26: tintoreriasandaluzas@gmail.com | I26: TRUE
A27: TINTORERÍA LA ZUBIA | B27: Tintorería | C27: Calle Cerezo, 10, 18140 La Zubia, Granada, España | D27: La Zubia, España | E27: España | F27: lavanderiablancolor.com | G27: +34 958 89 06 56 | H27: blancolorzubia@hotmail.es | I27: TRUE
... A99: LavanderiaAzul Lavandería Autoservicio Adeje | TheBlueLaundry Self Service Laundry | B99: Lavandería de autoservicio | C99: Av. de la Constitución, 45, 38670 Adeje, Santa Cruz de Tenerife, España | D99: Adeje, España | E99: España | F99: lavanderiaazul.es | G99: +34 661 13 59 96 | H99: lavanderiaautolavado@gmail.com | I99: TRUE
A100: La Lavandería | B100: Servicio de lavandería | D100: Adeje | F100: lalavanderiasur.com | G100: +34 699 81 17 15 | H100: lalavanderiasur@gmail.com | I100: TRUE
A101: Santander Lavanderia Industrial | B101: Tintorería | C101: Calle el Somo, 56, 39012 Santander, Cantabria, España | D101: Santander, España | E101: España | F101: santanderlavanderiaindustrial.com | G101: +34 685 91 01 57 | H101: santanderlavanderiaindustrial@gmail.com | I101: TRUE
A102: TINTORERIA LAVANDERIA Y ARREGLOS MALLABIA | B102: Tintorería | C102: Gernikako Arbola Etorbidea, 36, 48902 Barakaldo, Bizkaia, España | D102: Baracaldo, España | E102: España | F102: tintoreriamallabia.com | G102: +34 944 37 21 00 | H102: tintomallabia@gmail.com | I102: TRUE
A103: LAYFIL,S.L. | B103: Lavandería | C103: 48810 Alonsotegi, BI, España | D103: Alonsótegui, España | E103: España | F103: layfil.com | G103: +34 944 86 01 33 | H103: layfil@layfil.com | I103: TRUE
A104: Lavanindu S.L. | B104: Lavandería | C104: Barrio de Martiartu, 18, 48480 Martiartu, BI, España | D104: Martiartu, España | E104: España | F104: lavanindu.es | G104: +34 946 71 39 11 | H104: lavanindu@lavanindu.es | I104: TRUE
A105: Lavandería Limcos Burgos | B105: Lavandería | C105: Calle Los Rompizales, 5, 09001 Burgos, España | D105: Burgos, España | E105: España | F105: grupolimcos.es | G105: +34 947 20 48 71 | H105: limcosburgos@gmail.com | I105: TRUE
A106: Tintorería - Lavandería Garbiñe | B106: Lavandería de autoservicio | C106: Gorbea Kalea, 46, BJ, 01012 Gasteiz, Araba, España | D106: Vitoria-Gasteiz, España | E106: España | F106: tintoreriagarbine.com | G106: +34 945 24 88 48 | H106: tintegarbine@gmail.com | I106: TRUE
A107: Albalimp | B107: Servicios de limpieza | C107: Calle Antonio Gotor, 7, 02002 Albacete, España | D107: Albacete, España | E107: España | F107: albalimp.com | G107: +34 967 50 41 97 | H107: limpieza@albalimp.com | I107: TRUE
A108: TINTORERIA APRESTO | B108: Tintorería | C108: Calle Padres Capuchinos, 8, 13200 Manzanares, Cdad. Real, España | D108: Manzanares, España | E108: España | F108: tintoreriarapidaydecalidad.es | G108: +34 926 61 15 45 | H108: ifernandez@padellasede.com | I108: TRUE
A109: Lavandería autoservicio Bloomest en Campo de Criptana | B109: Lavandería de autoservicio | C109: Calle Isaac Peral, 38, 13610 Campo de Criptana, Cdad. Real, España | D109: Campo de Criptana, España | E109: España | F109: campodecriptana.bloomest.es | G109: +34 634 54 60 85 | H109: campodecriptana@bloomest.es | I109: TRUE
A110: Lavandería Autoservicio Bloomest en Alcorcón | B110: Lavandería de autoservicio | C110: Paseo Castilla, 3, 28921 Alcorcón, Madrid, España | D110: Alcorcón, España | E110: España | F110: alcorcon.bloomest.es | G110: +34 628 33 74 64 | H110: alcorcon@bloomest.es | I110: TRUE
A111: Lavanderia Autoservicio Bloomest Leganés | B111: Lavandería de autoservicio | C111: Plaza Hernán Cortés, 4, 28911 Leganés, Madrid, España | D111: Leganés, España | E111: España | F111: leganes.bloomest.es | G111: +34 640 83 12 74 | H111: leganes@bloomest.es | I111: TRUE
A112: Lavandería Coslada - Bloomest | B112: Lavandería de autoservicio | C112: Calle Venezuela, 9, 28823 Coslada, Madrid, España | D112: Coslada, España | E112: España | F112: coslada.bloomest.es | G112: +34 687 16 22 25 | H112: coslada@bloomest.es | I112: TRUE
... A114: Limpiezas el Pilar | B114: Servicios de limpieza | C114: Calle San José, 2, 16400 Tarancón, Cuenca, España | D114: Tarancón, España | E114: España | F114: limpiezaselpilar.es | G114: +34 619 74 99 30 | H114: limpiezaselpilar@gmail.com | I114: TRUE
A115: YAKLEAN | B115: Servicio de limpieza de tapicería | D115: Abia de la Obispalía | F115: yaklean.com | G115: +34 601 27 14 63 | H115: infoyaklean@gmail.com | I115: TRUE
A116: Hnos Velasco Martel | B116: Servicio de lavandería | C116: Downtown Henares Corridor Area, 28013 Guadalajara, Madrid, España | D116: Abánades | E116: España | F116: hnosvelascomartel.es | G116: +34 630 00 35 80 | H116: david@hnosvelascomartel.es | I116: TRUE
A117: Tintorería Seq | B117: Tintorería | C117: Calle de Jorge Manrique, 8, 28110 Algete, Madrid, España | D117: Algete, España | E117: España | F117: tintoreriaseq.com | G117: +34 916 28 14 82 | H117: lanegralina@hotmail.com | I117: TRUE
A118: Tintoreria Lavanderia Higiensec Avila | B118: Tintorería | C118: Paseo Ntra. Sra. de Sonsoles, 2, 05002 Ávila, España | D118: Ávila, España | E118: España | F118: avilatintoreriahigiensec.es | G118: +34 920 21 21 25 | H118: vitelacastillayleon@gmail.com | I118: TRUE
A119: Carmen Deza Limpiezas Brillo S L | B119: Servicios de limpieza | C119: Calle Río Tera, 56, 05004 Ávila, España | D119: Ávila, España | E119: España | F119: limpiezasbrillo.net | G119: +34 920 25 04 46 | H119: jose@limpiezasbrillo.net | I119: TRUE
A120: Lavandería Industrial Kenia | B120: Servicio de lavandería | C120: Calle Andalucía, 48, P76, 78, 34004 Palencia, España | D120: Palencia, España | E120: España | F120: lavanderiakenia.es | G120: +34 979 16 01 14 | H120: kenia@lavanderiakenia.es | I120: TRUE
A121: Tintorería Lavandería Imperial | B121: Tintorería | C121: Rúa de Alfonso XIII, 38, 36201 Vigo, Pontevedra, España | D121: Vigo, España | E121: España | F121: tintoreriaimperial.es | G121: +34 986 22 26 59 | H121: imperialtintoreria@gmail.com | I121: TRUE
A122: Lavamac Burgos | B122: Lavandería de autoservicio | C122: C. de las Calzadas, 4, 09004 Burgos, España | D122: Burgos, España | E122: España | F122: lavamacburgos.com | G122: +34 947 10 88 97 | H122: pintorgalgo@gmail.com | I122: TRUE
A123: Lavandería Autoservicio ECO30 | B123: Lavandería de autoservicio | C123: Calle Doña Constanza, 13, 09007 Burgos, España | D123: Burgos, España | E123: España | F123: eco30.es | G123: +34 947 65 59 03 | H123: hernandocorral@gmail.com | I123: TRUE
A124: Tintorerías Tarma | B124: Tintorería | C124: Calle Gral. Sanz Pastor, 18, 09003 Burgos, España | D124: Burgos, España | E124: España | F124: tintoreriastarma.es | G124: +34 947 27 52 25 | H124: ricardotarma@gmail.com | I124: TRUE
A125: Teleplancha Burgos | B125: Servicio de limpieza | C125: Calle la Catedra, 14, 09003 Burgos, España | D125: Burgos, España | E125: España | F125: teleplanchaburgos.es | G125: +34 644 60 31 13 | H125: teleplanchaburgos@hotmail.com | I125: TRUE
A126: Electronica Industrial Bocanegra Sl | C126: Calle de Manuel Muñoz Guillén, 9, 09007 Burgos, España | D126: Burgos, España | E126: España | F126: elecbocanegra.com | H126: eib@elecbocanegra.com | I126: TRUE
A127: Lavandería Autoservicio La Colada de Adri | B127: Lavandería de autoservicio | C127: Av. San Mamés, 31, 24007 León, España | D127: León, España | E127: España | F127: lacoladadeadri.es | G127: +34 651 61 19 33 | H127: lacoladadeadri@hotmail.com | I127: TRUE
A128: Lavandería Grupo Sangar | B128: Tintorería | C128: Av Emilio Hurtado, 24007 León, España | D128: León, España | E128: España | F128: gruposangar.com | G128: +34 987 22 89 21 | H128: gruposangar@hotmail.com | I128: TRUE
A129: Tintorería La Torre | B129: Tintorería | C129: Calle Conde de Barcelona, 6, 24007 León, España | D129: León, España | E129: España | F129: tintorerialatorre.es | G129: +34 987 24 70 03 | H129: aloyoso@hotmail.com | I129: TRUE
A130: Vit-Sec | B130: Tintorería | C130: Calle Maestro Nicolás, 40, 24005 León, España | D130: León, España | E130: España | F130: leolimp.blogspot.com | G130: +34 987 26 34 43 | H130: leolimp@gmail.com | I130: TRUE
A131: LAVACOR TINTORERÍAS SL | B131: Tintorería | C131: Calle Colón, 7, 24001 León, España | D131: León, España | E131: España | F131: lavacortintorerias.com | G131: +34 987 04 94 74 | H131: lavacor@gmail.com | I131: TRUE
A132: La Colada Palencia | B132: Lavandería | C132: Av. Santander, 29, 34003 Palencia, España | D132: Palencia, España | E132: España | F132: lacoladapalencia.com | G132: +34 661 33 78 67 | H132: lacoladapalencia@gmail.com | I132: TRUE
A133: Todo Limpio | B133: Tintorería | C133: Av. Santander, 53, 49, 34003 Palencia, España | D133: Palencia, España | E133: España | F133: todolimpiopalencia.com | H133: todolimpiopalencia@hotmail.com | I133: TRUE
A134: Grupo Lince Limpiezas | B134: Servicio de limpieza | C134: Calle de Pilar Miró, 1, 47008 Valladolid, España | D134: Valladolid, España | E134: España | F134: grupolince.com | G134: +34 983 59 19 46 | H134: daniel.clavero@grupolince.com | I134: TRUE
A135: Colada Jamaica | B135: Lavandería de autoservicio | C135: Calle Jamaica, 2, 10, 37003 Salamanca, España | D135: Salamanca, España | E135: España | F135: coladajamaica.es | G135: +34 661 24 16 77 | H135: coladajamaica@coladajamaica.es | I135: TRUE
A136: LaColada Pizarrales | B136: Lavandería | C136: 37006 ctra/ledesma101, 37006 Salamanca, España | D136: Salamanca, España | E136: España | F136: la-colada.ueniweb.com | G136: +34 609 78 48 09 | H136: antoniocabero13@gmail.com | I136: TRUE
A137: Azor Limpiezas y Servicios | B137: Servicio de limpieza | C137: Calle de Jesús Arambarri, 37, 37003 Salamanca, España | D137: Salamanca, España | E137: España | F137: azorlimpiezas.com | G137: +34 923 18 29 29 | H137: azor@azorlimpiezas.com | I137: TRUE
A138: Lavanderia Cartagena 21 | B138: Lavandería | C138: Calle de Cartagena, 21, 28012 Madrid, España | D138: Madrid, España | E138: España | F138: lavayseca.com | G138: +34 910 91 03 13 | H138: sample@Email.com | I138: TRUE
A139: LA PLANCHA VELOZ | B139: Tintorería | C139: Calle de Villafranca, 15, 28028 Madrid, España | D139: Madrid, España | E139: España | F139: laplanchaveloz.com | H139: pedidos@laplanchaveloz.com | I139: TRUE
A140: Lavanderia Industrial Colmenar | B140: Lavandería | C140: Calle de la Navalaosa, 45, 28770 Colmenar Viejo, Madrid, España | D140: Colmenar Viejo, España | E140: España | F140: lavanderiacolmenar.com | G140: +34 918 45 43 72 | H140: lavanderiaindustrialcolmenar@gmail.com | I140: TRUE
A141: Lavandería Casla | B141: Servicio de lavandería | C141: Calle el Sol, 30, 40590 Casla, Segovia, España | D141: Casla, España | E141: España | F141: lavanderiacasla.com | G141: +34 921 50 81 95 | H141: lavanderia.casla.segovia@gmail.com | I141: TRUE
A142: La Tintorería | B142: Tintorería | C142: Calle de Cobos de Segovia, 19, 28005 Madrid, España | D142: Madrid, España | E142: España | F142: latintoreriaonline.es | G142: +34 913 66 71 76 | H142: tintocobos@gmail.com | I142: TRUE
A143: LAVANDERÍA INDUSTRIAL ANIRA | B143: Servicio de lavandería | C143: Calle del Bronce, 12, 28450 Collado Mediano, Madrid, España | D143: Collado Mediano, España | E143: España | F143: aniralavanderia.com | G143: +34 918 59 87 12 | H143: anira@aniralavanderia.com | I143: TRUE
A144: La lavandería de Sergio | B144: Lavandería | C144: Calle San Benito, 10, 42001 Soria, España | D144: Soria, España | E144: España | F144: lalavanderiadesergio.com | G144: +34 975 24 66 38 | H144: lalavanderiadesergio@gmail.com | I144: TRUE
A145: Lavandería del Razón | B145: Servicio de lavandería | C145: Urb. Los Servales, 42165 Molinos de Razón, Soria, España | D145: Molinos de Razón, España | E145: España | F145: lavanderiadelrazon.com | G145: +34 975 27 31 15 | H145: francisco@lavanderiarazon.com | I145: TRUE
A146: Lavandería Autoservicio La Casa de la Colada Alcorcon | B146: Lavandería de autoservicio | C146: Calle Soria, 7, 28921 Alcorcón, Madrid, España | D146: Alcorcón, España | E146: España | F146: lacasadelacoladaalcorcon.com | G146: +34 640 10 33 59 | H146: alcorcon@lacasadelacolada.com | I146: TRUE
A147: Lavanderia Autoservicio Bloomest en Valladolid | B147: Lavandería de autoservicio | C147: Calle Huelgas, 14, 47005 Valladolid, España | D147: Valladolid, España | E147: España | F147: valladolid.bloomest.es | G147: +34 675 80 13 80 | H147: valladolid@bloomest.es | I147: TRUE
A148: LavaTuColada Torrelago | B148: Lavandería de autoservicio | C148: Av. de la Libertad, 24, 47140 Laguna de Duero, Valladolid, España | D148: Laguna de Duero, España | E148: España | F148: lavatucolada.com | G148: +34 640 88 21 19 | H148: lava@lavatucolada.com | I148: TRUE
A149: Alfombraexpress | B149: Servicio de limpieza de alfombras | D149: Adalia | F149: alfombraexpress.com | G149: +34 983 30 24 62 | H149: alfombra@alfombraexpress.com | I149: TRUE
A150: Lavandería Self Service Bloomest en Alcobendas | B150: Lavandería de autoservicio | C150: Calle de Ramón Fernández Guisasola, 5, 28100 Alcobendas, Madrid, España | D150: Alcobendas, España | E150: España | F150: alcobendas.bloomest.es | G150: +34 616 73 46 76 | H150: alcobendas@bloomest.es | I150: TRUE
A151: Tintorería Higiensec Madrid | B151: Tintorería | C151: Cl. de Antonio Zamora, 13, 28011 Madrid, España | D151: Madrid, España | E151: España | F151: tintoreriahigiensecmadrid.es | G151: +34 914 64 38 27 | H151: simonrdguez@gmail.com | I151: TRUE
A152: Martrilimp S L | B152: Servicios de limpieza | C152: Calle de las Delicias, 1, 28300 Aranjuez, Madrid, España | D152: Aranjuez, España | E152: España | F152: martrilimp.es | G152: +34 918 91 57 64 | H152: martrilimp@martrilimp.es | I152: TRUE
A153: Lavandería Mirallers | B153: Lavandería de autoservicio | C153: Carrer dels Mirallers, 2 BAJO, TIENDA-2, 08003 Barcelona, España | D153: Barcelona, España | E153: España | F153: lavanderiamirallers.net | G153: +34 933 10 57 88 | H153: alnobay@hotmail.com | I153: TRUE
A154: Mary Wash Gombau Lavandería | B154: Lavandería de autoservicio | C154: Carrer de Gombau, 10, 08003 Barcelona, España | D154: Barcelona, España | E154: España | F154: marywash.es | G154: +34 934 70 58 70 | H154: contacte@marywash.es | I154: TRUE
A155: LAVANDERÍA AUTOSERVICIO BLOOMEST EN BARCELONA | B155: Lavandería de autoservicio | C155: Carrer de los Castillejos, 207, 08013 Barcelona, España | D155: Barcelona, España | E155: España | F155: glories.bloomest.es | G155: +34 691 83 19 76 | H155: glories@bloomest.es | I155: TRUE
A156: Lavanderia Industrial Barceloneta | B156: Servicio de lavandería | C156: Carrer del Dr. Giné i Partagàs, 32, 08003 Barcelona, España | D156: Barcelona, España | E156: España | F156: lavanderiaindustrialbarceloneta.com | G156: +34 933 10 11 26 | H156: bbarceloneta@hotmail.com | I156: TRUE
A157: Bugaderia Autoservei Speed Queen | B157: Lavandería de autoservicio | C157: Lavandería autoservicio, Carrer de Sicília, 240, 08013 Barcelona, España | D157: Barcelona, España | E157: España | F157: lavanderiautoserviciobcn.com | G157: +34 654 69 40 58 | H157: sqsicilia@gmail.com | I157: TRUE
A158: Bugaderia Pie | B158: Lavandería | C158: C/ d&apos;Aragó, 485, 08013 Barcelona, España | D158: Barcelona, España | E158: España | F158: lavanderiapie.com | G158: +34 932 31 38 66 | H158: lavanderiapie@hotmail.com | I158: TRUE
A159: Lavandería Autoservicio La Wash Carrer Londres Barcelona | B159: Lavandería de autoservicio | C159: Carrer de Londres, 81, 08036 Barcelona, España | D159: Barcelona, España | E159: España | F159: lawash-londresbcn.es | G159: +34 666 24 24 60 | H159: cvandenbussche@gmail.com | I159: TRUE
A160: La Colada | B160: Lavandería de autoservicio | C160: Carrer de l&apos;Estadella, 79, 08030 Barcelona, España | D160: Barcelona, España | E160: España | F160: lavalotodo.net | H160: lavalotodo@lavalotodo.net | I160: TRUE
A161: Tintoreria Ninot Villarroel | B161: Tintorería | C161: C. de Villarroel, 217, 08036 Barcelona, España | D161: Barcelona, España | E161: España | F161: tintoreria-ninot.com | G161: +34 933 22 28 56 | H161: ninottintoreria@telefonica.net | I161: TRUE
A162: Bloomest | B162: Servicio de lavandería | C162: Carrer de Concepción Arenal, 240, 08030 Barcelona, España | D162: Barcelona, España | E162: España | F162: santandreu.bloomest.es | G162: +34 640 62 74 59 | H162: santandreu@bloomest.es | I162: TRUE
A163: Bugaderia Blanc Blau Lavandería Industrial | B163: Lavandería | C163: Carrer de Sant Eudald, 41, 08023 Barcelona, España | D163: Barcelona, España | E163: España | F163: bugaderiablancblau.es | G163: +34 932 10 32 13 | H163: bugaderiablancblau@gmail.com | I163: TRUE
A164: Lavandería Industrial Alluma | B164: Servicio de lavandería | C164: Carrer de Caracas, 12, 08030 Barcelona, España | D164: Barcelona, España | E164: España | F164: alluma.es | G164: +34 933 49 32 90 | H164: jordi@alclama.es | I164: TRUE
A165: JordiJoantintorers | B165: Tintorería | C165: Carrer de Casanova, 136, 08036 Barcelona, España | D165: Barcelona, España | E165: España | F165: jordijoantintorers.com | G165: +34 934 54 94 42 | H165: jordijoantintorers@gmail.com | I165: TRUE
A166: Bugaderia Roy | B166: Tintorería | C166: Carrer de Sant Antoni Abat, 59, 08001 Barcelona, España | D166: Barcelona, España | E166: España | F166: tintoreriaroy.es | G166: +34 934 41 16 93 | H166: roy@tintorerias.net | I166: TRUE
A167: Noplanxing | B167: Tintorería | C167: Carrer d&apos;Enric Granados, nº9, 08172 Barcelona, España | D167: Barcelona, España | E167: España | F167: noplanxing.com | G167: +34 937 21 18 88 | H167: noplanxing@gmail.com | I167: TRUE
A168: Lisersa, Lavanderia Industrial | B168: Lavandería | C168: Av. Taronger, 99, 08755 Castellbisbal, Barcelona, España | D168: Castellbisbal, España | E168: España | F168: lisersa.es | G168: +34 930 38 40 39 | H168: lisersa@lisersa.es | I168: TRUE
A169: Bugaderia Gubern SL | B169: Lavandería | C169: Carrer del Capcir, 1, 08211 Castellar del Vallès, Barcelona, España | D169: Castellar del Vallés, España | E169: España | F169: bugaderiagubern.com | G169: +34 937 14 53 32 | H169: buggubern@gmail.com | I169: TRUE
A170: Lavandería Speed Queen | B170: Lavandería de autoservicio | C170: Avinguda de Puig i Cadafalch, 284, 08303 Mataró, Barcelona, España | D170: Mataró, España | E170: España | F170: speedqueen.cat | H170: speedqueenametlla@gmail.com | I170: TRUE
A171: Girbau - Esponellà I Fills | C171: Carrer, Disseminat del Campdorà, 78, 17461 Campdorà, Girona, España | D171: Campdorá, España | E171: España | F171: girbauesponellaifills.com | G171: +34 972 20 49 51 | H171: girbau@esponellaifills.com | I171: TRUE
A172: Bugaderia laFundació (Grup Fundació Ramon Noguera) | B172: Lavandería | C172: Carrer de la Indústria, 22, 17005 Girona, España | D172: Gerona, España | E172: España | F172: grupfrn.cat | G172: +34 972 24 94 03 | H172: comunicacio@grupfrn.cat | I172: TRUE
...
