Workbook

Sheet Canteras
A1: ﻿Nombre | B1: Categoría | C1: Rating | D1: Nº Reviews | E1: Horario | F1: Código Plus | G1: Direccion | H1: Localidad | I1: Provincia | J1: Website | K1: Teléfono | L1: email | M1: Reclamar | N1: Latitud | O1: Longitud | P1: Url en Maps | Q1: Iframe | R1: Imagen Url
A2: Mina de Talco | B2: Mina | C2: 4,7 | D2: 3 | E2: viernes, Abierto 24 horas; sábado, Abierto 24 horas; domingo, Abierto 24 horas; lunes, Abierto 24 horas; martes, Abierto 24 horas; miércoles, Abierto 24 horas; jueves, Abierto 24 horas | F2: VG3C+9W Almería | G2: Acceso a A-7, 04008 Almería | H2: Almería | I2: Almería | L2: - | M2: Sí | N2: 36.8534497 | O2: -2.4776319 | P2: https://goo.gl/maps/H7zr6KFoZGtTPcYe8 | Q2: <iframe src="https://www.google.com/maps/embed?pb=!1m18!1m12!1m3!1d102177.29575124479!2d-2.5096470540265146!3d36.84150627352816!2m3!1f0!2f0!3f0!3m2!1i1024!2i768!4f13.1!3m3!1m2!1s0xd7075e3c8d5c031%3A0xb3a18684c09ff2ed!2sMina%20de%20Talco!5e0!3m2!1ses!2ses!4v1651828762041!5m2!1ses!2ses" width="600" height="450" style="border:0;" allowfullscreen="" loading="lazy" referrerpolicy="no-referrer-when-downgrade"></iframe> | R2: https://lh5.googleusercontent.com/p/AF1QipNYA_-JNgsH10SzKiBpJER4nVp8QOnuUIR-QQmX=w408-h544-k-no
A3: Instituto Geologico Y Minero De España | B3: Oficina de gobierno local | F3: RGPM+C9 Almería | G3: C. Real, 115, 04002 Almería | H3: Almería | I3: Almería | K3: 950 25 11 66 | L3: - | M3: Sí | N3: 36.836107 | O3: -2.4666197 | P3: https://goo.gl/maps/s5APDuVoixjdzfCm9 | Q3: <iframe src="https://www.google.com/maps/embed?pb=!1m18!1m12!1m3!1d102177.29575124479!2d-2.5096470540265146!3d36.84150627352816!2m3!1f0!2f0!3f0!3m2!1i1024!2i768!4f13.1!3m3!1m2!1s0xd7076043e130c4d%3A0xbe8908974fb212c8!2sInstituto%20Geologico%20Y%20Minero%20De%20Espa%C3%B1a!5e0!3m2!1ses!2ses!4v1651828770778!5m2!1ses!2ses" width="600" height="450" style="border:0;" allowfullscreen="" loading="lazy" referrerpolicy="no-referrer-when-downgrade"></iframe> | R3: https://streetviewpixels-pa.googleapis.com/v1/thumbnail?panoid=VyhU0bYhaHdxzEqojEztsw&cb_client=search.gws-prod.gps&w=408&h=240&yaw=133.7938&pitch=0&thumbfov=100
A4: Minas De Rodalquilar | B4: Mina | C4: 4,3 | D4: 108 | E4: viernes, Abierto 24 horas; sábado, Abierto 24 horas; domingo, Abierto 24 horas; lunes, Abierto 24 horas; martes, Abierto 24 horas; miércoles, Abierto 24 horas; jueves, Abierto 24 horas | F4: VX33+87 Níjar | G4: C. Apartadero, 9, 04115 Níjar, Almería | H4: Níjar | I4: Almería | L4: - | M4: Sí | N4: 36.8532568 | O4: -2.0467748 | P4: https://goo.gl/maps/SD9PnMMPdjKsf6qAA | Q4: <iframe src="https://www.google.com/maps/embed?pb=!1m18!1m12!1m3!1d102161.5935192764!2d-2.1168126417968627!3d36.853256800000004!2m3!1f0!2f0!3f0!3m2!1i1024!2i768!4f13.1!3m3!1m2!1s0xd7ae953d0696c25%3A0x8a62f495a746f766!2sMinas%20De%20Rodalquilar!5e0!3m2!1ses!2ses!4v1651828776746!5m2!1ses!2ses" width="600" height="450" style="border:0;" allowfullscreen="" loading="lazy" referrerpolicy="no-referrer-when-downgrade"></iframe> | R4: https://lh5.googleusercontent.com/p/AF1QipM7JNxYV8MiPi3HM41YePyLgqPUWbAgqo8XW1CK=w426-h240-k-no
A5: Minas de La Partala | B5: Lugar de interés histórico | C5: 5,0 | D5: 2 | F5: WG9C+RC Benahadux | G5: 04410 Benahadux, Almería | H5: Benahadux | I5: Almería | L5: - | M5: Sí | N5: 36.9196174 | O5: -2.4789464 | P5: https://goo.gl/maps/SmUHY1fFsZWVYxPk8 | Q5: <iframe src="https://www.google.com/maps/embed?pb=!1m18!1m12!1m3!1d102072.83519346103!2d-2.5489842417968744!3d36.91961739999999!2m3!1f0!2f0!3f0!3m2!1i1024!2i768!4f13.1!3m3!1m2!1s0xd70759b1e56f223%3A0x8b8797f288f78fbf!2sMinas%20de%20La%20Partala!5e0!3m2!1ses!2ses!4v1651828782527!5m2!1ses!2ses" width="600" height="450" style="border:0;" allowfullscreen="" loading="lazy" referrerpolicy="no-referrer-when-downgrade"></iframe> | R5: https://lh5.googleusercontent.com/p/AF1QipOs0wJod4bzUqg84etBq1bUn7o0tW1VFa8Lsx1D=w408-h541-k-no
A6: Minas del Carmen | B6: Mina | C6: 4,0 | D6: 4 | F6: V9P9+WX El Marchal de Antón López | G6: Barranco de Plateros, 04729 El Marchal de Antón López, Almería | H6: El Marchal de Antón López | I6: Almería | L6: - | M6: Sí | N6: 36.8872855 | O6: -2.6301245 | P6: https://goo.gl/maps/zfidVebut4PraLzH7 | Q6: <iframe src="https://www.google.com/maps/embed?pb=!1m18!1m12!1m3!1d102116.09672020565!2d-2.700162341796924!3d36.88728550000001!2m3!1f0!2f0!3f0!3m2!1i1024!2i768!4f13.1!3m3!1m2!1s0xd706d77358504af%3A0x37b9100bdcc479e!2sMinas%20del%20Carmen!5e0!3m2!1ses!2ses!4v1651828788372!5m2!1ses!2ses" width="600" height="450" style="border:0;" allowfullscreen="" loading="lazy" referrerpolicy="no-referrer-when-downgrade"></iframe> | R6: https://lh5.googleusercontent.com/p/AF1QipPwoDRQBuprdGz2YFbXC241WUL55fdjpLrXuSV9=w408-h663-k-no
A7: Coto Láisquez | B7: Mina | C7: 5,0 | D7: 1 | F7: XPPW+R2 Huebro | G7: 04119, Almería | H7: Huebro | I7: Almería | L7: - | M7: Sí | N7: 36.9870472 | O7: -2.2549732 | P7: https://goo.gl/maps/WWaxpbBjMZybCnaB7 | Q7: <iframe src="https://www.google.com/maps/embed?pb=!1m18!1m12!1m3!1d101982.50654396469!2d-2.325011041796891!3d36.98704719999999!2m3!1f0!2f0!3f0!3m2!1i1024!2i768!4f13.1!3m3!1m2!1s0xd7abc5a9ac3a90d%3A0xf7da6cb6cc27f67!2sCoto%20L%C3%A1isquez!5e0!3m2!1ses!2ses!4v1651828795700!5m2!1ses!2ses" width="600" height="450" style="border:0;" allowfullscreen="" loading="lazy" referrerpolicy="no-referrer-when-downgrade"></iframe> | R7: https://lh5.googleusercontent.com/p/AF1QipMYoUFQJt3hJsAjeZV-P92PkECTwivwkSYagNmG=w408-h306-k-no
A8: Ingeniera Técnica Minera Fadrique | B8: Ingeniero de minas | E8: viernes, De 7:00 a 20:00; sábado, De 7:00 a 14:00; domingo, Cerrado; lunes, De 7:00 a 20:00; martes, De 7:00 a 20:00; miércoles, De 7:00 a 20:00; jueves, De 7:00 a 20:00 | F8: R9MQ+9C La Envía | G8: Calle de los Nogales, 25, 04727 La Envía, Almería | H8: La Envía | I8: Almería | K8: 655 64 34 85 | L8: - | M8: No | N8: 36.8333937 | O8: -2.6114838 | P8: https://goo.gl/maps/KxMmiMVJdCop3rMB9 | Q8: <iframe src="https://www.google.com/maps/embed?pb=!1m18!1m12!1m3!1d102188.12606272443!2d-2.681470341796881!3d36.833399700000015!2m3!1f0!2f0!3f0!3m2!1i1024!2i768!4f13.1!3m3!1m2!1s0xd707114dd75b5f1%3A0x56f1858ef64cd51e!2sIngeniera%20T%C3%A9cnica%20Minera%20Fadrique!5e0!3m2!1ses!2ses!4v1651828801903!5m2!1ses!2ses" width="600" height="450" style="border:0;" allowfullscreen="" loading="lazy" referrerpolicy="no-referrer-when-downgrade"></iframe>
A9: Poblado minero de San Diego | B9: Mina | C9: 4,7 | D9: 9 | E9: viernes, Abierto 24 horas; sábado, Abierto 24 horas; domingo, Abierto 24 horas; lunes, Abierto 24 horas; martes, Abierto 24 horas; miércoles, Abierto 24 horas; jueves, Abierto 24 horas | F9: RWXM+7W Níjar | G9: 04115 Níjar, Almería | H9: Níjar | I9: Almería | L9: - | M9: Sí | N9: 36.84815 | O9: -2.0651921 | P9: https://goo.gl/maps/D7BfbL3PA9u6PSAk9 | Q9: <iframe src="https://www.google.com/maps/embed?pb=!1m18!1m12!1m3!1d102168.41826557778!2d-2.1352299417968745!3d36.84815000000001!2m3!1f0!2f0!3f0!3m2!1i1024!2i768!4f13.1!3m3!1m2!1s0xd7aeeaaf2909097%3A0x386f3f166850bbf8!2sPoblado%20minero%20de%20San%20Diego!5e0!3m2!1ses!2ses!4v1651828809200!5m2!1ses!2ses" width="600" height="450" style="border:0;" allowfullscreen="" loading="lazy" referrerpolicy="no-referrer-when-downgrade"></iframe> | R9: https://lh5.googleusercontent.com/p/AF1QipO09354IuIgbGZU2eDfYwYEx4EyVn2WhgWSMCh3=w408-h306-k-no
A10: Mina Felisa | B10: Zona de senderismo | E10: viernes, Abierto 24 horas; sábado, Abierto 24 horas; domingo, Abierto 24 horas; lunes, Abierto 24 horas; martes, Abierto 24 horas; miércoles, Abierto 24 horas; jueves, Abierto 24 horas | F10: XHHF+77 Rioja | G10: 04260 Rioja, Almería | H10: Rioja | I10: Almería | L10: - | M10: Sí | N10: 36.9782066 | O10: -2.4267534 | P10: https://goo.gl/maps/Y5wNWRgPgevQFJuy5 | Q10: <iframe src="https://www.google.com/maps/embed?pb=!1m18!1m12!1m3!1d101994.35741913112!2d-2.496791241796892!3d36.97820660000001!2m3!1f0!2f0!3f0!3m2!1i1024!2i768!4f13.1!3m3!1m2!1s0xd7aa1efb46fc53d%3A0x1bc8cfa011f2779f!2sMina%20Felisa!5e0!3m2!1ses!2ses!4v1651828815684!5m2!1ses!2ses" width="600" height="450" style="border:0;" allowfullscreen="" loading="lazy" referrerpolicy="no-referrer-when-downgrade"></iframe> | R10: https://lh5.googleusercontent.com/p/AF1QipNwOCS-JHDjZfmfJ-6f6QHAXrT3hoKVMn8ziDJV=w408-h306-k-no
A11: COMISUR COMPAÑIAS MINERAS DEL SUR S.A. | B11: Empresa minera | F11: 8MMX+M8 Macael | G11: Av. Almería, 21, 04867 Macael, Almería | H11: Macael | I11: Almería | K11: 950 12 88 34 | L11: - | M11: No | N11: 37.3342412 | O11: -2.3016892 | P11: https://goo.gl/maps/5WygwnVrhBAre5YD8 | Q11: <iframe src="https://www.google.com/maps/embed?pb=!1m18!1m12!1m3!1d101515.173781624!2d-2.3717270417968748!3d37.334241200000015!2m3!1f0!2f0!3f0!3m2!1i1024!2i768!4f13.1!3m3!1m2!1s0xd654d04830d5cf1%3A0x600cf9e3fe2978!2sCOMISUR%20COMPA%C3%91IAS%20MINERAS%20DEL%20SUR%20S.A.!5e0!3m2!1ses!2ses!4v1651828821856!5m2!1ses!2ses" width="600" height="450" style="border:0;" allowfullscreen="" loading="lazy" referrerpolicy="no-referrer-when-downgrade"></iframe> | R11: https://streetviewpixels-pa.googleapis.com/v1/thumbnail?panoid=AtJ6xYJe92dlU4Okf9_5gA&cb_client=search.gws-prod.gps&w=408&h=240&yaw=341.44754&pitch=0&thumbfov=100
A12: Hornos de calcinación | B12: Museo | C12: 4,4 | D12: 211 | E12: viernes, Abierto 24 horas; sábado, Abierto 24 horas; domingo, Abierto 24 horas; lunes, Abierto 24 horas; martes, Abierto 24 horas; miércoles, Abierto 24 horas; jueves, Abierto 24 horas | F12: 2QRQ+43 Lucainena de las Torres | G12: 04210 Lucainena de las Torres, Almería | H12: Lucainena de las Torres | I12: Almería | K12: 950 36 30 71 | L12: - | M12: Sí | N12: 37.040343 | O12: -2.2122642 | P12: https://goo.gl/maps/WnrR8ztznt4wtdBE8 | Q12: <iframe src="https://www.google.com/maps/embed?pb=!1m18!1m12!1m3!1d101911.01178879624!2d-2.282302041796875!3d37.04034299999999!2m3!1f0!2f0!3f0!3m2!1i1024!2i768!4f13.1!3m3!1m2!1s0xd7ab9429a1bb43b%3A0x3cec3ea2160950f3!2sHornos%20de%20calcinaci%C3%B3n!5e0!3m2!1ses!2ses!4v1651828828966!5m2!1ses!2ses" width="600" height="450" style="border:0;" allowfullscreen="" loading="lazy" referrerpolicy="no-referrer-when-downgrade"></iframe> | R12: https://lh5.googleusercontent.com/p/AF1QipMAjIT8oMCLRrD0AjgCihCh7vbC2HqHRRyuji08=w408-h306-k-no
A13: Las Menas poblado minero | B13: Lugar de interés histórico | C13: 4,3 | D13: 19 | F13: 7FMR+GF Serón | G13: 04897 Serón, Almería | H13: Serón | I13: Almería | J13: turismoseron.es | L13: info@turismoseron.es | M13: Sí | N13: 37.2837955 | O13: -2.5088387 | P13: https://goo.gl/maps/v4uWqBUEYe7z9ssv9 | Q13: <iframe src="https://www.google.com/maps/embed?pb=!1m18!1m12!1m3!1d101583.30695762283!2d-2.5788765417968746!3d37.28379549999998!2m3!1f0!2f0!3f0!3m2!1i1024!2i768!4f13.1!3m3!1m2!1s0xd6fff4c0b1d9edb%3A0x9a749ea8bcf64cd0!2sLas%20Menas%20poblado%20minero!5e0!3m2!1ses!2ses!4v1651828843215!5m2!1ses!2ses" width="600" height="450" style="border:0;" allowfullscreen="" loading="lazy" referrerpolicy="no-referrer-when-downgrade"></iframe> | R13: https://lh5.googleusercontent.com/p/AF1QipNsrk5I9WZNglbVetmgqi8jnI_izfWxtmvYr6Sv=w408-h271-k-no
A14: Monumento al minero | B14: Parque | C14: 4,6 | D14: 22 | E14: viernes, Abierto 24 horas; sábado, Abierto 24 horas; domingo, Abierto 24 horas; lunes, Abierto 24 horas; martes, Abierto 24 horas; miércoles, Abierto 24 horas; jueves, Abierto 24 horas | F14: X4JV+6F Fondón | G14: 04460 Fondón, Almería | H14: Fondón | I14: Almería | L14: - | M14: Sí | N14: 36.9805923 | O14: -2.8563226 | P14: https://goo.gl/maps/ZwKtyt9kc1zXyTu26 | Q14: <iframe src="https://www.google.com/maps/embed?pb=!1m18!1m12!1m3!1d101991.15961376754!2d-2.926360441796875!3d36.980592299999984!2m3!1f0!2f0!3f0!3m2!1i1024!2i768!4f13.1!3m3!1m2!1s0xd703fa88c9e6aa5%3A0xa5fdc0b20e50b9d9!2sMonumento%20al%20minero!5e0!3m2!1ses!2ses!4v1651828856512!5m2!1ses!2ses" width="600" height="450" style="border:0;" allowfullscreen="" loading="lazy" referrerpolicy="no-referrer-when-downgrade"></iframe> | R14: https://lh5.googleusercontent.com/p/AF1QipMbazg4gNgEpO03rWgWkxpHD__FgdiEb1PgOGsi=w408-h306-k-no
A15: Bitmineros | B15: Equipo para minería | C15: 5,0 | D15: 7 | E15: viernes, De 9:00 a 17:00; sábado, Cerrado; domingo, Cerrado; lunes, De 9:00 a 17:00; martes, De 9:00 a 17:00; miércoles, De 9:00 a 17:00; jueves, De 9:00 a 17:00 | F15: Q9GR+43 Roquetas de Mar | G15: C. Lugo, 12, puerta 4, 04740 Roquetas de Mar, Almería | H15: Roquetas de Mar | I15: Almería | J15: bitmineros.net | K15: 672 01 20 05 | L15: core-js-bundle@3.2.1 | M15: No | N15: 36.7753057 | O15: -2.6098554 | P15: https://goo.gl/maps/M4nSq51M7SB843jE8 | Q15: <iframe src="https://www.google.com/maps/embed?pb=!1m18!1m12!1m3!1d102265.6855392626!2d-2.6798951417968664!3d36.775301!2m3!1f0!2f0!3f0!3m2!1i1024!2i768!4f13.1!3m3!1m2!1s0xd7071d06732952f%3A0xafe2f126298786d6!2sBitmineros!5e0!3m2!1ses!2ses!4v1651828864231!5m2!1ses!2ses" width="600" height="450" style="border:0;" allowfullscreen="" loading="lazy" referrerpolicy="no-referrer-when-downgrade"></iframe> | R15: https://lh5.googleusercontent.com/p/AF1QipM-GNrNlKv3K4PRpFm0JEOsRjzU_f7IJyakIIER=w408-h333-k-no
A16: Poblado Minero El Arteal | B16: Lugar de interés histórico | C16: 3,8 | D16: 16 | E16: viernes, Abierto 24 horas; sábado, Abierto 24 horas; domingo, Abierto 24 horas; lunes, Abierto 24 horas; martes, Abierto 24 horas; miércoles, Abierto 24 horas; jueves, Abierto 24 horas | F16: 76C9+PC El Arteal | G16: Unnamed Road, 04618, Almería | H16: El Arteal | I16: Almería | L16: - | M16: Sí | N16: 37.2717802 | O16: -1.7814317 | P16: https://goo.gl/maps/1joQjeRWa7dbnkRDA | Q16: <iframe src="https://www.google.com/maps/embed?pb=!1m18!1m12!1m3!1d101599.52350127177!2d-1.8514695417968752!3d37.27178020000001!2m3!1f0!2f0!3f0!3m2!1i1024!2i768!4f13.1!3m3!1m2!1s0xd7b2b889fe46bc7%3A0x3df4b2950223e484!2sPoblado%20Minero%20El%20Arteal!5e0!3m2!1ses!2ses!4v1651828870402!5m2!1ses!2ses" width="600" height="450" style="border:0;" allowfullscreen="" loading="lazy" referrerpolicy="no-referrer-when-downgrade"></iframe> | R16: https://lh5.googleusercontent.com/p/AF1QipP4OXw1pkmp-Hct5DGS7DHUwdwz8ELWOEwXAfSu=w426-h240-k-no
A17: Monumento a la Mineria | B17: Museo | C17: 4,5 | D17: 2 | F17: 7FMQ+8J Serón | G17: 04897 Serón, Almería | H17: Serón | I17: Almería | L17: - | M17: Sí | N17: 37.2833103 | O17: -2.5109057 | P17: https://goo.gl/maps/b3LAWYVp5FmT5LyA6 | Q17: <iframe src="https://www.google.com/maps/embed?pb=!1m18!1m12!1m3!1d101583.9618981604!2d-2.580943541796875!3d37.283310300000004!2m3!1f0!2f0!3f0!3m2!1i1024!2i768!4f13.1!3m3!1m2!1s0xd6ffe3a8da6cab1%3A0xa43339deece9f8c4!2sMonumento%20a%20la%20Mineria!5e0!3m2!1ses!2ses!4v1651828876714!5m2!1ses!2ses" width="600" height="450" style="border:0;" allowfullscreen="" loading="lazy" referrerpolicy="no-referrer-when-downgrade"></iframe> | R17: https://lh5.googleusercontent.com/p/AF1QipPGQFN70KW_6J6O6RBdVEW6pX_hlMK1XVYAH7qc=w408-h306-k-no
A18: Minera De Orgiva S L | B18: Empresa minera | C18: 4,0 | D18: 2 | F18: WH2J+P7 Órgiva | G18: C. Almeria, 8, 18400 Órgiva, Granada | H18: Órgiva | I18: Granada | K18: 858 78 40 58 | L18: - | M18: Sí | N18: 36.90176 | O18: -3.4193022 | P18: https://goo.gl/maps/VdJJBQKJ186iyYro7 | Q18: <iframe src="https://www.google.com/maps/embed?pb=!1m18!1m12!1m3!1d102096.73321181926!2d-3.489347841796875!3d36.90175999999998!2m3!1f0!2f0!3f0!3m2!1i1024!2i768!4f13.1!3m3!1m2!1s0xd71bffe28f5a17f%3A0x4ae3cd8f325c317c!2sMinera%20De%20Orgiva%20S%20L!5e0!3m2!1ses!2ses!4v1651828882792!5m2!1ses!2ses" width="600" height="450" style="border:0;" allowfullscreen="" loading="lazy" referrerpolicy="no-referrer-when-downgrade"></iframe> | R18: https://lh5.googleusercontent.com/p/AF1QipN4tY5c2pF41fVVqE2hJlvDWvPYCbMdKxYTiQdJ=w426-h240-k-no
A19: Poblado minero ruinas Rodalquilar | B19: Lugar de interés histórico | C19: 3,4 | D19: 5 | E19: viernes, Abierto 24 horas; sábado, Abierto 24 horas; domingo, Abierto 24 horas; lunes, Abierto 24 horas; martes, Abierto 24 horas; miércoles, Abierto 24 horas; jueves, Abierto 24 horas | F19: RXW4+5Q Rodalquilar | G19: C. Villa Cepillo, 97, 04115 Rodalquilar, Almería | H19: Rodalquilar | I19: Almería | L19: - | M19: Sí | N19: 36.8454564 | O19: -2.0430272 | P19: https://goo.gl/maps/iLDef4deToM5pqzy6 | Q19: <iframe src="https://www.google.com/maps/embed?pb=!1m18!1m12!1m3!1d102172.01767557008!2d-2.1130650417968746!3d36.84545639999998!2m3!1f0!2f0!3f0!3m2!1i1024!2i768!4f13.1!3m3!1m2!1s0xd7aefeacd8e8d73%3A0xe3a9ce2ad0ae5e99!2sPoblado%20minero%20ruinas%20Rodalquilar!5e0!3m2!1ses!2ses!4v1651828888934!5m2!1ses!2ses" width="600" height="450" style="border:0;" allowfullscreen="" loading="lazy" referrerpolicy="no-referrer-when-downgrade"></iframe> | R19: https://lh5.googleusercontent.com/p/AF1QipOgMCKJi3obldJlNci0402XKtQCgsevmrESh4mz=w426-h240-k-no
A20: Paseo de la fama de Almería | B20: Lugar de interés histórico | C20: 4,2 | D20: 419 | E20: viernes, Abierto 24 horas; sábado, Abierto 24 horas; domingo, Abierto 24 horas; lunes, Abierto 24 horas; martes, Abierto 24 horas; miércoles, Abierto 24 horas; jueves, Abierto 24 horas | F20: RGPP+WJ Almería | G20: C. Poeta Villaespesa, 2, 04001 Almería | H20: Almería | I20: Almería | K20: 950 21 00 00 | L20: - | M20: Sí | N20: 36.8373313 | O20: -2.4634543 | P20: https://goo.gl/maps/dkopgQjVQTdobwaK7 | Q20: <iframe src="https://www.google.com/maps/embed?pb=!1m18!1m12!1m3!1d25545.718433725233!2d-2.4809637604492187!3d36.837331299999995!2m3!1f0!2f0!3f0!3m2!1i1024!2i768!4f13.1!3m3!1m2!1s0xd7076017d445ab7%3A0x2c051c67fe2dfa80!2sPaseo%20de%20la%20fama%20de%20Almer%C3%ADa!5e0!3m2!1ses!2ses!4v1651828924294!5m2!1ses!2ses" width="600" height="450" style="border:0;" allowfullscreen="" loading="lazy" referrerpolicy="no-referrer-when-downgrade"></iframe> | R20: https://lh5.googleusercontent.com/p/AF1QipOjZA0_XokWR6KWs7fE7bQn9sx3cPmhjOd0dWZq=w408-h544-k-no
A21: Segura | B21: Empresa minera | F21: 2QRX+9M Lucainena de las Torres | G21: C. Juan Pablo II, 10, 04210 Lucainena de las Torres, Almería | H21: Lucainena de las Torres | I21: Almería | L21: - | M21: Sí | N21: 37.0409017 | O21: -2.2008412 | P21: https://goo.gl/maps/VQuMcE9yKGYC7pC1A | Q21: <iframe src="https://www.google.com/maps/embed?pb=!1m18!1m12!1m3!1d25477.565460491365!2d-2.2183506604492185!3d37.0409017!2m3!1f0!2f0!3f0!3m2!1i1024!2i768!4f13.1!3m3!1m2!1s0xd7ac75000000001%3A0x86029fcc8cb93820!2sSegura!5e0!3m2!1ses!2ses!4v1651828946121!5m2!1ses!2ses" width="600" height="450" style="border:0;" allowfullscreen="" loading="lazy" referrerpolicy="no-referrer-when-downgrade"></iframe> | R21: https://streetviewpixels-pa.googleapis.com/v1/thumbnail?panoid=GGHDgkYQiiQtujUES6IXNg&cb_client=search.gws-prod.gps&w=408&h=240&yaw=316.67154&pitch=0&thumbfov=100
A22: Luis Estévez E Hijos | F22: RGQQ+G3 Almería | G22: C. Minero, 2, 04001 Almería | H22: Almería | I22: Almería | L22: - | M22: Sí | N22: 36.83885 | O22: -2.46226 | P22: https://goo.gl/maps/VQzKLUUoffxLCAkm8 | Q22: <iframe src="https://www.google.com/maps/embed?pb=!1m18!1m12!1m3!1d25545.21118370273!2d-2.4797694604492184!3d36.83885000000001!2m3!1f0!2f0!3f0!3m2!1i1024!2i768!4f13.1!3m3!1m2!1s0xd707601a4a76137%3A0xb5759707184235e7!2sLuis%20Est%C3%A9vez%20E%20Hijos!5e0!3m2!1ses!2ses!4v1651828952341!5m2!1ses!2ses" width="600" height="450" style="border:0;" allowfullscreen="" loading="lazy" referrerpolicy="no-referrer-when-downgrade"></iframe> | R22: https://streetviewpixels-pa.googleapis.com/v1/thumbnail?panoid=TyOlrXO0yF-D0IIrL_uIqg&cb_client=search.gws-prod.gps&w=408&h=240&yaw=164.96098&pitch=0&thumbfov=100
A23: El Cable Inglés | B23: Lugar de interés histórico | C23: 4,4 | D23: 242 | E23: viernes, Abierto 24 horas; sábado, Abierto 24 horas; domingo, Abierto 24 horas; lunes, Abierto 24 horas; martes, Abierto 24 horas; miércoles, Abierto 24 horas; jueves, Abierto 24 horas | F23: RGJP+QJ Almería | G23: 04007 Almería | H23: Almería | I23: Almería | L23: - | M23: Sí | N23: 36.8319927 | O23: -2.4634833 | P23: https://goo.gl/maps/drtu8pXDptUSKxPB8 | Q23: <iframe src="https://www.google.com/maps/embed?pb=!1m18!1m12!1m3!1d25545.23399647806!2d-2.479838660449219!3d36.8387817!2m3!1f0!2f0!3f0!3m2!1i1024!2i768!4f13.1!3m3!1m2!1s0xd707712b1e5caad%3A0x41dc8f4dd4e4e00c!2sEl%20Cable%20Ingl%C3%A9s!5e0!3m2!1ses!2ses!4v1651828979934!5m2!1ses!2ses" width="600" height="450" style="border:0;" allowfullscreen="" loading="lazy" referrerpolicy="no-referrer-when-downgrade"></iframe> | R23: https://lh5.googleusercontent.com/p/AF1QipOJZJeKvJ2E9_u3X_k4cfg4clPqCygnba_oKKx4=w408-h305-k-no
A24: Minas de Gádor | B24: Lugar de interés histórico | C24: 5,0 | D24: 1 | F24: WFH7+98 Gádor | G24: 04560 Gádor, Almería | H24: Gádor | I24: Almería | L24: - | M24: Sí | N24: 36.9284412 | O24: -2.5366715 | P24: https://goo.gl/maps/QWwhFkfKGPkyyWK56 | Q24: <iframe src="https://www.google.com/maps/embed?pb=!1m18!1m12!1m3!1d25515.25572712748!2d-2.5541809604492185!3d36.92844120000001!2m3!1f0!2f0!3f0!3m2!1i1024!2i768!4f13.1!3m3!1m2!1s0xd700b862d3e8fc3%3A0x3bc3b34eaaa1de6e!2sMinas%20de%20G%C3%A1dor!5e0!3m2!1ses!2ses!4v1651828986934!5m2!1ses!2ses" width="600" height="450" style="border:0;" allowfullscreen="" loading="lazy" referrerpolicy="no-referrer-when-downgrade"></iframe> | R24: https://lh5.googleusercontent.com/p/AF1QipMQZcF7i06x0m5ctSLtvl6xselgf4oCiE0ZAroa=w408-h544-k-no
A25: Minas de la Solana | B25: Ruta por explotaciones agrícolas | C25: 5,0 | D25: 1 | F25: X5RH+2G Fondón | G25: Unnamed Road, 04458, Almería | H25: Fondón | I25: Almería | L25: - | M25: Sí | N25: 36.9900245 | O25: -2.8211354 | P25: https://goo.gl/maps/gMrgcS76XGHS12uv5 | Q25: <iframe src="https://www.google.com/maps/embed?pb=!1m18!1m12!1m3!1d25494.628727410258!2d-2.8386448604492185!3d36.9900245!2m3!1f0!2f0!3f0!3m2!1i1024!2i768!4f13.1!3m3!1m2!1s0xd703fb616f1b573%3A0x9de393ed1ea10fe!2sMinas%20de%20la%20Solana!5e0!3m2!1ses!2ses!4v1651829006496!5m2!1ses!2ses" width="600" height="450" style="border:0;" allowfullscreen="" loading="lazy" referrerpolicy="no-referrer-when-downgrade"></iframe> | R25: https://lh5.googleusercontent.com/p/AF1QipNrfU9I12rWYXZd4Ug2G6j7nA2T8uff4i-8KSVY=w408-h240-k-no-pi-20-ya240-ro0-fo100
A26: Centro de Interpretación de la Minería de Beires | B26: Museo | F26: 2665+GF Beires | G26: 04458 Beires, Almería | H26: Beires | I26: Almería | L26: - | M26: Sí | N26: 37.0112477 | O26: -2.7912278 | P26: https://goo.gl/maps/tEEDZDkCWNkS6Ka17 | Q26: <iframe src="https://www.google.com/maps/embed?pb=!1m18!1m12!1m3!1d25487.50585902929!2d-2.808795560449218!3d37.0112699!2m3!1f0!2f0!3f0!3m2!1i1024!2i768!4f13.1!3m3!1m2!1s0xd703dcee7f10d47%3A0x766082e6355c81d3!2sCentro%20de%20Interpretaci%C3%B3n%20de%20la%20Miner%C3%ADa%20de%20Beires!5e0!3m2!1ses!2ses!4v1651829060497!5m2!1ses!2ses" width="600" height="450" style="border:0;" allowfullscreen="" loading="lazy" referrerpolicy="no-referrer-when-downgrade"></iframe> | R26: https://streetviewpixels-pa.googleapis.com/v1/thumbnail?panoid=JCFiK43kKFK0eN8XS4ayhg&cb_client=search.gws-prod.gps&w=408&h=240&yaw=284.80847&pitch=0&thumbfov=100
A27: Amigos de la Alcazaba de Almería | B27: Oficinas de empresa | C27: 4,7 | D27: 3 | E27: viernes, De 9:00 a 15:30, De 18:30 a 22:00; sábado, De 9:00 a 15:30, De 18:30 a 22:00; domingo, De 10:00 a 17:00; lunes, Cerrado; martes, De 9:00 a 15:30, De 18:30 a 22:00; miércoles, De 9:00 a 15:30, De 18:30 a 22:00; jueves, De 9:00 a 15:30, De 18:30 a 22:00 | F27: RGQJ+H5 Almería | G27: C. de la Almedina, 16, 04002 Almería | H27: Almería | I27: Almería | J27: amigosdelaalcazaba.org | K27: 608 04 70 08 | L27: asociacion@amigosdelaalcazaba.org | M27: Sí | N27: 36.8389475 | O27: -2.469605 | P27: https://goo.gl/maps/bFvQ6naosScugN5cA | Q27: <iframe src="https://www.google.com/maps/embed?pb=!1m18!1m12!1m3!1d25545.17801660152!2d-2.487115260449219!3d36.83894930000001!2m3!1f0!2f0!3f0!3m2!1i1024!2i768!4f13.1!3m3!1m2!1s0xd7076063b17c725%3A0x2a33ac7ab506b401!2sAmigos%20de%20la%20Alcazaba%20de%20Almer%C3%ADa!5e0!3m2!1ses!2ses!4v1651829067481!5m2!1ses!2ses" width="600" height="450" style="border:0;" allowfullscreen="" loading="lazy" referrerpolicy="no-referrer-when-downgrade"></iframe> | R27: https://lh5.googleusercontent.com/p/AF1QipO7PcCYVOqXoGDuBMymVHFA-ss_mwKPSJeJAAJx=w408-h544-k-no
A28: Mina María Josefa | B28: Mina | C28: 4,0 | D28: 1 | F28: VW58+V9 Albaricoques | G28: 04116, Almería | H28: Albaricoques | I28: Almería | L28: - | M28: Sí | N28: 36.859666 | O28: -2.0840552 | P28: https://goo.gl/maps/CnQjV3gUU2c21rSK8 | Q28: <iframe src="https://www.google.com/maps/embed?pb=!1m18!1m12!1m3!1d25538.256773091554!2d-2.1015646604492186!3d36.859666!2m3!1f0!2f0!3f0!3m2!1i1024!2i768!4f13.1!3m3!1m2!1s0xd7aebf28ea2fc51%3A0xe326d27f2e0ec1a7!2sMina%20Mar%C3%ADa%20Josefa!5e0!3m2!1ses!2ses!4v1651829092387!5m2!1ses!2ses" width="600" height="450" style="border:0;" allowfullscreen="" loading="lazy" referrerpolicy="no-referrer-when-downgrade"></iframe> | R28: https://lh5.googleusercontent.com/p/AF1QipMueoBsbd9SIwZ5uuWv-IWrFNehQPXly5JAyVN-=w426-h240-k-no
A29: Técnicos Consultores Del Sureste S L | B29: Topógrafo | C29: 3,0 | D29: 2 | F29: RHV3+JH Almería | G29: C. Fray Bernardo Martínez Noval, 7, 04006 Almería | H29: Almería | I29: Almería | K29: 950 22 00 82 | L29: - | M29: Sí | N29: 36.8440828 | O29: -2.446094 | P29: https://goo.gl/maps/47ubfF9peHU3Zu9t8 | Q29: <iframe src="https://www.google.com/maps/embed?pb=!1m18!1m12!1m3!1d25543.46334330833!2d-2.463593160449196!3d36.84408259999999!2m3!1f0!2f0!3f0!3m2!1i1024!2i768!4f13.1!3m3!1m2!1s0xd7a9e09f230aa1b%3A0x4fe8767933714e3c!2sT%C3%A9cnicos%20Consultores%20Del%20Sureste%20S%20L!5e0!3m2!1ses!2ses!4v1651829104340!5m2!1ses!2ses" width="600" height="450" style="border:0;" allowfullscreen="" loading="lazy" referrerpolicy="no-referrer-when-downgrade"></iframe> | R29: https://streetviewpixels-pa.googleapis.com/v1/thumbnail?panoid=Q6rUSQZEFvvXPY0L9-OoFg&cb_client=search.gws-prod.gps&w=408&h=240&yaw=222.41898&pitch=0&thumbfov=100
A30: Monumento al Minero | B30: Lugar de interés histórico | C30: 5,0 | D30: 2 | E30: viernes, Abierto 24 horas; sábado, Abierto 24 horas; domingo, Abierto 24 horas; lunes, Abierto 24 horas; martes, Abierto 24 horas; miércoles, Abierto 24 horas; jueves, Abierto 24 horas | F30: 52R9+7P Bédar | G30: C. San Gregorio, 04288 Bédar, Almería | H30: Bédar | I30: Almería | L30: - | M30: Sí | N30: 37.190681 | O30: -1.9807396 | P30: https://goo.gl/maps/JYQARdUW567LWxCn9 | Q30: <iframe src="https://www.google.com/maps/embed?pb=!1m18!1m12!1m3!1d25427.217513275657!2d-1.9982076604492187!3d37.19067560000001!2m3!1f0!2f0!3f0!3m2!1i1024!2i768!4f13.1!3m3!1m2!1s0xd7ad12482cb7721%3A0x14e8910e83a8db61!2sMonumento%20al%20Minero!5e0!3m2!1ses!2ses!4v1651829123888!5m2!1ses!2ses" width="600" height="450" style="border:0;" allowfullscreen="" loading="lazy" referrerpolicy="no-referrer-when-downgrade"></iframe> | R30: https://lh5.googleusercontent.com/p/AF1QipNmjyBwejonhRtKpDaqmTvme-X-9Jp_vdSJ5wzg=w408-h306-k-no
A31: Centro De Interpretación Casa Don Mariano | B31: Museo de artesanía | C31: 4,0 | D31: 1 | F31: XG27+6V Gádor | G31: 04560 Gádor, Almería | H31: Gádor | I31: Almería | J31: gador.es | K31: 950 64 52 11 | L31: - | M31: Sí | N31: 36.9505022 | O31: -2.4851972 | P31: https://goo.gl/maps/fADKuojc1hjnWMB5A | Q31: <iframe src="https://www.google.com/maps/embed?pb=!1m18!1m12!1m3!1d25507.861025081776!2d-2.5027631604492195!3d36.9505287!2m3!1f0!2f0!3f0!3m2!1i1024!2i768!4f13.1!3m3!1m2!1s0xd700bea203faded%3A0xe8b657dd0e6f3e32!2sCentro%20De%20Interpretaci%C3%B3n%20Casa%20Don%20Mariano!5e0!3m2!1ses!2ses!4v1651829136184!5m2!1ses!2ses" width="600" height="450" style="border:0;" allowfullscreen="" loading="lazy" referrerpolicy="no-referrer-when-downgrade"></iframe> | R31: https://lh5.googleusercontent.com/p/AF1QipOY6VvHFpqAM_iryGoz8MCxz2IKvsyQg-7evw-f=w408-h272-k-no
A32: Edison | F32: RGQQ+H4 Almería | G32: C. Minero, 2, 04001 Almería | H32: Almería | I32: Almería | L32: - | M32: Sí | N32: 36.8389162 | O32: -2.4621581 | P32: https://goo.gl/maps/kmbEnfQetAjnxw9c6 | Q32: <iframe src="https://www.google.com/maps/embed?pb=!1m18!1m12!1m3!1d25545.189072310448!2d-2.4796675604492187!3d36.83891620000001!2m3!1f0!2f0!3f0!3m2!1i1024!2i768!4f13.1!3m3!1m2!1s0xd707601bc923fcd%3A0xac96b777375a3b2d!2sEdison!5e0!3m2!1ses!2ses!4v1651829142277!5m2!1ses!2ses" width="600" height="450" style="border:0;" allowfullscreen="" loading="lazy" referrerpolicy="no-referrer-when-downgrade"></iframe> | R32: https://streetviewpixels-pa.googleapis.com/v1/thumbnail?panoid=gx74uHnOVx19NwrE36ESRg&cb_client=search.gws-prod.gps&w=408&h=240&yaw=262.364&pitch=0&thumbfov=100
A33: Viviendas Rurales | B33: Empresa constructora | F33: RGQQ+H5 Almería | G33: C. Minero, 4, 04001 Almería | H33: Almería | I33: Almería | K33: 950 27 44 52 | L33: - | M33: Sí | N33: 36.8389525 | O33: -2.4620378 | P33: https://goo.gl/maps/drb2cxt8BhbKV89M9 | Q33: <iframe src="https://www.google.com/maps/embed?pb=!1m18!1m12!1m3!1d25545.189072310448!2d-2.4796675604492187!3d36.83891620000001!2m3!1f0!2f0!3f0!3m2!1i1024!2i768!4f13.1!3m3!1m2!1s0xd707601bc72d261%3A0xf91dfd492a0ee693!2sViviendas%20Rurales!5e0!3m2!1ses!2ses!4v1651829148340!5m2!1ses!2ses" width="600" height="450" style="border:0;" allowfullscreen="" loading="lazy" referrerpolicy="no-referrer-when-downgrade"></iframe> | R33: https://streetviewpixels-pa.googleapis.com/v1/thumbnail?panoid=s0IsgXhOCek5YnWN-2FUyQ&cb_client=search.gws-prod.gps&w=408&h=240&yaw=229.61386&pitch=0&thumbfov=100
A34: Explotaciones Río De Aguas S L | B34: Contratista de excavación | C34: 5,0 | D34: 2 | F34: 3V7R+X8 Sorbas | G34: Lugar Barriada El Hueli, s/n, 04270 Hueli, Almería | H34: Sorbas | I34: Almería | K34: 950 36 44 00 | L34: - | M34: Sí | N34: 37.06499 | O34: -2.10913 | P34: https://goo.gl/maps/EKVQXooimmwdyp3w5 | Q34: <iframe src="https://www.google.com/maps/embed?pb=!1m18!1m12!1m3!1d25469.47968442922!2d-2.126639460449219!3d37.064989999999995!2m3!1f0!2f0!3f0!3m2!1i1024!2i768!4f13.1!3m3!1m2!1s0xd7ac7aa6dfd670d%3A0x7706546460073507!2sExplotaciones%20R%C3%ADo%20De%20Aguas%20S%20L!5e0!3m2!1ses!2ses!4v1651829154465!5m2!1ses!2ses" width="600" height="450" style="border:0;" allowfullscreen="" loading="lazy" referrerpolicy="no-referrer-when-downgrade"></iframe> | R34: https://lh5.googleusercontent.com/p/AF1QipMEHHWxJu2I2oZ23MTS86JOKEQNWgh7QEOUVfCv=w408-h306-k-no
A35: Mármoles Rosmar | B35: Empresa de mármoles | C35: 4,7 | D35: 12 | E35: viernes, De 8:15 a 13:00, De 15:00 a 19:00; sábado, Cerrado; domingo, Cerrado; lunes, De 8:15 a 13:00, De 15:00 a 19:00; martes, De 8:15 a 13:00, De 15:00 a 19:00; miércoles, De 8:15 a 13:00, De 15:00 a 19:00; jueves, De 8:15 a 13:00, De 15:00 a 19:00 | F35: RHR7+P6 Almería | G35: C. Mármoles, 29, 04007 Almería | H35: Almería | I35: Almería | K35: 950 22 44 37 | L35: - | M35: Sí | N35: 36.8417863 | O35: -2.4369025 | P35: https://goo.gl/maps/QPWsJsurHiBLi7Eo6 | Q35: <iframe src="https://www.google.com/maps/embed?pb=!1m18!1m12!1m3!1d25544.219845042822!2d-2.454387760449219!3d36.84181789999999!2m3!1f0!2f0!3f0!3m2!1i1024!2i768!4f13.1!3m3!1m2!1s0xd7a9ddf14d538fb%3A0x2c1c57b22af0bfca!2sM%C3%A1rmoles%20Rosmar!5e0!3m2!1ses!2ses!4v1651829169919!5m2!1ses!2ses" width="600" height="450" style="border:0;" allowfullscreen="" loading="lazy" referrerpolicy="no-referrer-when-downgrade"></iframe> | R35: https://lh5.googleusercontent.com/p/AF1QipOvgHj16I7CweNEwvAdtSsVanJQ7iQUjk4omqaX=w426-h240-k-no
A36: Instituto Español de Investigación de Estudios Avanzados - IEIEA | B36: Escuela de estudios superiores de posgrado | E36: viernes, De 8:00 a 20:00; sábado, De 10:00 a 14:00; domingo, Cerrado; lunes, De 8:00 a 20:00; martes, De 8:00 a 20:00; miércoles, De 8:00 a 20:00; jueves, De 8:00 a 20:00 | F36: RGQQ+H7 Almería | G36: C. Minero, 8, 04001 Almería | H36: Almería | I36: Almería | K36: 950 25 85 44 | L36: - | M36: No | N36: 36.8389515 | O36: -2.4617941 | P36: https://goo.gl/maps/DTXaoLhn7R22hgX28 | Q36: <iframe src="https://www.google.com/maps/embed?pb=!1m18!1m12!1m3!1d25545.176947771197!2d-2.4795472604492503!3d36.83895250000002!2m3!1f0!2f0!3f0!3m2!1i1024!2i768!4f13.1!3m3!1m2!1s0xd707601bf2885b1%3A0x931d0b3ce91255fe!2sInstituto%20Espa%C3%B1ol%20de%20Investigaci%C3%B3n%20de%20Estudios%20Avanzados%20-%20IEIEA!5e0!3m2!1ses!2ses!4v1651829216091!5m2!1ses!2ses" width="600" height="450" style="border:0;" allowfullscreen="" loading="lazy" referrerpolicy="no-referrer-when-downgrade"></iframe> | R36: https://lh5.googleusercontent.com/p/AF1QipPIeK2-CypPCtNyO-jUr9btSlPpfgjm41_niOsm=w408-h306-k-no
A37: Galería de Los Lobos | B37: Mina | C37: 3,0 | D37: 1 | F37: R54H+W9 El Ejido | G37: Unnamed Road, 04715, Almería | H37: El Ejido | I37: Almería | L37: - | M37: Sí | N37: 36.8072567 | O37: -2.8215612 | P37: https://goo.gl/maps/sUPMbRH6wwZctgqR6 | Q37: <iframe src="https://www.google.com/maps/embed?pb=!1m18!1m12!1m3!1d25555.75973638268!2d-2.8390706604492184!3d36.807256699999996!2m3!1f0!2f0!3f0!3m2!1i1024!2i768!4f13.1!3m3!1m2!1s0xd704334f6206c85%3A0x6a1451c3c82c3746!2sGaler%C3%ADa%20de%20Los%20Lobos!5e0!3m2!1ses!2ses!4v1651829249309!5m2!1ses!2ses" width="600" height="450" style="border:0;" allowfullscreen="" loading="lazy" referrerpolicy="no-referrer-when-downgrade"></iframe>
A38: Minas de Alquife | B38: Mina | C38: 4,1 | D38: 13 | F38: 5VHP+Q5 Alquife | G38: Barriada de Minas del Marquesado, s/n, 18518 Alquife, Granada | H38: Alquife | I38: Granada | J38: alquifemines.com | L38: - | M38: No | N38: 37.1794947 | O38: -3.1146216 | P38: https://goo.gl/maps/2DAXffQd9YoYjPwA8 | Q38: <iframe src="https://www.google.com/maps/embed?pb=!1m18!1m12!1m3!1d25430.9820866196!2d-3.1321310604492187!3d37.1794947!2m3!1f0!2f0!3f0!3m2!1i1024!2i768!4f13.1!3m3!1m2!1s0xd71d4bebc1688d1%3A0xcd7b1a98df7b88a7!2sMinas%20de%20Alquife!5e0!3m2!1ses!2ses!4v1651829263153!5m2!1ses!2ses" width="600" height="450" style="border:0;" allowfullscreen="" loading="lazy" referrerpolicy="no-referrer-when-downgrade"></iframe> | R38: https://lh5.googleusercontent.com/p/AF1QipOzgOZaAQ34nZUg6JEZ_qiR9PCT4WI4ZCr4vMPA=w408-h262-k-no
A39: Torre de los Alumbres | B39: Lugar de interés histórico | C39: 4,0 | D39: 55 | E39: viernes, Abierto 24 horas; sábado, Abierto 24 horas; domingo, Abierto 24 horas; lunes, Abierto 24 horas; martes, Abierto 24 horas; miércoles, Abierto 24 horas; jueves, Abierto 24 horas | F39: VX4P+52 Níjar | G39: 04115 Níjar, Almería | H39: Níjar | I39: Almería | K39: 950 52 51 37 | L39: - | M39: Sí | N39: 36.8555144 | O39: -2.0149463 | P39: https://goo.gl/maps/Fc5EBF3HVSZWrHJC8 | Q39: <iframe src="https://www.google.com/maps/embed?pb=!1m18!1m12!1m3!1d25539.662560160148!2d-2.032470160449219!3d36.855459!2m3!1f0!2f0!3f0!3m2!1i1024!2i768!4f13.1!3m3!1m2!1s0xd7ae8cc337cb295%3A0xf47ef4554748788e!2sTorre%20de%20los%20Alumbres!5e0!3m2!1ses!2ses!4v1651829269325!5m2!1ses!2ses" width="600" height="450" style="border:0;" allowfullscreen="" loading="lazy" referrerpolicy="no-referrer-when-downgrade"></iframe> | R39: https://lh5.googleusercontent.com/p/AF1QipO8gMsOacH7TtusvuoP4cJIbd8Ac6ZZESfjU4BP=w408-h544-k-no
A40: Mina romana de lapis specularis del Espejuelo | C40: 4,4 | D40: 14 | F40: CW3P+W3 Arboleas | G40: 04661 Arboleas, Almería | H40: Arboleas | I40: Almería | J40: arboleas.org | K40: 950 44 94 30 | L40: - | M40: Sí | N40: 37.4048035 | O40: -2.0648623 | P40: https://goo.gl/maps/wCYnLD5S6pjor6EbA | Q40: <iframe src="https://www.google.com/maps/embed?pb=!1m18!1m12!1m3!1d25354.934658167367!2d-2.0823717604492185!3d37.404803499999986!2m3!1f0!2f0!3f0!3m2!1i1024!2i768!4f13.1!3m3!1m2!1s0xd65312b1d86f985%3A0x55a0ba35f2d56ad4!2sMina%20romana%20de%20lapis%20specularis%20del%20Espejuelo!5e0!3m2!1ses!2ses!4v1651829275652!5m2!1ses!2ses" width="600" height="450" style="border:0;" allowfullscreen="" loading="lazy" referrerpolicy="no-referrer-when-downgrade"></iframe> | R40: https://lh5.googleusercontent.com/p/AF1QipNQUDAeGbGPHUkv-p41yaBjFKrKnc-OKGPlZHre=w408-h272-k-no
A41: Las Minas | H41: Abla | L41: - | M41: No | N41: 37.4786708 | O41: -1.9913184 | P41: https://goo.gl/maps/a9RTwjPy1zWyfrPdA | Q41: <iframe src="https://www.google.com/maps/embed?pb=!1m18!1m12!1m3!1d25329.917172798156!2d-2.0088278604492187!3d37.4786708!2m3!1f0!2f0!3f0!3m2!1i1024!2i768!4f13.1!3m3!1m2!1s0xd653acc79e58b67%3A0xc6718f7e6e36c370!2s04693%20Las%20Minas%2C%20Almer%C3%ADa!5e0!3m2!1ses!2ses!4v1651829282294!5m2!1ses!2ses" width="600" height="450" style="border:0;" allowfullscreen="" loading="lazy" referrerpolicy="no-referrer-when-downgrade"></iframe> | R41: https://lh5.googleusercontent.com/p/AF1QipOt6efz8k6aNjpQHmlFzUg6POb4aDGSX8sqb_5_=w408-h306-k-no
A42: Ecomuseo La Casa de los Volcanes-Medio Ambiente | B42: Museo | C42: 4,0 | D42: 98 | E42: viernes, De 10:00 a 14:00; sábado, De 10:00 a 14:00; domingo, De 10:00 a 14:00; lunes, Cerrado; martes, Cerrado; miércoles, De 10:00 a 14:00; jueves, De 10:00 a 14:00 | F42: VX23+RP Níjar | G42: C. Apartadero, 9, 04115 Níjar, Almería | H42: Níjar | I42: Almería | J42: juntadeandalucia.es | K42: 670 34 15 64 | L42: - | M42: No | N42: 36.8521008 | O42: -2.0457379 | P42: https://goo.gl/maps/6M1kd81VofuKwT159 | Q42: <iframe src="https://www.google.com/maps/embed?pb=!1m18!1m12!1m3!1d25540.78461824869!2d-2.0632473604492185!3d36.85210079999999!2m3!1f0!2f0!3f0!3m2!1i1024!2i768!4f13.1!3m3!1m2!1s0xd7ae9356b252a0b%3A0x12df60fe9afe7028!2sEcomuseo%20La%20Casa%20de%20los%20Volcanes-Medio%20Ambiente!5e0!3m2!1ses!2ses!4v1651829288637!5m2!1ses!2ses" width="600" height="450" style="border:0;" allowfullscreen="" loading="lazy" referrerpolicy="no-referrer-when-downgrade"></iframe> | R42: https://lh5.googleusercontent.com/p/AF1QipPdxi5RPGEnyNXge2cT9ls5GUwvfIJZxJVe9eTk=w408-h306-k-no
A43: Mármoles Quesada y Lopez | B43: Fábrica | C43: 5,0 | D43: 1 | F43: VHG3+M7 Huércal de Almería | G43: C. Sagitario, 12, 04230 Huércal de Almería, Almería | H43: Huércal de Almería | I43: Almería | K43: 615 25 22 06 | L43: - | M43: No | N43: 36.8767046 | O43: -2.4468748 | P43: https://goo.gl/maps/CE1QRH6wFePSHLGk7 | Q43: <iframe src="https://www.google.com/maps/embed?pb=!1m18!1m12!1m3!1d25532.561843951324!2d-2.464384260449219!3d36.876704600000004!2m3!1f0!2f0!3f0!3m2!1i1024!2i768!4f13.1!3m3!1m2!1s0xd7a9e30ea96a10b%3A0x591c33514e5db238!2sM%C3%A1rmoles%20Quesada%20y%20Lopez!5e0!3m2!1ses!2ses!4v1651829295013!5m2!1ses!2ses" width="600" height="450" style="border:0;" allowfullscreen="" loading="lazy" referrerpolicy="no-referrer-when-downgrade"></iframe> | R43: https://lh5.googleusercontent.com/p/AF1QipMJgj7ZKBBivcnTKAUXWOqHCfEshRQtvKwjKR7k=w438-h240-k-no
A44: Minas Tres Pacos | B44: Ingeniero de minas | C44: 4,3 | D44: 16 | F44: 84MG+CQ Cuevas del Almanzora | G44: Unnamed Road,, 04619 Cuevas del Almanzora, Almería | H44: Cuevas del Almanzora | I44: Almería | L44: - | M44: Sí | N44: 37.3335611 | O44: -1.8730926 | P44: https://goo.gl/maps/iwjS9r6RAreQThxQ6 | Q44: <iframe src="https://www.google.com/maps/embed?pb=!1m18!1m12!1m3!1d25379.02321611813!2d-1.890602060449219!3d37.3335611!2m3!1f0!2f0!3f0!3m2!1i1024!2i768!4f13.1!3m3!1m2!1s0xd652baddf7397a3%3A0xf04d92260aa7f910!2sMinas%20Tres%20Pacos!5e0!3m2!1ses!2ses!4v1651829301372!5m2!1ses!2ses" width="600" height="450" style="border:0;" allowfullscreen="" loading="lazy" referrerpolicy="no-referrer-when-downgrade"></iframe> | R44: https://lh5.googleusercontent.com/p/AF1QipMJEKPLXZsfoj6n7N6dTSYZrW1WMAlQTX4svH4Z=w426-h240-k-no
A45: Minas de hierro del Cerro del Conjuro | B45: Mina | C45: 3,0 | D45: 1 | F45: WPG7+R6 Cástaras | G45: 18439 Cástaras, Granada | H45: Cástaras | I45: Granada | J45: turgranada.es | L45: fjtitos@turgranada.es | M45: Sí | N45: 36.9271055 | O45: -3.2868322 | P45: https://goo.gl/maps/tEHN4qjDe9CnFEJY9 | Q45: <iframe src="https://www.google.com/maps/embed?pb=!1m18!1m12!1m3!1d25515.702819714523!2d-3.3043866604492185!3d36.927105400000016!2m3!1f0!2f0!3f0!3m2!1i1024!2i768!4f13.1!3m3!1m2!1s0xd71c8740d75803f%3A0xdbcaad7920b6c8a!2sMinas%20de%20hierro%20del%20Cerro%20del%20Conjuro!5e0!3m2!1ses!2ses!4v1651829314169!5m2!1ses!2ses" width="600" height="450" style="border:0;" allowfullscreen="" loading="lazy" referrerpolicy="no-referrer-when-downgrade"></iframe> | R45: https://lh5.googleusercontent.com/p/AF1QipOD_SJndDbxAZgtgBMEiYlhZ5lWUmYCOFQTSnOw=w408-h306-k-no
A46: Mina La Probadora | B46: Mina | F46: 4M73+7W Güejar Sierra | G46: 18160 Güejar Sierra, Granada | H46: Güejar Sierra | I46: Granada | L46: - | M46: Sí | N46: 37.1132316 | O46: -3.3451627 | P46: https://goo.gl/maps/CJMTgtMPpDaHTmop7 | Q46: <iframe src="https://www.google.com/maps/embed?pb=!1m18!1m12!1m3!1d50906.54555845185!2d-3.3801816208984374!3d37.1132316!2m3!1f0!2f0!3f0!3m2!1i1024!2i768!4f13.1!3m3!1m2!1s0xd71dde9731e7eff%3A0x6a82b034604d3512!2sMina%20La%20Probadora!5e0!3m2!1ses!2ses!4v1651829358464!5m2!1ses!2ses" width="600" height="450" style="border:0;" allowfullscreen="" loading="lazy" referrerpolicy="no-referrer-when-downgrade"></iframe> | R46: https://lh5.googleusercontent.com/p/AF1QipPUSo75tCqIMOBFdQU0qj6YZ5pJYyO3kWfkXM-e=w408-h306-k-no
A47: Peña Flamenca El Yunque | B47: Lugar de interés histórico | C47: 1,0 | D47: 1 | F47: WH86+84 Pechina | G47: C. Angustias, 16, 04250 Pechina, Almería | H47: Pechina | I47: Almería | L47: - | M47: Sí | N47: 36.915858 | O47: -2.4397142 | P47: https://goo.gl/maps/H4VmxJJ9sqHu3Em27 | Q47: <iframe src="https://www.google.com/maps/embed?pb=!1m18!1m12!1m3!1d51038.933554416275!2d-2.4747331208984376!3d36.915858!2m3!1f0!2f0!3f0!3m2!1i1024!2i768!4f13.1!3m3!1m2!1s0xd7a9fbd2e08a809%3A0xb832df0b1d7e88e9!2sPe%C3%B1a%20Flamenca%20El%20Yunque!5e0!3m2!1ses!2ses!4v1651829368183!5m2!1ses!2ses" width="600" height="450" style="border:0;" allowfullscreen="" loading="lazy" referrerpolicy="no-referrer-when-downgrade"></iframe> | R47: https://lh5.googleusercontent.com/p/AF1QipNPBdqPSlMJEtFlGJdGe3RY7bCN_ffABNwQIN3N=w408-h725-k-no
A48: Rodalquilar | H48: Abla | L48: - | M48: No | N48: 36.8458936 | O48: -2.0426277 | P48: https://goo.gl/maps/1meLGkZB4GVm2hJz6 | Q48: <iframe src="https://www.google.com/maps/embed?pb=!1m18!1m12!1m3!1d51085.71673415089!2d-2.077646620898437!3d36.845893600000004!2m3!1f0!2f0!3f0!3m2!1i1024!2i768!4f13.1!3m3!1m2!1s0xd7aeecc801d0389%3A0xa240de6647f52b86!2s04115%20Rodalquilar%2C%20Almer%C3%ADa!5e0!3m2!1ses!2ses!4v1651829380292!5m2!1ses!2ses" width="600" height="450" style="border:0;" allowfullscreen="" loading="lazy" referrerpolicy="no-referrer-when-downgrade"></iframe> | R48: https://lh5.googleusercontent.com/p/AF1QipMwWxLHEsZdr3xpt7-4uGc0LALgox1T6kePOY_i=w426-h240-k-no
A49: Explotaciones Arrioca SL | B49: Cantera | C49: 5,0 | D49: 2 | E49: viernes, De 6:30 a 15:30; sábado, De 6:30 a 12:30; domingo, Cerrado; lunes, De 6:30 a 15:30; martes, De 6:30 a 15:30; miércoles, De 6:30 a 15:30; jueves, De 6:30 a 15:30 | F49: R685+4G El Ejido | G49: Paraje el Capitan, 04700 El Ejido, Almería | H49: El Ejido | I49: Almería | J49: arrioca.com | K49: 663 44 11 44 | L49: jrcc@arrioca.com | M49: No | N49: 36.815326 | O49: -2.791202 | P49: https://g.page/ExplotacionesArrioca?share | Q49: <iframe src="https://www.google.com/maps/embed?pb=!1m18!1m12!1m3!1d51106.13250165241!2d-2.8262209208984372!3d36.81532599999999!2m3!1f0!2f0!3f0!3m2!1i1024!2i768!4f13.1!3m3!1m2!1s0xd7042e6ffffffff%3A0x55aba875fc82b7ec!2sExplotaciones%20Arrioca%20SL!5e0!3m2!1ses!2ses!4v1651829386512!5m2!1ses!2ses" width="600" height="450" style="border:0;" allowfullscreen="" loading="lazy" referrerpolicy="no-referrer-when-downgrade"></iframe> | R49: https://lh5.googleusercontent.com/p/AF1QipOJpiIwZYRpxqKuzCWvbm5Ji96rg4oyMcItihcv=w408-h306-k-no
A50: Fuente de los 16 caños | B50: Lugar de interés histórico | C50: 4,5 | D50: 10 | E50: viernes, Abierto 24 horas; sábado, Abierto 24 horas; domingo, Abierto 24 horas; lunes, Abierto 24 horas; martes, Abierto 24 horas; miércoles, Abierto 24 horas; jueves, Abierto 24 horas | F50: R3W2+G4 Berja | G50: Pl. de la Constitución, 4, 3, 04760 Berja, Almería | H50: Berja | I50: Almería | L50: - | M50: Sí | N50: 36.8462994 | O50: -2.9496592 | P50: https://goo.gl/maps/pFnS8tHzcxFKaJiM7 | Q50: <iframe src="https://www.google.com/maps/embed?pb=!1m18!1m12!1m3!1d51085.44560693566!2d-2.984678120898437!3d36.846299400000014!2m3!1f0!2f0!3f0!3m2!1i1024!2i768!4f13.1!3m3!1m2!1s0xd7048bb0cec35d9%3A0x5265bd5102e89856!2sFuente%20de%20los%2016%20ca%C3%B1os!5e0!3m2!1ses!2ses!4v1651829398871!5m2!1ses!2ses" width="600" height="450" style="border:0;" allowfullscreen="" loading="lazy" referrerpolicy="no-referrer-when-downgrade"></iframe> | R50: https://lh5.googleusercontent.com/p/AF1QipN-8cKfM6Pv7zuCyf3kKhWNgxbIWjezx1IBk3qY=w426-h240-k-no
A51: Paraje Natural Sierra Alhamilla | B51: Reserva natural | C51: 4,6 | D51: 285 | F51: XJWQ+39 Tabernas | G51: Almería | H51: Tabernas | I51: Almería | L51: - | M51: Sí | N51: 36.9951608 | O51: -2.3616203 | P51: https://goo.gl/maps/KXEKGXa39Y2Sr8pf8 | Q51: <iframe src="https://www.google.com/maps/embed?pb=!1m18!1m12!1m3!1d50985.81403989269!2d-2.3966392208984373!3d36.995160799999994!2m3!1f0!2f0!3f0!3m2!1i1024!2i768!4f13.1!3m3!1m2!1s0xd7aa37544e1055b%3A0x5c31fad04585fc98!2sParaje%20Natural%20Sierra%20Alhamilla!5e0!3m2!1ses!2ses!4v1651829404949!5m2!1ses!2ses" width="600" height="450" style="border:0;" allowfullscreen="" loading="lazy" referrerpolicy="no-referrer-when-downgrade"></iframe> | R51: https://lh5.googleusercontent.com/p/AF1QipPMR6apOwxRyE8FyC9mrV9ZSAvbPZhJIoI5Ti2z=w426-h240-k-no
A52: MINAS DE ALQUIFE SL | B52: Empresa minera | C52: 5,0 | D52: 2 | F52: 5VC6+JC Lanteira | G52: Carr. del Marquesado, S-N, 18518 Lanteira, Granada | H52: Lanteira | I52: Granada | K52: 958 67 36 48 | L52: - | M52: No | N52: 37.1716 | O52: -3.13889 | P52: https://goo.gl/maps/d1uc1Jwqs8i7gvDs6 | Q52: <iframe src="https://www.google.com/maps/embed?pb=!1m18!1m12!1m3!1d50867.279247214916!2d-3.173908920898437!3d37.17159999999999!2m3!1f0!2f0!3f0!3m2!1i1024!2i768!4f13.1!3m3!1m2!1s0xd71d5171ce209af%3A0x554c42ac82ca8e9!2sMINAS%20DE%20ALQUIFE%20SL!5e0!3m2!1ses!2ses!4v1651829425043!5m2!1ses!2ses" width="600" height="450" style="border:0;" allowfullscreen="" loading="lazy" referrerpolicy="no-referrer-when-downgrade"></iframe> | R52: https://lh5.googleusercontent.com/p/AF1QipNfSKjPAM5FNAn0sY1_zjOp3PvPEU_aT8mSr3w=w408-h271-k-no
A53: Minas de la Cruz | B53: Mina | F53: 9572+H7 Las Juntas | G53: 18870, Granada | H53: Las Juntas | I53: Granada | L53: - | M53: Sí | N53: 37.3638884 | O53: -2.8492675 | P53: https://goo.gl/maps/xvmaNdeoVRqRru5k7 | Q53: <iframe src="https://www.google.com/maps/embed?pb=!1m18!1m12!1m3!1d50737.547421273535!2d-2.8842864208984373!3d37.363888400000015!2m3!1f0!2f0!3f0!3m2!1i1024!2i768!4f13.1!3m3!1m2!1s0xd6fdd5a9b0501b9%3A0x5d4e8974acaa2472!2sMinas%20de%20la%20Cruz!5e0!3m2!1ses!2ses!4v1651829431386!5m2!1ses!2ses" width="600" height="450" style="border:0;" allowfullscreen="" loading="lazy" referrerpolicy="no-referrer-when-downgrade"></iframe>
A54: AM Gabinete de Aguas Subterráneas y Mineria | B54: Asesor en ingeniería | F54: 59QJ+F6 Granada | G54: Ático a, Calle Trucha, 4, 18015 Granada | H54: Granada | I54: Granada | J54: aguaymineria.com | K54: 958 20 81 02 | L54: - | M54: Sí | N54: 37.1886269 | O54: -3.6194087 | P54: https://goo.gl/maps/tec8fxhmidFu76F56 | Q54: <iframe src="https://www.google.com/maps/embed?pb=!1m18!1m12!1m3!1d50855.81475297506!2d-3.6544276208984376!3d37.188626899999996!2m3!1f0!2f0!3f0!3m2!1i1024!2i768!4f13.1!3m3!1m2!1s0xd71fcf82a7def83%3A0x1f9d32a9841300d7!2sAM%20Gabinete%20de%20Aguas%20Subterr%C3%A1neas%20y%20Mineria!5e0!3m2!1ses!2ses!4v1651829437511!5m2!1ses!2ses" width="600" height="450" style="border:0;" allowfullscreen="" loading="lazy" referrerpolicy="no-referrer-when-downgrade"></iframe> | R54: https://streetviewpixels-pa.googleapis.com/v1/thumbnail?panoid=agXBR0QZX3YuuxsdeN9Cvw&cb_client=search.gws-prod.gps&w=408&h=240&yaw=347.0483&pitch=0&thumbfov=100
A55: MARMOLES ORFEMAR S.L.U | B55: Comercio | F55: 9M5C+JF Purchena | G55: CARRETERA HUERCAL OVERA - BAZA 49,5, 04870 Purchena, Almería | H55: Purchena | I55: Almería | K55: 669 70 55 65 | L55: - | M55: No | N55: 37.3590608 | O55: -2.3287815 | P55: https://goo.gl/maps/YBWifGvfqwMKJ7Pt5 | Q55: <iframe src="https://www.google.com/maps/embed?pb=!1m18!1m12!1m3!1d50740.81147314733!2d-2.363800420898438!3d37.359060799999995!2m3!1f0!2f0!3f0!3m2!1i1024!2i768!4f13.1!3m3!1m2!1s0xd655327e52446ff%3A0x4e168dbab17d98b!2sMARMOLES%20ORFEMAR%20S.L.U!5e0!3m2!1ses!2ses!4v1651829450714!5m2!1ses!2ses" width="600" height="450" style="border:0;" allowfullscreen="" loading="lazy" referrerpolicy="no-referrer-when-downgrade"></iframe> | R55: https://lh5.googleusercontent.com/p/AF1QipOkrrPuNnXGVR7TYkw7nB0FyQtc3yZmLF8XFdXA=w517-h240-k-no
A56: Reino Mineral | B56: Empresa minera | F56: 2P3J+2X Trevélez | G56: C. Carcel, 0 S N, 18417 Trevélez, Granada | H56: Trevélez | I56: Granada | K56: 628 81 33 52 | L56: - | M56: Sí | N56: 37.0025326 | O56: -3.2675387 | P56: https://goo.gl/maps/m7FnkaKSRgQ1CXxc9 | Q56: <iframe src="https://www.google.com/maps/embed?pb=!1m18!1m12!1m3!1d50980.8647751811!2d-3.3025591208984375!3d37.002542200000015!2m3!1f0!2f0!3f0!3m2!1i1024!2i768!4f13.1!3m3!1m2!1s0xd71c5fb3b48431f%3A0xf1f82fdb1716e601!2sReino%20Mineral!5e0!3m2!1ses!2ses!4v1651829456824!5m2!1ses!2ses" width="600" height="450" style="border:0;" allowfullscreen="" loading="lazy" referrerpolicy="no-referrer-when-downgrade"></iframe> | R56: https://lh5.googleusercontent.com/p/AF1QipM2XjMSTkY-MPax5KtOIotrFPjy-mXafDqOAE_9=w408-h306-k-no
A57: Mina De La Gabiarra | B57: Museo | C57: 4,0 | D57: 3 | F57: 33GF+22 Paterna del Río | G57: Unnamed Road, 04479, Paterna del Río, Almería | H57: Paterna del Río | I57: Almería | L57: - | M57: Sí | N57: 37.0750458 | O57: -2.9274119 | P57: https://goo.gl/maps/ujN5XpDRHtoc7zPS8 | Q57: <iframe src="https://www.google.com/maps/embed?pb=!1m18!1m12!1m3!1d50932.20579699848!2d-2.9624308208984376!3d37.07504580000002!2m3!1f0!2f0!3f0!3m2!1i1024!2i768!4f13.1!3m3!1m2!1s0xd703abb4a60c377%3A0x534c8fc333b038a4!2sMina%20De%20La%20Gabiarra!5e0!3m2!1ses!2ses!4v1651829462966!5m2!1ses!2ses" width="600" height="450" style="border:0;" allowfullscreen="" loading="lazy" referrerpolicy="no-referrer-when-downgrade"></iframe> | R57: https://lh5.googleusercontent.com/p/AF1QipPw5hEg1-DrxFiWXMsq7dvGuuTe4AUngb0fMhXF=w426-h240-k-no
A58: Zamagara Obras e Ingeniería | B58: Empresa constructora | E58: viernes, De 9:00 a 14:00, De 16:30 a 20:30; sábado, Cerrado; domingo, Cerrado; lunes, De 9:00 a 14:00, De 16:30 a 20:30; martes, De 9:00 a 14:00, De 16:30 a 20:30; miércoles, De 9:00 a 14:00, De 16:30 a 20:30; jueves, De 9:00 a 14:00, De 16:30 a 20:30 | F58: WH76+GQ Pechina | G58: Av. blas Infante, 2, 04250 Pechina, Almería | H58: Pechina | I58: Almería | J58: zoi.es | K58: 950 31 76 00 | L58: info@zoi.es | M58: No | N58: 36.9138553 | O58: -2.438102 | P58: https://goo.gl/maps/etZiBUBs2PV4NiDm7 | Q58: <iframe src="https://www.google.com/maps/embed?pb=!1m18!1m12!1m3!1d51040.27376062406!2d-2.4731209208984377!3d36.91385529999999!2m3!1f0!2f0!3f0!3m2!1i1024!2i768!4f13.1!3m3!1m2!1s0xd7a9f939d487551%3A0x2210f6e1f4d10999!2sZamagara%20Obras%20e%20Ingenier%C3%ADa!5e0!3m2!1ses!2ses!4v1651829477309!5m2!1ses!2ses" width="600" height="450" style="border:0;" allowfullscreen="" loading="lazy" referrerpolicy="no-referrer-when-downgrade"></iframe> | R58: https://streetviewpixels-pa.googleapis.com/v1/thumbnail?panoid=nJiixtkYalfF5b23BIG80g&cb_client=search.gws-prod.gps&w=408&h=240&yaw=318.96222&pitch=0&thumbfov=100
A59: Oxidos Ferricos S.a. | B59: Empresa minera | C59: 5,0 | D59: 1 | F59: 7VXC+QF Guadix | G59: Calle Margarita Nelken, 8 BL.2 - 3, 18500 Guadix, Granada | H59: Guadix | I59: Granada | J59: oxidosferricos.com | K59: 958 66 21 12 | L59: core-js-bundle@3.2.1 | M59: No | N59: 37.2993981 | O59: -3.1287953 | P59: https://goo.gl/maps/ck5RVWv1ud4jEEn69 | Q59: <iframe src="https://www.google.com/maps/embed?pb=!1m18!1m12!1m3!1d50781.121059751735!2d-3.1638142208984372!3d37.299398100000005!2m3!1f0!2f0!3f0!3m2!1i1024!2i768!4f13.1!3m3!1m2!1s0xd6e2b02bcff17eb%3A0xb1002696873c547!2sOxidos%20Ferricos%20S.a.!5e0!3m2!1ses!2ses!4v1651829483590!5m2!1ses!2ses" width="600" height="450" style="border:0;" allowfullscreen="" loading="lazy" referrerpolicy="no-referrer-when-downgrade"></iframe> | R59: https://streetviewpixels-pa.googleapis.com/v1/thumbnail?panoid=hKlPjSs2I2xUdMH-3nuFZg&cb_client=search.gws-prod.gps&w=408&h=240&yaw=329.14694&pitch=0&thumbfov=100
A60: Puente de los mineros albuñaneros | B60: Lugar de interés histórico | F60: 6VC8+9P Jerez del Marquesado | G60: 18518 Jerez del Marquesado, Granada | H60: Jerez del Marquesado | I60: Granada | L60: - | M60: Sí | N60: 37.2209493 | O60: -3.1331413 | P60: https://goo.gl/maps/5F83bGWs7PE6f1FEA | Q60: <iframe src="https://www.google.com/maps/embed?pb=!1m18!1m12!1m3!1d406672.3135237453!2d-3.4132926671874806!3d37.22094930000001!2m3!1f0!2f0!3f0!3m2!1i1024!2i768!4f13.1!3m3!1m2!1s0xd71d5129fc222d5%3A0x31ffcb37d3be3593!2sPuente%20de%20los%20mineros%20albu%C3%B1aneros!5e0!3m2!1ses!2ses!4v1651829515278!5m2!1ses!2ses" width="600" height="450" style="border:0;" allowfullscreen="" loading="lazy" referrerpolicy="no-referrer-when-downgrade"></iframe>
A61: TURBERA DEL AGIA, SL | B61: Empresa minera | C61: 5,0 | D61: 3 | E61: viernes, De 9:00 a 20:00; sábado, Cerrado; domingo, Cerrado; lunes, De 9:00 a 20:00; martes, De 9:00 a 20:00; miércoles, De 9:00 a 20:00; jueves, De 9:00 a 20:00 | F61: 59QQ+4M Granada | G61: Av. de Andalucía, 2, 18014 Granada | H61: Granada | I61: Granada | J61: turberadelagia.com | K61: 958 28 17 10 | L61: comercial@turberadelagia.com | M61: No | N61: 37.1877908 | O61: -3.6108325 | P61: https://goo.gl/maps/LHZNzyEt9PytimmV6 | Q61: <iframe src="https://www.google.com/maps/embed?pb=!1m18!1m12!1m3!1d406851.2121820859!2d-3.8910102671874944!3d37.18775560000002!2m3!1f0!2f0!3f0!3m2!1i1024!2i768!4f13.1!3m3!1m2!1s0xd71f6d49e528f11%3A0xa240e339b46885e4!2sTURBERA%20DEL%20AGIA%2C%20SL!5e0!3m2!1ses!2ses!4v1651829524762!5m2!1ses!2ses" width="600" height="450" style="border:0;" allowfullscreen="" loading="lazy" referrerpolicy="no-referrer-when-downgrade"></iframe> | R61: https://lh5.googleusercontent.com/p/AF1QipOltBRNZ_QxMsNs2FOpxG_ZLzJ9S9aTEF4WfMGF=w408-h550-k-no
A62: Minas de Orgiva S.L. | B62: Oficinas de empresa | F62: VHMW+X6 Los Tablones | G62: Diseminado Diseminados, 186, 18418, Granada | H62: Los Tablones | I62: Granada | K62: 944 00 88 68 | L62: - | M62: Sí | N62: 36.884926 | O62: -3.404385 | P62: https://goo.gl/maps/pjv4eq7oWiM1L2dh9 | Q62: <iframe src="https://www.google.com/maps/embed?pb=!1m18!1m12!1m3!1d408477.0102547862!2d-3.6845363671875035!3d36.88492600000001!2m3!1f0!2f0!3f0!3m2!1i1024!2i768!4f13.1!3m3!1m2!1s0xd71bf631f21c7ff%3A0xddaa5d68505ff730!2sMinas%20de%20Orgiva%20S.L.!5e0!3m2!1ses!2ses!4v1651829537090!5m2!1ses!2ses" width="600" height="450" style="border:0;" allowfullscreen="" loading="lazy" referrerpolicy="no-referrer-when-downgrade"></iframe>
A63: Instituto Geologico Y Minero De España | B63: Comercio | C63: 5,0 | D63: 4 | E63: viernes, De 9:00 a 14:30, De 16:30 a 20:00; sábado, Cerrado; domingo, Cerrado; lunes, De 9:00 a 14:30, De 16:30 a 20:00; martes, De 9:00 a 14:30, De 16:30 a 20:00; miércoles, De 9:00 a 14:30, De 16:30 a 20:00; jueves, De 9:00 a 14:30, De 16:30 a 20:00 | F63: 597X+MP Granada | G63: C. Alcázar Genil, 0, 18001 Granada | H63: Granada | I63: Granada | K63: 958 18 33 14 | L63: - | M63: Sí | N63: 37.1642048 | O63: -3.6006505 | P63: https://goo.gl/maps/unejDaQcG1Tv7wbTA | Q63: <iframe src="https://www.google.com/maps/embed?pb=!1m18!1m12!1m3!1d406978.057270921!2d-3.8808018671874445!3d37.16420479999999!2m3!1f0!2f0!3f0!3m2!1i1024!2i768!4f13.1!3m3!1m2!1s0xd71fca26ee9df4f%3A0x5cd2367d6ea93009!2sInstituto%20Geologico%20Y%20Minero%20De%20Espa%C3%B1a!5e0!3m2!1ses!2ses!4v1651829555683!5m2!1ses!2ses" width="600" height="450" style="border:0;" allowfullscreen="" loading="lazy" referrerpolicy="no-referrer-when-downgrade"></iframe> | R63: https://streetviewpixels-pa.googleapis.com/v1/thumbnail?panoid=BQrUpK3xy0gFYhlYkk05Lg&cb_client=search.gws-prod.gps&w=408&h=240&yaw=151.75882&pitch=0&thumbfov=100
A64: Los Filabres-Tabernas | H64: Abla | L64: - | M64: No | N64: 37.055028 | O64: -2.5792482 | P64: https://goo.gl/maps/Fm3bc6k8CJWwA5T58 | Q64: <iframe src="https://www.google.com/maps/embed?pb=!1m18!1m12!1m3!1d407565.1871725534!2d-2.8593995671875176!3d37.05502799999999!2m3!1f0!2f0!3f0!3m2!1i1024!2i768!4f13.1!3m3!1m2!1s0xd700f4bf62298ab%3A0x703a7fb71e7a5d14!2sLos%20Filabres-Tabernas%2C%20Almer%C3%ADa!5e0!3m2!1ses!2ses!4v1651829594090!5m2!1ses!2ses" width="600" height="450" style="border:0;" allowfullscreen="" loading="lazy" referrerpolicy="no-referrer-when-downgrade"></iframe> | R64: https://lh5.googleusercontent.com/p/AF1QipOoiOMBIOwhvQFDYJKsUorlo4WjNJJMmEUaUu_R=w533-h240-k-no
A65: LEGALIZACIÓN POZOS BELÉN DELGADO | B65: Ingeniero de minas | C65: 4,9 | D65: 49 | E65: viernes, Abierto 24 horas; sábado, Abierto 24 horas; domingo, Abierto 24 horas; lunes, Abierto 24 horas; martes, Abierto 24 horas; miércoles, Abierto 24 horas; jueves, Abierto 24 horas | F65: 68GR+MP Albolote | G65: C. Magallanes, Nº17, 18220 Albolote, Granada | H65: Albolote | I65: Granada | K65: 669 01 56 34 | L65: - | M65: No | N65: 37.2267479 | O65: -3.6582004 | P65: https://goo.gl/maps/VtyQaq3AN6JBM8fB8 | Q65: <iframe src="https://www.google.com/maps/embed?pb=!1m18!1m12!1m3!1d406641.0477509711!2d-3.9383517671874984!3d37.22674789999999!2m3!1f0!2f0!3f0!3m2!1i1024!2i768!4f13.1!3m3!1m2!1s0xd71fdedaebec3df%3A0x3d2366d21de23e2d!2sLEGALIZACI%C3%93N%20POZOS%20BEL%C3%89N%20DELGADO!5e0!3m2!1ses!2ses!4v1651829613434!5m2!1ses!2ses" width="600" height="450" style="border:0;" allowfullscreen="" loading="lazy" referrerpolicy="no-referrer-when-downgrade"></iframe> | R65: https://lh5.googleusercontent.com/p/AF1QipPbs1jmptDAumSjwO7R7VuNc4FBZXDMIOLXEIM0=w408-h306-k-no
A66: Lucainena de las Torres | H66: Abla | L66: - | M66: No | N66: 37.0407929 | O66: -2.201005 | P66: https://goo.gl/maps/zsLrgVY3Nu3g8t3n9 | Q66: <iframe src="https://www.google.com/maps/embed?pb=!1m18!1m12!1m3!1d408183.94820543245!2d-2.2139796671874987!3d36.939670400000004!2m3!1f0!2f0!3f0!3m2!1i1024!2i768!4f13.1!3m3!1m2!1s0xd7ab93e20c90385%3A0xcb019f19d6f7e74e!2s04210%20Lucainena%20de%20las%20Torres%2C%20Almer%C3%ADa!5e0!3m2!1ses!2ses!4v1651829638293!5m2!1ses!2ses" width="600" height="450" style="border:0;" allowfullscreen="" loading="lazy" referrerpolicy="no-referrer-when-downgrade"></iframe> | R66: https://lh5.googleusercontent.com/p/AF1QipOgrBnP1lLgC78GaDRGrSSd5szR8LBd19WaDtnu=w408-h544-k-no
A67: TECNION - PREVENCION DE RIESGOS LABORALES - EL EJIDO | B67: Servicios de empresa a empresa | F67: Q5FR+CP El Ejido | G67: Plaza Poseidón, 24, 04700 El Ejido, Almería | H67: El Ejido | I67: Almería | J67: grupotecnion.es | K67: 950 03 08 88 | L67: legal@grupotecnion.es | M67: No | N67: 36.7735003 | O67: -2.8082208 | P67: https://goo.gl/maps/wmxcoj32K2z15geN6 | Q67: <iframe src="https://www.google.com/maps/embed?pb=!1m18!1m12!1m3!1d409072.3508929033!2d-3.088372167187497!3d36.773500299999995!2m3!1f0!2f0!3f0!3m2!1i1024!2i768!4f13.1!3m3!1m2!1s0xd70432055f2a8cf%3A0x4105f0593f3e21fa!2sTECNION%20-%20PREVENCION%20DE%20RIESGOS%20LABORALES%20-%20EL%20EJIDO!5e0!3m2!1ses!2ses!4v1651829670294!5m2!1ses!2ses" width="600" height="450" style="border:0;" allowfullscreen="" loading="lazy" referrerpolicy="no-referrer-when-downgrade"></iframe> | R67: https://streetviewpixels-pa.googleapis.com/v1/thumbnail?panoid=QXdjqcc6P9-8MY6R0H8OTA&cb_client=search.gws-prod.gps&w=408&h=240&yaw=334.8561&pitch=0&thumbfov=100
A68: MATSA, Minas de Aguas Teñidas | B68: Empresa minera | C68: 4,1 | D68: 86 | E68: viernes, De 8:30 a 17:45; sábado, Cerrado; domingo, Cerrado; lunes, De 8:30 a 17:45; martes, De 8:30 a 17:45; miércoles, De 8:30 a 17:45; jueves, De 8:30 a 17:45 | F68: Q5J7+M7 Almonaster la Real | G68: HU-7104, Km. 12, 21330 Almonaster la Real, Huelva | H68: Almonaster la Real | I68: Huelva | J68: matsamining.com | K68: 959 05 40 12 | L68: dpto.comunicacion@matsamining.com | M68: No | N68: 37.7817126 | O68: -6.8367664 | P68: https://goo.gl/maps/Jhu3mWFfemoFPi8q6 | Q68: <iframe src="https://www.google.com/maps/embed?pb=!1m18!1m12!1m3!1d403629.4772706543!2d-7.116917767187499!3d37.781712600000006!2m3!1f0!2f0!3f0!3m2!1i1024!2i768!4f13.1!3m3!1m2!1s0xd110b9370f46b47%3A0xe24fa09610e7573b!2sMATSA%2C%20Minas%20de%20Aguas%20Te%C3%B1idas!5e0!3m2!1ses!2ses!4v1651829685216!5m2!1ses!2ses" width="600" height="450" style="border:0;" allowfullscreen="" loading="lazy" referrerpolicy="no-referrer-when-downgrade"></iframe> | R68: https://lh5.googleusercontent.com/p/AF1QipOow_F0tNqfE5ARRayYRLqh3tNUugieWJ4Ri4Tt=w427-h240-k-no
A69: Eulogio Caravantes Iniciativas Geomineras | B69: Empresa minera | E69: viernes, De 8:30 a 20:00; sábado, Cerrado; domingo, Cerrado; lunes, De 8:30 a 20:00; martes, De 8:30 a 20:00; miércoles, De 8:30 a 20:00; jueves, De 8:30 a 20:00 | F69: 599W+XR Granada | G69: C. Tejeiro, 23, 18005 Granada | H69: Granada | I69: Granada | K69: 958 52 34 36 | L69: - | M69: No | N69: 37.1699012 | O69: -3.6029047 | P69: https://goo.gl/maps/N485vnL3gbJSNKvL7 | Q69: <iframe src="https://www.google.com/maps/embed?pb=!1m18!1m12!1m3!1d406947.3826479659!2d-3.8830519671875!3d37.16990119999999!2m3!1f0!2f0!3f0!3m2!1i1024!2i768!4f13.1!3m3!1m2!1s0xd71fc97b6fca1af%3A0x8a03a80ee4c7fe0a!2sEulogio%20Caravantes%20Iniciativas%20Geomineras!5e0!3m2!1ses!2ses!4v1651829691403!5m2!1ses!2ses" width="600" height="450" style="border:0;" allowfullscreen="" loading="lazy" referrerpolicy="no-referrer-when-downgrade"></iframe> | R69: https://streetviewpixels-pa.googleapis.com/v1/thumbnail?panoid=NXFPrvetPsWHkYmIpKk4jQ&cb_client=search.gws-prod.gps&w=408&h=240&yaw=31.395649&pitch=0&thumbfov=100
A70: Turrillas | H70: Abla | L70: - | M70: No | N70: 37.0294816 | O70: -2.2647931 | P70: https://goo.gl/maps/uNCqFy2Paib3UxGx7 | Q70: <iframe src="https://www.google.com/maps/embed?pb=!1m18!1m12!1m3!1d407702.3567795835!2d-2.544944467187532!3d37.029481600000004!2m3!1f0!2f0!3f0!3m2!1i1024!2i768!4f13.1!3m3!1m2!1s0xd7abb78279a716f%3A0x282d8681af5fa6c9!2s04211%20Turrillas%2C%20Almer%C3%ADa!5e0!3m2!1ses!2ses!4v1651829704356!5m2!1ses!2ses" width="600" height="450" style="border:0;" allowfullscreen="" loading="lazy" referrerpolicy="no-referrer-when-downgrade"></iframe> | R70: https://lh5.googleusercontent.com/p/AF1QipNVwRhG545YhQKPRZb9EvvF7W7rGbBM406LqBxF=w408-h408-k-no
A71: Cobos Ingenieros | B71: Oficinas de empresa | F71: 59VQ+XQ Granada | G71: Cl. el Guerra, 8, 18014 Granada | H71: Granada | I71: Granada | J71: cobosingenieros.com | K71: 655 77 49 71 | L71: - | M71: Sí | N71: 37.1949525 | O71: -3.6105792 | P71: https://goo.gl/maps/4fhosNHSTMkTfrs69 | Q71: <iframe src="https://www.google.com/maps/embed?pb=!1m18!1m12!1m3!1d406812.4358184452!2d-3.890730567187526!3d37.19495250000001!2m3!1f0!2f0!3f0!3m2!1i1024!2i768!4f13.1!3m3!1m2!1s0xd71fd90475cb6a1%3A0x9202b1ca68775517!2sCobos%20Ingenieros!5e0!3m2!1ses!2ses!4v1651829710387!5m2!1ses!2ses" width="600" height="450" style="border:0;" allowfullscreen="" loading="lazy" referrerpolicy="no-referrer-when-downgrade"></iframe> | R71: https://streetviewpixels-pa.googleapis.com/v1/thumbnail?panoid=kxJE2YvRf-FVHKIG6jeTzw&cb_client=search.gws-prod.gps&w=408&h=240&yaw=336.76044&pitch=0&thumbfov=100
A72: Geomina S L | B72: Empresa de mármoles | C72: 3,0 | D72: 1 | F72: 5C92+49 Granada | G72: C. San Antón, 72, 18005 Granada | H72: Granada | I72: Granada | L72: - | M72: Sí | N72: 37.1678588 | O72: -3.5990156 | P72: https://goo.gl/maps/qBu4Dq7eMzp7taFY8 | Q72: <iframe src="https://www.google.com/maps/embed?pb=!1m18!1m12!1m3!1d406958.3812584863!2d-3.879166967187466!3d37.16785879999999!2m3!1f0!2f0!3f0!3m2!1i1024!2i768!4f13.1!3m3!1m2!1s0xd71fcbd2aaf12cb%3A0xb7c00990db295317!2sGeomina%20S%20L!5e0!3m2!1ses!2ses!4v1651829723294!5m2!1ses!2ses" width="600" height="450" style="border:0;" allowfullscreen="" loading="lazy" referrerpolicy="no-referrer-when-downgrade"></iframe> | R72: https://streetviewpixels-pa.googleapis.com/v1/thumbnail?panoid=DeuwL38VuLnkHtdvO7o6OA&cb_client=search.gws-prod.gps&w=408&h=240&yaw=217.72356&pitch=0&thumbfov=100
A73: Aridos Hermanos Guerrero (SOLO OFICINAS) | B73: Empresa minera | C73: 4,9 | D73: 7 | E73: viernes, De 7:00 a 18:00; sábado, Cerrado; domingo, Cerrado; lunes, De 7:00 a 18:00; martes, De 7:00 a 18:00; miércoles, De 7:00 a 18:00; jueves, De 7:00 a 18:00 | F73: 4932+9C Alhendín | G73: Cam. de Jayena, 19, 18620 Alhendín, Granada | H73: Alhendín | I73: Granada | J73: aridosguerrero.com | K73: 958 57 60 51 | L73: info@aridosguerrero.com | M73: No | N73: 37.1034774 | O73: -3.6489426 | P73: https://goo.gl/maps/YrR6k8JP7bfxivvU8 | Q73: <iframe src="https://www.google.com/maps/embed?pb=!1m18!1m12!1m3!1d406958.3812584863!2d-3.879166967187466!3d37.16785879999999!2m3!1f0!2f0!3f0!3m2!1i1024!2i768!4f13.1!3m3!1m2!1s0xd71fa369033d9ef%3A0xc6401bf05f95d640!2sAridos%20Hermanos%20Guerrero%20(SOLO%20OFICINAS)!5e0!3m2!1ses!2ses!4v1651829729465!5m2!1ses!2ses" width="600" height="450" style="border:0;" allowfullscreen="" loading="lazy" referrerpolicy="no-referrer-when-downgrade"></iframe> | R73: https://lh5.googleusercontent.com/p/AF1QipOubRSJ4L_x9GV3fMCLZmgNjz31Zpv8k8NPLoGQ=w408-h544-k-no
A74: Gérgal | H74: Abla | L74: - | M74: No | N74: 37.1181546 | O74: -2.5414607 | P74: https://goo.gl/maps/MFZ7GtdEwDo2D6U5A | Q74: <iframe src="https://www.google.com/maps/embed?pb=!1m18!1m12!1m3!1d407225.88589227945!2d-2.8216120671875027!3d37.1181546!2m3!1f0!2f0!3f0!3m2!1i1024!2i768!4f13.1!3m3!1m2!1s0xd7005e06ef33a79%3A0xb2b257921f0ae035!2zMDQ1NTAgR8OpcmdhbCwgQWxtZXLDrWE!5e0!3m2!1ses!2ses!4v1651829737168!5m2!1ses!2ses" width="600" height="450" style="border:0;" allowfullscreen="" loading="lazy" referrerpolicy="no-referrer-when-downgrade"></iframe> | R74: https://lh5.googleusercontent.com/p/AF1QipNZ2TFXj43pNTYN524OIyJhghS0dFfJMzYZEoxk=w408-h306-k-no
A75: Kalpae Ibérica | B75: Contratista de excavación | C75: 4,7 | D75: 12 | E75: viernes, De 7:00 a 19:00; sábado, Cerrado; domingo, Cerrado; lunes, De 7:00 a 19:00; martes, De 7:00 a 19:00; miércoles, De 7:00 a 19:00; jueves, De 7:00 a 19:00 | F75: 6GG4+XV Granada | G75: Huetor Santillan, 18183 Granada | H75: Granada | I75: Granada | J75: kalpaeiberica.com | K75: 958 41 40 81 | L75: - | M75: No | N75: 37.227493 | O75: -3.492834 | P75: https://goo.gl/maps/8n7FAyeSK1hf3b4RA | Q75: <iframe src="https://www.google.com/maps/embed?pb=!1m18!1m12!1m3!1d406637.0299055651!2d-3.7729853671874976!3d37.22749300000001!2m3!1f0!2f0!3f0!3m2!1i1024!2i768!4f13.1!3m3!1m2!1s0xd71fd24c10daab7%3A0xe5a16a039ac5a0bf!2sKalpae%20Ib%C3%A9rica!5e0!3m2!1ses!2ses!4v1651829749965!5m2!1ses!2ses" width="600" height="450" style="border:0;" allowfullscreen="" loading="lazy" referrerpolicy="no-referrer-when-downgrade"></iframe> | R75: https://lh5.googleusercontent.com/p/AF1QipME-L-7JbBSy2tBoZOSplxXixZ8xPjGRrpYA0NH=w426-h240-k-no
A76: Abla | H76: Abla | L76: - | M76: No | N76: 37.1423439 | O76: -2.777359 | P76: https://goo.gl/maps/bcrHShQcs8nnsaax9 | Q76: <iframe src="https://www.google.com/maps/embed?pb=!1m18!1m12!1m3!1d407095.73898804997!2d-3.0575103671874704!3d37.142343900000014!2m3!1f0!2f0!3f0!3m2!1i1024!2i768!4f13.1!3m3!1m2!1s0xd702278b7486673%3A0xd77fece04685232d!2zQWJsYSwgQWxtZXLDrWE!5e0!3m2!1ses!2ses!4v1651829762481!5m2!1ses!2ses" width="600" height="450" style="border:0;" allowfullscreen="" loading="lazy" referrerpolicy="no-referrer-when-downgrade"></iframe> | R76: https://lh5.googleusercontent.com/p/AF1QipPWJUy4B7vZnOSDCkyGPsEEoeV02ONb2a1SJeio=w408-h305-k-no
A77: Beires | H77: Abla | L77: - | M77: No | N77: 37.012377 | O77: -2.7907414 | P77: https://goo.gl/maps/jzCdVoSCs6ZMGfuZ7 | Q77: <iframe src="https://www.google.com/maps/embed?pb=!1m18!1m12!1m3!1d409286.090982297!2d-2.901074167187506!3d36.73342530000001!2m3!1f0!2f0!3f0!3m2!1i1024!2i768!4f13.1!3m3!1m2!1s0xd703de37f7f278d%3A0x5304cbbdc2991932!2s04458%20Beires%2C%20Almer%C3%ADa!5e0!3m2!1ses!2ses!4v1651829782824!5m2!1ses!2ses" width="600" height="450" style="border:0;" allowfullscreen="" loading="lazy" referrerpolicy="no-referrer-when-downgrade"></iframe> | R77: https://lh5.googleusercontent.com/p/AF1QipMzNsHLFSFF03VbNikXnIx7nnIiyIO2KxfJlS08=w408-h725-k-no
A78: ARIDOS CARMONA SA | B78: Cantera | F78: 29FV+98 Padul | G78: Ctra. N-323a km 152.8,18640, Padul, Granada | H78: Padul | I78: Granada | K78: 958 77 30 12 | L78: - | M78: Sí | N78: 37.0233998 | O78: -3.6066521 | P78: https://goo.gl/maps/xmeGhGkgDbXPMCNz7 | Q78: <iframe src="https://www.google.com/maps/embed?pb=!1m18!1m12!1m3!1d3261880.0050832815!2d-5.8478630375000025!3d37.0233998!2m3!1f0!2f0!3f0!3m2!1i1024!2i768!4f13.1!3m3!1m2!1s0xd71f1a212f5bdab%3A0x22bcc5cb11a40cc9!2sARIDOS%20CARMONA%20SA!5e0!3m2!1ses!2ses!4v1651829827480!5m2!1ses!2ses" width="600" height="450" style="border:0;" allowfullscreen="" loading="lazy" referrerpolicy="no-referrer-when-downgrade"></iframe>
A79: Maritima de Sales | B79: Empresa minera | F79: GRWR+92 Puerto Real | G79: CA 3113 KM, 10, CA-3113, 5, 5, 11510 Puerto Real, Cádiz | H79: Puerto Real | I79: Cádiz | L79: - | M79: Sí | N79: 36.5459506 | O79: -6.1599369 | P79: https://goo.gl/maps/5QCdCwzsSf4dbJGp8 | Q79: <iframe src="https://www.google.com/maps/embed?pb=!1m18!1m12!1m3!1d102570.8319239282!2d-6.229974541796873!3d36.545950399999995!2m3!1f0!2f0!3f0!3m2!1i1024!2i768!4f13.1!3m3!1m2!1s0xd0dceae45b7b489%3A0x5a61479878f40f5a!2sMaritima%20de%20Sales!5e0!3m2!1ses!2ses!4v1651829886505!5m2!1ses!2ses" width="600" height="450" style="border:0;" allowfullscreen="" loading="lazy" referrerpolicy="no-referrer-when-downgrade"></iframe> | R79: https://streetviewpixels-pa.googleapis.com/v1/thumbnail?panoid=Daozi4h6JW2hjNhLQ-Y1zA&cb_client=search.gws-prod.gps&w=408&h=240&yaw=348.72897&pitch=0&thumbfov=100
A80: ARENAS DE LA JANDA S.L. | B80: Empresa minera | F80: 723M+PR Vejer de la Frontera | G80: Ctra. Barbate-Vejer, KM 41, 11150 Vejer de la Frontera, Cádiz | H80: Vejer de la Frontera | I80: Cádiz | K80: 956 44 57 75 | L80: - | M80: No | N80: 36.2542703 | O80: -5.9654496 | P80: https://goo.gl/maps/jE4TRLdj7SEnQ9wD6 | Q80: <iframe src="https://www.google.com/maps/embed?pb=!1m18!1m12!1m3!1d102956.5451926633!2d-6.035457841796875!3d36.25426000000001!2m3!1f0!2f0!3f0!3m2!1i1024!2i768!4f13.1!3m3!1m2!1s0xd0c45f3c547ecbf%3A0x3ffdf00445a2f0ed!2sARENAS%20DE%20LA%20JANDA%20S.L.!5e0!3m2!1ses!2ses!4v1651829894731!5m2!1ses!2ses" width="600" height="450" style="border:0;" allowfullscreen="" loading="lazy" referrerpolicy="no-referrer-when-downgrade"></iframe> | R80: https://streetviewpixels-pa.googleapis.com/v1/thumbnail?panoid=-zhR-IhlAmZ2C0-e8tDWkQ&cb_client=search.gws-prod.gps&w=408&h=240&yaw=121.36096&pitch=0&thumbfov=100
A81: Cantera | B81: Empresa minera | F81: 6HH2+37 Los Barrios | G81: 11379 Los Barrios, Cádiz | H81: Los Barrios | I81: Cádiz | L81: - | M81: Sí | N81: 36.227632 | O81: -5.4492536 | P81: https://goo.gl/maps/JYkP38NuvKSkFpCr7 | Q81: <iframe src="https://www.google.com/maps/embed?pb=!1m18!1m12!1m3!1d102991.62364010417!2d-5.519291441796875!3d36.227631999999986!2m3!1f0!2f0!3f0!3m2!1i1024!2i768!4f13.1!3m3!1m2!1s0xd0ce9625ea46d7f%3A0x76b4266bcde72dab!2sCantera!5e0!3m2!1ses!2ses!4v1651829900949!5m2!1ses!2ses" width="600" height="450" style="border:0;" allowfullscreen="" loading="lazy" referrerpolicy="no-referrer-when-downgrade"></iframe>
A82: Alabasía, S.L. | B82: Empresa minera | C82: 4,0 | D82: 22 | E82: viernes, De 7:00 a 14:00; sábado, Cerrado; domingo, Cerrado; lunes, De 7:00 a 15:00; martes, De 7:00 a 15:00; miércoles, De 7:00 a 15:00; jueves, De 7:00 a 15:00 | F82: RM87+8X Sanlúcar de Barrameda | G82: Carr. de Bonanza, 0 S N, 11540 Sanlúcar de Barrameda, Cádiz | H82: Sanlúcar de Barrameda | I82: Cádiz | J82: alabasia.es | K82: 956 36 00 71 | L82: - | M82: Sí | N82: 36.8158496 | O82: -6.335068 | P82: https://goo.gl/maps/s2sAjSUrQkeqYNPA7 | Q82: <iframe src="https://www.google.com/maps/embed?pb=!1m18!1m12!1m3!1d102211.56196225726!2d-6.405053141796874!3d36.8158525!2m3!1f0!2f0!3f0!3m2!1i1024!2i768!4f13.1!3m3!1m2!1s0x152fb1a2e7693289%3A0x3aecc08796b239d4!2zQWxhYmFzw61hLCBTLkwu!5e0!3m2!1ses!2ses!4v1651829907292!5m2!1ses!2ses" width="600" height="450" style="border:0;" allowfullscreen="" loading="lazy" referrerpolicy="no-referrer-when-downgrade"></iframe> | R82: https://lh5.googleusercontent.com/p/AF1QipMgEq7C1PG_pXQns3ijT8_6dbE__WZUfeUXVVrr=w408-h272-k-no
A83: INE | B83: Oficinas de empresa | C83: 3,0 | D83: 1 | E83: viernes, De 8:00 a 15:45; sábado, Cerrado; domingo, Cerrado; lunes, De 8:00 a 15:45; martes, De 8:00 a 15:45; miércoles, De 8:00 a 15:45; jueves, De 8:00 a 15:45 | F83: GP2H+HW Cádiz | G83: Glorieta Zona Franca, 11011 Cádiz | H83: Cádiz | I83: Cádiz | J83: ine.es | L83: - | M83: Sí | N83: 36.5014113 | O83: -6.2701412 | P83: https://goo.gl/maps/79V4x7X2DQQPrskq9 | Q83: <iframe src="https://www.google.com/maps/embed?pb=!1m18!1m12!1m3!1d102629.89298990274!2d-6.3401711417968745!3d36.50141650000001!2m3!1f0!2f0!3f0!3m2!1i1024!2i768!4f13.1!3m3!1m2!1s0xd0dd2457c4335eb%3A0xd1cb1259635519e1!2sINE!5e0!3m2!1ses!2ses!4v1651829913433!5m2!1ses!2ses" width="600" height="450" style="border:0;" allowfullscreen="" loading="lazy" referrerpolicy="no-referrer-when-downgrade"></iframe> | R83: https://streetviewpixels-pa.googleapis.com/v1/thumbnail?panoid=n55_DlZjz0GOceaopM2syA&cb_client=search.gws-prod.gps&w=408&h=240&yaw=254.84607&pitch=0&thumbfov=100
A84: ASIRO, S.A. | B84: Empresa minera | C84: 4,4 | D84: 11 | E84: viernes, De 7:00 a 17:30; sábado, Cerrado; domingo, Cerrado; lunes, De 7:00 a 17:30; martes, De 7:00 a 17:30; miércoles, De 7:00 a 17:30; jueves, De 7:00 a 17:30 | F84: J59J+6H San José del Valle | G84: A-2003, Km 29, 1, 11580 San José del Valle, Cádiz | H84: San José del Valle | I84: Cádiz | J84: asirosa.es | K84: 956 23 76 58 | L84: info@asirosa.es | M84: No | N84: 36.6180191 | O84: -5.8186001 | P84: https://goo.gl/maps/yBhH328yAiDAxWSY8 | Q84: <iframe src="https://www.google.com/maps/embed?pb=!1m18!1m12!1m3!1d102475.12281181448!2d-5.8886379417968735!3d36.61801909999999!2m3!1f0!2f0!3f0!3m2!1i1024!2i768!4f13.1!3m3!1m2!1s0xd0da8cc1eef038b%3A0x5ccca39c4498f356!2sASIRO%2C%20S.A.!5e0!3m2!1ses!2ses!4v1651829919980!5m2!1ses!2ses" width="600" height="450" style="border:0;" allowfullscreen="" loading="lazy" referrerpolicy="no-referrer-when-downgrade"></iframe> | R84: https://lh5.googleusercontent.com/p/AF1QipPb-WGrp6eT5ehG8Yw3UTgt2oYwhD87LKEAkr1u=w408-h409-k-no
A85: Bitcoin minería Chiclana | B85: Oficinas de empresa | E85: viernes, Abierto 24 horas; sábado, Abierto 24 horas; domingo, Abierto 24 horas; lunes, Abierto 24 horas; martes, Abierto 24 horas; miércoles, Abierto 24 horas; jueves, Abierto 24 horas | F85: CVH5+MC Chiclana de la Frontera | G85: C. Huerta la Concha, 14, 11130 Chiclana de la Frontera, Cádiz | H85: Chiclana de la Frontera | I85: Cádiz | J85: safir.com | K85: 619 90 66 42 | L85: - | M85: No | N85: 36.4291473 | O85: -6.1414791 | P85: https://goo.gl/maps/fuwLSmidec8Kbu897 | Q85: <iframe src="https://www.google.com/maps/embed?pb=!1m18!1m12!1m3!1d102725.60477536875!2d-6.211516941796882!3d36.429147300000004!2m3!1f0!2f0!3f0!3m2!1i1024!2i768!4f13.1!3m3!1m2!1s0xd0c349e8859a555%3A0xda899a37d0422e73!2sBitcoin%20miner%C3%ADa%20Chiclana!5e0!3m2!1ses!2ses!4v1651829926168!5m2!1ses!2ses" width="600" height="450" style="border:0;" allowfullscreen="" loading="lazy" referrerpolicy="no-referrer-when-downgrade"></iframe> | R85: https://lh5.googleusercontent.com/p/AF1QipPE_IPJBobWoquQmxWN7vNX0L2Pz92AIZ9EVe2d=w408-h333-k-no
A86: Sierra Valleja | B86: Empresa de mármoles | F86: P9CW+JV Abrajanejo | G86: Carretera Arcos - Algar, 0 km 3 , 800, 11630 Abrajanejo, Cádiz | H86: Abrajanejo | I86: Cádiz | K86: 956 23 13 17 | L86: - | M86: Sí | N86: 36.72155 | O86: -5.60287 | P86: https://goo.gl/maps/sFG7nWWUAftPjUjy5 | Q86: <iframe src="https://www.google.com/maps/embed?pb=!1m18!1m12!1m3!1d102337.34736613688!2d-5.672907841796874!3d36.72155!2m3!1f0!2f0!3f0!3m2!1i1024!2i768!4f13.1!3m3!1m2!1s0xd0d0e62130ef26d%3A0x206323578b63e1d2!2sSierra%20Valleja!5e0!3m2!1ses!2ses!4v1651829939949!5m2!1ses!2ses" width="600" height="450" style="border:0;" allowfullscreen="" loading="lazy" referrerpolicy="no-referrer-when-downgrade"></iframe>
A87: Crucegar | B87: Ingeniero | C87: 3,2 | D87: 6 | E87: viernes, De 8:00 a 15:00; sábado, Cerrado; domingo, Cerrado; lunes, De 8:30 a 14:40; martes, De 8:30 a 14:30; miércoles, De 8:30 a 14:30; jueves, De 8:30 a 14:30 | F87: FQ4P+FF San Fernando | G87: C. Real, 256, 11100 San Fernando, Cádiz | H87: San Fernando | I87: Cádiz | J87: crucegar.es | K87: 856 10 60 28 | L87: rfcruceira@crucegar.es | M87: No | N87: 36.4561338 | O87: -6.2138453 | P87: https://goo.gl/maps/tLdPJMGA9crp6Vgw5 | Q87: <iframe src="https://www.google.com/maps/embed?pb=!1m18!1m12!1m3!1d102689.88354255802!2d-6.283883141796875!3d36.4561338!2m3!1f0!2f0!3f0!3m2!1i1024!2i768!4f13.1!3m3!1m2!1s0xd0dcd37aafba199%3A0x5b70d149aaaad405!2sCrucegar!5e0!3m2!1ses!2ses!4v1651829946293!5m2!1ses!2ses" width="600" height="450" style="border:0;" allowfullscreen="" loading="lazy" referrerpolicy="no-referrer-when-downgrade"></iframe> | R87: https://lh5.googleusercontent.com/p/AF1QipM8BmaX1HGsNssHJB68j9iqUX3idX0XrO_GvgIE=w408-h306-k-no
A88: Enermine.es OFICINA TÉCNICA | B88: Oficinas de empresa | E88: viernes, De 10:00 a 18:00; sábado, Cerrado; domingo, Cerrado; lunes, De 10:00 a 18:00; martes, De 10:00 a 18:00; miércoles, De 10:00 a 18:00; jueves, De 10:00 a 18:00 | F88: VR9F+HQ Trebujena | G88: C. Matilla, 1, 11560 Trebujena, Cádiz | H88: Trebujena | I88: Cádiz | J88: enermine.es | K88: 672 23 81 05 | L88: clientes@enermine.es | M88: No | N88: 36.868926 | O88: -6.1756024 | P88: https://goo.gl/maps/ywYNusEWjddvPM2E7 | Q88: <iframe src="https://www.google.com/maps/embed?pb=!1m18!1m12!1m3!1d102140.65262321605!2d-6.245650641796876!3d36.8689226!2m3!1f0!2f0!3f0!3m2!1i1024!2i768!4f13.1!3m3!1m2!1s0xd0de93826d5161d%3A0xc08e7d9fa32c8ecf!2sEnermine.es%20OFICINA%20T%C3%89CNICA!5e0!3m2!1ses!2ses!4v1651829952574!5m2!1ses!2ses" width="600" height="450" style="border:0;" allowfullscreen="" loading="lazy" referrerpolicy="no-referrer-when-downgrade"></iframe> | R88: https://streetviewpixels-pa.googleapis.com/v1/thumbnail?panoid=gVY_Xss03CyZesUnN-DGHA&cb_client=search.gws-prod.gps&w=408&h=240&yaw=134.10092&pitch=0&thumbfov=100
A89: FYM | B89: Proveedor de materiales de construcción | F89: 5GFQ+PX Puente Romano | G89: Carretera Los Barrios, km. 102,5, Planta de los Barrios, 11011 Cádiz | H89: Puente Romano | I89: Cádiz | J89: fym.es | K89: 956 62 08 78 | L89: info@fym.es | M89: No | N89: 36.174326 | O89: -5.460119 | P89: https://goo.gl/maps/hQmRm7HteMeZbHVh7 | Q89: <iframe src="https://www.google.com/maps/embed?pb=!1m18!1m12!1m3!1d103061.77955531795!2d-5.530156841796874!3d36.174326!2m3!1f0!2f0!3f0!3m2!1i1024!2i768!4f13.1!3m3!1m2!1s0xd0cec60aff8dd51%3A0x8d889b573d8999bc!2sFYM!5e0!3m2!1ses!2ses!4v1651829958950!5m2!1ses!2ses" width="600" height="450" style="border:0;" allowfullscreen="" loading="lazy" referrerpolicy="no-referrer-when-downgrade"></iframe> | R89: https://streetviewpixels-pa.googleapis.com/v1/thumbnail?panoid=hvGrPu7DmnMBDGpHdoyKsQ&cb_client=search.gws-prod.gps&w=408&h=240&yaw=170.3609&pitch=0&thumbfov=100
A90: Proyecto Riotinto - Atalaya Mining | B90: Empresa minera | C90: 4,6 | D90: 72 | F90: PC66+J7 Minas de Riotinto | G90: La Dehesa, s/n, 21660 Minas de Riotinto, Huelva | H90: Minas de Riotinto | I90: Huelva | K90: 959 59 28 50 | L90: - | M90: No | N90: 37.7115631 | O90: -6.589272 | P90: https://goo.gl/maps/NXeufpj44sfb8LfS8 | Q90: <iframe src="https://www.google.com/maps/embed?pb=!1m18!1m12!1m3!1d101003.06177043999!2d-6.659309841796874!3d37.71156310000001!2m3!1f0!2f0!3f0!3m2!1i1024!2i768!4f13.1!3m3!1m2!1s0xd119ca95d3d76b5%3A0x491d263144a0c6e7!2sProyecto%20Riotinto%20-%20Atalaya%20Mining!5e0!3m2!1ses!2ses!4v1651829965042!5m2!1ses!2ses" width="600" height="450" style="border:0;" allowfullscreen="" loading="lazy" referrerpolicy="no-referrer-when-downgrade"></iframe> | R90: https://lh5.googleusercontent.com/p/AF1QipP6wMsjRx7eVnuDSySeq90_2cvVQDqYOjfliOmk=w426-h240-k-no
A91: Cantera | B91: Empresa minera | F91: CQH8+F7 Casares | G91: 29690 Casares, Málaga | H91: Casares | I91: Málaga | L91: - | M91: Sí | N91: 36.4286834 | O91: -5.2343007 | P91: https://goo.gl/maps/ViNmGgfCre5cvQ9x7 | Q91: <iframe src="https://www.google.com/maps/embed?pb=!1m18!1m12!1m3!1d102726.21862687686!2d-5.3043385417968745!3d36.4286834!2m3!1f0!2f0!3f0!3m2!1i1024!2i768!4f13.1!3m3!1m2!1s0xd0cd9e70b229a03%3A0xbee89c3be25f76a4!2sCantera!5e0!3m2!1ses!2ses!4v1651829970949!5m2!1ses!2ses" width="600" height="450" style="border:0;" allowfullscreen="" loading="lazy" referrerpolicy="no-referrer-when-downgrade"></iframe>
A92: Parque Minero de Almadén | B92: Museo | C92: 4,7 | D92: 1.219 | E92: viernes, De 10:30 a 14:00, De 15:30 a 18:30; sábado, De 10:30 a 14:00, De 15:30 a 18:30; domingo, De 10:30 a 14:00, De 15:30 a 18:30; lunes, Cerrado; martes, De 10:30 a 14:00, De 15:30 a 18:30; miércoles, De 10:30 a 14:00, De 15:30 a 18:30; jueves, De 10:30 a 14:00, De 15:30 a 18:30 | F92: Q5G4+2R Almadén | G92: Cerco San Teodoro, S/N, 13400 Almadén, Cdad. Real | H92: Almadén | I92: Cdad. Real | J92: parqueminerodealmaden.es | K92: 926 26 50 02 | L92: reservas@mayasa.es | M92: Sí | N92: 38.7750638 | O92: -4.8429268 | P92: https://goo.gl/maps/8AxHWTy9tGB3Ufpr9 | Q92: <iframe src="https://www.google.com/maps/embed?pb=!1m18!1m12!1m3!1d99536.13482407975!2d-4.912960941796875!3d38.77507400000002!2m3!1f0!2f0!3f0!3m2!1i1024!2i768!4f13.1!3m3!1m2!1s0xd6b444f995b08e7%3A0x92766a008642448d!2sParque%20Minero%20de%20Almad%C3%A9n!5e0!3m2!1ses!2ses!4v1651829980652!5m2!1ses!2ses" width="600" height="450" style="border:0;" allowfullscreen="" loading="lazy" referrerpolicy="no-referrer-when-downgrade"></iframe> | R92: https://lh5.googleusercontent.com/p/AF1QipNCRhqpxhhDlHEgHske7NL6rb1CE8jdfjNh2SIp=w408-h306-k-no
A93: CANTERA &quot;LOS GUIJOS&quot; - ESCOMBRERA AUTORIZADA | B93: Empresa de recogida de escombros | C93: 3,8 | D93: 8 | E93: viernes, De 8:00 a 18:00; sábado, Cerrado; domingo, Cerrado; lunes, De 8:00 a 18:00; martes, De 8:00 a 18:00; miércoles, De 8:00 a 18:00; jueves, De 8:00 a 18:00 | F93: 4G4R+RJ Algeciras | G93: N-340, 11206 Algeciras, Cádiz | H93: Algeciras | I93: Cádiz | L93: - | M93: Sí | N93: 36.1070875 | O93: -5.4584335 | P93: https://goo.gl/maps/X2Yv5NeCeC5ouGJ47 | Q93: <iframe src="https://www.google.com/maps/embed?pb=!1m18!1m12!1m3!1d103150.14476764855!2d-5.528471341796876!3d36.10708749999999!2m3!1f0!2f0!3f0!3m2!1i1024!2i768!4f13.1!3m3!1m2!1s0xd0c949299f41b41%3A0x19d5dbd2c98ca855!2sCANTERA%20%22LOS%20GUIJOS%22%20-%20ESCOMBRERA%20AUTORIZADA!5e0!3m2!1ses!2ses!4v1651829986871!5m2!1ses!2ses" width="600" height="450" style="border:0;" allowfullscreen="" loading="lazy" referrerpolicy="no-referrer-when-downgrade"></iframe> | R93: https://lh5.googleusercontent.com/p/AF1QipOSwDyIJx6Hzwi5L5bQsMykD8wHMdanr0j8mb2p=w408-h544-k-no
A94: Omnia Life Time Mining | B94: Empresa minera | F94: 4JRW+45 Gibraltar | G94: 1 Line Wall Rd, GX11 GX11 1AA, Gibraltar | H94: Gibraltar | I94: Gibraltar | L94: - | M94: Sí | N94: 36.1403586 | O94: -5.3545814 | P94: https://goo.gl/maps/i82Xv1qNejZm2oLG8 | Q94: <iframe src="https://www.google.com/maps/embed?pb=!1m18!1m12!1m3!1d103106.43219294051!2d-5.424583541796875!3d36.14036259999999!2m3!1f0!2f0!3f0!3m2!1i1024!2i768!4f13.1!3m3!1m2!1s0xd0cbf81a85fdcd7%3A0x3e9cd15a70327461!2sOmnia%20Life%20Time%20Mining!5e0!3m2!1ses!2ses!4v1651829999122!5m2!1ses!2ses" width="600" height="450" style="border:0;" allowfullscreen="" loading="lazy" referrerpolicy="no-referrer-when-downgrade"></iframe> | R94: https://streetviewpixels-pa.googleapis.com/v1/thumbnail?panoid=Nb9fen3j1ZlxoU09ArNN0Q&cb_client=search.gws-prod.gps&w=408&h=240&yaw=69.70546&pitch=0&thumbfov=100
A95: Corta Atalaya | B95: Lugar de interés histórico | C95: 4,6 | D95: 55 | F95: P92W+JX Minas de Riotinto | G95: Plaza del Minero, s/n, 21660 Minas de Riotinto, Huelva | H95: Minas de Riotinto | I95: Huelva | J95: aytoriotinto.es | K95: 959 59 02 60 | L95: - | M95: No | N95: 37.7015302 | O95: -6.6025616 | P95: https://goo.gl/maps/vMk5DTu5y1ynvGgx8 | Q95: <iframe src="https://www.google.com/maps/embed?pb=!1m18!1m12!1m3!1d101016.73549448756!2d-6.6725994417968755!3d37.701530199999986!2m3!1f0!2f0!3f0!3m2!1i1024!2i768!4f13.1!3m3!1m2!1s0xd119b66d745cd7f%3A0xdcf37c19fe4d0f34!2sCorta%20Atalaya!5e0!3m2!1ses!2ses!4v1651830006043!5m2!1ses!2ses" width="600" height="450" style="border:0;" allowfullscreen="" loading="lazy" referrerpolicy="no-referrer-when-downgrade"></iframe> | R95: https://lh5.googleusercontent.com/p/AF1QipOs7AKSBEiANGr3F9fdsaQWaRYwGqFdNKspfPAQ=w483-h240-k-no
A96: ANDALUZA DE CALES S.A | B96: Empresa minera | C96: 3,1 | D96: 15 | E96: viernes, De 9:00 a 18:00; sábado, Cerrado; domingo, Cerrado; lunes, De 9:00 a 18:00; martes, De 9:00 a 18:00; miércoles, De 9:00 a 18:00; jueves, De 9:00 a 18:00 | F96: 3GX9+5F Morón de la Frontera | G96: Carretera Morón - Montellano, km 3, 41530 Morón de la Frontera, Sevilla | H96: Morón de la Frontera | I96: Sevilla | J96: calcinor.com | K96: 954 85 11 12 | L96: calcinor@calcinor.com | M96: No | N96: 37.0979461 | O96: -5.4812817 | P96: https://goo.gl/maps/cfrx6LUxre3uhJyJA | Q96: <iframe src="https://www.google.com/maps/embed?pb=!1m18!1m12!1m3!1d101833.63976269274!2d-5.551319541796874!3d37.0979461!2m3!1f0!2f0!3f0!3m2!1i1024!2i768!4f13.1!3m3!1m2!1s0xd0d61710c987291%3A0xdb11da0d471cec86!2sANDALUZA%20DE%20CALES%20S.A!5e0!3m2!1ses!2ses!4v1651830046935!5m2!1ses!2ses" width="600" height="450" style="border:0;" allowfullscreen="" loading="lazy" referrerpolicy="no-referrer-when-downgrade"></iframe>
A97: FYM | B97: Cantera | C97: 3,0 | D97: 2 | F97: P65R+96 Arcos de la Frontera | G97: Carretera CA 334 Arcos-Algar, km. 4, Cantera Sierra Valleja, 11630 Arcos de la Frontera, Cádiz | H97: Arcos de la Frontera | I97: Cádiz | J97: fym.es | K97: 956 23 13 17 | L97: info@fym.es | M97: No | N97: 36.708441 | O97: -5.759496 | P97: https://goo.gl/maps/sUSa5wKKSSEKf98K7 | Q97: <iframe src="https://www.google.com/maps/embed?pb=!1m18!1m12!1m3!1d102354.81086830037!2d-5.8295338417968745!3d36.708441!2m3!1f0!2f0!3f0!3m2!1i1024!2i768!4f13.1!3m3!1m2!1s0xd0da70120cc61f5%3A0xd320ce7fb19af696!2sFYM!5e0!3m2!1ses!2ses!4v1651830053497!5m2!1ses!2ses" width="600" height="450" style="border:0;" allowfullscreen="" loading="lazy" referrerpolicy="no-referrer-when-downgrade"></iframe>
A98: Catrasur, S.L. | B98: Empresa minera | C98: 3,0 | D98: 1 | E98: viernes, De 8:00 a 18:00; sábado, Cerrado; domingo, Cerrado; lunes, De 8:00 a 19:00; martes, De 8:00 a 19:00; miércoles, De 8:00 a 19:00; jueves, De 8:00 a 19:00 | F98: X3Q6+7J Las Cabezas de San Juan | G98: Francisco de la Rosa, 4 - local bajo, 41730 Las Cabezas de San Juan, Sevilla | H98: Las Cabezas de San Juan | I98: Sevilla | J98: catrasur.com | K98: 955 87 14 70 | L98: catrasur@catrasur.com | M98: Sí | N98: 36.988185 | O98: -5.9384548 | P98: https://goo.gl/maps/F3DesuoV6yKCiMiv9 | Q98: <iframe src="https://www.google.com/maps/embed?pb=!1m18!1m12!1m3!1d101980.95968930276!2d-6.008514241796875!3d36.988201!2m3!1f0!2f0!3f0!3m2!1i1024!2i768!4f13.1!3m3!1m2!1s0xd0d8fcd93159567%3A0x6d67ef4d027b986c!2sCatrasur%2C%20S.L.!5e0!3m2!1ses!2ses!4v1651830060137!5m2!1ses!2ses" width="600" height="450" style="border:0;" allowfullscreen="" loading="lazy" referrerpolicy="no-referrer-when-downgrade"></iframe> | R98: https://lh5.googleusercontent.com/p/AF1QipMRsHobzAzfRhQwHhlkpswtOHfyJerPRHP8DfST=w408-h306-k-no
A99: Mina Aguablanca | B99: Mina | C99: 3,0 | D99: 3 | F99: XR89+6V Monesterio | G99: Paraje Mina Aguablanca, s/n, 06260 Monesterio, Badajoz | H99: Monesterio | I99: Badajoz | K99: 924 58 80 00 | L99: - | M99: Sí | N99: 37.9656176 | O99: -6.1802168 | P99: https://goo.gl/maps/Ko3tmCiRgPD1LcGS9 | Q99: <iframe src="https://www.google.com/maps/embed?pb=!1m18!1m12!1m3!1d100655.82778324383!2d-6.250365041796875!3d37.96558480000001!2m3!1f0!2f0!3f0!3m2!1i1024!2i768!4f13.1!3m3!1m2!1s0xd13cf6cbee8f077%3A0xc54669c16605f5fa!2sMina%20Aguablanca!5e0!3m2!1ses!2ses!4v1651830066543!5m2!1ses!2ses" width="600" height="450" style="border:0;" allowfullscreen="" loading="lazy" referrerpolicy="no-referrer-when-downgrade"></iframe> | R99: https://streetviewpixels-pa.googleapis.com/v1/thumbnail?panoid=hWZ4YfjID6_qL7CbmmwRTA&cb_client=search.gws-prod.gps&w=408&h=240&yaw=231.42943&pitch=0&thumbfov=100
A100: AYMA Mining Solutions | B100: Empresa minera | F100: 9W4V+MG Mairena del Aljarafe | G100: C. Innovación, 6-8, 41927 Mairena del Aljarafe, Sevilla | H100: Mairena del Aljarafe | I100: Sevilla | J100: aymamining.com | K100: 659 14 23 01 | L100: ayma@aymamining.com | M100: Sí | N100: 37.356653 | O100: -6.056148 | P100: https://goo.gl/maps/sEnJ6C8qBB5Gvw4J6 | Q100: <iframe src="https://www.google.com/maps/embed?pb=!1m18!1m12!1m3!1d101484.87861541986!2d-6.126185841796874!3d37.356653000000016!2m3!1f0!2f0!3f0!3m2!1i1024!2i768!4f13.1!3m3!1m2!1s0xd126cd80d70db3f%3A0xcc90c087772096b7!2sAYMA%20Mining%20Solutions!5e0!3m2!1ses!2ses!4v1651830072949!5m2!1ses!2ses" width="600" height="450" style="border:0;" allowfullscreen="" loading="lazy" referrerpolicy="no-referrer-when-downgrade"></iframe> | R100: https://streetviewpixels-pa.googleapis.com/v1/thumbnail?panoid=jutntGu_9mvMhEmfPPcpWw&cb_client=search.gws-prod.gps&w=408&h=240&yaw=357.01654&pitch=0&thumbfov=100
...

Sheet Minas
A1: ﻿Nombre | B1: Categoría | C1: Rating | D1: Nº Reviews | E1: Horario | F1: Código Plus | G1: Direccion | H1: Localidad | I1: Provincia | J1: Website | K1: Teléfono | L1: email | M1: Reclamar | N1: Latitud | O1: Longitud | P1: Url en Maps | Q1: Iframe | R1: Imagen Url
A2: Mina de Talco | B2: Mina | C2: 4,7 | D2: 3 | E2: viernes, Abierto 24 horas; sábado, Abierto 24 horas; domingo, Abierto 24 horas; lunes, Abierto 24 horas; martes, Abierto 24 horas; miércoles, Abierto 24 horas; jueves, Abierto 24 horas | F2: VG3C+9W Almería | G2: Acceso a A-7, 04008 Almería | H2: Almería | I2: Almería | L2: - | M2: Sí | N2: 36.8534497 | O2: -2.4776319 | P2: https://goo.gl/maps/H7zr6KFoZGtTPcYe8 | Q2: <iframe src="https://www.google.com/maps/embed?pb=!1m18!1m12!1m3!1d102177.29575124479!2d-2.5096470540265146!3d36.84150627352816!2m3!1f0!2f0!3f0!3m2!1i1024!2i768!4f13.1!3m3!1m2!1s0xd7075e3c8d5c031%3A0xb3a18684c09ff2ed!2sMina%20de%20Talco!5e0!3m2!1ses!2ses!4v1651828762041!5m2!1ses!2ses" width="600" height="450" style="border:0;" allowfullscreen="" loading="lazy" referrerpolicy="no-referrer-when-downgrade"></iframe> | R2: https://lh5.googleusercontent.com/p/AF1QipNYA_-JNgsH10SzKiBpJER4nVp8QOnuUIR-QQmX=w408-h544-k-no
A3: Minas De Rodalquilar | B3: Mina | C3: 4,3 | D3: 108 | E3: viernes, Abierto 24 horas; sábado, Abierto 24 horas; domingo, Abierto 24 horas; lunes, Abierto 24 horas; martes, Abierto 24 horas; miércoles, Abierto 24 horas; jueves, Abierto 24 horas | F3: VX33+87 Níjar | G3: C. Apartadero, 9, 04115 Níjar, Almería | H3: Níjar | I3: Almería | L3: - | M3: Sí | N3: 36.8532568 | O3: -2.0467748 | P3: https://goo.gl/maps/SD9PnMMPdjKsf6qAA | Q3: <iframe src="https://www.google.com/maps/embed?pb=!1m18!1m12!1m3!1d102161.5935192764!2d-2.1168126417968627!3d36.853256800000004!2m3!1f0!2f0!3f0!3m2!1i1024!2i768!4f13.1!3m3!1m2!1s0xd7ae953d0696c25%3A0x8a62f495a746f766!2sMinas%20De%20Rodalquilar!5e0!3m2!1ses!2ses!4v1651828776746!5m2!1ses!2ses" width="600" height="450" style="border:0;" allowfullscreen="" loading="lazy" referrerpolicy="no-referrer-when-downgrade"></iframe> | R3: https://lh5.googleusercontent.com/p/AF1QipM7JNxYV8MiPi3HM41YePyLgqPUWbAgqo8XW1CK=w426-h240-k-no
A4: Minas del Carmen | B4: Mina | C4: 4,0 | D4: 4 | F4: V9P9+WX El Marchal de Antón López | G4: Barranco de Plateros, 04729 El Marchal de Antón López, Almería | H4: El Marchal de Antón López | I4: Almería | L4: - | M4: Sí | N4: 36.8872855 | O4: -2.6301245 | P4: https://goo.gl/maps/zfidVebut4PraLzH7 | Q4: <iframe src="https://www.google.com/maps/embed?pb=!1m18!1m12!1m3!1d102116.09672020565!2d-2.700162341796924!3d36.88728550000001!2m3!1f0!2f0!3f0!3m2!1i1024!2i768!4f13.1!3m3!1m2!1s0xd706d77358504af%3A0x37b9100bdcc479e!2sMinas%20del%20Carmen!5e0!3m2!1ses!2ses!4v1651828788372!5m2!1ses!2ses" width="600" height="450" style="border:0;" allowfullscreen="" loading="lazy" referrerpolicy="no-referrer-when-downgrade"></iframe> | R4: https://lh5.googleusercontent.com/p/AF1QipPwoDRQBuprdGz2YFbXC241WUL55fdjpLrXuSV9=w408-h663-k-no
A5: Coto Láisquez | B5: Mina | C5: 5,0 | D5: 1 | F5: XPPW+R2 Huebro | G5: 04119, Almería | H5: Huebro | I5: Almería | L5: - | M5: Sí | N5: 36.9870472 | O5: -2.2549732 | P5: https://goo.gl/maps/WWaxpbBjMZybCnaB7 | Q5: <iframe src="https://www.google.com/maps/embed?pb=!1m18!1m12!1m3!1d101982.50654396469!2d-2.325011041796891!3d36.98704719999999!2m3!1f0!2f0!3f0!3m2!1i1024!2i768!4f13.1!3m3!1m2!1s0xd7abc5a9ac3a90d%3A0xf7da6cb6cc27f67!2sCoto%20L%C3%A1isquez!5e0!3m2!1ses!2ses!4v1651828795700!5m2!1ses!2ses" width="600" height="450" style="border:0;" allowfullscreen="" loading="lazy" referrerpolicy="no-referrer-when-downgrade"></iframe> | R5: https://lh5.googleusercontent.com/p/AF1QipMYoUFQJt3hJsAjeZV-P92PkECTwivwkSYagNmG=w408-h306-k-no
A6: Ingeniera Técnica Minera Fadrique | B6: Ingeniero de minas | E6: viernes, De 7:00 a 20:00; sábado, De 7:00 a 14:00; domingo, Cerrado; lunes, De 7:00 a 20:00; martes, De 7:00 a 20:00; miércoles, De 7:00 a 20:00; jueves, De 7:00 a 20:00 | F6: R9MQ+9C La Envía | G6: Calle de los Nogales, 25, 04727 La Envía, Almería | H6: La Envía | I6: Almería | K6: 655 64 34 85 | L6: - | M6: No | N6: 36.8333937 | O6: -2.6114838 | P6: https://goo.gl/maps/KxMmiMVJdCop3rMB9 | Q6: <iframe src="https://www.google.com/maps/embed?pb=!1m18!1m12!1m3!1d102188.12606272443!2d-2.681470341796881!3d36.833399700000015!2m3!1f0!2f0!3f0!3m2!1i1024!2i768!4f13.1!3m3!1m2!1s0xd707114dd75b5f1%3A0x56f1858ef64cd51e!2sIngeniera%20T%C3%A9cnica%20Minera%20Fadrique!5e0!3m2!1ses!2ses!4v1651828801903!5m2!1ses!2ses" width="600" height="450" style="border:0;" allowfullscreen="" loading="lazy" referrerpolicy="no-referrer-when-downgrade"></iframe>
A7: Poblado minero de San Diego | B7: Mina | C7: 4,7 | D7: 9 | E7: viernes, Abierto 24 horas; sábado, Abierto 24 horas; domingo, Abierto 24 horas; lunes, Abierto 24 horas; martes, Abierto 24 horas; miércoles, Abierto 24 horas; jueves, Abierto 24 horas | F7: RWXM+7W Níjar | G7: 04115 Níjar, Almería | H7: Níjar | I7: Almería | L7: - | M7: Sí | N7: 36.84815 | O7: -2.0651921 | P7: https://goo.gl/maps/D7BfbL3PA9u6PSAk9 | Q7: <iframe src="https://www.google.com/maps/embed?pb=!1m18!1m12!1m3!1d102168.41826557778!2d-2.1352299417968745!3d36.84815000000001!2m3!1f0!2f0!3f0!3m2!1i1024!2i768!4f13.1!3m3!1m2!1s0xd7aeeaaf2909097%3A0x386f3f166850bbf8!2sPoblado%20minero%20de%20San%20Diego!5e0!3m2!1ses!2ses!4v1651828809200!5m2!1ses!2ses" width="600" height="450" style="border:0;" allowfullscreen="" loading="lazy" referrerpolicy="no-referrer-when-downgrade"></iframe> | R7: https://lh5.googleusercontent.com/p/AF1QipO09354IuIgbGZU2eDfYwYEx4EyVn2WhgWSMCh3=w408-h306-k-no
A8: Mina María Josefa | B8: Mina | C8: 4,0 | D8: 1 | F8: VW58+V9 Albaricoques | G8: 04116, Almería | H8: Albaricoques | I8: Almería | L8: - | M8: Sí | N8: 36.859666 | O8: -2.0840552 | P8: https://goo.gl/maps/CnQjV3gUU2c21rSK8 | Q8: <iframe src="https://www.google.com/maps/embed?pb=!1m18!1m12!1m3!1d25538.256773091554!2d-2.1015646604492186!3d36.859666!2m3!1f0!2f0!3f0!3m2!1i1024!2i768!4f13.1!3m3!1m2!1s0xd7aebf28ea2fc51%3A0xe326d27f2e0ec1a7!2sMina%20Mar%C3%ADa%20Josefa!5e0!3m2!1ses!2ses!4v1651829092387!5m2!1ses!2ses" width="600" height="450" style="border:0;" allowfullscreen="" loading="lazy" referrerpolicy="no-referrer-when-downgrade"></iframe> | R8: https://lh5.googleusercontent.com/p/AF1QipMueoBsbd9SIwZ5uuWv-IWrFNehQPXly5JAyVN-=w426-h240-k-no
A9: Galería de Los Lobos | B9: Mina | C9: 3,0 | D9: 1 | F9: R54H+W9 El Ejido | G9: Unnamed Road, 04715, Almería | H9: El Ejido | I9: Almería | L9: - | M9: Sí | N9: 36.8072567 | O9: -2.8215612 | P9: https://goo.gl/maps/sUPMbRH6wwZctgqR6 | Q9: <iframe src="https://www.google.com/maps/embed?pb=!1m18!1m12!1m3!1d25555.75973638268!2d-2.8390706604492184!3d36.807256699999996!2m3!1f0!2f0!3f0!3m2!1i1024!2i768!4f13.1!3m3!1m2!1s0xd704334f6206c85%3A0x6a1451c3c82c3746!2sGaler%C3%ADa%20de%20Los%20Lobos!5e0!3m2!1ses!2ses!4v1651829249309!5m2!1ses!2ses" width="600" height="450" style="border:0;" allowfullscreen="" loading="lazy" referrerpolicy="no-referrer-when-downgrade"></iframe>
A10: Minas de Alquife | B10: Mina | C10: 4,1 | D10: 13 | F10: 5VHP+Q5 Alquife | G10: Barriada de Minas del Marquesado, s/n, 18518 Alquife, Granada | H10: Alquife | I10: Granada | J10: alquifemines.com | L10: - | M10: No | N10: 37.1794947 | O10: -3.1146216 | P10: https://goo.gl/maps/2DAXffQd9YoYjPwA8 | Q10: <iframe src="https://www.google.com/maps/embed?pb=!1m18!1m12!1m3!1d25430.9820866196!2d-3.1321310604492187!3d37.1794947!2m3!1f0!2f0!3f0!3m2!1i1024!2i768!4f13.1!3m3!1m2!1s0xd71d4bebc1688d1%3A0xcd7b1a98df7b88a7!2sMinas%20de%20Alquife!5e0!3m2!1ses!2ses!4v1651829263153!5m2!1ses!2ses" width="600" height="450" style="border:0;" allowfullscreen="" loading="lazy" referrerpolicy="no-referrer-when-downgrade"></iframe> | R10: https://lh5.googleusercontent.com/p/AF1QipOzgOZaAQ34nZUg6JEZ_qiR9PCT4WI4ZCr4vMPA=w408-h262-k-no
A11: Minas Tres Pacos | B11: Ingeniero de minas | C11: 4,3 | D11: 16 | F11: 84MG+CQ Cuevas del Almanzora | G11: Unnamed Road,, 04619 Cuevas del Almanzora, Almería | H11: Cuevas del Almanzora | I11: Almería | L11: - | M11: Sí | N11: 37.3335611 | O11: -1.8730926 | P11: https://goo.gl/maps/iwjS9r6RAreQThxQ6 | Q11: <iframe src="https://www.google.com/maps/embed?pb=!1m18!1m12!1m3!1d25379.02321611813!2d-1.890602060449219!3d37.3335611!2m3!1f0!2f0!3f0!3m2!1i1024!2i768!4f13.1!3m3!1m2!1s0xd652baddf7397a3%3A0xf04d92260aa7f910!2sMinas%20Tres%20Pacos!5e0!3m2!1ses!2ses!4v1651829301372!5m2!1ses!2ses" width="600" height="450" style="border:0;" allowfullscreen="" loading="lazy" referrerpolicy="no-referrer-when-downgrade"></iframe> | R11: https://lh5.googleusercontent.com/p/AF1QipMJEKPLXZsfoj6n7N6dTSYZrW1WMAlQTX4svH4Z=w426-h240-k-no
A12: Minas de hierro del Cerro del Conjuro | B12: Mina | C12: 3,0 | D12: 1 | F12: WPG7+R6 Cástaras | G12: 18439 Cástaras, Granada | H12: Cástaras | I12: Granada | J12: turgranada.es | L12: fjtitos@turgranada.es | M12: Sí | N12: 36.9271055 | O12: -3.2868322 | P12: https://goo.gl/maps/tEHN4qjDe9CnFEJY9 | Q12: <iframe src="https://www.google.com/maps/embed?pb=!1m18!1m12!1m3!1d25515.702819714523!2d-3.3043866604492185!3d36.927105400000016!2m3!1f0!2f0!3f0!3m2!1i1024!2i768!4f13.1!3m3!1m2!1s0xd71c8740d75803f%3A0xdbcaad7920b6c8a!2sMinas%20de%20hierro%20del%20Cerro%20del%20Conjuro!5e0!3m2!1ses!2ses!4v1651829314169!5m2!1ses!2ses" width="600" height="450" style="border:0;" allowfullscreen="" loading="lazy" referrerpolicy="no-referrer-when-downgrade"></iframe> | R12: https://lh5.googleusercontent.com/p/AF1QipOD_SJndDbxAZgtgBMEiYlhZ5lWUmYCOFQTSnOw=w408-h306-k-no
A13: Mina La Probadora | B13: Mina | F13: 4M73+7W Güejar Sierra | G13: 18160 Güejar Sierra, Granada | H13: Güejar Sierra | I13: Granada | L13: - | M13: Sí | N13: 37.1132316 | O13: -3.3451627 | P13: https://goo.gl/maps/CJMTgtMPpDaHTmop7 | Q13: <iframe src="https://www.google.com/maps/embed?pb=!1m18!1m12!1m3!1d50906.54555845185!2d-3.3801816208984374!3d37.1132316!2m3!1f0!2f0!3f0!3m2!1i1024!2i768!4f13.1!3m3!1m2!1s0xd71dde9731e7eff%3A0x6a82b034604d3512!2sMina%20La%20Probadora!5e0!3m2!1ses!2ses!4v1651829358464!5m2!1ses!2ses" width="600" height="450" style="border:0;" allowfullscreen="" loading="lazy" referrerpolicy="no-referrer-when-downgrade"></iframe> | R13: https://lh5.googleusercontent.com/p/AF1QipPUSo75tCqIMOBFdQU0qj6YZ5pJYyO3kWfkXM-e=w408-h306-k-no
A14: Minas de la Cruz | B14: Mina | F14: 9572+H7 Las Juntas | G14: 18870, Granada | H14: Las Juntas | I14: Granada | L14: - | M14: Sí | N14: 37.3638884 | O14: -2.8492675 | P14: https://goo.gl/maps/xvmaNdeoVRqRru5k7 | Q14: <iframe src="https://www.google.com/maps/embed?pb=!1m18!1m12!1m3!1d50737.547421273535!2d-2.8842864208984373!3d37.363888400000015!2m3!1f0!2f0!3f0!3m2!1i1024!2i768!4f13.1!3m3!1m2!1s0xd6fdd5a9b0501b9%3A0x5d4e8974acaa2472!2sMinas%20de%20la%20Cruz!5e0!3m2!1ses!2ses!4v1651829431386!5m2!1ses!2ses" width="600" height="450" style="border:0;" allowfullscreen="" loading="lazy" referrerpolicy="no-referrer-when-downgrade"></iframe>
A15: LEGALIZACIÓN POZOS BELÉN DELGADO | B15: Ingeniero de minas | C15: 4,9 | D15: 49 | E15: viernes, Abierto 24 horas; sábado, Abierto 24 horas; domingo, Abierto 24 horas; lunes, Abierto 24 horas; martes, Abierto 24 horas; miércoles, Abierto 24 horas; jueves, Abierto 24 horas | F15: 68GR+MP Albolote | G15: C. Magallanes, Nº17, 18220 Albolote, Granada | H15: Albolote | I15: Granada | K15: 669 01 56 34 | L15: - | M15: No | N15: 37.2267479 | O15: -3.6582004 | P15: https://goo.gl/maps/VtyQaq3AN6JBM8fB8 | Q15: <iframe src="https://www.google.com/maps/embed?pb=!1m18!1m12!1m3!1d406641.0477509711!2d-3.9383517671874984!3d37.22674789999999!2m3!1f0!2f0!3f0!3m2!1i1024!2i768!4f13.1!3m3!1m2!1s0xd71fdedaebec3df%3A0x3d2366d21de23e2d!2sLEGALIZACI%C3%93N%20POZOS%20BEL%C3%89N%20DELGADO!5e0!3m2!1ses!2ses!4v1651829613434!5m2!1ses!2ses" width="600" height="450" style="border:0;" allowfullscreen="" loading="lazy" referrerpolicy="no-referrer-when-downgrade"></iframe> | R15: https://lh5.googleusercontent.com/p/AF1QipPbs1jmptDAumSjwO7R7VuNc4FBZXDMIOLXEIM0=w408-h306-k-no
A16: Mina Aguablanca | B16: Mina | C16: 3,0 | D16: 3 | F16: XR89+6V Monesterio | G16: Paraje Mina Aguablanca, s/n, 06260 Monesterio, Badajoz | H16: Monesterio | I16: Badajoz | K16: 924 58 80 00 | L16: - | M16: Sí | N16: 37.9656176 | O16: -6.1802168 | P16: https://goo.gl/maps/Ko3tmCiRgPD1LcGS9 | Q16: <iframe src="https://www.google.com/maps/embed?pb=!1m18!1m12!1m3!1d100655.82778324383!2d-6.250365041796875!3d37.96558480000001!2m3!1f0!2f0!3f0!3m2!1i1024!2i768!4f13.1!3m3!1m2!1s0xd13cf6cbee8f077%3A0xc54669c16605f5fa!2sMina%20Aguablanca!5e0!3m2!1ses!2ses!4v1651830066543!5m2!1ses!2ses" width="600" height="450" style="border:0;" allowfullscreen="" loading="lazy" referrerpolicy="no-referrer-when-downgrade"></iframe> | R16: https://streetviewpixels-pa.googleapis.com/v1/thumbnail?panoid=hWZ4YfjID6_qL7CbmmwRTA&cb_client=search.gws-prod.gps&w=408&h=240&yaw=231.42943&pitch=0&thumbfov=100
A17: Emilio del Rey Delgado | B17: Ingeniero de minas | E17: viernes, De 8:00 a 20:00; sábado, Cerrado; domingo, Cerrado; lunes, De 8:00 a 20:00; martes, De 8:00 a 20:00; miércoles, De 8:00 a 20:00; jueves, De 8:00 a 20:00 | F17: V6M9+VG Córdoba | G17: C. Conde de Gondomar, 13, 2º-8, 14003 Córdoba | H17: Córdoba | I17: Córdoba | K17: 677 87 36 54 | L17: - | M17: No | N17: 37.8846456 | O17: -4.7812327 | P17: https://goo.gl/maps/uq7Y3eXcMRAzJSam8 | Q17: <iframe src="https://www.google.com/maps/embed?pb=!1m18!1m12!1m3!1d50378.627910679126!2d-4.784485328307191!3d37.891534025745564!2m3!1f0!2f0!3f0!3m2!1i1024!2i768!4f13.1!3m3!1m2!1s0xd6cdf631d8460bb%3A0x188eb23a83fd3afe!2sEmilio%20del%20Rey%20Delgado!5e0!3m2!1ses!2ses!4v1651830143997!5m2!1ses!2ses" width="600" height="450" style="border:0;" allowfullscreen="" loading="lazy" referrerpolicy="no-referrer-when-downgrade"></iframe> | R17: https://streetviewpixels-pa.googleapis.com/v1/thumbnail?panoid=X70RSuaNRsnY3VfC2h6-ug&cb_client=search.gws-prod.gps&w=408&h=240&yaw=81.007355&pitch=0&thumbfov=100
A18: PGMA S.L.P. | B18: Ingeniero de minas | F18: V6Q9+8Q Córdoba | G18: Av. Ronda de los Tejares, 13, 14001 Córdoba | H18: Córdoba | I18: Córdoba | J18: pgma.es | K18: 957 48 00 01 | L18: info@pgma.es | M18: No | N18: 37.8882625 | O18: -4.78062 | P18: https://goo.gl/maps/W37jK7imBcNmnqrA9 | Q18: <iframe src="https://www.google.com/maps/embed?pb=!1m18!1m12!1m3!1d50378.627910679126!2d-4.784485328307191!3d37.891534025745564!2m3!1f0!2f0!3f0!3m2!1i1024!2i768!4f13.1!3m3!1m2!1s0xd6cdf64ea57a99f%3A0x21b1fe601bb175d3!2sPGMA%20S.L.P.!5e0!3m2!1ses!2ses!4v1651830161387!5m2!1ses!2ses" width="600" height="450" style="border:0;" allowfullscreen="" loading="lazy" referrerpolicy="no-referrer-when-downgrade"></iframe> | R18: https://streetviewpixels-pa.googleapis.com/v1/thumbnail?panoid=ZweIsjFUv8ECIuNGf1jV5A&cb_client=search.gws-prod.gps&w=408&h=240&yaw=146.02719&pitch=0&thumbfov=100
A19: Minas de Calamón | B19: Mina | C19: 5,0 | D19: 4 | F19: RWV3+VP Posadas | G19: 14730 Posadas, Córdoba | H19: Posadas | I19: Córdoba | L19: - | M19: Sí | N19: 37.8447222 | O19: -5.0956362 | P19: https://goo.gl/maps/Ur3TVJvUUJXrNCUm7 | Q19: <iframe src="https://www.google.com/maps/embed?pb=!1m18!1m12!1m3!1d50410.64380094292!2d-5.130655120898437!3d37.84472220000001!2m3!1f0!2f0!3f0!3m2!1i1024!2i768!4f13.1!3m3!1m2!1s0xd12d50c880cc5c3%3A0x932066eb9021d2bf!2sMinas%20de%20Calam%C3%B3n!5e0!3m2!1ses!2ses!4v1651830197247!5m2!1ses!2ses" width="600" height="450" style="border:0;" allowfullscreen="" loading="lazy" referrerpolicy="no-referrer-when-downgrade"></iframe> | R19: https://lh5.googleusercontent.com/p/AF1QipPBvOhQVV-7X3MHL3oqcmjLDAGvyQvWB4gzudbK=w408-h306-k-no
A20: Mario Antonio León Solís | B20: Ingeniero de minas | C20: 5,0 | D20: 1 | F20: V6VC+J4 Córdoba | G20: C. de los Plateros, 9, 14006 Córdoba | H20: Córdoba | I20: Córdoba | K20: 957 40 25 15 | L20: - | M20: Sí | N20: 37.8940679 | O20: -4.7797064 | P20: https://goo.gl/maps/4LjMQE2vp8iVu4VH7 | Q20: <iframe src="https://www.google.com/maps/embed?pb=!1m18!1m12!1m3!1d50378.627910679126!2d-4.784485328307217!3d37.891534025745564!2m3!1f0!2f0!3f0!3m2!1i1024!2i768!4f13.1!3m3!1m2!1s0xd6cdf6fdc3cd789%3A0xf9fd740f68c5fd8b!2sMario%20Antonio%20Le%C3%B3n%20Sol%C3%ADs!5e0!3m2!1ses!2ses!4v1651830214340!5m2!1ses!2ses" width="600" height="450" style="border:0;" allowfullscreen="" loading="lazy" referrerpolicy="no-referrer-when-downgrade"></iframe> | R20: https://streetviewpixels-pa.googleapis.com/v1/thumbnail?panoid=bmCHoTGtVsoiDfog24ySZw&cb_client=search.gws-prod.gps&w=408&h=240&yaw=265.68716&pitch=0&thumbfov=100
A21: pozosyproyectosmineros SERVICIOS DE PROYECTOS Y GESTIÓN MINERA | B21: Ingeniero de minas | C21: 5,0 | D21: 2 | E21: viernes, De 9:00 a 20:00; sábado, Cerrado; domingo, Cerrado; lunes, De 9:00 a 20:00; martes, De 9:00 a 20:00; miércoles, De 9:00 a 20:00; jueves, De 9:00 a 20:00 | F21: 8JFJ+M3 Rute | G21: C/ Cervantes s/n, casa nº 8 (Residencial Don Juan, 14960 Rute, Córdoba | H21: Rute | I21: Córdoba | J21: pozosyproyectosmineros.es | K21: 639 71 56 56 | L21: info@pozosyproyectosmineros.es | M21: No | N21: 37.3242278 | O21: -4.3698016 | P21: https://goo.gl/maps/JJtThvobQY7zQ44p9 | Q21: <iframe src="https://www.google.com/maps/embed?pb=!1m18!1m12!1m3!1d50764.35671722261!2d-4.404818020898437!3d37.324221099999995!2m3!1f0!2f0!3f0!3m2!1i1024!2i768!4f13.1!3m3!1m2!1s0xd6d82476aaaaaab%3A0x259f3dc0dafa17b2!2spozosyproyectosmineros%20SERVICIOS%20DE%20PROYECTOS%20Y%20GESTI%C3%93N%20MINERA!5e0!3m2!1ses!2ses!4v1651830266262!5m2!1ses!2ses" width="600" height="450" style="border:0;" allowfullscreen="" loading="lazy" referrerpolicy="no-referrer-when-downgrade"></iframe> | R21: https://streetviewpixels-pa.googleapis.com/v1/thumbnail?panoid=1mJEiGB5emr6BjQN1lGzdQ&cb_client=search.gws-prod.gps&w=408&h=240&yaw=289.07404&pitch=0&thumbfov=100
A22: Mina Diógenes | B22: Mina | C22: 4,8 | D22: 4 | F22: GV9M+Q7 Solana del Pino | G22: Cdad., 13593 Solana del Pino, Cdad. Real | H22: Solana del Pino | I22: Cdad. Real | L22: - | M22: Sí | N22: 38.5193885 | O22: -4.1167625 | P22: https://goo.gl/maps/DQgnu5WFvYa3PJCY6 | Q22: <iframe src="https://www.google.com/maps/embed?pb=!1m18!1m12!1m3!1d799135.2887361534!2d-4.677093234374993!3d38.51942280000001!2m3!1f0!2f0!3f0!3m2!1i1024!2i768!4f13.1!3m3!1m2!1s0xd6c745dc090dc9f%3A0xd81fe4765d6682bc!2sMina%20Di%C3%B3genes!5e0!3m2!1ses!2ses!4v1651830520621!5m2!1ses!2ses" width="600" height="450" style="border:0;" allowfullscreen="" loading="lazy" referrerpolicy="no-referrer-when-downgrade"></iframe> | R22: https://lh5.googleusercontent.com/p/AF1QipPr_5ABd9xPWZF1DHGmHdqE3uZghMi8BHwdDtFA=w408-h306-k-no
A23: Mina La Petaca | B23: Mina | C23: 4,0 | D23: 1 | F23: HQ32+C2 Ventillas | G23: Unnamed Road, 13591, Cdad. Real | H23: Ventillas | I23: Cdad. Real | L23: - | M23: Sí | N23: 38.5535495 | O23: -4.2499592 | P23: https://goo.gl/maps/a65Df4uPxLBLGudh7 | Q23: <iframe src="https://www.google.com/maps/embed?pb=!1m18!1m12!1m3!1d798756.2690521735!2d-4.810261934375004!3d38.553549499999995!2m3!1f0!2f0!3f0!3m2!1i1024!2i768!4f13.1!3m3!1m2!1s0xd6c799b71c55e21%3A0x666beda37c7954dd!2sMina%20La%20Petaca!5e0!3m2!1ses!2ses!4v1651830540293!5m2!1ses!2ses" width="600" height="450" style="border:0;" allowfullscreen="" loading="lazy" referrerpolicy="no-referrer-when-downgrade"></iframe> | R23: https://lh5.googleusercontent.com/p/AF1QipOLMuwETFKmG1QCmTFYNg0nNcXh_eCiAzmDrj8i=w408-h306-k-no
A24: Oxidos ferricos s.a. Mina las piletas | B24: Mina | E24: viernes, De 8:00 a 18:00; sábado, Cerrado; domingo, Cerrado; lunes, De 8:00 a 18:00; martes, De 8:00 a 18:00; miércoles, De 8:00 a 18:00; jueves, De 8:00 a 18:00 | F24: 63XF+R5 Rambla del Agua | G24: Cam. Nuevo del Gobernador, 18512 Huéneja, Granada | H24: Rambla del Agua | I24: Granada | L24: - | M24: Sí | N24: 37.2495701 | O24: -2.9270595 | P24: https://goo.gl/maps/v89K9RS66c68sdh87 | Q24: <iframe src="https://www.google.com/maps/embed?pb=!1m18!1m12!1m3!1d101629.48777304254!2d-2.997097341796875!3d37.2495701!2m3!1f0!2f0!3f0!3m2!1i1024!2i768!4f13.1!3m3!1m2!1s0xd7027eff1bbc4c5%3A0xfc21f7b7c1b1bcd1!2sOxidos%20ferricos%20s.a.%20Mina%20las%20piletas!5e0!3m2!1ses!2ses!4v1651830864694!5m2!1ses!2ses" width="600" height="450" style="border:0;" allowfullscreen="" loading="lazy" referrerpolicy="no-referrer-when-downgrade"></iframe> | R24: https://streetviewpixels-pa.googleapis.com/v1/thumbnail?panoid=NRalodNjPRfmkXjMtzS65g&cb_client=search.gws-prod.gps&w=408&h=240&yaw=278.11935&pitch=0&thumbfov=100
A25: Argudo &amp; Castillo Ingeniería | B25: Ingeniero de minas | C25: 5,0 | D25: 1 | E25: viernes, De 8:30 a 14:00; sábado, Cerrado; domingo, Cerrado; lunes, De 8:30 a 19:00; martes, De 8:30 a 19:00; miércoles, De 8:30 a 19:00; jueves, De 8:30 a 19:00 | F25: Q699+QM Jaén | G25: Av. Granada, 57, 23003 Jaén | H25: Jaén | I25: Jaén | J25: argudoycastillo.com | K25: 953 00 00 22 | L25: - | M25: No | N25: 37.7694977 | O25: -3.7808412 | P25: https://goo.gl/maps/zduyq87yUevr4r8w8 | Q25: <iframe src="https://www.google.com/maps/embed?pb=!1m18!1m12!1m3!1d100924.06273402969!2d-3.850880241796875!3d37.7694831!2m3!1f0!2f0!3f0!3m2!1i1024!2i768!4f13.1!3m3!1m2!1s0xd6dd79f62edb121%3A0xe2932fc5f5cdf55a!2sArgudo%20%26%20Castillo%20Ingenier%C3%ADa!5e0!3m2!1ses!2ses!4v1651830978012!5m2!1ses!2ses" width="600" height="450" style="border:0;" allowfullscreen="" loading="lazy" referrerpolicy="no-referrer-when-downgrade"></iframe> | R25: https://lh5.googleusercontent.com/p/AF1QipP5k1VtnsbRa62tFI47xE3OE2-P9MXJy_8yCao_=w408-h272-k-no
A26: Pozo de San Vicente | B26: Mina | C26: 4,5 | D26: 15 | E26: viernes, Abierto 24 horas; sábado, Abierto 24 horas; domingo, Abierto 24 horas; lunes, Abierto 24 horas; martes, Abierto 24 horas; miércoles, Abierto 24 horas; jueves, Abierto 24 horas | F26: 49HH+W6 Linares | G26: 23700 Linares, Jaén | H26: Linares | I26: Jaén | J26: redjaen.es | L26: - | M26: Sí | N26: 38.1298638 | O26: -3.6219149 | P26: https://goo.gl/maps/5ep373h7VjTg4hg57 | Q26: <iframe src="https://www.google.com/maps/embed?pb=!1m18!1m12!1m3!1d200860.42661567146!2d-3.7619905835937204!3d38.129863799999995!2m3!1f0!2f0!3f0!3m2!1i1024!2i768!4f13.1!3m3!1m2!1s0xd6e9b01e2f8dcbd%3A0x486dab6a2c0bc4de!2sPozo%20de%20San%20Vicente!5e0!3m2!1ses!2ses!4v1651831281450!5m2!1ses!2ses" width="600" height="450" style="border:0;" allowfullscreen="" loading="lazy" referrerpolicy="no-referrer-when-downgrade"></iframe> | R26: https://lh5.googleusercontent.com/p/AF1QipMj2xnIksuo4ToqQzrblIj1E_RRSzxKPHyAU-pu=w426-h240-k-no
A27: Pozo San Jose | B27: Mina | F27: 49RF+HQ Linares | G27: 23700 Linares, Jaén | H27: Linares | I27: Jaén | L27: - | M27: Sí | N27: 38.1414785 | O27: -3.6255265 | P27: https://goo.gl/maps/d8GLambLnXHLPK7u7 | Q27: <iframe src="https://www.google.com/maps/embed?pb=!1m18!1m12!1m3!1d200828.46170584048!2d-3.7656021835937112!3d38.141478500000005!2m3!1f0!2f0!3f0!3m2!1i1024!2i768!4f13.1!3m3!1m2!1s0xd6e9b8504ab4f21%3A0xdc916e912398d68f!2sPozo%20San%20Jose!5e0!3m2!1ses!2ses!4v1651831290012!5m2!1ses!2ses" width="600" height="450" style="border:0;" allowfullscreen="" loading="lazy" referrerpolicy="no-referrer-when-downgrade"></iframe> | R27: https://lh5.googleusercontent.com/p/AF1QipOl041eZR2zxFcaN_OuWquiYCe_QDHj7NzpS15G=w426-h240-k-no
A28: Pozo La Union | B28: Mina | F28: 49Q7+73 Linares | G28: 23700 Linares, Jaén | H28: Linares | I28: Jaén | L28: - | M28: Sí | N28: 38.1381702 | O28: -3.637355 | P28: https://goo.gl/maps/7DwFNTztXsTmy4Dj7 | Q28: <iframe src="https://www.google.com/maps/embed?pb=!1m18!1m12!1m3!1d200837.56734564947!2d-3.7774306835937526!3d38.138170200000005!2m3!1f0!2f0!3f0!3m2!1i1024!2i768!4f13.1!3m3!1m2!1s0xd6e9ba67ae6e1a3%3A0x367d4778e677ef22!2sPozo%20La%20Union!5e0!3m2!1ses!2ses!4v1651831312121!5m2!1ses!2ses" width="600" height="450" style="border:0;" allowfullscreen="" loading="lazy" referrerpolicy="no-referrer-when-downgrade"></iframe> | R28: https://streetviewpixels-pa.googleapis.com/v1/thumbnail?panoid=WdZ0UmcjtLZJbvaGf0XsKQ&cb_client=search.gws-prod.gps&w=408&h=240&yaw=282.62646&pitch=0&thumbfov=100
A29: Pozo San Guillermo | B29: Mina | F29: 49MC+X8 Linares | G29: 23700 Linares, Jaén | H29: Linares | I29: Jaén | L29: - | M29: Sí | N29: 38.134877 | O29: -3.6291897 | P29: https://goo.gl/maps/LDKJUMXpcYHpKQxs5 | Q29: <iframe src="https://www.google.com/maps/embed?pb=!1m18!1m12!1m3!1d200846.63075977605!2d-3.7692653835937127!3d38.13487700000002!2m3!1f0!2f0!3f0!3m2!1i1024!2i768!4f13.1!3m3!1m2!1s0xd6e9b058bfe134f%3A0x68d9fe125f738e64!2sPozo%20San%20Guillermo!5e0!3m2!1ses!2ses!4v1651831321090!5m2!1ses!2ses" width="600" height="450" style="border:0;" allowfullscreen="" loading="lazy" referrerpolicy="no-referrer-when-downgrade"></iframe>
A30: Ruinas grupo minas Sinapismo | B30: Mina | C30: 3,0 | D30: 1 | E30: viernes, Abierto 24 horas; sábado, Abierto 24 horas; domingo, Abierto 24 horas; lunes, Abierto 24 horas; martes, Abierto 24 horas; miércoles, Abierto 24 horas; jueves, Abierto 24 horas | F30: 892R+WW La Carolina | G30: 23200 La Carolina, Jaén | H30: La Carolina | I30: Jaén | L30: - | M30: Sí | N30: 38.3023368 | O30: -3.6077491 | P30: https://goo.gl/maps/RJDVCNykgrff3UZH6 | Q30: <iframe src="https://www.google.com/maps/embed?pb=!1m18!1m12!1m3!1d25048.114279202964!2d-3.6252585604492187!3d38.30233679999999!2m3!1f0!2f0!3f0!3m2!1i1024!2i768!4f13.1!3m3!1m2!1s0xd6ea340a8f8855b%3A0x5d1c388f4a04d69c!2sRuinas%20grupo%20minas%20Sinapismo!5e0!3m2!1ses!2ses!4v1651831428043!5m2!1ses!2ses" width="600" height="450" style="border:0;" allowfullscreen="" loading="lazy" referrerpolicy="no-referrer-when-downgrade"></iframe> | R30: https://lh5.googleusercontent.com/p/AF1QipPBWcdlnSLXWVl0F2iyAGVUtWtK93t6xjafNdkg=w408-h545-k-no
A31: Ruinas Mina Burcio | B31: Mina | C31: 5,0 | D31: 1 | F31: H234+JF Mestanza | G31: 13594 Mestanza, Cdad. Real | H31: Mestanza | I31: Cdad. Real | L31: - | M31: Sí | N31: 38.5540918 | O31: -3.9937553 | P31: https://goo.gl/maps/oeXEbrKyM9gSLorn6 | Q31: <iframe src="https://www.google.com/maps/embed?pb=!1m18!1m12!1m3!1d399375.16747559333!2d-4.273955867187475!3d38.55408360000002!2m3!1f0!2f0!3f0!3m2!1i1024!2i768!4f13.1!3m3!1m2!1s0xd6c0b6c2191abeb%3A0xa3700bf8f30b94a6!2sRuinas%20Mina%20Burcio!5e0!3m2!1ses!2ses!4v1651831665419!5m2!1ses!2ses" width="600" height="450" style="border:0;" allowfullscreen="" loading="lazy" referrerpolicy="no-referrer-when-downgrade"></iframe> | R31: https://lh5.googleusercontent.com/p/AF1QipO-Ybu_u5pmhgSNXqDlSqsJGOtSfrZNnmReBqHd=w408-h306-k-no
A32: Gabinete Técnico Minero - Andrés Velasco León | B32: Ingeniero de minas | C32: 5,0 | D32: 1 | E32: viernes, De 9:00 a 14:00, De 17:00 a 20:00; sábado, Cerrado; domingo, Cerrado; lunes, De 9:00 a 14:00, De 17:00 a 20:00; martes, De 9:00 a 14:00, De 17:00 a 20:00; miércoles, De 9:00 a 14:00, De 17:00 a 20:00; jueves, De 9:00 a 14:00, De 17:00 a 20:00 | F32: MHW4+CQ Málaga | G32: C. Pico de las Palomas, 15, 29004 Málaga | H32: Málaga | I32: Málaga | J32: andresvelasco.es | K32: 952 31 24 20 | L32: info@andresvelasco.es | M32: No | N32: 36.6961108 | O32: -4.4430941 | P32: https://g.page/LegalizacionPozos?share | Q32: <iframe src="https://www.google.com/maps/embed?pb=!1m18!1m12!1m3!1d409484.92792569025!2d-4.7232454671875!3d36.69611080000001!2m3!1f0!2f0!3f0!3m2!1i1024!2i768!4f13.1!3m3!1m2!1s0xd72f9d4304a417d%3A0x8e4442cb186b1827!2sGabinete%20T%C3%A9cnico%20Minero%20-%20Andr%C3%A9s%20Velasco%20Le%C3%B3n!5e0!3m2!1ses!2ses!4v1651831721234!5m2!1ses!2ses" width="600" height="450" style="border:0;" allowfullscreen="" loading="lazy" referrerpolicy="no-referrer-when-downgrade"></iframe> | R32: https://lh5.googleusercontent.com/p/AF1QipM6xlLpOSStHsO5TRqqm62x-LFccwZphSvYqmwh=w408-h272-k-no
A33: Minera Mara, SL | B33: Ingeniero de minas | C33: 5,0 | D33: 30 | E33: viernes, De 9:00 a 14:00; sábado, Cerrado; domingo, Cerrado; lunes, De 9:00 a 17:00; martes, De 9:00 a 17:00; miércoles, De 9:00 a 17:00; jueves, De 9:00 a 17:00 | F33: PH96+FV Málaga | G33: Calle Ingeniero de la Torre Acosta, nº1, Portal 3 - Entreplanta, 29007 Málaga | H33: Málaga | I33: Málaga | J33: mineramara.es | K33: 952 07 07 25 | L33: mineramara@mineramara.es | M33: No | N33: 36.7186756 | O33: -4.4378316 | P33: https://goo.gl/maps/gs2oGkvUoBHJsu8J6 | Q33: <iframe src="https://www.google.com/maps/embed?pb=!1m18!1m12!1m3!1d102341.8360243772!2d-4.449267015017109!3d36.7181809669757!2m3!1f0!2f0!3f0!3m2!1i1024!2i768!4f13.1!3m3!1m2!1s0xd72f79fca61f7e9%3A0xdfc715ad2d8eb142!2sMinera%20Mara%2C%20SL!5e0!3m2!1ses!2ses!4v1651831841520!5m2!1ses!2ses" width="600" height="450" style="border:0;" allowfullscreen="" loading="lazy" referrerpolicy="no-referrer-when-downgrade"></iframe> | R33: https://streetviewpixels-pa.googleapis.com/v1/thumbnail?panoid=r4g4CTDeU5MK22SpRGtUVA&cb_client=search.gws-prod.gps&w=408&h=240&yaw=233.70274&pitch=0&thumbfov=100
A34: Gestión Minera y Medioambiental, S.L. | B34: Ingeniero de minas | E34: viernes, De 8:30 a 14:00; sábado, Cerrado; domingo, Cerrado; lunes, De 8:30 a 20:00; martes, De 8:30 a 20:00; miércoles, De 8:30 a 20:00; jueves, De 8:30 a 20:00 | F34: PH99+8J Málaga | G34: Calle Hilera, Edificio Scala 2000 (nº 8), portal 6, 2ºE, 29007 Málaga | H34: Málaga | I34: Málaga | J34: gestionminera.com | K34: 952 61 05 04 | L34: malaga@gestionminera.com | M34: No | N34: 36.7182874 | O34: -4.4308938 | P34: https://goo.gl/maps/KEx7sKL9tZkx8Aua7 | Q34: <iframe src="https://www.google.com/maps/embed?pb=!1m18!1m12!1m3!1d102341.8360243772!2d-4.449267015017109!3d36.7181809669757!2m3!1f0!2f0!3f0!3m2!1i1024!2i768!4f13.1!3m3!1m2!1s0xd72f799b155b6c9%3A0xd64eafa79005d5fb!2sGesti%C3%B3n%20Minera%20y%20Medioambiental%2C%20S.L.!5e0!3m2!1ses!2ses!4v1651831852216!5m2!1ses!2ses" width="600" height="450" style="border:0;" allowfullscreen="" loading="lazy" referrerpolicy="no-referrer-when-downgrade"></iframe> | R34: https://streetviewpixels-pa.googleapis.com/v1/thumbnail?panoid=8GckVDd65ppJkYLNq7RV8Q&cb_client=search.gws-prod.gps&w=408&h=240&yaw=355.7523&pitch=0&thumbfov=100
A35: VELASCO &amp; SOLIS INGENIERÍA TS slp | B35: Ingeniero de minas | C35: 5,0 | D35: 4 | E35: viernes, De 9:00 a 14:00, De 17:00 a 20:00; sábado, Cerrado; domingo, Cerrado; lunes, De 9:00 a 14:00, De 17:00 a 20:00; martes, De 9:00 a 14:00, De 17:00 a 20:00; miércoles, De 9:00 a 14:00, De 17:00 a 20:00; jueves, De 9:00 a 14:00, De 17:00 a 20:00 | F35: MHW4+CP Málaga | G35: C. Pico de las Palomas, 15, local 47-48, 29004 Málaga | H35: Málaga | I35: Málaga | J35: velascosolis.es | K35: 952 31 24 20 | L35: info@velascosolis.es | M35: Sí | N35: 36.6960806 | O35: -4.4431865 | P35: https://goo.gl/maps/sJeMysiizo5Vnkch7 | Q35: <iframe src="https://www.google.com/maps/embed?pb=!1m18!1m12!1m3!1d102341.8360243772!2d-4.449267015017058!3d36.7181809669757!2m3!1f0!2f0!3f0!3m2!1i1024!2i768!4f13.1!3m3!1m2!1s0xd72f9d429149b95%3A0x4108ac507be3cd49!2sVELASCO%20%26%20SOLIS%20INGENIER%C3%8DA%20TS%20slp!5e0!3m2!1ses!2ses!4v1651831890918!5m2!1ses!2ses" width="600" height="450" style="border:0;" allowfullscreen="" loading="lazy" referrerpolicy="no-referrer-when-downgrade"></iframe> | R35: https://lh5.googleusercontent.com/p/AF1QipP97vi5nZhLOM-QKGfGRRxvHVPdOVRs7_eKmjz1=w408-h544-k-no
A36: Mina del Peñoncillo o la Concepción | B36: Mina | F36: G4QH+5C Ojén | G36: 29610 Ojén, Málaga | H36: Ojén | I36: Málaga | L36: - | M36: Sí | N36: 36.5379795 | O36: -4.8714308 | P36: https://goo.gl/maps/xbHRDzuN9e1rK8g69 | Q36: <iframe src="https://www.google.com/maps/embed?pb=!1m18!1m12!1m3!1d102581.40752273258!2d-4.941468641796875!3d36.537979500000006!2m3!1f0!2f0!3f0!3m2!1i1024!2i768!4f13.1!3m3!1m2!1s0xd72d847385e29a7%3A0xc0ac0bd4ce7a3d4f!2sMina%20del%20Pe%C3%B1oncillo%20o%20la%20Concepci%C3%B3n!5e0!3m2!1ses!2ses!4v1651831925044!5m2!1ses!2ses" width="600" height="450" style="border:0;" allowfullscreen="" loading="lazy" referrerpolicy="no-referrer-when-downgrade"></iframe> | R36: https://lh5.googleusercontent.com/p/AF1QipNSCNgK8eELq1VzkRmmVe57A23ClTp2oyUoZQLb=w408-h306-k-no
A37: Mina de San Eulogio | B37: Mina | C37: 4,5 | D37: 2 | F37: P2RF+WF El Burgo | G37: 29420 El Burgo, Málaga | H37: El Burgo | I37: Málaga | L37: - | M37: Sí | N37: 36.7423543 | O37: -4.976372 | P37: https://goo.gl/maps/ouBf8LBHJnL4UmCW9 | Q37: <iframe src="https://www.google.com/maps/embed?pb=!1m18!1m12!1m3!1d102309.62136907295!2d-5.046409841796875!3d36.742354299999995!2m3!1f0!2f0!3f0!3m2!1i1024!2i768!4f13.1!3m3!1m2!1s0xd72cf923938cf29%3A0x25ae9b689c5bf64b!2sMina%20de%20San%20Eulogio!5e0!3m2!1ses!2ses!4v1651831942558!5m2!1ses!2ses" width="600" height="450" style="border:0;" allowfullscreen="" loading="lazy" referrerpolicy="no-referrer-when-downgrade"></iframe> | R37: https://lh5.googleusercontent.com/p/AF1QipMDKhOfEfHq1gb1YjPhM3FEiOEif-qY6GH7FKB_=w408-h544-k-no
A38: Minera De Orgiva S L | B38: Mina | C38: 4,5 | D38: 2 | F38: VH8G+7P Órgiva | G38: Mina Carriles, Parcela 1 Poligono 13, 18400 Órgiva, Granada | H38: Órgiva | I38: Granada | J38: mineradeorgiva.com | K38: 858 78 40 58 | L38: - | M38: Sí | N38: 36.8657704 | O38: -3.423237 | P38: https://goo.gl/maps/rNW5YL6SYpuYyAt37 | Q38: <iframe src="https://www.google.com/maps/embed?pb=!1m18!1m12!1m3!1d408579.69955058146!2d-3.7033363671874646!3d36.86572700000002!2m3!1f0!2f0!3f0!3m2!1i1024!2i768!4f13.1!3m3!1m2!1s0xd71957eea32e8e5%3A0xf7b3a8af8739d653!2sMinera%20De%20Orgiva%20S%20L!5e0!3m2!1ses!2ses!4v1651832130840!5m2!1ses!2ses" width="600" height="450" style="border:0;" allowfullscreen="" loading="lazy" referrerpolicy="no-referrer-when-downgrade"></iframe> | R38: https://lh5.googleusercontent.com/p/AF1QipOEW3PnV4WMkrxjxDlTthqgs05bLTzOA-5lXhMj=w408-h579-k-no
A39: Mina Cobre Las Cruces | B39: Mina | C39: 4,4 | D39: 23 | F39: FVWW+V3 Gerena | G39: Cobre Las Cruces, Gerena | H39: Gerena | I39: Gerena | J39: cobrelascruces.com | K39: 955 65 79 50 | L39: info.fundacioncobrelascruces@fqml.com | M39: No | N39: 37.4971923 | O39: -6.1047787 | P39: https://goo.gl/maps/C5Lby2wtkM5hfVhQ8 | Q39: <iframe src="https://www.google.com/maps/embed?pb=!1m18!1m12!1m3!1d101294.55072297966!2d-6.174816541796837!3d37.497192299999995!2m3!1f0!2f0!3f0!3m2!1i1024!2i768!4f13.1!3m3!1m2!1s0xd123fcea6922277%3A0x35ff90805bd19a28!2sMina%20Cobre%20Las%20Cruces!5e0!3m2!1ses!2ses!4v1651832369621!5m2!1ses!2ses" width="600" height="450" style="border:0;" allowfullscreen="" loading="lazy" referrerpolicy="no-referrer-when-downgrade"></iframe> | R39: https://lh5.googleusercontent.com/p/AF1QipN8-dGTFy5WUw9Xcd5M8D9KpGgpEKhhOk5gibT_=w408-h306-k-no
A40: Minera Los Frailes | B40: Ingeniero de minas | C40: 4,2 | D40: 20 | F40: GQ6C+4H Aznalcóllar | G40: 41870 Aznalcóllar, Sevilla | H40: Aznalcóllar | I40: Sevilla | K40: 954 13 52 12 | L40: - | M40: Sí | N40: 37.5103029 | O40: -6.2285113 | P40: https://goo.gl/maps/UXyKV1of729uJPKE6 | Q40: <iframe src="https://www.google.com/maps/embed?pb=!1m18!1m12!1m3!1d101276.76435890778!2d-6.298549141796815!3d37.51030290000001!2m3!1f0!2f0!3f0!3m2!1i1024!2i768!4f13.1!3m3!1m2!1s0xd123d2f21fa0229%3A0x48d696d4ea7cee31!2sMinera%20Los%20Frailes!5e0!3m2!1ses!2ses!4v1651832405840!5m2!1ses!2ses" width="600" height="450" style="border:0;" allowfullscreen="" loading="lazy" referrerpolicy="no-referrer-when-downgrade"></iframe> | R40: https://lh5.googleusercontent.com/p/AF1QipNQRQSAItTBLPfswAeRba9CymnrvmSCFwvclk4L=w408-h270-k-no
A41: Estación Tren Turístico Minero | B41: Mina | C41: 4,4 | D41: 819 | F41: MCQQ+9W Minas de Riotinto | G41: HV-5015, 21660 Minas de Riotinto, Huelva | H41: Minas de Riotinto | I41: Huelva | J41: parquemineroderiotinto.es | K41: 959 59 00 25 | L41: - | M41: Sí | N41: 37.6884957 | O41: -6.5601914 | P41: https://goo.gl/maps/65w8GGNeCp6aDAVB8 | Q41: <iframe src="https://www.google.com/maps/embed?pb=!1m18!1m12!1m3!1d404137.98175416363!2d-6.840342767187484!3d37.68849570000001!2m3!1f0!2f0!3f0!3m2!1i1024!2i768!4f13.1!3m3!1m2!1s0xd1184c0f19a5855%3A0x8694ad26ff7df1ee!2sEstaci%C3%B3n%20Tren%20Tur%C3%ADstico%20Minero!5e0!3m2!1ses!2ses!4v1651832756981!5m2!1ses!2ses" width="600" height="450" style="border:0;" allowfullscreen="" loading="lazy" referrerpolicy="no-referrer-when-downgrade"></iframe> | R41: https://lh5.googleusercontent.com/p/AF1QipO46HTppwDZ3ta3GCmRK35-HbOkHVdI3YpNpLNX=w408-h306-k-no
A42: Sociedad de Investigación y Explotación Minera de Castilla y León (SIEMCALSA) | B42: Mina | E42: viernes, De 8:00 a 15:00; sábado, Cerrado; domingo, Cerrado; lunes, De 8:00 a 15:00; martes, De 8:00 a 15:00; miércoles, De 8:00 a 15:00; jueves, De 8:00 a 15:00 | F42: G7FM+M9 Boecillo | G42: Av. Rodrigo Zamorano, 6, 47151 Boecillo, Valladolid | H42: Boecillo | I42: Valladolid | J42: siemcalsa.com | K42: 983 47 55 54 | L42: - | M42: Sí | N42: 41.5241912 | O42: -4.7165815 | P42: https://goo.gl/maps/EE6C2uPUsoKmv7t6A | Q42: <iframe src="https://www.google.com/maps/embed?pb=!1m18!1m12!1m3!1d382346.3376317953!2d-4.9967328671875!3d41.52419120000001!2m3!1f0!2f0!3f0!3m2!1i1024!2i768!4f13.1!3m3!1m2!1s0xd471547fdc57c6b%3A0xee9a20d667b1593c!2sSociedad%20de%20Investigaci%C3%B3n%20y%20Explotaci%C3%B3n%20Minera%20de%20Castilla%20y%20Le%C3%B3n%20(SIEMCALSA)!5e0!3m2!1ses!2ses!4v1651832846683!5m2!1ses!2ses" width="600" height="450" style="border:0;" allowfullscreen="" loading="lazy" referrerpolicy="no-referrer-when-downgrade"></iframe> | R42: https://streetviewpixels-pa.googleapis.com/v1/thumbnail?panoid=urMgHhszzn7Q8ARnRv9wkQ&cb_client=search.gws-prod.gps&w=408&h=240&yaw=70.25265&pitch=0&thumbfov=100
A43: Minas de Parzan | B43: Mina | F43: M5PC+P3 Bielsa | G43: 22365 Bielsa, Huesca | H43: Bielsa | I43: Huesca | L43: - | M43: Sí | N43: 42.6868701 | O43: 0.1702246 | P43: https://goo.gl/maps/N9gxrpYaiQLL6fV66 | Q43: <iframe src="https://www.google.com/maps/embed?pb=!1m18!1m12!1m3!1d11731.182738225236!2d0.16146986977539068!3d42.6868701!2m3!1f0!2f0!3f0!3m2!1i1024!2i768!4f13.1!3m3!1m2!1s0x12a80fdfc038bdf1%3A0x8c247137a03af0b3!2sMinas%20de%20Parzan!5e0!3m2!1ses!2ses!4v1651832976043!5m2!1ses!2ses" width="600" height="450" style="border:0;" allowfullscreen="" loading="lazy" referrerpolicy="no-referrer-when-downgrade"></iframe> | R43: https://lh5.googleusercontent.com/p/AF1QipNDNgbVGoi1D3Uo8sCp8Cg9Ko2HeyPDTyz1tbNo=w408-h544-k-no
A44: Mina Rosario | B44: Mina | F44: QHWR+8C Sallent de Gállego | G44: 22640 Sallent de Gállego, Huesca | H44: Sallent de Gállego | I44: Huesca | L44: - | M44: Sí | N44: 42.7958728 | O44: -0.4089021 | P44: https://goo.gl/maps/cLejS947rjp5kisA6 | Q44: <iframe src="https://www.google.com/maps/embed?pb=!1m18!1m12!1m3!1d23421.15295255964!2d-0.4264115604492188!3d42.795872800000005!2m3!1f0!2f0!3f0!3m2!1i1024!2i768!4f13.1!3m3!1m2!1s0xd5797d4c05b821f%3A0x2fa9b61c0e25ffcb!2sMina%20Rosario!5e0!3m2!1ses!2ses!4v1651833133013!5m2!1ses!2ses" width="600" height="450" style="border:0;" allowfullscreen="" loading="lazy" referrerpolicy="no-referrer-when-downgrade"></iframe> | R44: https://lh5.googleusercontent.com/p/AF1QipNGsD2Cnr7sHov99mBFS2qjZa2W-AxvtRELgKMU=w408-h306-k-no
A45: Visita Pozo Sotón | B45: Mina | C45: 5,0 | D45: 345 | E45: viernes, De 8:20 a 14:00; sábado, De 8:20 a 14:00; domingo, De 8:20 a 14:00; lunes, Cerrado; martes, De 8:20 a 14:00; miércoles, De 8:20 a 14:00; jueves, De 8:20 a 14:00 | F45: 79JH+85 San Martín del Rey Aurelio | G45: El Sotón, 2, 33940 San Martín del Rey Aurelio, Asturias | H45: San Martín del Rey Aurelio | I45: Asturias | J45: visitapozosoton.es | K45: 630 11 96 42 | L45: - | M45: No | N45: 43.2808087 | O45: -5.6220688 | P45: https://goo.gl/maps/wXKreSMMfP172Pkr8 | Q45: <iframe src="https://www.google.com/maps/embed?pb=!1m18!1m12!1m3!1d743687.0158947932!2d-5.846548344651628!3d43.2718016607612!2m3!1f0!2f0!3f0!3m2!1i1024!2i768!4f13.1!3m3!1m2!1s0xd365c6c913c32e1%3A0x4d90717c39090853!2sVisita%20Pozo%20Sot%C3%B3n!5e0!3m2!1ses!2ses!4v1651833894821!5m2!1ses!2ses" width="600" height="450" style="border:0;" allowfullscreen="" loading="lazy" referrerpolicy="no-referrer-when-downgrade"></iframe> | R45: https://lh5.googleusercontent.com/p/AF1QipPNzhMBgRVsSWWUUGAvmhlnzRrWbW9ioP20wJTc=w408-h306-k-no
A46: Antigua Mina de Hierro | B46: Mina | C46: 3,6 | D46: 10 | F46: J5Q9+9C Viodo | G46: Lugar el Monte, 1, 33448, Asturias | H46: Viodo | I46: Asturias | L46: - | M46: Sí | N46: 43.6384555 | O46: -5.831455 | P46: https://goo.gl/maps/ZvhdLfgfnD3ygiZN6 | Q46: <iframe src="https://www.google.com/maps/embed?pb=!1m18!1m12!1m3!1d743687.0158947932!2d-5.846548344651628!3d43.2718016607612!2m3!1f0!2f0!3f0!3m2!1i1024!2i768!4f13.1!3m3!1m2!1s0xd36820b9356cc0f%3A0xa82c3da4a4afecb2!2sAntigua%20Mina%20de%20Hierro!5e0!3m2!1ses!2ses!4v1651833942278!5m2!1ses!2ses" width="600" height="450" style="border:0;" allowfullscreen="" loading="lazy" referrerpolicy="no-referrer-when-downgrade"></iframe> | R46: https://lh5.googleusercontent.com/p/AF1QipO0us_SwTX7efPQO9Sb2qSxNXOZCLqQigFfoghf=w408-h306-k-no
A47: Pozu Barreo | B47: Mina | C47: 3,8 | D47: 4 | F47: 66VG+66 Mieres | G47: C. Rector Julio Rodríguez, 33600 Mieres, Asturias | H47: Mieres | I47: Asturias | J47: patrimoniuindustrial.com | K47: 985 45 05 33 | L47: info@patrimoniuindustrial.com | M47: Sí | N47: 43.2430564 | O47: -5.7744296 | P47: https://goo.gl/maps/iuw8jTLi1ECGdefYA | Q47: <iframe src="https://www.google.com/maps/embed?pb=!1m18!1m12!1m3!1d743687.0158947932!2d-5.846548344651655!3d43.2718016607612!2m3!1f0!2f0!3f0!3m2!1i1024!2i768!4f13.1!3m3!1m2!1s0xd36f7f36054c1d9%3A0xdc08f054f9e37a80!2sPozu%20Barreo!5e0!3m2!1ses!2ses!4v1651833987778!5m2!1ses!2ses" width="600" height="450" style="border:0;" allowfullscreen="" loading="lazy" referrerpolicy="no-referrer-when-downgrade"></iframe> | R47: https://lh5.googleusercontent.com/p/AF1QipMBIJdKfGrzeEk7avOXIh_z1e4PwW8NAzntmraW=w408-h906-k-no
A48: MINA EMILIO | B48: Mina | C48: 4,5 | D48: 2 | F48: FQ5G+4W Colunga | G48: 33342 Colunga, Asturias | H48: Colunga | I48: Asturias | L48: - | M48: Sí | N48: 43.4578355 | O48: -5.2227479 | P48: https://goo.gl/maps/UW9Qw2ULnKTy8QGV7 | Q48: <iframe src="https://www.google.com/maps/embed?pb=!1m18!1m12!1m3!1d743687.0158947932!2d-5.846548344651655!3d43.2718016607612!2m3!1f0!2f0!3f0!3m2!1i1024!2i768!4f13.1!3m3!1m2!1s0xd361a0b97e215c7%3A0xc08fdc08bef5c22b!2sMINA%20EMILIO!5e0!3m2!1ses!2ses!4v1651834023965!5m2!1ses!2ses" width="600" height="450" style="border:0;" allowfullscreen="" loading="lazy" referrerpolicy="no-referrer-when-downgrade"></iframe>
A49: Pozu Samuño | B49: Mina | C49: 4,6 | D49: 18 | F49: 789F+XX Langreo | G49: LA-7, 15, 33909 Langreo, Asturias | H49: Langreo | I49: Asturias | L49: - | M49: Sí | N49: 43.2699157 | O49: -5.6749536 | P49: https://goo.gl/maps/9hf7MCbRUx5JFcqT6 | Q49: <iframe src="https://www.google.com/maps/embed?pb=!1m18!1m12!1m3!1d743687.0158947932!2d-5.846548344651655!3d43.2718016607612!2m3!1f0!2f0!3f0!3m2!1i1024!2i768!4f13.1!3m3!1m2!1s0xd365ecdcbd2ba9f%3A0xa13e5e1a2f5e8897!2sPozu%20Samu%C3%B1o!5e0!3m2!1ses!2ses!4v1651834232059!5m2!1ses!2ses" width="600" height="450" style="border:0;" allowfullscreen="" loading="lazy" referrerpolicy="no-referrer-when-downgrade"></iframe> | R49: https://lh5.googleusercontent.com/p/AF1QipPcnv_Ujzz00qeU7Ru8PvFZRZY6E08PBp45_01Y=w408-h725-k-no
A50: Minas de Lieres | B50: Mina | C50: 4,2 | D50: 31 | F50: 9C9F+86 Fresneda | G50: Av. Solvay, 112, 33580 Fresneda, Asturias | H50: Fresneda | I50: Asturias | L50: - | M50: Sí | N50: 43.3683194 | O50: -5.5769999 | P50: https://goo.gl/maps/CjZSeXGAxhWj7Rws6 | Q50: <iframe src="https://www.google.com/maps/embed?pb=!1m18!1m12!1m3!1d743687.0158947932!2d-5.846548344651655!3d43.2718016607612!2m3!1f0!2f0!3f0!3m2!1i1024!2i768!4f13.1!3m3!1m2!1s0xd3667c218fe32f9%3A0xea6db4840c73bcaf!2sMinas%20de%20Lieres!5e0!3m2!1ses!2ses!4v1651834260777!5m2!1ses!2ses" width="600" height="450" style="border:0;" allowfullscreen="" loading="lazy" referrerpolicy="no-referrer-when-downgrade"></iframe> | R50: https://lh5.googleusercontent.com/p/AF1QipOaF7BPexTPXTJ5pwIdQJ41MB-9t5XxnwXzF4yD=w408-h306-k-no
A51: Virtual Data SLU | B51: Ingeniero de minas | C51: 4,9 | D51: 49 | E51: viernes, Abierto 24 horas; sábado, Abierto 24 horas; domingo, Abierto 24 horas; lunes, Abierto 24 horas; martes, Abierto 24 horas; miércoles, Abierto 24 horas; jueves, Abierto 24 horas | F51: 68GR+MP Albolote | G51: C. Magallanes, Nº17, 18220 Albolote, Granada | H51: Albolote | I51: Granada | K51: 669 01 56 34 | L51: - | M51: No | N51: 37.2267479 | O51: -3.6582004 | P51: https://goo.gl/maps/VtyQaq3AN6JBM8fB8 | Q51: <iframe src="https://www.google.com/maps/embed?pb=!1m18!1m12!1m3!1d406641.0477509711!2d-3.9383517671874984!3d37.22674789999999!2m3!1f0!2f0!3f0!3m2!1i1024!2i768!4f13.1!3m3!1m2!1s0xd71fdedaebec3df%3A0x3d2366d21de23e2d!2sLEGALIZACI%C3%93N%20POZOS%20BEL%C3%89N%20DELGADO!5e0!3m2!1ses!2ses!4v1651829613434!5m2!1ses!2ses" width="600" height="450" style="border:0;" allowfullscreen="" loading="lazy" referrerpolicy="no-referrer-when-downgrade"></iframe> | R51: https://lh5.googleusercontent.com/p/AF1QipPbs1jmptDAumSjwO7R7VuNc4FBZXDMIOLXEIM0=w408-h306-k-no
A52: Movimientos Y Voladuras S.l. | B52: Mina | E52: viernes, De 10:00 a 17:00; sábado, Cerrado; domingo, Cerrado; lunes, De 10:00 a 17:00; martes, De 10:00 a 17:00; miércoles, De 10:00 a 17:00; jueves, De 10:00 a 17:00 | F52: 66XG+X2 Mieres | G52: C. Martínez de Vega, 2, 33600 Mieres, Asturias | H52: Mieres | I52: Asturias | K52: 985 46 41 51 | L52: - | M52: Sí | N52: 43.249961 | O52: -5.774999 | P52: https://goo.gl/maps/tN1iwywsWQ2ugNG5A | Q52: <iframe src="https://www.google.com/maps/embed?pb=!1m18!1m12!1m3!1d743687.0158947932!2d-5.846548344651628!3d43.2718016607612!2m3!1f0!2f0!3f0!3m2!1i1024!2i768!4f13.1!3m3!1m2!1s0xd36f688f698119b%3A0xc9ac81d94e846fff!2sMovimientos%20Y%20Voladuras%20S.l.!5e0!3m2!1ses!2ses!4v1651834688919!5m2!1ses!2ses" width="600" height="450" style="border:0;" allowfullscreen="" loading="lazy" referrerpolicy="no-referrer-when-downgrade"></iframe> | R52: https://streetviewpixels-pa.googleapis.com/v1/thumbnail?panoid=nLKYlRYYn73ujw02viavSQ&cb_client=search.gws-prod.gps&w=408&h=240&yaw=233.51384&pitch=0&thumbfov=100
A53: Factoria Minera Vegamediana | B53: Mina | C53: 4,8 | D53: 10 | F53: RVHC+9V Sabero | G53: 24810 Sabero, León | H53: Sabero | I53: León | L53: - | M53: Sí | N53: 42.828379 | O53: -5.1277714 | P53: https://goo.gl/maps/P3E9yPPdPeHtv1tX8 | Q53: <iframe src="https://www.google.com/maps/embed?pb=!1m18!1m12!1m3!1d743687.0158947932!2d-5.846548344651628!3d43.2718016607612!2m3!1f0!2f0!3f0!3m2!1i1024!2i768!4f13.1!3m3!1m2!1s0xd37d94c9f7abbf7%3A0xcdc79383d9a80246!2sFactoria%20Minera%20Vegamediana!5e0!3m2!1ses!2ses!4v1651835249215!5m2!1ses!2ses" width="600" height="450" style="border:0;" allowfullscreen="" loading="lazy" referrerpolicy="no-referrer-when-downgrade"></iframe> | R53: https://lh5.googleusercontent.com/p/AF1QipNiAi4F8QZwH3MiUclDEyLiBgSeMDet67aw-GwP=w408-h612-k-no
A54: Restos mineros de Baltezana | B54: Mina | C54: 4,5 | D54: 4 | F54: 8RWG+F2 Castro Urdiales | G54: 39706 Castro Urdiales, Cantabria | H54: Castro Urdiales | I54: Cantabria | L54: - | M54: Sí | N54: 43.346199 | O54: -3.1749275 | P54: https://goo.gl/maps/17Fs5W5r15cueygC9 | Q54: <iframe src="https://www.google.com/maps/embed?pb=!1m18!1m12!1m3!1d745379.2546442841!2d-4.000721809886247!3d43.133136288602024!2m3!1f0!2f0!3f0!3m2!1i1024!2i768!4f13.1!3m3!1m2!1s0xd4ef7d34661c7a3%3A0x1fe0d7c5e2ba8b2!2sRestos%20mineros%20de%20Baltezana!5e0!3m2!1ses!2ses!4v1651836007418!5m2!1ses!2ses" width="600" height="450" style="border:0;" allowfullscreen="" loading="lazy" referrerpolicy="no-referrer-when-downgrade"></iframe> | R54: https://lh5.googleusercontent.com/p/AF1QipOLRcCOBdMR6jlhUSEpGcLh_btO7Y15j3ofeXCz=w408-h544-k-no
A55: Setares | B55: Mina | C55: 4,2 | D55: 6 | E55: viernes, Abierto 24 horas; sábado, Abierto 24 horas; domingo, Abierto 24 horas; lunes, Abierto 24 horas; martes, Abierto 24 horas; miércoles, Abierto 24 horas; jueves, Abierto 24 horas | F55: 8RM9+WM Castro Urdiales | G55: 39707 Castro Urdiales, Cantabria | H55: Castro Urdiales | I55: Cantabria | L55: - | M55: Sí | N55: 43.3348282 | O55: -3.1808695 | P55: https://goo.gl/maps/WBLWqRqEqQ6XpK5w9 | Q55: <iframe src="https://www.google.com/maps/embed?pb=!1m18!1m12!1m3!1d745379.2546442841!2d-4.000721809886247!3d43.133136288602024!2m3!1f0!2f0!3f0!3m2!1i1024!2i768!4f13.1!3m3!1m2!1s0xd4ef132676079e9%3A0xe7c184b265301047!2sSetares!5e0!3m2!1ses!2ses!4v1651836015777!5m2!1ses!2ses" width="600" height="450" style="border:0;" allowfullscreen="" loading="lazy" referrerpolicy="no-referrer-when-downgrade"></iframe> | R55: https://lh5.googleusercontent.com/p/AF1QipMfhQyi_R10yZESbteiBloSSOdpbcXJh0qMZy5d=w408-h273-k-no
A56: Pozo Peña Monteros | B56: Mina | C56: 5,0 | D56: 3 | F56: 9Q5J+F7 Soto | G56: 39320, Cantabria | H56: Soto | I56: Cantabria | L56: - | M56: Sí | N56: 43.3586651 | O56: -4.2193495 | P56: https://goo.gl/maps/opUWuc8ZQuxyVL24A | Q56: <iframe src="https://www.google.com/maps/embed?pb=!1m18!1m12!1m3!1d742625.0124304211!2d-4.779636134374969!3d43.35864250000001!2m3!1f0!2f0!3f0!3m2!1i1024!2i768!4f13.1!3m3!1m2!1s0xd49126593b1142f%3A0x2a6b8b71fa9ff84b!2sPozo%20Pe%C3%B1a%20Monteros!5e0!3m2!1ses!2ses!4v1651836025058!5m2!1ses!2ses" width="600" height="450" style="border:0;" allowfullscreen="" loading="lazy" referrerpolicy="no-referrer-when-downgrade"></iframe> | R56: https://lh5.googleusercontent.com/p/AF1QipOVhvQhUSxSq8GSF6btxklg_od8xj2KZ4deAbNU=w408-h306-k-no
A57: Antigua Sociedad William Baird and Company | B57: Mina | C57: 4,0 | D57: 1 | F57: 94V8+FJ Camargo | G57: 39609 Camargo, Cantabria | H57: Camargo | I57: Cantabria | L57: - | M57: Sí | N57: 43.3937055 | O57: -3.8834156 | P57: https://goo.gl/maps/926KyMdS2dFdu3jD8 | Q57: <iframe src="https://www.google.com/maps/embed?pb=!1m18!1m12!1m3!1d745379.2546442841!2d-4.000721809886247!3d43.133136288602024!2m3!1f0!2f0!3f0!3m2!1i1024!2i768!4f13.1!3m3!1m2!1s0xd4937bdd4c3db13%3A0x156e05d479b44ac1!2sAntigua%20Sociedad%20William%20Baird%20and%20Company!5e0!3m2!1ses!2ses!4v1651836050434!5m2!1ses!2ses" width="600" height="450" style="border:0;" allowfullscreen="" loading="lazy" referrerpolicy="no-referrer-when-downgrade"></iframe>
A58: Mina de Buferrera | B58: Mina | C58: 4,6 | D58: 65 | E58: viernes, Abierto 24 horas; sábado, Abierto 24 horas; domingo, Abierto 24 horas; lunes, Abierto 24 horas; martes, Abierto 24 horas; miércoles, Abierto 24 horas; jueves, Abierto 24 horas | F58: 72F9+HP Cangas de Onís | G58: 33556 Cangas de Onís, Asturias | H58: Cangas de Onís | I58: Asturias | L58: - | M58: Sí | N58: 43.2739873 | O58: -4.9806596 | P58: https://goo.gl/maps/L6pfMyaVopCgyNTJ8 | Q58: <iframe src="https://www.google.com/maps/embed?pb=!1m18!1m12!1m3!1d743660.3079846336!2d-5.540962334375046!3d43.273987299999995!2m3!1f0!2f0!3f0!3m2!1i1024!2i768!4f13.1!3m3!1m2!1s0xd49d963c111a369%3A0x687bd279e07586f6!2sMina%20de%20Buferrera!5e0!3m2!1ses!2ses!4v1651836545105!5m2!1ses!2ses" width="600" height="450" style="border:0;" allowfullscreen="" loading="lazy" referrerpolicy="no-referrer-when-downgrade"></iframe> | R58: https://lh5.googleusercontent.com/p/AF1QipMONWL88Td59eizM9A5xJYLyOllB4Zpuu-ey-8D=w408-h306-k-no
A59: Mina romana de lapis specularis La Condenada | B59: Mina | C59: 4,8 | D59: 40 | E59: viernes, Cerrado; sábado, De 11:30 a 13:30, De 16:30 a 18:30; domingo, De 11:30 a 13:30, De 16:30 a 18:30; lunes, Cerrado; martes, Cerrado; miércoles, Cerrado; jueves, Cerrado | F59: M66Q+VH Osa de la Vega | G59: C. del Agua, 4, 16423 Osa de la Vega, Cuenca | H59: Osa de la Vega | I59: Cuenca | J59: minalacondenada.com | K59: 647 75 33 76 | L59: core-js-bundle@3.2.1 | M59: No | N59: 39.662219 | O59: -2.7611223 | P59: https://goo.gl/maps/4NotLizPgSzarYDD6 | Q59: <iframe src="https://www.google.com/maps/embed?pb=!1m18!1m12!1m3!1d6367864.349956957!2d-7.960588547398471!3d38.80247795440378!2m3!1f0!2f0!3f0!3m2!1i1024!2i768!4f13.1!3m3!1m2!1s0xd68151880760c0f%3A0xa62b4696bea0de1a!2sMina%20romana%20de%20lapis%20specularis%20La%20Condenada!5e0!3m2!1ses!2ses!4v1651836864278!5m2!1ses!2ses" width="600" height="450" style="border:0;" allowfullscreen="" loading="lazy" referrerpolicy="no-referrer-when-downgrade"></iframe> | R59: https://lh5.googleusercontent.com/p/AF1QipP5wOgNM17NYNMBB7iPttqz5dLCqly1-6ftBIHl=w408-h245-k-no
A60: Minas de Gilico | B60: Mina | C60: 4,4 | D60: 5 | F60: 48RW+GR Cehegín | G60: 30439 Cehegín, Murcia | H60: Cehegín | I60: Murcia | L60: - | M60: Sí | N60: 38.1413452 | O60: -1.6529662 | P60: https://goo.gl/maps/k3KboNtDsp1mF47M7 | Q60: <iframe src="https://www.google.com/maps/embed?pb=!1m18!1m12!1m3!1d6367864.349956957!2d-7.960588547398471!3d38.80247795440378!2m3!1f0!2f0!3f0!3m2!1i1024!2i768!4f13.1!3m3!1m2!1s0xd6445341ff2d6ff%3A0x10c332bd69009ba6!2sMinas%20de%20Gilico!5e0!3m2!1ses!2ses!4v1651836873449!5m2!1ses!2ses" width="600" height="450" style="border:0;" allowfullscreen="" loading="lazy" referrerpolicy="no-referrer-when-downgrade"></iframe> | R60: https://lh5.googleusercontent.com/p/AF1QipNtMLrxDIEtRZVdAgX0lkTi1we1ofX4WgT9WLu9=w426-h240-k-no
A61: Pozo Elorza Castillete | B61: Mina | C61: 3,3 | D61: 3 | F61: MV88+49 Puertollano | G61: 13597 Puertollano, Cdad. Real | H61: Puertollano | I61: Cdad. Real | L61: - | M61: Sí | N61: 38.6653374 | O61: -4.1340643 | P61: https://goo.gl/maps/eJiKExK6iyuGiJjX7 | Q61: <iframe src="https://www.google.com/maps/embed?pb=!1m18!1m12!1m3!1d49844.54630719602!2d-4.169083220898438!3d38.66533740000001!2m3!1f0!2f0!3f0!3m2!1i1024!2i768!4f13.1!3m3!1m2!1s0xd6b8c0a5d457d9d%3A0xad10420459143b28!2sPozo%20Elorza%20Castillete!5e0!3m2!1ses!2ses!4v1651836994919!5m2!1ses!2ses" width="600" height="450" style="border:0;" allowfullscreen="" loading="lazy" referrerpolicy="no-referrer-when-downgrade"></iframe> | R61: https://lh5.googleusercontent.com/p/AF1QipMYIPzxBaffFimWI6GXAKp6vnQVcgN9DwEASjlJ=w408-h272-k-no
A62: Ruinas &quot;Mina Asdrubal&quot; | B62: Mina | C62: 4,0 | D62: 1 | F62: MV5R+CW Puertollano | G62: España, Calle Jardin, 12, 13500 Puertollano, Cdad. Real | H62: Puertollano | I62: Cdad. Real | L62: - | M62: Sí | N62: 38.6585475 | O62: -4.1079793 | P62: https://goo.gl/maps/M5Amcnqda6RuybUf9 | Q62: <iframe src="https://www.google.com/maps/embed?pb=!1m18!1m12!1m3!1d49849.28457868557!2d-4.1427289208984375!3d38.658530000000006!2m3!1f0!2f0!3f0!3m2!1i1024!2i768!4f13.1!3m3!1m2!1s0xd6b8b792100afc5%3A0x746685405b3fb0aa!2sRuinas%20%22Mina%20Asdrubal%22!5e0!3m2!1ses!2ses!4v1651837004840!5m2!1ses!2ses" width="600" height="450" style="border:0;" allowfullscreen="" loading="lazy" referrerpolicy="no-referrer-when-downgrade"></iframe> | R62: https://lh5.googleusercontent.com/p/AF1QipOcnZ2lo6VL855HaoFcY4H_mHhV6xXDm0-2z0vU=w426-h240-k-no
A63: Pozo norte (Castillete) | B63: Mina | C63: 5,0 | D63: 1 | F63: MVGX+JF Puertollano | G63: Ctra. Pozo Norte, 4, 13500 Puertollano, Cdad. Real | H63: Puertollano | I63: Cdad. Real | K63: 615 71 06 88 | L63: - | M63: Sí | N63: 38.6765242 | O63: -4.1013303 | P63: https://goo.gl/maps/WsDjJAojim4dsysd7 | Q63: <iframe src="https://www.google.com/maps/embed?pb=!1m18!1m12!1m3!1d1581552.515043821!2d-5.13207819687922!3d39.266252811795!2m3!1f0!2f0!3f0!3m2!1i1024!2i768!4f13.1!3m3!1m2!1s0xd6b8c8fec625e0d%3A0x9e08c34083905942!2sPozo%20norte%20(Castillete)!5e0!3m2!1ses!2ses!4v1651837168527!5m2!1ses!2ses" width="600" height="450" style="border:0;" allowfullscreen="" loading="lazy" referrerpolicy="no-referrer-when-downgrade"></iframe> | R63: https://lh5.googleusercontent.com/p/AF1QipN_Ktey7cHQlkY55PIwq6Bfo48iAArIiW3QOhBz=w408-h306-k-no
A64: Mina La Fuerza | B64: Mina | E64: viernes, Abierto 24 horas; sábado, Abierto 24 horas; domingo, Abierto 24 horas; lunes, Abierto 24 horas; martes, Abierto 24 horas; miércoles, Abierto 24 horas; jueves, Abierto 24 horas | F64: 3X7M+JM Hiendelaencina | G64: 19242 Hiendelaencina, Guadalajara | H64: Hiendelaencina | I64: Guadalajara | L64: - | M64: Sí | N64: 41.0640859 | O64: -3.0158037 | P64: https://goo.gl/maps/4pkdiow48FiKGitE8 | Q64: <iframe src="https://www.google.com/maps/embed?pb=!1m18!1m12!1m3!1d48131.591422733465!2d-3.0508226208984377!3d41.064085899999995!2m3!1f0!2f0!3f0!3m2!1i1024!2i768!4f13.1!3m3!1m2!1s0xd437177d275ae73%3A0x4db641f2e84c72!2sMina%20La%20Fuerza!5e0!3m2!1ses!2ses!4v1651837531371!5m2!1ses!2ses" width="600" height="450" style="border:0;" allowfullscreen="" loading="lazy" referrerpolicy="no-referrer-when-downgrade"></iframe> | R64: https://lh5.googleusercontent.com/p/AF1QipM1BqeLHtokYr0PNNqGi9wtFPRFgUXdsvdd36Ww=w408-h544-k-no
A65: Mina San Carlos | B65: Mina | F65: 32R4+JX Hiendelaencina | G65: 19242 Hiendelaencina, Guadalajara | H65: Hiendelaencina | I65: Guadalajara | L65: - | M65: Sí | N65: 41.0915029 | O65: -2.99254 | P65: https://goo.gl/maps/ZwcwFhVaVPMcUSDq5 | Q65: <iframe src="https://www.google.com/maps/embed?pb=!1m18!1m12!1m3!1d48111.51941917401!2d-3.0275589208984375!3d41.0915029!2m3!1f0!2f0!3f0!3m2!1i1024!2i768!4f13.1!3m3!1m2!1s0xd437a6e0080d727%3A0xba17001484dc4d1!2sMina%20San%20Carlos!5e0!3m2!1ses!2ses!4v1651837539763!5m2!1ses!2ses" width="600" height="450" style="border:0;" allowfullscreen="" loading="lazy" referrerpolicy="no-referrer-when-downgrade"></iframe> | R65: https://lh5.googleusercontent.com/p/AF1QipMEhx10aLSvBsajFKvvK3UfKqU12CI-h3BJhx4r=w408-h271-k-no
A66: Sondeos IGM | B66: Ingeniero de minas | C66: 5,0 | D66: 2 | E66: viernes, De 9:00 a 21:00; sábado, Cerrado; domingo, Cerrado; lunes, De 9:00 a 21:00; martes, De 9:00 a 21:00; miércoles, De 9:00 a 21:00; jueves, De 9:00 a 21:00 | F66: H97F+JM San Sebastián de los Reyes | G66: Av. de la Coruña, 37, bajo, 28702 San Sebastián de los Reyes, Madrid | H66: San Sebastián de los Reyes | I66: Madrid | J66: sondeosigm.es | K66: 675 89 23 09 | L66: info@sondeosigm.es | M66: No | N66: 40.5640389 | O66: -3.625854 | P66: https://goo.gl/maps/4jp1kuKEJPDvSutZ8 | Q66: <iframe src="https://www.google.com/maps/embed?pb=!1m18!1m12!1m3!1d387965.96290195035!2d-3.9060002671875047!3d40.5640287!2m3!1f0!2f0!3f0!3m2!1i1024!2i768!4f13.1!3m3!1m2!1s0xd422cd96a79a4b7%3A0x2c2b19cb7dfc64e7!2sSondeos%20IGM!5e0!3m2!1ses!2ses!4v1651837660106!5m2!1ses!2ses" width="600" height="450" style="border:0;" allowfullscreen="" loading="lazy" referrerpolicy="no-referrer-when-downgrade"></iframe> | R66: https://streetviewpixels-pa.googleapis.com/v1/thumbnail?panoid=sHMmr_XR3bB-cb8IuZgLwQ&cb_client=search.gws-prod.gps&w=408&h=240&yaw=26.220423&pitch=0&thumbfov=100
A67: Promiex S.L. | B67: Ingeniero de minas | F67: J8W8+RR Ávila | G67: C. Vereda de las Mozas, 6, Bajo, 05003 Ávila | H67: Ávila | I67: Ávila | J67: promiex.com | K67: 610 22 19 24 | L67: - | M67: No | N67: 40.64712 | O67: -4.68295 | P67: https://goo.gl/maps/zerkQdq7BCRxzwRd9 | Q67: <iframe src="https://www.google.com/maps/embed?pb=!1m18!1m12!1m3!1d24217.745699833347!2d-4.700459460449203!3d40.64712!2m3!1f0!2f0!3f0!3m2!1i1024!2i768!4f13.1!3m3!1m2!1s0xd40f3a6c587f35d%3A0x91aa710eb007f88!2sPromiex%20S.L.!5e0!3m2!1ses!2ses!4v1651838038562!5m2!1ses!2ses" width="600" height="450" style="border:0;" allowfullscreen="" loading="lazy" referrerpolicy="no-referrer-when-downgrade"></iframe> | R67: https://streetviewpixels-pa.googleapis.com/v1/thumbnail?panoid=UIiKVzWi03yDPnc5Uiz4AA&cb_client=search.gws-prod.gps&w=408&h=240&yaw=282.62125&pitch=0&thumbfov=100
A68: Mina de la Osera | B68: Mina | C68: 4,5 | D68: 2 | F68: G2MC+3F Las Cuestas | G68: Unnamed Road, 28260, Madrid | H68: Las Cuestas | I68: Madrid | L68: - | M68: Sí | N68: 40.5326869 | O68: -3.9787805 | P68: https://goo.gl/maps/cD7EmrwxtDbJCrPU8 | Q68: <iframe src="https://www.google.com/maps/embed?pb=!1m18!1m12!1m3!1d3113323.663988985!2d-7.216084765231528!3d40.35664907956948!2m3!1f0!2f0!3f0!3m2!1i1024!2i768!4f13.1!3m3!1m2!1s0xd419d7d64edf4e7%3A0xd8dd3ce3a5af5695!2sMina%20de%20la%20Osera!5e0!3m2!1ses!2ses!4v1651838215122!5m2!1ses!2ses" width="600" height="450" style="border:0;" allowfullscreen="" loading="lazy" referrerpolicy="no-referrer-when-downgrade"></iframe> | R68: https://lh5.googleusercontent.com/p/AF1QipOBHhah8cNOihBPz5qkuLW4NjquloqOc_2WW_vD=w408-h306-k-no
A69: Jesús Izquierdo, minería. | B69: Ingeniero de minas | C69: 5,0 | D69: 4 | E69: viernes, De 9:00 a 20:00; sábado, Cerrado; domingo, Cerrado; lunes, De 9:00 a 20:00; martes, De 9:00 a 20:00; miércoles, De 9:00 a 20:00; jueves, De 9:00 a 20:00 | F69: 88W8+4W Burgos | G69: C. Alhucemas, nº 2, 3º C, 09006 Burgos | H69: Burgos | I69: Burgos | J69: jesusizquierdomineria.es | K69: 676 47 69 98 | L69: jesus@jesusizquierdomineria.es | M69: No | N69: 42.3453316 | O69: -3.6827537 | P69: https://goo.gl/maps/t1pNGcdbxYKfFCnH9 | Q69: <iframe src="https://www.google.com/maps/embed?pb=!1m18!1m12!1m3!1d47182.80526551711!2d-3.6946930765114048!3d42.344115343951316!2m3!1f0!2f0!3f0!3m2!1i1024!2i768!4f13.1!3m3!1m2!1s0xd45fcc7f7872b0b%3A0x6f47ffdcb54ef251!2zSmVzw7pzIEl6cXVpZXJkbywgbWluZXLDrWEu!5e0!3m2!1ses!2ses!4v1651838264351!5m2!1ses!2ses" width="600" height="450" style="border:0;" allowfullscreen="" loading="lazy" referrerpolicy="no-referrer-when-downgrade"></iframe> | R69: https://lh5.googleusercontent.com/p/AF1QipORT-xEKnGzK4BE0tvybHxSaYefBx07ygISEuTR=w408-h306-k-no
A70: Dyproim Minería Y Medio Ambiente | B70: Ingeniero de minas | C70: 3,7 | D70: 3 | F70: 88W8+VJ Burgos | G70: Av. de Castilla y León, 16, 09006 Burgos | H70: Burgos | I70: Burgos | K70: 947 22 46 60 | L70: - | M70: No | N70: 42.3473342 | O70: -3.6835185 | P70: https://goo.gl/maps/gYdGxouQa1cRnVDu9 | Q70: <iframe src="https://www.google.com/maps/embed?pb=!1m18!1m12!1m3!1d47182.80526551711!2d-3.6946930765114048!3d42.344115343951316!2m3!1f0!2f0!3f0!3m2!1i1024!2i768!4f13.1!3m3!1m2!1s0xd45fcb8a9b3853b%3A0xe273ec7f97d22552!2sDyproim%20Miner%C3%ADa%20Y%20Medio%20Ambiente!5e0!3m2!1ses!2ses!4v1651838275185!5m2!1ses!2ses" width="600" height="450" style="border:0;" allowfullscreen="" loading="lazy" referrerpolicy="no-referrer-when-downgrade"></iframe> | R70: https://streetviewpixels-pa.googleapis.com/v1/thumbnail?panoid=xLcotiuSlvnyg42I-D9PNA&cb_client=search.gws-prod.gps&w=408&h=240&yaw=144.73819&pitch=0&thumbfov=100
A71: Acmina | B71: Ingeniero de minas | E71: viernes, De 9:00 a 14:00; sábado, Cerrado; domingo, Cerrado; lunes, De 9:00 a 14:00; martes, De 9:00 a 14:00; miércoles, De 9:00 a 14:00; jueves, De 9:00 a 14:00 | F71: 88X5+54 Burgos | G71: Av. Reyes Católicos, 34, ENTREPLANTA IZQUIERDA, 09005 Burgos | H71: Burgos | I71: Burgos | J71: acminaburgos.com | K71: 699 94 75 93 | L71: acmina@acmina.es | M71: No | N71: 42.3479891 | O71: -3.6921941 | P71: https://goo.gl/maps/h9qRoAimaAMGcrPZ6 | Q71: <iframe src="https://www.google.com/maps/embed?pb=!1m18!1m12!1m3!1d47182.80526551711!2d-3.6946930765114048!3d42.344115343951316!2m3!1f0!2f0!3f0!3m2!1i1024!2i768!4f13.1!3m3!1m2!1s0xd45fcc4c797d65b%3A0x382a08ad867de140!2sAcmina!5e0!3m2!1ses!2ses!4v1651838283825!5m2!1ses!2ses" width="600" height="450" style="border:0;" allowfullscreen="" loading="lazy" referrerpolicy="no-referrer-when-downgrade"></iframe> | R71: https://streetviewpixels-pa.googleapis.com/v1/thumbnail?panoid=vh2ayufJ5qCviLUTPflYWg&cb_client=search.gws-prod.gps&w=408&h=240&yaw=160.11456&pitch=0&thumbfov=100
A72: Mina Esperanza | B72: Mina | C72: 4,6 | D72: 44 | E72: viernes, De 10:00 a 20:00; sábado, De 10:00 a 20:00; domingo, De 10:00 a 20:00; lunes, De 10:00 a 20:00; martes, De 10:00 a 20:00; miércoles, De 10:00 a 20:00; jueves, De 10:00 a 20:00 | F72: 9FQ4+CF Olmos de Atapuerca | G72: Cam. de Fuente Paldeja, 09199 Olmos de Atapuerca, Burgos | H72: Olmos de Atapuerca | I72: Burgos | J72: minaesperanza.com | K72: 947 42 17 14 | L72: reservas@minaesperanza.com | M72: No | N72: 42.3886229 | O72: -3.5438282 | P72: https://goo.gl/maps/KoKUEpr1VcAVXfzM6 | Q72: <iframe src="https://www.google.com/maps/embed?pb=!1m18!1m12!1m3!1d47149.38887256093!2d-3.5788471208984576!3d42.38862290000001!2m3!1f0!2f0!3f0!3m2!1i1024!2i768!4f13.1!3m3!1m2!1s0xd45f11a50000001%3A0x868a4f3579a77926!2sMina%20Esperanza!5e0!3m2!1ses!2ses!4v1651838292372!5m2!1ses!2ses" width="600" height="450" style="border:0;" allowfullscreen="" loading="lazy" referrerpolicy="no-referrer-when-downgrade"></iframe> | R72: https://lh5.googleusercontent.com/p/AF1QipPtF4csEwlY1s8sc9W3TzuICeHPooUT6qoC__rl=w408-h271-k-no
A73: AMINSA | B73: Mina | E73: viernes, De 8:00 a 18:00; sábado, Cerrado; domingo, Cerrado; lunes, De 8:00 a 18:00; martes, De 8:00 a 18:00; miércoles, De 8:00 a 18:00; jueves, De 8:00 a 18:00 | F73: FM6C+Q7 Villalmóndar | G73: 09258, Burgos | H73: Villalmóndar | I73: Burgos | J73: aplicacionesminerales.es | K73: 947 59 02 81 | L73: comercial@aplicacionesminerales.es | M73: Sí | N73: 42.4619526 | O73: -3.3293356 | P73: https://goo.gl/maps/v2icT469R9WLHWxi7 | Q73: <iframe src="https://www.google.com/maps/embed?pb=!1m18!1m12!1m3!1d47094.27069272236!2d-3.364354520898438!3d42.461952600000004!2m3!1f0!2f0!3f0!3m2!1i1024!2i768!4f13.1!3m3!1m2!1s0xd458978249ae91f%3A0x50f6c1f5c22277c9!2sAMINSA!5e0!3m2!1ses!2ses!4v1651838331481!5m2!1ses!2ses" width="600" height="450" style="border:0;" allowfullscreen="" loading="lazy" referrerpolicy="no-referrer-when-downgrade"></iframe>
A74: Minas de Manganeso Centro recepción | B74: Mina | C74: 4,9 | D74: 31 | E74: viernes, Abierto 24 horas; sábado, Abierto 24 horas; domingo, Abierto 24 horas; lunes, Abierto 24 horas; martes, Abierto 24 horas; miércoles, Abierto 24 horas; jueves, Abierto 24 horas | F74: 9QH5+37 Puras de Villafranca | G74: Diseminado Puras, 7, 09258 Puras de Villafranca, Burgos | H74: Puras de Villafranca | I74: Burgos | J74: minasdepuras.com | L74: info@minasdepuras.com | M74: Sí | N74: 42.377741 | O74: -3.2417395 | P74: https://goo.gl/maps/MruUVAiqyG2X4Mim6 | Q74: <iframe src="https://www.google.com/maps/embed?pb=!1m18!1m12!1m3!1d47157.570897747435!2d-3.2768160208984374!3d42.37772869999999!2m3!1f0!2f0!3f0!3m2!1i1024!2i768!4f13.1!3m3!1m2!1s0xd45857275be56f7%3A0x3a544d9ceaa2e096!2sMinas%20de%20Manganeso%20Centro%20recepci%C3%B3n!5e0!3m2!1ses!2ses!4v1651838348996!5m2!1ses!2ses" width="600" height="450" style="border:0;" allowfullscreen="" loading="lazy" referrerpolicy="no-referrer-when-downgrade"></iframe> | R74: https://lh5.googleusercontent.com/p/AF1QipMqytROfswmlzrlQsJzN4fprqoNIyXdZLQp0qsg=w408-h884-k-no
A75: Cantera de Pozarrate, mina de Sílex de Treviño | B75: Mina | C75: 5,0 | D75: 3 | E75: viernes, Abierto 24 horas; sábado, Abierto 24 horas; domingo, Abierto 24 horas; lunes, Abierto 24 horas; martes, Abierto 24 horas; miércoles, Abierto 24 horas; jueves, Abierto 24 horas | F75: P639+5Q Grandíval | G75: 09217, Burgos | H75: Grandíval | I75: Burgos | J75: condadodetreviño.es | K75: 945 36 00 18 | L75: - | M75: Sí | N75: 42.702971 | O75: -2.7805268 | P75: https://goo.gl/maps/yjWsSbzAWMNbrC3F6 | Q75: <iframe src="https://www.google.com/maps/embed?pb=!1m18!1m12!1m3!1d46912.56654840778!2d-2.8155457208984376!3d42.70297100000001!2m3!1f0!2f0!3f0!3m2!1i1024!2i768!4f13.1!3m3!1m2!1s0xd4f92cd821c24b3%3A0x678fb53a589b56ec!2sCantera%20de%20Pozarrate%2C%20mina%20de%20S%C3%ADlex%20de%20Trevi%C3%B1o!5e0!3m2!1ses!2ses!4v1651838522685!5m2!1ses!2ses" width="600" height="450" style="border:0;" allowfullscreen="" loading="lazy" referrerpolicy="no-referrer-when-downgrade"></iframe> | R75: https://lh5.googleusercontent.com/p/AF1QipNY9kGnP288hbE5J4i4KgGYCqSdIZ0tBG-u8MbA=w408-h306-k-no
A76: Inproobras Ingeniería | B76: Ingeniero de minas | C76: 5,0 | D76: 1 | E76: viernes, De 8:00 a 15:00; sábado, Cerrado; domingo, Cerrado; lunes, De 8:00 a 15:00; martes, De 8:00 a 15:00; miércoles, De 8:00 a 15:00; jueves, De 8:00 a 15:00 | F76: HCX9+76 León | G76: P.º Salamanca, 27, 24009 León | H76: León | I76: León | J76: inproobras.com | K76: 987 22 56 44 | L76: simple-line-icons@2.4.1 | M76: No | N76: 42.598127 | O76: -5.5819776 | P76: https://goo.gl/maps/QQFybYaCEA5MBpdi8 | Q76: <iframe src="https://www.google.com/maps/embed?pb=!1m18!1m12!1m3!1d23495.854987061735!2d-5.599508660449199!3d42.5981281!2m3!1f0!2f0!3f0!3m2!1i1024!2i768!4f13.1!3m3!1m2!1s0xd379a933a023c8d%3A0x19f7d39c4108823e!2sInproobras%20Ingenier%C3%ADa!5e0!3m2!1ses!2ses!4v1651838811403!5m2!1ses!2ses" width="600" height="450" style="border:0;" allowfullscreen="" loading="lazy" referrerpolicy="no-referrer-when-downgrade"></iframe> | R76: https://lh5.googleusercontent.com/p/AF1QipNGCr_CsELVUWiuoSh-ahonWyWTKGLLj_xiG_Hh=w426-h240-k-no
A77: Pozo Herrera II | B77: Mina | C77: 4,6 | D77: 8 | E77: viernes, Abierto 24 horas; sábado, Abierto 24 horas; domingo, Abierto 24 horas; lunes, Abierto 24 horas; martes, Abierto 24 horas; miércoles, Abierto 24 horas; jueves, Abierto 24 horas | F77: RRP2+4H Sotillos de Sabero | G77: 24814 Sotillos de Sabero, León | H77: Sotillos de Sabero | I77: León | L77: - | M77: Sí | N77: 42.8352408 | O77: -5.1984656 | P77: https://goo.gl/maps/cEqJ6nCyNhzCYxkT8 | Q77: <iframe src="https://www.google.com/maps/embed?pb=!1m18!1m12!1m3!1d23406.20053032356!2d-5.216015460449219!3d42.835364999999996!2m3!1f0!2f0!3f0!3m2!1i1024!2i768!4f13.1!3m3!1m2!1s0xd37db6f0fb10cdd%3A0xbb4d6018e04dfedc!2sPozo%20Herrera%20II!5e0!3m2!1ses!2ses!4v1651838946219!5m2!1ses!2ses" width="600" height="450" style="border:0;" allowfullscreen="" loading="lazy" referrerpolicy="no-referrer-when-downgrade"></iframe> | R77: https://lh5.googleusercontent.com/p/AF1QipNHiVGRyxpnyALYThma5UvN-y4NZkL3CW_Di5SS=w408-h306-k-no
A78: Pozo Herrera I | B78: Mina | C78: 3,8 | D78: 4 | E78: viernes, Abierto 24 horas; sábado, Abierto 24 horas; domingo, Abierto 24 horas; lunes, Abierto 24 horas; martes, Abierto 24 horas; miércoles, Abierto 24 horas; jueves, Abierto 24 horas | F78: RRHG+Q7 Olleros de Sabero | G78: C. Pozo Herrera, 9, 24811 Olleros de Sabero, León | H78: Olleros de Sabero | I78: León | L78: - | M78: Sí | N78: 42.8294288 | O78: -5.1739929 | P78: https://goo.gl/maps/mox5rqaBsg3rqm7m6 | Q78: <iframe src="https://www.google.com/maps/embed?pb=!1m18!1m12!1m3!1d23408.431593755555!2d-5.191869460449219!3d42.82947420000001!2m3!1f0!2f0!3f0!3m2!1i1024!2i768!4f13.1!3m3!1m2!1s0xd37db88a9afa4ed%3A0xd536d59cf7dd2dd6!2sPozo%20Herrera%20I!5e0!3m2!1ses!2ses!4v1651839056246!5m2!1ses!2ses" width="600" height="450" style="border:0;" allowfullscreen="" loading="lazy" referrerpolicy="no-referrer-when-downgrade"></iframe> | R78: https://lh5.googleusercontent.com/p/AF1QipNDycCGIsGgEFX8kYEvCiqbPHP19A1CVRR1sGSa=w408-h306-k-no
A79: Pozo Las Cuevas | B79: Mina | C79: 3,0 | D79: 1 | F79: R4XF+83 Velilla del Río Carrión | G79: 34886, Palencia | H79: Velilla del Río Carrión | I79: Palencia | L79: - | M79: Sí | N79: 42.8483263 | O79: -4.8772789 | P79: https://goo.gl/maps/Yq1XiaUbBEhvZiKL9 | Q79: <iframe src="https://www.google.com/maps/embed?pb=!1m18!1m12!1m3!1d374420.6517833545!2d-5.157430267187484!3d42.8483263!2m3!1f0!2f0!3f0!3m2!1i1024!2i768!4f13.1!3m3!1m2!1s0xd483b8e641114fd%3A0x1fb32c9617d31696!2sPozo%20Las%20Cuevas!5e0!3m2!1ses!2ses!4v1651839352637!5m2!1ses!2ses" width="600" height="450" style="border:0;" allowfullscreen="" loading="lazy" referrerpolicy="no-referrer-when-downgrade"></iframe> | R79: https://lh5.googleusercontent.com/p/AF1QipOo3WxkhSfXvBSLYzjlPjn9F-t8ixYWa5Rpkb3e=w408-h306-k-no
A80: Pozo San Vicente | B80: Mina | C80: 5,0 | D80: 1 | F80: 665M+F6 Agualestro | G80: 33683, Asturias | H80: Agualestro | I80: Asturias | L80: - | M80: Sí | N80: 43.2086404 | O80: -5.7669543 | P80: https://goo.gl/maps/LvXQZFJQuaWwArFk8 | Q80: <iframe src="https://www.google.com/maps/embed?pb=!1m18!1m12!1m3!1d372229.23748287174!2d-6.047106267187445!3d43.208631099999984!2m3!1f0!2f0!3f0!3m2!1i1024!2i768!4f13.1!3m3!1m2!1s0xd36f7cad68a8953%3A0xe2759e74f59b5481!2sPozo%20San%20Vicente!5e0!3m2!1ses!2ses!4v1651839408028!5m2!1ses!2ses" width="600" height="450" style="border:0;" allowfullscreen="" loading="lazy" referrerpolicy="no-referrer-when-downgrade"></iframe>
A81: REALITEC Ingeniería | B81: Ingeniero de minas | C81: 5,0 | D81: 5 | E81: viernes, De 10:00 a 14:15, De 16:15 a 21:30; sábado, Cerrado; domingo, Cerrado; lunes, De 10:00 a 14:15, De 16:15 a 21:30; martes, De 10:00 a 14:15, De 16:15 a 21:30; miércoles, De 10:00 a 14:15, De 16:15 a 21:30; jueves, De 10:00 a 14:15, De 16:15 a 21:30 | F81: X87P+XW Salamanca | G81: Pl. del Mercado, 8, piso 1º oficina 4, 37001 Salamanca | H81: Salamanca | I81: Salamanca | J81: realitec.com | K81: 923 04 92 06 | L81: info@realitec.com | M81: No | N81: 40.96499 | O81: -5.6627434 | P81: https://goo.gl/maps/NtSss1ktKkdvcrDg7 | Q81: <iframe src="https://www.google.com/maps/embed?pb=!1m18!1m12!1m3!1d24102.59142980745!2d-5.6692121067712895!3d40.96343585105039!2m3!1f0!2f0!3f0!3m2!1i1024!2i768!4f13.1!3m3!1m2!1s0xd3f261430854beb%3A0x93a14efda78007b8!2sREALITEC%20Ingenier%C3%ADa!5e0!3m2!1ses!2ses!4v1651840069277!5m2!1ses!2ses" width="600" height="450" style="border:0;" allowfullscreen="" loading="lazy" referrerpolicy="no-referrer-when-downgrade"></iframe> | R81: https://lh5.googleusercontent.com/p/AF1QipMP3b4k4XoY3K0IdvjuCbtEatZguHmxtIG3HXGM=w408-h408-k-no
A82: Mining Sense | B82: Ingeniero de minas | E82: viernes, De 8:00 a 22:00; sábado, Cerrado; domingo, Cerrado; lunes, De 8:00 a 22:00; martes, De 8:00 a 22:00; miércoles, De 8:00 a 22:00; jueves, De 8:00 a 22:00 | F82: X7WJ+54 Villamayor | G82: C. del Adaja, 10, Edificio M3, 37185 Villamayor, Salamanca | H82: Villamayor | I82: Salamanca | J82: mining-sense.com | K82: 650 72 60 56 | L82: info@mining-sense.com | M82: No | N82: 40.995397 | O82: -5.719648 | P82: https://goo.gl/maps/5EwWKYazJsASdxjJ7 | Q82: <iframe src="https://www.google.com/maps/embed?pb=!1m18!1m12!1m3!1d24090.915103521085!2d-5.737157460449237!3d40.99539700000001!2m3!1f0!2f0!3f0!3m2!1i1024!2i768!4f13.1!3m3!1m2!1s0xd3f2819d77062f7%3A0x69456447ed3d9a4f!2sMining%20Sense!5e0!3m2!1ses!2ses!4v1651840086777!5m2!1ses!2ses" width="600" height="450" style="border:0;" allowfullscreen="" loading="lazy" referrerpolicy="no-referrer-when-downgrade"></iframe>
A83: antigua mina de estaño | B83: Mina | C83: 4,6 | D83: 7 | F83: 238H+J2 Golpejas | G83: DSA-523, 14, 37170 Golpejas, Salamanca | H83: Golpejas | I83: Salamanca | L83: - | M83: Sí | N83: 41.0165557 | O83: -5.9224758 | P83: https://goo.gl/maps/qEuSimMVimdZuHMh9 | Q83: <iframe src="https://www.google.com/maps/embed?pb=!1m18!1m12!1m3!1d24083.181098027846!2d-5.93998526044922!3d41.01655570000002!2m3!1f0!2f0!3f0!3m2!1i1024!2i768!4f13.1!3m3!1m2!1s0xd3ece48dfc270c3%3A0x418af1d98f4c0c78!2santigua%20mina%20de%20esta%C3%B1o!5e0!3m2!1ses!2ses!4v1651840149293!5m2!1ses!2ses" width="600" height="450" style="border:0;" allowfullscreen="" loading="lazy" referrerpolicy="no-referrer-when-downgrade"></iframe> | R83: https://lh5.googleusercontent.com/p/AF1QipN8z-uHEdtUs7rVo1bXNmzF6UPkISgYXKoBKqFt=w408-h277-k-no
A84: Euroarce Minería | B84: Mina | C84: 2,5 | D84: 6 | E84: viernes, De 7:00 a 22:00; sábado, Cerrado; domingo, Cerrado; lunes, De 7:00 a 22:00; martes, De 7:00 a 22:00; miércoles, De 7:00 a 22:00; jueves, De 7:00 a 22:00 | F84: 5JWJ+XX Navas de Oro | G84: 40470 Navas de Oro, Segovia | H84: Navas de Oro | I84: Segovia | K84: 921 59 12 88 | L84: - | M84: Sí | N84: 41.1974067 | O84: -4.3676147 | P84: https://goo.gl/maps/AHjoAzPqgNKdCjep9 | Q84: <iframe src="https://www.google.com/maps/embed?pb=!1m18!1m12!1m3!1d48033.883756861076!2d-4.402633620898437!3d41.197406699999995!2m3!1f0!2f0!3f0!3m2!1i1024!2i768!4f13.1!3m3!1m2!1s0xd412acd49135629%3A0x2f32379b345345fb!2sEuroarce%20Miner%C3%ADa!5e0!3m2!1ses!2ses!4v1651840557152!5m2!1ses!2ses" width="600" height="450" style="border:0;" allowfullscreen="" loading="lazy" referrerpolicy="no-referrer-when-downgrade"></iframe> | R84: https://lh5.googleusercontent.com/p/AF1QipM08OVJ82ewrzIh6QBPWrjadrw6z8NDhldN5EKq=w480-h240-k-no
A85: Mina La Montañesa | B85: Mina | C85: 4,5 | D85: 2 | E85: viernes, Abierto 24 horas; sábado, Abierto 24 horas; domingo, Abierto 24 horas; lunes, Abierto 24 horas; martes, Abierto 24 horas; miércoles, Abierto 24 horas; jueves, Abierto 24 horas | F85: CVPG+2C Navalagamella | G85: 28212 Navalagamella, Madrid | H85: Navalagamella | I85: Madrid | L85: - | M85: Sí | N85: 40.4350694 | O85: -4.1238967 | P85: https://goo.gl/maps/SRtm1atCwuwbkb6s8 | Q85: <iframe src="https://www.google.com/maps/embed?pb=!1m18!1m12!1m3!1d388712.46914949233!2d-4.404048067187469!3d40.43506940000001!2m3!1f0!2f0!3f0!3m2!1i1024!2i768!4f13.1!3m3!1m2!1s0xd41a3f9d25e0b83%3A0x506c3e81d9a70c5e!2sMina%20La%20Monta%C3%B1esa!5e0!3m2!1ses!2ses!4v1651840716341!5m2!1ses!2ses" width="600" height="450" style="border:0;" allowfullscreen="" loading="lazy" referrerpolicy="no-referrer-when-downgrade"></iframe> | R85: https://lh5.googleusercontent.com/p/AF1QipN7HJFmnUWm4fxT3MnwP9xvqgrh0243K51nk9is=w408-h306-k-no
A86: Mina del Carrascal | B86: Mina | C86: 5,0 | D86: 3 | F86: HR6Q+96 Villadepera | G86: 49250 Villadepera, Zamora | H86: Villadepera | I86: Zamora | L86: - | M86: Sí | N86: 41.5608897 | O86: -6.1619481 | P86: https://goo.gl/maps/Cwux3sVPeeTQ4r117 | Q86: <iframe src="https://www.google.com/maps/embed?pb=!1m18!1m12!1m3!1d23883.088042202395!2d-6.179457560449219!3d41.560889700000004!2m3!1f0!2f0!3f0!3m2!1i1024!2i768!4f13.1!3m3!1m2!1s0xd396e7c9ff3d585%3A0xbc6f9d5c0c9862bb!2sMina%20del%20Carrascal!5e0!3m2!1ses!2ses!4v1651841171934!5m2!1ses!2ses" width="600" height="450" style="border:0;" allowfullscreen="" loading="lazy" referrerpolicy="no-referrer-when-downgrade"></iframe> | R86: https://lh5.googleusercontent.com/p/AF1QipO4l1QvNrzJL_dqMr66ScVfGy61BRtY1bklkscb=w426-h240-k-no
A87: Oficina Tècnica Minera | B87: Ingeniero de minas | F87: C57X+49 Barcelona | G87: Gran Via de les Corts Catalanes, 993, 8º-1ª, 08020 Barcelona | H87: Barcelona | I87: Barcelona | K87: 933 08 90 81 | L87: - | M87: No | N87: 41.4128506 | O87: 2.1983755 | P87: https://goo.gl/maps/owi1j2on9XxsMouh6 | Q87: <iframe src="https://www.google.com/maps/embed?pb=!1m18!1m12!1m3!1d95780.68689215166!2d2.1401889923574107!3d41.392625479666414!2m3!1f0!2f0!3f0!3m2!1i1024!2i768!4f13.1!3m3!1m2!1s0x12a4a3184997f0e1%3A0x8d61e0c0e2395b97!2sOficina%20T%C3%A8cnica%20Minera!5e0!3m2!1ses!2ses!4v1651841367841!5m2!1ses!2ses" width="600" height="450" style="border:0;" allowfullscreen="" loading="lazy" referrerpolicy="no-referrer-when-downgrade"></iframe> | R87: https://streetviewpixels-pa.googleapis.com/v1/thumbnail?panoid=HCQNCIFO6SIf7eKJCJP1lw&cb_client=search.gws-prod.gps&w=408&h=240&yaw=340.94897&pitch=0&thumbfov=100
A88: Técnica Minera Aplicada, S.L. (tecmina) | B88: Ingeniero de minas | C88: 4,9 | D88: 20 | E88: viernes, Abierto 24 horas; sábado, Abierto 24 horas; domingo, Abierto 24 horas; lunes, Abierto 24 horas; martes, Abierto 24 horas; miércoles, Abierto 24 horas; jueves, Abierto 24 horas | F88: C58J+68 Barcelona | G88: Passeig de Maragall, 48, 08041 Barcelona | H88: Barcelona | I88: Barcelona | J88: tecmina.net | K88: 934 50 01 73 | L88: info@tecmina.net | M88: No | N88: 41.415557 | O88: 2.1808218 | P88: https://g.page/tecminagroup?share | Q88: <iframe src="https://www.google.com/maps/embed?pb=!1m18!1m12!1m3!1d95780.68689215166!2d2.1401889923574107!3d41.392625479666414!2m3!1f0!2f0!3f0!3m2!1i1024!2i768!4f13.1!3m3!1m2!1s0x12a4a2d69fbece75%3A0xd82e3dbef5968714!2sT%C3%A9cnica%20Minera%20Aplicada%2C%20S.L.%20(tecmina)!5e0!3m2!1ses!2ses!4v1651841376575!5m2!1ses!2ses" width="600" height="450" style="border:0;" allowfullscreen="" loading="lazy" referrerpolicy="no-referrer-when-downgrade"></iframe> | R88: https://lh5.googleusercontent.com/p/AF1QipPez8PsYfRdO9_4fTvkW2rQxWzp2VcBEqfVZ7kR=w426-h240-k-no
A89: Imagi Girona | B89: Ingeniero de minas | C89: 5,0 | D89: 1 | E89: viernes, De 9:00 a 19:00; sábado, Cerrado; domingo, Cerrado; lunes, De 9:00 a 19:00; martes, De 9:00 a 19:00; miércoles, De 9:00 a 19:00; jueves, De 9:00 a 19:00 | F89: XRG9+67 Gerona | G89: Carrer Cor de Maria, 10, 17002 Girona | H89: Gerona | I89: Girona | K89: 696 07 10 97 | L89: - | M89: No | N89: 41.975598 | O89: 2.818214 | P89: https://goo.gl/maps/qieDWjR2LUnb7v8aA | Q89: <iframe src="https://www.google.com/maps/embed?pb=!1m18!1m12!1m3!1d47458.39398842054!2d2.78319897910155!3d41.975597199999996!2m3!1f0!2f0!3f0!3m2!1i1024!2i768!4f13.1!3m3!1m2!1s0x12bae6d80d4c0b9d%3A0xfc7b11b3ba0bdede!2sImagi%20Girona!5e0!3m2!1ses!2ses!4v1651842907981!5m2!1ses!2ses" width="600" height="450" style="border:0;" allowfullscreen="" loading="lazy" referrerpolicy="no-referrer-when-downgrade"></iframe> | R89: https://streetviewpixels-pa.googleapis.com/v1/thumbnail?panoid=Jbya5hIXPT33zv0ZDIPC_A&cb_client=search.gws-prod.gps&w=408&h=240&yaw=276.72345&pitch=0&thumbfov=100
A90: Mina Pepito (Ruinas) | B90: Mina | F90: W46P+R7 Mont-ras | G90: 17253 Mont-ras, Girona | H90: Mont-ras | I90: Girona | L90: - | M90: Sí | N90: 41.9120869 | O90: 3.1356332 | P90: https://goo.gl/maps/DWMPHSvFqJSNur4S7 | Q90: <iframe src="https://www.google.com/maps/embed?pb=!1m18!1m12!1m3!1d47505.690845999554!2d3.1006142791015625!3d41.9120869!2m3!1f0!2f0!3f0!3m2!1i1024!2i768!4f13.1!3m3!1m2!1s0x12ba5535acffdf2f%3A0xae31c66b5c07901b!2sMina%20Pepito%20(Ruinas)!5e0!3m2!1ses!2ses!4v1651842966543!5m2!1ses!2ses" width="600" height="450" style="border:0;" allowfullscreen="" loading="lazy" referrerpolicy="no-referrer-when-downgrade"></iframe> | R90: https://lh5.googleusercontent.com/p/AF1QipNh1BdSWFH45XwmjhXKiYqz2vpQSxXQ1LuQUUTI=w408-h544-k-no
A91: Mina Dolça | B91: Mina | F91: 778G+73 Sant Martí d&apos;Ogassa | G91: 17861 Sant Martí d&apos;Ogassa, Girona | H91: Sant Martí d&apos;Ogassa | I91: Girona | L91: - | M91: Sí | N91: 42.2657479 | O91: 2.2752361 | P91: https://goo.gl/maps/9nFDSttgeA2j3Ma89 | Q91: <iframe src="https://www.google.com/maps/embed?pb=!1m18!1m12!1m3!1d47241.57454083488!2d2.2402171791015624!3d42.2657479!2m3!1f0!2f0!3f0!3m2!1i1024!2i768!4f13.1!3m3!1m2!1s0x12a54644ff3d4e0f%3A0xb8bacddf2dc1eb73!2sMina%20Dol%C3%A7a!5e0!3m2!1ses!2ses!4v1651843022214!5m2!1ses!2ses" width="600" height="450" style="border:0;" allowfullscreen="" loading="lazy" referrerpolicy="no-referrer-when-downgrade"></iframe> | R91: https://streetviewpixels-pa.googleapis.com/v1/thumbnail?panoid=X09LALlKPzYfn-iwVz5-Vg&cb_client=search.gws-prod.gps&w=408&h=240&yaw=339.773&pitch=0&thumbfov=100
A92: Mines de La Crestella | B92: Mina | C92: 4,0 | D92: 1 | F92: 97HP+GX Setcases | G92: 17869 Setcases, Girona | H92: Setcases | I92: Girona | L92: - | M92: Sí | N92: 42.3788736 | O92: 2.2874269 | P92: https://goo.gl/maps/Hjeum6Lg9cMBKV8j6 | Q92: <iframe src="https://www.google.com/maps/embed?pb=!1m18!1m12!1m3!1d47156.71110746509!2d2.252407979101562!3d42.37887359999999!2m3!1f0!2f0!3f0!3m2!1i1024!2i768!4f13.1!3m3!1m2!1s0x12a55ab72c3f322b%3A0x69b183d4885acc7a!2sMines%20de%20La%20Crestella!5e0!3m2!1ses!2ses!4v1651843040777!5m2!1ses!2ses" width="600" height="450" style="border:0;" allowfullscreen="" loading="lazy" referrerpolicy="no-referrer-when-downgrade"></iframe> | R92: https://lh5.googleusercontent.com/p/AF1QipMeuHTwZu1nVZOjNpA8y3t1sCgPU9Hh9bcGl8z6=w408-h306-k-no
A93: Engiminer | B93: Ingeniero de minas | E93: viernes, De 9:00 a 19:00; sábado, Cerrado; domingo, Cerrado; lunes, De 9:00 a 19:00; martes, De 9:00 a 19:00; miércoles, De 9:00 a 19:00; jueves, De 9:00 a 19:00 | F93: 47CC+GQ Tarragona | G93: Carrer Josep Pla Casadevall, 6, 3-5.Bajos, 43007 Tarragona | H93: Tarragona | I93: Tarragona | J93: engiminer.com | K93: 606 38 50 71 | L93: oficina@engiminer.com | M93: No | N93: 41.1212977 | O93: 1.2719984 | P93: https://g.page/engiminer?share | Q93: <iframe src="https://www.google.com/maps/embed?pb=!1m18!1m12!1m3!1d96172.82178103918!2d1.203562950308483!3d41.12577828861127!2m3!1f0!2f0!3f0!3m2!1i1024!2i768!4f13.1!3m3!1m2!1s0x12a3fd18b058a7fd%3A0xaa84f303c33a50de!2sEngiminer!5e0!3m2!1ses!2ses!4v1651843324771!5m2!1ses!2ses" width="600" height="450" style="border:0;" allowfullscreen="" loading="lazy" referrerpolicy="no-referrer-when-downgrade"></iframe> | R93: https://streetviewpixels-pa.googleapis.com/v1/thumbnail?panoid=W5jxHsCC6ZZCs5hIg_Dx_g&cb_client=search.gws-prod.gps&w=408&h=240&yaw=244.40508&pitch=0&thumbfov=100
A94: GEO-MIN Oficina Tècnica Minera | B94: Ingeniero de minas | F94: 5768+CP Tarragona | G94: Carrer Noguera, nº6, 43151 Tarragona | H94: Tarragona | I94: Tarragona | K94: 695 37 08 44 | L94: - | M94: Sí | N94: 41.1611092 | O94: 1.2668311 | P94: https://goo.gl/maps/csyZaEtF4HRf1AQ97 | Q94: <iframe src="https://www.google.com/maps/embed?pb=!1m18!1m12!1m3!1d96172.82178103918!2d1.203562950308483!3d41.12577828861127!2m3!1f0!2f0!3f0!3m2!1i1024!2i768!4f13.1!3m3!1m2!1s0x12a3fc5cf15c087b%3A0x2b285c7ee027c26!2sGEO-MIN%20Oficina%20T%C3%A8cnica%20Minera!5e0!3m2!1ses!2ses!4v1651843345106!5m2!1ses!2ses" width="600" height="450" style="border:0;" allowfullscreen="" loading="lazy" referrerpolicy="no-referrer-when-downgrade"></iframe> | R94: https://streetviewpixels-pa.googleapis.com/v1/thumbnail?panoid=6tjBKKwCMDQWv4pgxDbpjQ&cb_client=search.gws-prod.gps&w=408&h=240&yaw=204.02965&pitch=0&thumbfov=100
A95: Mina Linda Mariquita | B95: Mina | C95: 4,5 | D95: 11 | F95: 5P85+X3 El Molar | G95: 43736, Tarragona | H95: El Molar | I95: Tarragona | J95: invarquit.cultura.gencat.cat | L95: suport.tecnic@gencat.cat | M95: Sí | N95: 41.1674079 | O95: 0.7076806 | P95: https://goo.gl/maps/T5pKLzpaSWFJGWSGA | Q95: <iframe src="https://www.google.com/maps/embed?pb=!1m18!1m12!1m3!1d96111.78372785842!2d0.6376427582031251!3d41.167407899999986!2m3!1f0!2f0!3f0!3m2!1i1024!2i768!4f13.1!3m3!1m2!1s0x12a12efa8fa5811b%3A0xdb9c36f8f87b42a7!2sMina%20Linda%20Mariquita!5e0!3m2!1ses!2ses!4v1651843453309!5m2!1ses!2ses" width="600" height="450" style="border:0;" allowfullscreen="" loading="lazy" referrerpolicy="no-referrer-when-downgrade"></iframe> | R95: https://lh5.googleusercontent.com/p/AF1QipMw5zLxgbemuT3_xdWYPjcGJb5Zohb4olzFYk28=w408-h306-k-no
A96: Rodes Ingeniería de Recursos Naturales, S.L. | B96: Ingeniero de minas | C96: 5,0 | D96: 2 | E96: viernes, De 8:30 a 19:00; sábado, Cerrado; domingo, Cerrado; lunes, De 8:30 a 19:00; martes, De 8:30 a 19:00; miércoles, De 8:30 a 19:00; jueves, De 8:30 a 19:00 | F96: J4MJ+4W Villena | G96: C/ Ronda Estación, 10, 03400 Villena, Alicante | H96: Villena | I96: Alicante | J96: rodesingenieria.com | K96: 965 80 09 83 | L96: rodes@rodesingenieria.com | M96: No | N96: 38.6327566 | O96: -0.8676703 | P96: https://goo.gl/maps/fhZjgDBzrPpEkMGL8 | Q96: <iframe src="https://www.google.com/maps/embed?pb=!1m18!1m12!1m3!1d99734.4354093062!2d-0.9377081417968749!3d38.63275660000001!2m3!1f0!2f0!3f0!3m2!1i1024!2i768!4f13.1!3m3!1m2!1s0xd63df9e1f7c242b%3A0xb72d2d38319e69b!2sRodes%20Ingenier%C3%ADa%20de%20Recursos%20Naturales%2C%20S.L.!5e0!3m2!1ses!2ses!4v1651843907403!5m2!1ses!2ses" width="600" height="450" style="border:0;" allowfullscreen="" loading="lazy" referrerpolicy="no-referrer-when-downgrade"></iframe> | R96: https://lh5.googleusercontent.com/p/AF1QipMb4SiwhvDZI_uK5V9rFOdRzfVq-UPHkYbQb1mc=w408-h905-k-no
A97: Asesoramiento y Proyectos Mineros del Levante, S.L. | B97: Ingeniero de minas | C97: 4,0 | D97: 1 | E97: viernes, De 9:00 a 20:00; sábado, De 9:00 a 20:00; domingo, Cerrado; lunes, De 9:00 a 20:00; martes, De 9:00 a 20:00; miércoles, De 9:00 a 20:00; jueves, De 9:00 a 20:00 | F97: XVR7+5M Murcia | G97: C. Poeta Cano Pato, 2, 30009 Murcia | H97: Murcia | I97: Murcia | K97: 606 78 59 85 | L97: - | M97: No | N97: 37.9904859 | O97: -1.1358437 | P97: https://goo.gl/maps/26QrGBbwMdLmq15A8 | Q97: <iframe src="https://www.google.com/maps/embed?pb=!1m18!1m12!1m3!1d100621.70220692571!2d-1.205878341796875!3d37.990471700000015!2m3!1f0!2f0!3f0!3m2!1i1024!2i768!4f13.1!3m3!1m2!1s0xd6381f58bf12bd5%3A0x430575d31fb1d38a!2sAsesoramiento%20y%20Proyectos%20Mineros%20del%20Levante%2C%20S.L.!5e0!3m2!1ses!2ses!4v1651843987699!5m2!1ses!2ses" width="600" height="450" style="border:0;" allowfullscreen="" loading="lazy" referrerpolicy="no-referrer-when-downgrade"></iframe> | R97: https://streetviewpixels-pa.googleapis.com/v1/thumbnail?panoid=3_D3ZjIPRy2m0_uSXApzIw&cb_client=search.gws-prod.gps&w=408&h=240&yaw=334.728&pitch=0&thumbfov=100
A98: Parc Miner del Maestrat | B98: Mina | C98: 4,7 | D98: 216 | F98: 8W62+2J Torre de Embesora | G98: 12161 La Torre d&apos;En Besora, Castellón | H98: Torre de Embesora | I98: Castellón | J98: parcminerdelmaestrat.es | K98: 651 17 70 71 | L98: - | M98: No | N98: 40.3100956 | O98: -0.0983866 | P98: https://goo.gl/maps/qoGxo8PajKFDFD2a7 | Q98: <iframe src="https://www.google.com/maps/embed?pb=!1m18!1m12!1m3!1d778868.1933252164!2d-0.6587122343750041!3d40.3100833!2m3!1f0!2f0!3f0!3m2!1i1024!2i768!4f13.1!3m3!1m2!1s0xd5ff32d430fc3bf%3A0xcd0a9d251f9a3d95!2sParc%20Miner%20del%20Maestrat!5e0!3m2!1ses!2ses!4v1651844151700!5m2!1ses!2ses" width="600" height="450" style="border:0;" allowfullscreen="" loading="lazy" referrerpolicy="no-referrer-when-downgrade"></iframe> | R98: https://lh5.googleusercontent.com/p/AF1QipPnRScnJd02dFjoJyZrtmHpVTqQz-hnkiTxejA7=w408-h306-k-no
A99: GEOMINER | B99: Ingeniero de minas | C99: 3,0 | D99: 3 | E99: viernes, Abierto 24 horas; sábado, Abierto 24 horas; domingo, Abierto 24 horas; lunes, Abierto 24 horas; martes, Abierto 24 horas; miércoles, Abierto 24 horas; jueves, Abierto 24 horas | F99: H9XW+CQ Benaguacil | G99: C. Pascual Y Genis, 39, 46180 Benaguasil, Valencia | H99: Benaguacil | I99: Valencia | J99: geominer.es | L99: lacm@geominer.es | M99: No | N99: 39.5985535 | O99: -0.6031179 | P99: https://goo.gl/maps/BDiw95vhsN5T2EcD8 | Q99: <iframe src="https://www.google.com/maps/embed?pb=!1m18!1m12!1m3!1d196753.41167153802!2d-0.7431935835937288!3d39.598553499999994!2m3!1f0!2f0!3f0!3m2!1i1024!2i768!4f13.1!3m3!1m2!1s0xd60f587d9aac611%3A0xf9889eeb788ed98d!2sGEOMINER!5e0!3m2!1ses!2ses!4v1651844491028!5m2!1ses!2ses" width="600" height="450" style="border:0;" allowfullscreen="" loading="lazy" referrerpolicy="no-referrer-when-downgrade"></iframe> | R99: https://lh5.googleusercontent.com/p/AF1QipMRdn8X35fdUqgPLoTq5NpqfNHSOjBM_XE0Ozgf=w408-h306-k-no
A100: Inema Ingenieros Asesores | B100: Ingeniero de minas | E100: viernes, De 8:00 a 18:00; sábado, Cerrado; domingo, Cerrado; lunes, De 8:00 a 18:00; martes, De 8:00 a 18:00; miércoles, De 8:00 a 18:00; jueves, De 8:00 a 18:00 | F100: GG7X+2C Paterna | G100: Pol Ind Tactica, Carrer Botiguers, 3, 46980 Paterna, Valencia | H100: Paterna | I100: Valencia | K100: 961 34 55 39 | L100: - | M100: Sí | N100: 39.5126039 | O100: -0.4514684 | P100: https://goo.gl/maps/C5KY6RRzP6pBZVCu7 | Q100: <iframe src="https://www.google.com/maps/embed?pb=!1m18!1m12!1m3!1d196997.34736603627!2d-0.5915440835937424!3d39.5126039!2m3!1f0!2f0!3f0!3m2!1i1024!2i768!4f13.1!3m3!1m2!1s0xd605b2d4bf0f4c5%3A0xc8b328be2639a5ae!2sInema%20Ingenieros%20Asesores!5e0!3m2!1ses!2ses!4v1651844576078!5m2!1ses!2ses" width="600" height="450" style="border:0;" allowfullscreen="" loading="lazy" referrerpolicy="no-referrer-when-downgrade"></iframe> | R100: https://streetviewpixels-pa.googleapis.com/v1/thumbnail?panoid=n3af5RNMnjGO4PedPllsHw&cb_client=search.gws-prod.gps&w=408&h=240&yaw=2.5250063&pitch=0&thumbfov=100
...

Sheet Minerias
A1: ﻿Nombre | B1: Categoría | C1: Rating | D1: Nº Reviews | E1: Horario | F1: Código Plus | G1: Direccion | H1: Localidad | I1: Provincia | J1: Website | K1: Teléfono | L1: email | M1: Reclamar | N1: Latitud | O1: Longitud | P1: Url en Maps | Q1: Iframe | R1: Imagen Url
A2: COMISUR COMPAÑIAS MINERAS DEL SUR S.A. | B2: Empresa minera | F2: 8MMX+M8 Macael | G2: Av. Almería, 21, 04867 Macael, Almería | H2: Macael | I2: Almería | K2: 950 12 88 34 | L2: - | M2: No | N2: 37.3342412 | O2: -2.3016892 | P2: https://goo.gl/maps/5WygwnVrhBAre5YD8 | Q2: <iframe src="https://www.google.com/maps/embed?pb=!1m18!1m12!1m3!1d101515.173781624!2d-2.3717270417968748!3d37.334241200000015!2m3!1f0!2f0!3f0!3m2!1i1024!2i768!4f13.1!3m3!1m2!1s0xd654d04830d5cf1%3A0x600cf9e3fe2978!2sCOMISUR%20COMPA%C3%91IAS%20MINERAS%20DEL%20SUR%20S.A.!5e0!3m2!1ses!2ses!4v1651828821856!5m2!1ses!2ses" width="600" height="450" style="border:0;" allowfullscreen="" loading="lazy" referrerpolicy="no-referrer-when-downgrade"></iframe> | R2: https://streetviewpixels-pa.googleapis.com/v1/thumbnail?panoid=AtJ6xYJe92dlU4Okf9_5gA&cb_client=search.gws-prod.gps&w=408&h=240&yaw=341.44754&pitch=0&thumbfov=100
A3: Bitmineros | B3: Equipo para minería | C3: 5,0 | D3: 7 | E3: viernes, De 9:00 a 17:00; sábado, Cerrado; domingo, Cerrado; lunes, De 9:00 a 17:00; martes, De 9:00 a 17:00; miércoles, De 9:00 a 17:00; jueves, De 9:00 a 17:00 | F3: Q9GR+43 Roquetas de Mar | G3: C. Lugo, 12, puerta 4, 04740 Roquetas de Mar, Almería | H3: Roquetas de Mar | I3: Almería | J3: bitmineros.net | K3: 672 01 20 05 | L3: core-js-bundle@3.2.1 | M3: No | N3: 36.7753057 | O3: -2.6098554 | P3: https://goo.gl/maps/M4nSq51M7SB843jE8 | Q3: <iframe src="https://www.google.com/maps/embed?pb=!1m18!1m12!1m3!1d102265.6855392626!2d-2.6798951417968664!3d36.775301!2m3!1f0!2f0!3f0!3m2!1i1024!2i768!4f13.1!3m3!1m2!1s0xd7071d06732952f%3A0xafe2f126298786d6!2sBitmineros!5e0!3m2!1ses!2ses!4v1651828864231!5m2!1ses!2ses" width="600" height="450" style="border:0;" allowfullscreen="" loading="lazy" referrerpolicy="no-referrer-when-downgrade"></iframe> | R3: https://lh5.googleusercontent.com/p/AF1QipM-GNrNlKv3K4PRpFm0JEOsRjzU_f7IJyakIIER=w408-h333-k-no
A4: Minera De Orgiva S L | B4: Empresa minera | C4: 4,0 | D4: 2 | F4: WH2J+P7 Órgiva | G4: C. Almeria, 8, 18400 Órgiva, Granada | H4: Órgiva | I4: Granada | K4: 858 78 40 58 | L4: - | M4: Sí | N4: 36.90176 | O4: -3.4193022 | P4: https://goo.gl/maps/VdJJBQKJ186iyYro7 | Q4: <iframe src="https://www.google.com/maps/embed?pb=!1m18!1m12!1m3!1d102096.73321181926!2d-3.489347841796875!3d36.90175999999998!2m3!1f0!2f0!3f0!3m2!1i1024!2i768!4f13.1!3m3!1m2!1s0xd71bffe28f5a17f%3A0x4ae3cd8f325c317c!2sMinera%20De%20Orgiva%20S%20L!5e0!3m2!1ses!2ses!4v1651828882792!5m2!1ses!2ses" width="600" height="450" style="border:0;" allowfullscreen="" loading="lazy" referrerpolicy="no-referrer-when-downgrade"></iframe> | R4: https://lh5.googleusercontent.com/p/AF1QipN4tY5c2pF41fVVqE2hJlvDWvPYCbMdKxYTiQdJ=w426-h240-k-no
A5: Segura | B5: Empresa minera | F5: 2QRX+9M Lucainena de las Torres | G5: C. Juan Pablo II, 10, 04210 Lucainena de las Torres, Almería | H5: Lucainena de las Torres | I5: Almería | L5: - | M5: Sí | N5: 37.0409017 | O5: -2.2008412 | P5: https://goo.gl/maps/VQuMcE9yKGYC7pC1A | Q5: <iframe src="https://www.google.com/maps/embed?pb=!1m18!1m12!1m3!1d25477.565460491365!2d-2.2183506604492185!3d37.0409017!2m3!1f0!2f0!3f0!3m2!1i1024!2i768!4f13.1!3m3!1m2!1s0xd7ac75000000001%3A0x86029fcc8cb93820!2sSegura!5e0!3m2!1ses!2ses!4v1651828946121!5m2!1ses!2ses" width="600" height="450" style="border:0;" allowfullscreen="" loading="lazy" referrerpolicy="no-referrer-when-downgrade"></iframe> | R5: https://streetviewpixels-pa.googleapis.com/v1/thumbnail?panoid=GGHDgkYQiiQtujUES6IXNg&cb_client=search.gws-prod.gps&w=408&h=240&yaw=316.67154&pitch=0&thumbfov=100
A6: MINAS DE ALQUIFE SL | B6: Empresa minera | C6: 5,0 | D6: 2 | F6: 5VC6+JC Lanteira | G6: Carr. del Marquesado, S-N, 18518 Lanteira, Granada | H6: Lanteira | I6: Granada | K6: 958 67 36 48 | L6: - | M6: No | N6: 37.1716 | O6: -3.13889 | P6: https://goo.gl/maps/d1uc1Jwqs8i7gvDs6 | Q6: <iframe src="https://www.google.com/maps/embed?pb=!1m18!1m12!1m3!1d50867.279247214916!2d-3.173908920898437!3d37.17159999999999!2m3!1f0!2f0!3f0!3m2!1i1024!2i768!4f13.1!3m3!1m2!1s0xd71d5171ce209af%3A0x554c42ac82ca8e9!2sMINAS%20DE%20ALQUIFE%20SL!5e0!3m2!1ses!2ses!4v1651829425043!5m2!1ses!2ses" width="600" height="450" style="border:0;" allowfullscreen="" loading="lazy" referrerpolicy="no-referrer-when-downgrade"></iframe> | R6: https://lh5.googleusercontent.com/p/AF1QipNfSKjPAM5FNAn0sY1_zjOp3PvPEU_aT8mSr3w=w408-h271-k-no
A7: Reino Mineral | B7: Empresa minera | F7: 2P3J+2X Trevélez | G7: C. Carcel, 0 S N, 18417 Trevélez, Granada | H7: Trevélez | I7: Granada | K7: 628 81 33 52 | L7: - | M7: Sí | N7: 37.0025326 | O7: -3.2675387 | P7: https://goo.gl/maps/m7FnkaKSRgQ1CXxc9 | Q7: <iframe src="https://www.google.com/maps/embed?pb=!1m18!1m12!1m3!1d50980.8647751811!2d-3.3025591208984375!3d37.002542200000015!2m3!1f0!2f0!3f0!3m2!1i1024!2i768!4f13.1!3m3!1m2!1s0xd71c5fb3b48431f%3A0xf1f82fdb1716e601!2sReino%20Mineral!5e0!3m2!1ses!2ses!4v1651829456824!5m2!1ses!2ses" width="600" height="450" style="border:0;" allowfullscreen="" loading="lazy" referrerpolicy="no-referrer-when-downgrade"></iframe> | R7: https://lh5.googleusercontent.com/p/AF1QipM2XjMSTkY-MPax5KtOIotrFPjy-mXafDqOAE_9=w408-h306-k-no
A8: Oxidos Ferricos S.a. | B8: Empresa minera | C8: 5,0 | D8: 1 | F8: 7VXC+QF Guadix | G8: Calle Margarita Nelken, 8 BL.2 - 3, 18500 Guadix, Granada | H8: Guadix | I8: Granada | J8: oxidosferricos.com | K8: 958 66 21 12 | L8: core-js-bundle@3.2.1 | M8: No | N8: 37.2993981 | O8: -3.1287953 | P8: https://goo.gl/maps/ck5RVWv1ud4jEEn69 | Q8: <iframe src="https://www.google.com/maps/embed?pb=!1m18!1m12!1m3!1d50781.121059751735!2d-3.1638142208984372!3d37.299398100000005!2m3!1f0!2f0!3f0!3m2!1i1024!2i768!4f13.1!3m3!1m2!1s0xd6e2b02bcff17eb%3A0xb1002696873c547!2sOxidos%20Ferricos%20S.a.!5e0!3m2!1ses!2ses!4v1651829483590!5m2!1ses!2ses" width="600" height="450" style="border:0;" allowfullscreen="" loading="lazy" referrerpolicy="no-referrer-when-downgrade"></iframe> | R8: https://streetviewpixels-pa.googleapis.com/v1/thumbnail?panoid=hKlPjSs2I2xUdMH-3nuFZg&cb_client=search.gws-prod.gps&w=408&h=240&yaw=329.14694&pitch=0&thumbfov=100
A9: TURBERA DEL AGIA, SL | B9: Empresa minera | C9: 5,0 | D9: 3 | E9: viernes, De 9:00 a 20:00; sábado, Cerrado; domingo, Cerrado; lunes, De 9:00 a 20:00; martes, De 9:00 a 20:00; miércoles, De 9:00 a 20:00; jueves, De 9:00 a 20:00 | F9: 59QQ+4M Granada | G9: Av. de Andalucía, 2, 18014 Granada | H9: Granada | I9: Granada | J9: turberadelagia.com | K9: 958 28 17 10 | L9: comercial@turberadelagia.com | M9: No | N9: 37.1877908 | O9: -3.6108325 | P9: https://goo.gl/maps/LHZNzyEt9PytimmV6 | Q9: <iframe src="https://www.google.com/maps/embed?pb=!1m18!1m12!1m3!1d406851.2121820859!2d-3.8910102671874944!3d37.18775560000002!2m3!1f0!2f0!3f0!3m2!1i1024!2i768!4f13.1!3m3!1m2!1s0xd71f6d49e528f11%3A0xa240e339b46885e4!2sTURBERA%20DEL%20AGIA%2C%20SL!5e0!3m2!1ses!2ses!4v1651829524762!5m2!1ses!2ses" width="600" height="450" style="border:0;" allowfullscreen="" loading="lazy" referrerpolicy="no-referrer-when-downgrade"></iframe> | R9: https://lh5.googleusercontent.com/p/AF1QipOltBRNZ_QxMsNs2FOpxG_ZLzJ9S9aTEF4WfMGF=w408-h550-k-no
A10: MATSA, Minas de Aguas Teñidas | B10: Empresa minera | C10: 4,1 | D10: 86 | E10: viernes, De 8:30 a 17:45; sábado, Cerrado; domingo, Cerrado; lunes, De 8:30 a 17:45; martes, De 8:30 a 17:45; miércoles, De 8:30 a 17:45; jueves, De 8:30 a 17:45 | F10: Q5J7+M7 Almonaster la Real | G10: HU-7104, Km. 12, 21330 Almonaster la Real, Huelva | H10: Almonaster la Real | I10: Huelva | J10: matsamining.com | K10: 959 05 40 12 | L10: dpto.comunicacion@matsamining.com | M10: No | N10: 37.7817126 | O10: -6.8367664 | P10: https://goo.gl/maps/Jhu3mWFfemoFPi8q6 | Q10: <iframe src="https://www.google.com/maps/embed?pb=!1m18!1m12!1m3!1d403629.4772706543!2d-7.116917767187499!3d37.781712600000006!2m3!1f0!2f0!3f0!3m2!1i1024!2i768!4f13.1!3m3!1m2!1s0xd110b9370f46b47%3A0xe24fa09610e7573b!2sMATSA%2C%20Minas%20de%20Aguas%20Te%C3%B1idas!5e0!3m2!1ses!2ses!4v1651829685216!5m2!1ses!2ses" width="600" height="450" style="border:0;" allowfullscreen="" loading="lazy" referrerpolicy="no-referrer-when-downgrade"></iframe> | R10: https://lh5.googleusercontent.com/p/AF1QipOow_F0tNqfE5ARRayYRLqh3tNUugieWJ4Ri4Tt=w427-h240-k-no
A11: Eulogio Caravantes Iniciativas Geomineras | B11: Empresa minera | E11: viernes, De 8:30 a 20:00; sábado, Cerrado; domingo, Cerrado; lunes, De 8:30 a 20:00; martes, De 8:30 a 20:00; miércoles, De 8:30 a 20:00; jueves, De 8:30 a 20:00 | F11: 599W+XR Granada | G11: C. Tejeiro, 23, 18005 Granada | H11: Granada | I11: Granada | K11: 958 52 34 36 | L11: - | M11: No | N11: 37.1699012 | O11: -3.6029047 | P11: https://goo.gl/maps/N485vnL3gbJSNKvL7 | Q11: <iframe src="https://www.google.com/maps/embed?pb=!1m18!1m12!1m3!1d406947.3826479659!2d-3.8830519671875!3d37.16990119999999!2m3!1f0!2f0!3f0!3m2!1i1024!2i768!4f13.1!3m3!1m2!1s0xd71fc97b6fca1af%3A0x8a03a80ee4c7fe0a!2sEulogio%20Caravantes%20Iniciativas%20Geomineras!5e0!3m2!1ses!2ses!4v1651829691403!5m2!1ses!2ses" width="600" height="450" style="border:0;" allowfullscreen="" loading="lazy" referrerpolicy="no-referrer-when-downgrade"></iframe> | R11: https://streetviewpixels-pa.googleapis.com/v1/thumbnail?panoid=NXFPrvetPsWHkYmIpKk4jQ&cb_client=search.gws-prod.gps&w=408&h=240&yaw=31.395649&pitch=0&thumbfov=100
A12: Aridos Hermanos Guerrero (SOLO OFICINAS) | B12: Empresa minera | C12: 4,9 | D12: 7 | E12: viernes, De 7:00 a 18:00; sábado, Cerrado; domingo, Cerrado; lunes, De 7:00 a 18:00; martes, De 7:00 a 18:00; miércoles, De 7:00 a 18:00; jueves, De 7:00 a 18:00 | F12: 4932+9C Alhendín | G12: Cam. de Jayena, 19, 18620 Alhendín, Granada | H12: Alhendín | I12: Granada | J12: aridosguerrero.com | K12: 958 57 60 51 | L12: info@aridosguerrero.com | M12: No | N12: 37.1034774 | O12: -3.6489426 | P12: https://goo.gl/maps/YrR6k8JP7bfxivvU8 | Q12: <iframe src="https://www.google.com/maps/embed?pb=!1m18!1m12!1m3!1d406958.3812584863!2d-3.879166967187466!3d37.16785879999999!2m3!1f0!2f0!3f0!3m2!1i1024!2i768!4f13.1!3m3!1m2!1s0xd71fa369033d9ef%3A0xc6401bf05f95d640!2sAridos%20Hermanos%20Guerrero%20(SOLO%20OFICINAS)!5e0!3m2!1ses!2ses!4v1651829729465!5m2!1ses!2ses" width="600" height="450" style="border:0;" allowfullscreen="" loading="lazy" referrerpolicy="no-referrer-when-downgrade"></iframe> | R12: https://lh5.googleusercontent.com/p/AF1QipOubRSJ4L_x9GV3fMCLZmgNjz31Zpv8k8NPLoGQ=w408-h544-k-no
A13: Maritima de Sales | B13: Empresa minera | F13: GRWR+92 Puerto Real | G13: CA 3113 KM, 10, CA-3113, 5, 5, 11510 Puerto Real, Cádiz | H13: Puerto Real | I13: Cádiz | L13: - | M13: Sí | N13: 36.5459506 | O13: -6.1599369 | P13: https://goo.gl/maps/5QCdCwzsSf4dbJGp8 | Q13: <iframe src="https://www.google.com/maps/embed?pb=!1m18!1m12!1m3!1d102570.8319239282!2d-6.229974541796873!3d36.545950399999995!2m3!1f0!2f0!3f0!3m2!1i1024!2i768!4f13.1!3m3!1m2!1s0xd0dceae45b7b489%3A0x5a61479878f40f5a!2sMaritima%20de%20Sales!5e0!3m2!1ses!2ses!4v1651829886505!5m2!1ses!2ses" width="600" height="450" style="border:0;" allowfullscreen="" loading="lazy" referrerpolicy="no-referrer-when-downgrade"></iframe> | R13: https://streetviewpixels-pa.googleapis.com/v1/thumbnail?panoid=Daozi4h6JW2hjNhLQ-Y1zA&cb_client=search.gws-prod.gps&w=408&h=240&yaw=348.72897&pitch=0&thumbfov=100
A14: ARENAS DE LA JANDA S.L. | B14: Empresa minera | F14: 723M+PR Vejer de la Frontera | G14: Ctra. Barbate-Vejer, KM 41, 11150 Vejer de la Frontera, Cádiz | H14: Vejer de la Frontera | I14: Cádiz | K14: 956 44 57 75 | L14: - | M14: No | N14: 36.2542703 | O14: -5.9654496 | P14: https://goo.gl/maps/jE4TRLdj7SEnQ9wD6 | Q14: <iframe src="https://www.google.com/maps/embed?pb=!1m18!1m12!1m3!1d102956.5451926633!2d-6.035457841796875!3d36.25426000000001!2m3!1f0!2f0!3f0!3m2!1i1024!2i768!4f13.1!3m3!1m2!1s0xd0c45f3c547ecbf%3A0x3ffdf00445a2f0ed!2sARENAS%20DE%20LA%20JANDA%20S.L.!5e0!3m2!1ses!2ses!4v1651829894731!5m2!1ses!2ses" width="600" height="450" style="border:0;" allowfullscreen="" loading="lazy" referrerpolicy="no-referrer-when-downgrade"></iframe> | R14: https://streetviewpixels-pa.googleapis.com/v1/thumbnail?panoid=-zhR-IhlAmZ2C0-e8tDWkQ&cb_client=search.gws-prod.gps&w=408&h=240&yaw=121.36096&pitch=0&thumbfov=100
A15: Cantera | B15: Empresa minera | F15: 6HH2+37 Los Barrios | G15: 11379 Los Barrios, Cádiz | H15: Los Barrios | I15: Cádiz | L15: - | M15: Sí | N15: 36.227632 | O15: -5.4492536 | P15: https://goo.gl/maps/JYkP38NuvKSkFpCr7 | Q15: <iframe src="https://www.google.com/maps/embed?pb=!1m18!1m12!1m3!1d102991.62364010417!2d-5.519291441796875!3d36.227631999999986!2m3!1f0!2f0!3f0!3m2!1i1024!2i768!4f13.1!3m3!1m2!1s0xd0ce9625ea46d7f%3A0x76b4266bcde72dab!2sCantera!5e0!3m2!1ses!2ses!4v1651829900949!5m2!1ses!2ses" width="600" height="450" style="border:0;" allowfullscreen="" loading="lazy" referrerpolicy="no-referrer-when-downgrade"></iframe>
A16: Alabasía, S.L. | B16: Empresa minera | C16: 4,0 | D16: 22 | E16: viernes, De 7:00 a 14:00; sábado, Cerrado; domingo, Cerrado; lunes, De 7:00 a 15:00; martes, De 7:00 a 15:00; miércoles, De 7:00 a 15:00; jueves, De 7:00 a 15:00 | F16: RM87+8X Sanlúcar de Barrameda | G16: Carr. de Bonanza, 0 S N, 11540 Sanlúcar de Barrameda, Cádiz | H16: Sanlúcar de Barrameda | I16: Cádiz | J16: alabasia.es | K16: 956 36 00 71 | L16: - | M16: Sí | N16: 36.8158496 | O16: -6.335068 | P16: https://goo.gl/maps/s2sAjSUrQkeqYNPA7 | Q16: <iframe src="https://www.google.com/maps/embed?pb=!1m18!1m12!1m3!1d102211.56196225726!2d-6.405053141796874!3d36.8158525!2m3!1f0!2f0!3f0!3m2!1i1024!2i768!4f13.1!3m3!1m2!1s0x152fb1a2e7693289%3A0x3aecc08796b239d4!2zQWxhYmFzw61hLCBTLkwu!5e0!3m2!1ses!2ses!4v1651829907292!5m2!1ses!2ses" width="600" height="450" style="border:0;" allowfullscreen="" loading="lazy" referrerpolicy="no-referrer-when-downgrade"></iframe> | R16: https://lh5.googleusercontent.com/p/AF1QipMgEq7C1PG_pXQns3ijT8_6dbE__WZUfeUXVVrr=w408-h272-k-no
A17: ASIRO, S.A. | B17: Empresa minera | C17: 4,4 | D17: 11 | E17: viernes, De 7:00 a 17:30; sábado, Cerrado; domingo, Cerrado; lunes, De 7:00 a 17:30; martes, De 7:00 a 17:30; miércoles, De 7:00 a 17:30; jueves, De 7:00 a 17:30 | F17: J59J+6H San José del Valle | G17: A-2003, Km 29, 1, 11580 San José del Valle, Cádiz | H17: San José del Valle | I17: Cádiz | J17: asirosa.es | K17: 956 23 76 58 | L17: info@asirosa.es | M17: No | N17: 36.6180191 | O17: -5.8186001 | P17: https://goo.gl/maps/yBhH328yAiDAxWSY8 | Q17: <iframe src="https://www.google.com/maps/embed?pb=!1m18!1m12!1m3!1d102475.12281181448!2d-5.8886379417968735!3d36.61801909999999!2m3!1f0!2f0!3f0!3m2!1i1024!2i768!4f13.1!3m3!1m2!1s0xd0da8cc1eef038b%3A0x5ccca39c4498f356!2sASIRO%2C%20S.A.!5e0!3m2!1ses!2ses!4v1651829919980!5m2!1ses!2ses" width="600" height="450" style="border:0;" allowfullscreen="" loading="lazy" referrerpolicy="no-referrer-when-downgrade"></iframe> | R17: https://lh5.googleusercontent.com/p/AF1QipPb-WGrp6eT5ehG8Yw3UTgt2oYwhD87LKEAkr1u=w408-h409-k-no
A18: Proyecto Riotinto - Atalaya Mining | B18: Empresa minera | C18: 4,6 | D18: 72 | F18: PC66+J7 Minas de Riotinto | G18: La Dehesa, s/n, 21660 Minas de Riotinto, Huelva | H18: Minas de Riotinto | I18: Huelva | K18: 959 59 28 50 | L18: - | M18: No | N18: 37.7115631 | O18: -6.589272 | P18: https://goo.gl/maps/NXeufpj44sfb8LfS8 | Q18: <iframe src="https://www.google.com/maps/embed?pb=!1m18!1m12!1m3!1d101003.06177043999!2d-6.659309841796874!3d37.71156310000001!2m3!1f0!2f0!3f0!3m2!1i1024!2i768!4f13.1!3m3!1m2!1s0xd119ca95d3d76b5%3A0x491d263144a0c6e7!2sProyecto%20Riotinto%20-%20Atalaya%20Mining!5e0!3m2!1ses!2ses!4v1651829965042!5m2!1ses!2ses" width="600" height="450" style="border:0;" allowfullscreen="" loading="lazy" referrerpolicy="no-referrer-when-downgrade"></iframe> | R18: https://lh5.googleusercontent.com/p/AF1QipP6wMsjRx7eVnuDSySeq90_2cvVQDqYOjfliOmk=w426-h240-k-no
A19: Cantera | B19: Empresa minera | F19: CQH8+F7 Casares | G19: 29690 Casares, Málaga | H19: Casares | I19: Málaga | L19: - | M19: Sí | N19: 36.4286834 | O19: -5.2343007 | P19: https://goo.gl/maps/ViNmGgfCre5cvQ9x7 | Q19: <iframe src="https://www.google.com/maps/embed?pb=!1m18!1m12!1m3!1d102726.21862687686!2d-5.3043385417968745!3d36.4286834!2m3!1f0!2f0!3f0!3m2!1i1024!2i768!4f13.1!3m3!1m2!1s0xd0cd9e70b229a03%3A0xbee89c3be25f76a4!2sCantera!5e0!3m2!1ses!2ses!4v1651829970949!5m2!1ses!2ses" width="600" height="450" style="border:0;" allowfullscreen="" loading="lazy" referrerpolicy="no-referrer-when-downgrade"></iframe>
A20: Omnia Life Time Mining | B20: Empresa minera | F20: 4JRW+45 Gibraltar | G20: 1 Line Wall Rd, GX11 GX11 1AA, Gibraltar | H20: Gibraltar | I20: Gibraltar | L20: - | M20: Sí | N20: 36.1403586 | O20: -5.3545814 | P20: https://goo.gl/maps/i82Xv1qNejZm2oLG8 | Q20: <iframe src="https://www.google.com/maps/embed?pb=!1m18!1m12!1m3!1d103106.43219294051!2d-5.424583541796875!3d36.14036259999999!2m3!1f0!2f0!3f0!3m2!1i1024!2i768!4f13.1!3m3!1m2!1s0xd0cbf81a85fdcd7%3A0x3e9cd15a70327461!2sOmnia%20Life%20Time%20Mining!5e0!3m2!1ses!2ses!4v1651829999122!5m2!1ses!2ses" width="600" height="450" style="border:0;" allowfullscreen="" loading="lazy" referrerpolicy="no-referrer-when-downgrade"></iframe> | R20: https://streetviewpixels-pa.googleapis.com/v1/thumbnail?panoid=Nb9fen3j1ZlxoU09ArNN0Q&cb_client=search.gws-prod.gps&w=408&h=240&yaw=69.70546&pitch=0&thumbfov=100
A21: ANDALUZA DE CALES S.A | B21: Empresa minera | C21: 3,1 | D21: 15 | E21: viernes, De 9:00 a 18:00; sábado, Cerrado; domingo, Cerrado; lunes, De 9:00 a 18:00; martes, De 9:00 a 18:00; miércoles, De 9:00 a 18:00; jueves, De 9:00 a 18:00 | F21: 3GX9+5F Morón de la Frontera | G21: Carretera Morón - Montellano, km 3, 41530 Morón de la Frontera, Sevilla | H21: Morón de la Frontera | I21: Sevilla | J21: calcinor.com | K21: 954 85 11 12 | L21: calcinor@calcinor.com | M21: No | N21: 37.0979461 | O21: -5.4812817 | P21: https://goo.gl/maps/cfrx6LUxre3uhJyJA | Q21: <iframe src="https://www.google.com/maps/embed?pb=!1m18!1m12!1m3!1d101833.63976269274!2d-5.551319541796874!3d37.0979461!2m3!1f0!2f0!3f0!3m2!1i1024!2i768!4f13.1!3m3!1m2!1s0xd0d61710c987291%3A0xdb11da0d471cec86!2sANDALUZA%20DE%20CALES%20S.A!5e0!3m2!1ses!2ses!4v1651830046935!5m2!1ses!2ses" width="600" height="450" style="border:0;" allowfullscreen="" loading="lazy" referrerpolicy="no-referrer-when-downgrade"></iframe>
A22: Catrasur, S.L. | B22: Empresa minera | C22: 3,0 | D22: 1 | E22: viernes, De 8:00 a 18:00; sábado, Cerrado; domingo, Cerrado; lunes, De 8:00 a 19:00; martes, De 8:00 a 19:00; miércoles, De 8:00 a 19:00; jueves, De 8:00 a 19:00 | F22: X3Q6+7J Las Cabezas de San Juan | G22: Francisco de la Rosa, 4 - local bajo, 41730 Las Cabezas de San Juan, Sevilla | H22: Las Cabezas de San Juan | I22: Sevilla | J22: catrasur.com | K22: 955 87 14 70 | L22: catrasur@catrasur.com | M22: Sí | N22: 36.988185 | O22: -5.9384548 | P22: https://goo.gl/maps/F3DesuoV6yKCiMiv9 | Q22: <iframe src="https://www.google.com/maps/embed?pb=!1m18!1m12!1m3!1d101980.95968930276!2d-6.008514241796875!3d36.988201!2m3!1f0!2f0!3f0!3m2!1i1024!2i768!4f13.1!3m3!1m2!1s0xd0d8fcd93159567%3A0x6d67ef4d027b986c!2sCatrasur%2C%20S.L.!5e0!3m2!1ses!2ses!4v1651830060137!5m2!1ses!2ses" width="600" height="450" style="border:0;" allowfullscreen="" loading="lazy" referrerpolicy="no-referrer-when-downgrade"></iframe> | R22: https://lh5.googleusercontent.com/p/AF1QipMRsHobzAzfRhQwHhlkpswtOHfyJerPRHP8DfST=w408-h306-k-no
A23: AYMA Mining Solutions | B23: Empresa minera | F23: 9W4V+MG Mairena del Aljarafe | G23: C. Innovación, 6-8, 41927 Mairena del Aljarafe, Sevilla | H23: Mairena del Aljarafe | I23: Sevilla | J23: aymamining.com | K23: 659 14 23 01 | L23: ayma@aymamining.com | M23: Sí | N23: 37.356653 | O23: -6.056148 | P23: https://goo.gl/maps/sEnJ6C8qBB5Gvw4J6 | Q23: <iframe src="https://www.google.com/maps/embed?pb=!1m18!1m12!1m3!1d101484.87861541986!2d-6.126185841796874!3d37.356653000000016!2m3!1f0!2f0!3f0!3m2!1i1024!2i768!4f13.1!3m3!1m2!1s0xd126cd80d70db3f%3A0xcc90c087772096b7!2sAYMA%20Mining%20Solutions!5e0!3m2!1ses!2ses!4v1651830072949!5m2!1ses!2ses" width="600" height="450" style="border:0;" allowfullscreen="" loading="lazy" referrerpolicy="no-referrer-when-downgrade"></iframe> | R23: https://streetviewpixels-pa.googleapis.com/v1/thumbnail?panoid=jutntGu_9mvMhEmfPPcpWw&cb_client=search.gws-prod.gps&w=408&h=240&yaw=357.01654&pitch=0&thumbfov=100
